Workbook

Sheet top-20-selection
A1: Rank | B1: Page URL | C1: Intent Pts | D1: Traffic Pts | E1: PageType Pts | F1: Engage Pts | G1: Weighted Score | H1: Sessions | I1: Page Type | J1: Bounce Rate | K1: Avg Engage Time | L1: Scroll Depth % | M1: Placement | N1: Click Hot Zones | O1: Impl Type | P1: Status | Q1: URL | S1: Click Hot Zone References (Column R)
A2: 1 | B2: /client-solutions/ | C2: 35 | D2: 24 | E2: 20 | F2: 15 | G2: =sum(C2:F2) -> 94 | H2: 249 | I2: Service | J2: 0.18 | K2: 39.2s | L2: 0.5583 | M2: UPPER MID | N2: nav menu | O2: =IF(AND(I2="Service", H2>100), "Banner", IF(OR(N2="nav menu", N2="nav CTA", N2="nav phone"), "Button", IF(OR(N2="below-fold", N2="trust carousel", N2="hero CTA", N2="hero image"), "Button", IF(OR(N2="hero headline", N2="hero text"), "Button", IF(OR(N2="text block", N2="headings"), "Anchor Link", IF(OR(I2="Industry", I2="Case Study"), "Button", IF(OR(N2="none", N2=""), "Banner", "Button"))))))) -> Banner | P2: TRUE | Q2: https://salesxceleration.com/client-solutions/ | S2: Priority | T2: Click Hot Zone | U2: Write | V2: What It Means | W2: Where to Place
A3: 2 | B3: /state-of-sales/ | C3: 35 | D3: 30 | E3: 20 | F3: 5 | G3: =sum(C3:F3) -> 90 | H3: 308 | I3: Service | J3: 0.73 | K3: 3.5s | L3: 0.4208 | M3: TOP | N3: nav menu | O3: =IF(AND(I3="Service", H3>100), "Banner", IF(OR(N3="nav menu", N3="nav CTA", N3="nav phone"), "Button", IF(OR(N3="below-fold", N3="trust carousel", N3="hero CTA", N3="hero image"), "Button", IF(OR(N3="hero headline", N3="hero text"), "Button", IF(OR(N3="text block", N3="headings"), "Anchor Link", IF(OR(I3="Industry", I3="Case Study"), "Button", IF(OR(N3="none", N3=""), "Banner", "Button"))))))) -> Banner | P3: TRUE | Q3: https://salesxceleration.com/state-of-sales/ | S3: 1 | T3: Service + >100 sessions | U3: (any) | V3: High-traffic flagship page | W3: Banner in upper-mid
A4: 3 | B4: /sales-strategy/ | C4: 35 | D4: 8 | E4: 20 | F4: 15 | G4: =sum(C4:F4) -> 78 | H4: 83 | I4: Service | J4: 0.18 | K4: 76.5s | L4: 0.5897 | M4: UPPER MID | N4: nav menu | O4: =IF(AND(I4="Service", H4>100), "Banner", IF(OR(N4="nav menu", N4="nav CTA", N4="nav phone"), "Button", IF(OR(N4="below-fold", N4="trust carousel", N4="hero CTA", N4="hero image"), "Button", IF(OR(N4="hero headline", N4="hero text"), "Button", IF(OR(N4="text block", N4="headings"), "Anchor Link", IF(OR(I4="Industry", I4="Case Study"), "Button", IF(OR(N4="none", N4=""), "Banner", "Button"))))))) -> Button | P4: TRUE | Q4: https://salesxceleration.com/sales-strategy/ | S4: 2 | T4: Nav menu/CTA/phone clicks | U4: nav menu / nav CTA / nav phone | V4: Users engaging with header | W4: Button in hero or next section
A5: 4 | B5: /private-equity-solutions/ | C5: 35 | D5: 5 | E5: 20 | F5: 15 | G5: =sum(C5:F5) -> 75 | H5: 47 | I5: Service | J5: 0.15 | K5: 86.2s | L5: 0.589 | M5: UPPER MID | N5: trust carousel | O5: =IF(AND(I5="Service", H5>100), "Banner", IF(OR(N5="nav menu", N5="nav CTA", N5="nav phone"), "Button", IF(OR(N5="below-fold", N5="trust carousel", N5="hero CTA", N5="hero image"), "Button", IF(OR(N5="hero headline", N5="hero text"), "Button", IF(OR(N5="text block", N5="headings"), "Anchor Link", IF(OR(I5="Industry", I5="Case Study"), "Button", IF(OR(N5="none", N5=""), "Banner", "Button"))))))) -> Button | P5: TRUE | Q5: https://salesxceleration.com/private-equity-solutions/ | S5: 3 | T5: Below-fold text, CTA or carousel | U5: below-fold / trust carousel | V5: Users scrolling and engaging | W5: Button BEFORE or AFTER hot zone
A6: 5 | B6: /private-equity-solutions/tech-mfg-case-study/ | C6: 35 | D6: 9 | E6: 15 | F6: 15 | G6: =sum(C6:F6) -> 74 | H6: 89 | I6: Case Study | J6: 0.43 | K6: 126.4s | L6: 0.5793 | M6: UPPER MID | N6: hero headline | O6: =IF(AND(I6="Service", H6>100), "Banner", IF(OR(N6="nav menu", N6="nav CTA", N6="nav phone"), "Button", IF(OR(N6="below-fold", N6="trust carousel", N6="hero CTA", N6="hero image"), "Button", IF(OR(N6="hero headline", N6="hero text"), "Button", IF(OR(N6="text block", N6="headings"), "Anchor Link", IF(OR(I6="Industry", I6="Case Study"), "Button", IF(OR(N6="none", N6=""), "Banner", "Button"))))))) -> Button | P6: TRUE | Q6: https://salesxceleration.com/private-equity-solutions/tech-mfg-case-study/ | S6: 4 | T6: Hero element clicks | U6: hero CTA / hero headline / hero text / hero image | V6: Users engaging with hero | W6: Button in hero (secondary) or below
A7: 6 | B7: /sales-infrastructure/ | C7: 35 | D7: 4 | E7: 20 | F7: 15 | G7: =sum(C7:F7) -> 74 | H7: 42 | I7: Service | J7: 0.29 | K7: 49.5s | L7: 0.5774 | M7: UPPER MID | N7: nav menu | O7: =IF(AND(I7="Service", H7>100), "Banner", IF(OR(N7="nav menu", N7="nav CTA", N7="nav phone"), "Button", IF(OR(N7="below-fold", N7="trust carousel", N7="hero CTA", N7="hero image"), "Button", IF(OR(N7="hero headline", N7="hero text"), "Button", IF(OR(N7="text block", N7="headings"), "Anchor Link", IF(OR(I7="Industry", I7="Case Study"), "Button", IF(OR(N7="none", N7=""), "Banner", "Button"))))))) -> Button | P7: TRUE | Q7: https://salesxceleration.com/sales-infrastructure/ | S7: 5 | T7: Text paragraphs | U7: text block | V7: Users treating text as clickable | W7: Anchor Link within text
A8: 7 | B8: /sales-team/ | C8: 35 | D8: 5 | E8: 20 | F8: 12 | G8: =sum(C8:F8) -> 72 | H8: 50 | I8: Service | J8: 0.12 | K8: 18.0s | L8: 0.5824 | M8: UPPER MID | N8: nav menu | O8: =IF(AND(I8="Service", H8>100), "Banner", IF(OR(N8="nav menu", N8="nav CTA", N8="nav phone"), "Button", IF(OR(N8="below-fold", N8="trust carousel", N8="hero CTA", N8="hero image"), "Button", IF(OR(N8="hero headline", N8="hero text"), "Button", IF(OR(N8="text block", N8="headings"), "Anchor Link", IF(OR(I8="Industry", I8="Case Study"), "Button", IF(OR(N8="none", N8=""), "Banner", "Button"))))))) -> Button | P8: TRUE | Q8: https://salesxceleration.com/sales-team/ | S8: 5 | T8: Headings | U8: headings | V8: Users trying to navigate | W8: Anchor Link in section
A9: 8 | B9: /private-equity-solutions/private-equity/ | C9: 35 | D9: 6 | E9: 20 | F9: 10 | G9: =sum(C9:F9) -> 71 | H9: 57 | I9: Service | J9: 0.46 | K9: 22.9s | L9: 0.5958 | M9: UPPER MID | N9: nav menu | O9: =IF(AND(I9="Service", H9>100), "Banner", IF(OR(N9="nav menu", N9="nav CTA", N9="nav phone"), "Button", IF(OR(N9="below-fold", N9="trust carousel", N9="hero CTA", N9="hero image"), "Button", IF(OR(N9="hero headline", N9="hero text"), "Button", IF(OR(N9="text block", N9="headings"), "Anchor Link", IF(OR(I9="Industry", I9="Case Study"), "Button", IF(OR(N9="none", N9=""), "Banner", "Button"))))))) -> Button | P9: TRUE | Q9: https://salesxceleration.com/private-equity-solutions/private-equity/ | S9: 6 | T9: Industry or Case Study page | U9: (any) | V9: Page type default | W9: Button after key section
A10: 9 | B10: /private-equity-solutions/portfolio-company/ | C10: 35 | D10: 4 | E10: 20 | F10: 12 | G10: =sum(C10:F10) -> 71 | H10: 46 | I10: Service | J10: 0.3 | K10: 15.2s | L10: 0.6264 | M10: MID | N10: nav menu | O10: =IF(AND(I10="Service", H10>100), "Banner", IF(OR(N10="nav menu", N10="nav CTA", N10="nav phone"), "Button", IF(OR(N10="below-fold", N10="trust carousel", N10="hero CTA", N10="hero image"), "Button", IF(OR(N10="hero headline", N10="hero text"), "Button", IF(OR(N10="text block", N10="headings"), "Anchor Link", IF(OR(I10="Industry", I10="Case Study"), "Button", IF(OR(N10="none", N10=""), "Banner", "Button"))))))) -> Button | P10: TRUE | Q10: https://salesxceleration.com/private-equity-solutions/portfolio-company/ | S10: 7 | T10: Image clicks | U10: images | V10: Users expect interaction | W10: Button below image
A11: 10 | B11: /industries/technology/ | C11: 35 | D11: 3 | E11: 18 | F11: 15 | G11: =sum(C11:F11) -> 71 | H11: 32 | I11: Industry | J11: 0.38 | K11: 55.6s | L11: 0.6226 | M11: MID | N11: below-fold | O11: =IF(AND(I11="Service", H11>100), "Banner", IF(OR(N11="nav menu", N11="nav CTA", N11="nav phone"), "Button", IF(OR(N11="below-fold", N11="trust carousel", N11="hero CTA", N11="hero image"), "Button", IF(OR(N11="hero headline", N11="hero text"), "Button", IF(OR(N11="text block", N11="headings"), "Anchor Link", IF(OR(I11="Industry", I11="Case Study"), "Button", IF(OR(N11="none", N11=""), "Banner", "Button"))))))) -> Button | P11: TRUE | Q11: https://salesxceleration.com/industries/technology/ | S11: 8 | T11: No clear pattern | U11: none | V11: Need to create attention | W11: Banner in upper-mid
A12: 11 | B12: /sales-management/ | C12: 35 | D12: 4 | E12: 20 | F12: 10 | G12: =sum(C12:F12) -> 69 | H12: 41 | I12: Service | J12: 0.44 | K12: 23.6s | L12: 0.5675 | M12: UPPER MID | N12: nav menu | O12: =IF(AND(I12="Service", H12>100), "Banner", IF(OR(N12="nav menu", N12="nav CTA", N12="nav phone"), "Button", IF(OR(N12="below-fold", N12="trust carousel", N12="hero CTA", N12="hero image"), "Button", IF(OR(N12="hero headline", N12="hero text"), "Button", IF(OR(N12="text block", N12="headings"), "Anchor Link", IF(OR(I12="Industry", I12="Case Study"), "Button", IF(OR(N12="none", N12=""), "Banner", "Button"))))))) -> Button | P12: TRUE | Q12: https://salesxceleration.com/sales-management/
A13: 12 | B13: /private-equity-solutions/healthcare-managed-services-case-study/ | C13: 35 | D13: 6 | E13: 15 | F13: 12 | G13: =sum(C13:F13) -> 68 | H13: 62 | I13: Case Study | J13: 0.34 | K13: 27.0s | L13: 0.4671 | M13: TOP | N13: below-fold | O13: =IF(AND(I13="Service", H13>100), "Banner", IF(OR(N13="nav menu", N13="nav CTA", N13="nav phone"), "Button", IF(OR(N13="below-fold", N13="trust carousel", N13="hero CTA", N13="hero image"), "Button", IF(OR(N13="hero headline", N13="hero text"), "Button", IF(OR(N13="text block", N13="headings"), "Anchor Link", IF(OR(I13="Industry", I13="Case Study"), "Button", IF(OR(N13="none", N13=""), "Banner", "Button"))))))) -> Button | P13: TRUE | Q13: https://salesxceleration.com/private-equity-solutions/healthcare-managed-services-case-study/
A14: 13 | B14: /industries/franchises/ | C14: 35 | D14: 1 | E14: 18 | F14: 12 | G14: =sum(C14:F14) -> 66 | H14: 12 | I14: Industry | J14: 0.17 | K14: 21.5s | L14: 0.622 | M14: MID | N14: nav menu | O14: =IF(AND(I14="Service", H14>100), "Banner", IF(OR(N14="nav menu", N14="nav CTA", N14="nav phone"), "Button", IF(OR(N14="below-fold", N14="trust carousel", N14="hero CTA", N14="hero image"), "Button", IF(OR(N14="hero headline", N14="hero text"), "Button", IF(OR(N14="text block", N14="headings"), "Anchor Link", IF(OR(I14="Industry", I14="Case Study"), "Button", IF(OR(N14="none", N14=""), "Banner", "Button"))))))) -> Button | P14: TRUE | Q14: https://salesxceleration.com/industries/franchises/
A15: 14 | B15: /industries/professional-services/ | C15: 35 | D15: 2 | E15: 18 | F15: 10 | G15: =sum(C15:F15) -> 65 | H15: 25 | I15: Industry | J15: 0.56 | K15: 26.7s | L15: 0.5754 | M15: UPPER MID | N15: below-fold | O15: =IF(AND(I15="Service", H15>100), "Banner", IF(OR(N15="nav menu", N15="nav CTA", N15="nav phone"), "Button", IF(OR(N15="below-fold", N15="trust carousel", N15="hero CTA", N15="hero image"), "Button", IF(OR(N15="hero headline", N15="hero text"), "Button", IF(OR(N15="text block", N15="headings"), "Anchor Link", IF(OR(I15="Industry", I15="Case Study"), "Button", IF(OR(N15="none", N15=""), "Banner", "Button"))))))) -> Button | P15: TRUE | Q15: https://salesxceleration.com/industries/professional-services/
A16: 15 | B16: /industries/manufacturing/ | C16: 35 | D16: 2 | E16: 18 | F16: 10 | G16: =sum(C16:F16) -> 65 | H16: 24 | I16: Industry | J16: 0.42 | K16: 18.6s | L16: 0.6054 | M16: MID | N16: below-fold | O16: =IF(AND(I16="Service", H16>100), "Banner", IF(OR(N16="nav menu", N16="nav CTA", N16="nav phone"), "Button", IF(OR(N16="below-fold", N16="trust carousel", N16="hero CTA", N16="hero image"), "Button", IF(OR(N16="hero headline", N16="hero text"), "Button", IF(OR(N16="text block", N16="headings"), "Anchor Link", IF(OR(I16="Industry", I16="Case Study"), "Button", IF(OR(N16="none", N16=""), "Banner", "Button"))))))) -> Button | P16: TRUE | Q16: https://salesxceleration.com/industries/manufacturing/
A17: 16 | B17: /industries/financial-services/ | C17: 35 | D17: 1 | E17: 18 | F17: 10 | G17: =sum(C17:F17) -> 64 | H17: 9 | I17: Industry | J17: 0.44 | K17: 14.1s | L17: 0.5181 | M17: UPPER MID | N17: nav menu | O17: =IF(AND(I17="Service", H17>100), "Banner", IF(OR(N17="nav menu", N17="nav CTA", N17="nav phone"), "Button", IF(OR(N17="below-fold", N17="trust carousel", N17="hero CTA", N17="hero image"), "Button", IF(OR(N17="hero headline", N17="hero text"), "Button", IF(OR(N17="text block", N17="headings"), "Anchor Link", IF(OR(I17="Industry", I17="Case Study"), "Button", IF(OR(N17="none", N17=""), "Banner", "Button"))))))) -> Button | P17: TRUE | Q17: https://salesxceleration.com/industries/financial-services/
A18: 17 | B18: /industries/legal/ | C18: 35 | D18: 1 | E18: 18 | F18: 5 | G18: =sum(C18:F18) -> 59 | H18: 9 | I18: Industry | J18: 0.67 | K18: 4.3s | L18: 0.462 | M18: TOP | N18: below-fold | O18: =IF(AND(I18="Service", H18>100), "Banner", IF(OR(N18="nav menu", N18="nav CTA", N18="nav phone"), "Button", IF(OR(N18="below-fold", N18="trust carousel", N18="hero CTA", N18="hero image"), "Button", IF(OR(N18="hero headline", N18="hero text"), "Button", IF(OR(N18="text block", N18="headings"), "Anchor Link", IF(OR(I18="Industry", I18="Case Study"), "Button", IF(OR(N18="none", N18=""), "Banner", "Button"))))))) -> Button | P18: TRUE | Q18: https://salesxceleration.com/industries/legal/
A19: 18 | B19: /industries/private-equity/ | C19: 35 | D19: 0 | E19: 18 | F19: 5 | G19: =sum(C19:F19) -> 58 | H19: 5 | I19: Industry | J19: 0.8 | K19: 5.0s | L19: 0.5664 | M19: UPPER MID | N19: below-fold | O19: =IF(AND(I19="Service", H19>100), "Banner", IF(OR(N19="nav menu", N19="nav CTA", N19="nav phone"), "Button", IF(OR(N19="below-fold", N19="trust carousel", N19="hero CTA", N19="hero image"), "Button", IF(OR(N19="hero headline", N19="hero text"), "Button", IF(OR(N19="text block", N19="headings"), "Anchor Link", IF(OR(I19="Industry", I19="Case Study"), "Button", IF(OR(N19="none", N19=""), "Banner", "Button"))))))) -> Button | P19: TRUE | Q19: https://salesxceleration.com/industries/private-equity/
A20: 19 | B20: /case-study/electrical-manufacturing-sales-strategy-and-processes-provide-immediate-growth/ | C20: 35 | D20: 1 | E20: 15 | F20: 5 | G20: =sum(C20:F20) -> 56 | H20: 15 | I20: Case Study | J20: 0.73 | K20: 13.3s | L20: 0.6136 | M20: MID | N20: nav menu | O20: =IF(AND(I20="Service", H20>100), "Banner", IF(OR(N20="nav menu", N20="nav CTA", N20="nav phone"), "Button", IF(OR(N20="below-fold", N20="trust carousel", N20="hero CTA", N20="hero image"), "Button", IF(OR(N20="hero headline", N20="hero text"), "Button", IF(OR(N20="text block", N20="headings"), "Anchor Link", IF(OR(I20="Industry", I20="Case Study"), "Button", IF(OR(N20="none", N20=""), "Banner", "Button"))))))) -> Button | P20: TRUE | Q20: https://salesxceleration.com/case-study/electrical-manufacturing-sales-strategy-and-processes-provide-immediate-growth/
A21: 20 | B21: /ai-for-sales/ | C21: 20 | D21: 3 | E21: 20 | F21: 12 | G21: =sum(C21:F21) -> 55 | H21: 35 | I21: Service | J21: 0.2 | K21: 22.9s | L21: 0.5609 | M21: UPPER MID | N21: below-fold | O21: =IF(AND(I21="Service", H21>100), "Banner", IF(OR(N21="nav menu", N21="nav CTA", N21="nav phone"), "Button", IF(OR(N21="below-fold", N21="trust carousel", N21="hero CTA", N21="hero image"), "Button", IF(OR(N21="hero headline", N21="hero text"), "Button", IF(OR(N21="text block", N21="headings"), "Anchor Link", IF(OR(I21="Industry", I21="Case Study"), "Button", IF(OR(N21="none", N21=""), "Banner", "Button"))))))) -> Button | P21: TRUE | Q21: https://salesxceleration.com/ai-for-sales/
C23: Weighted Score = "Does the page match sales challenges?" + "Does it get traffic?" + "Is it a service page?" + "Do visitors engage?" | M23: Placement Decision (based on scroll depth) | N23: Why?
M24: < 50% → HERO (must be in top 20%) | N24: More than half of users leave before scrolling. If the CTA isn't in the hero, most users will never see it. Maximize visibility for the majority.
C25: --- INTENT SCORING BASED ON H1/H2/H2-2 --- | M25: 50-60% → UPPER-MID after intro paragraph (top 25-30% of page) ← 55.8% falls here | N25: Users ARE scrolling past the intro, but 40-50% still drop off before mid-page. Place CTA just after the intro so engaged users see it early, while not wasting hero space.
M26: > 60% → MID-PAGE OK (40-60% of page) | N26: Majority of users scroll deep on this page. Placing CTA mid-page catches users when they're most engaged with content—after they've read enough to be convinced.
C27: Intent Level | D27: Score | E27: H1/H2 Keywords Required
C28: HIGH | D28: 35 pts | E28: Contains: Sales Strategy, Sales Management, Sales Leadership, Sales Infrastructure, Revenue Growth, Fractional Sales, Sales Challenges, Sales Success, Sales Performance, Private Equity Solutions
C29: MED | D29: 20 pts | E29: Contains: AI for Sales, Sales Tips, Sales Tools, General Sales Topics
C30: LOW | D30: 10 pts | E30: Contains: Non-sales topics, motivational content, general business
C32: --- SCORE COMPONENT DEFINITIONS ---
C34: Component | D34: Max Pts | E34: Calculation
C35: Intent Pts | D35: 35 | E35: Based on H1, H2-1, H2-2 keyword analysis
C36: Traffic Pts | D36: 30 | E36: (Sessions ÷ 308) × 30 [rounded]
C37: PageType Pts | D37: 20 | E37: Service=20 | Industry=18 | Case Study=15
C38: Engage Pts | D38: 15 | E38: Excellent=15 (bounce<35% + engage>30s) | Good=12 (bounce<50% + engage>15s) | Medium=10 | Low=5

Sheet analytics
A1: Page path and screen class | B1: Character Count | C1: Sessions | D1: Key events | E1: Total users | F1: Bounce rate | G1: New users | H1: Engaged sessions | I1: Views | J1: Active users | K1: Average engagement time per active user | L1: H1 | M1: H2-1 | N1: H2-2
A2: /state-of-sales/ | B2: =len(A2) -> 16 | C2: 308 | D2: 0 | E2: 300 | F2: 0.73376623 | G2: 266 | H2: 82 | I2: 309 | J2: 297 | K2: 3.5151515 | L2: =vlookup(A2,salesx_all!B:E,2,0) -> 2025 State of Sales | Small to Mid-Size Businesses | M2: =vlookup(A2,salesx_all!B:D,3,0) -> The State of Sales: Crafting High-Performing Sales Organizations | N2: =vlookup(A2,salesx_all!B:E,4,0) -> Sales Strategy
A3: /client-solutions/ | B3: =len(A3) -> 18 | C3: 249 | D3: 2 | E3: 206 | F3: 0.17670683 | G3: 28 | H3: 205 | I3: 269 | J3: 203 | K3: 39.221675 | L3: =vlookup(A3,salesx_all!B:E,2,0) -> Tailored Sales Solutions for Your Business | M3: =vlookup(A3,salesx_all!B:D,3,0) -> Fractional Sales Leader: Your Source for Sales Success | N3: =vlookup(A3,salesx_all!B:E,4,0) -> Certified Sales Operating Management SystemTM
A4: /contact-us/ | B4: =len(A4) -> 12 | C4: 153 | D4: 0 | E4: 152 | F4: 0.24836601 | G4: 50 | H4: 115 | I4: 205 | J4: 152 | K4: 24.026316 | L4: =vlookup(A4,salesx_all!B:E,2,0) -> Contact Us | M4: =vlookup(A4,salesx_all!B:D,3,0) | N4: =vlookup(A4,salesx_all!B:E,4,0)
A5: /podcasts/ | B5: =len(A5) -> 10 | C5: 126 | D5: 0 | E5: 114 | F5: 0.25396825 | G5: 58 | H5: 94 | I5: 121 | J5: 113 | K5: 21.141593 | L5: =vlookup(A5,salesx_all!B:E,2,0) -> Sales Against The Odds | M5: =vlookup(A5,salesx_all!B:D,3,0) -> Latest Episode | N5: =vlookup(A5,salesx_all!B:E,4,0) -> Episode Library
A6: /free-sales-resources/ | B6: =len(A6) -> 22 | C6: 95 | D6: 0 | E6: 75 | F6: 0.58947368 | G6: 43 | H6: 39 | I6: 135 | J6: 74 | K6: 51.662162 | L6: =vlookup(A6,salesx_all!B:E,2,0) -> Free Sales Tools and Resources | M6: =vlookup(A6,salesx_all!B:D,3,0) -> Not sure where to start? Here are our top picks: | N6: =vlookup(A6,salesx_all!B:E,4,0) -> The AI Security Playbook: 6 Essentials Every Sales Organization Needs
A7: /case-studies/ | B7: =len(A7) -> 14 | C7: 92 | D7: 0 | E7: 87 | F7: 0.52173913 | G7: 58 | H7: 44 | I7: 102 | J7: 86 | K7: 18.802326 | L7: =vlookup(A7,salesx_all!B:E,2,0) -> Sales Success Stories and Case Studies | M7: =vlookup(A7,salesx_all!B:D,3,0) -> Featured Case Studies | N7: =vlookup(A7,salesx_all!B:E,4,0)
A8: /private-equity-solutions/tech-mfg-case-study/ | B8: =len(A8) -> 46 | C8: 89 | D8: 0 | E8: 50 | F8: 0.42696629 | G8: 44 | H8: 51 | I8: 98 | J8: 49 | K8: 126.38776 | L8: =vlookup(A8,salesx_all!B:E,2,0) -> Investment Profile and Challenges | M8: =vlookup(A8,salesx_all!B:D,3,0) -> $5M Turnaround: Inside Sales Xceleration's Sales Growth Strategy | N8: =vlookup(A8,salesx_all!B:E,4,0) -> Portfolio Company Challenges
A9: /sales-strategy/ | B9: =len(A9) -> 16 | C9: 83 | D9: 0 | E9: 70 | F9: 0.18072289 | G9: 7 | H9: 68 | I9: 87 | J9: 70 | K9: 76.528571 | L9: =vlookup(A9,salesx_all!B:E,2,0) -> Sales Strategy Consulting Services | M9: =vlookup(A9,salesx_all!B:D,3,0) -> Transform Your Sales with Proven Expertise | N9: =vlookup(A9,salesx_all!B:E,4,0) -> Build Your Sales Strategy with Our Proven Framework
A10: /frequently-asked-questions/ | B10: =len(A10) -> 28 | C10: 65 | D10: 0 | E10: 57 | F10: 0.21538462 | G10: 11 | H10: 51 | I10: 64 | J10: 57 | K10: 57.684211 | L10: =vlookup(A10,salesx_all!B:E,2,0) -> Frequently Asked Questions | M10: =vlookup(A10,salesx_all!B:D,3,0) -> General Questions | N10: =vlookup(A10,salesx_all!B:E,4,0) -> Engagement & Pricing
A11: /private-equity-solutions/healthcare-managed-services-case-study/ | B11: =len(A11) -> 65 | C11: 62 | D11: 0 | E11: 60 | F11: 0.33870968 | G11: 27 | H11: 41 | I11: 61 | J11: 60 | K11: 27.016667 | L11: =vlookup(A11,salesx_all!B:E,2,0) -> Company Profile and Challenges | M11: =vlookup(A11,salesx_all!B:D,3,0) -> 25x Return On Investment In One Year: How Sales Xceleration Increased Value | N11: =vlookup(A11,salesx_all!B:E,4,0) -> Platform/Portfolio Company Challenges
A12: /turn-chaos-into-clarity-building-sales-infrastructure-that-scales/ | B12: =len(A12) -> 67 | C12: 59 | D12: 0 | E12: 56 | F12: 0.38983051 | G12: 26 | H12: 36 | I12: 50 | J12: 56 | K12: 7.9107143 | L12: =vlookup(A12,salesx_all!B:E,2,0) -> #N/A | M12: =vlookup(A12,salesx_all!B:D,3,0) -> #N/A | N12: =vlookup(A12,salesx_all!B:E,4,0) -> #N/A
A13: /private-equity-solutions/private-equity/ | B13: =len(A13) -> 41 | C13: 57 | D13: 0 | E13: 42 | F13: 0.45614035 | G13: 10 | H13: 31 | I13: 59 | J13: 40 | K13: 22.925 | L13: =vlookup(A13,salesx_all!B:E,2,0) -> Private Equity Growth with Expert Sales Strategies | M13: =vlookup(A13,salesx_all!B:D,3,0) -> Accelerate Growth. Maximize Returns. | N13: =vlookup(A13,salesx_all!B:E,4,0) -> Maximizing Organic Growth
... A671: /youve-earned-respect-but-are-you-still-getting-it | B671: =len(A671) -> 50 | C671: 1 | D671: 0 | E671: 1 | F671: 1 | G671: 1 | H671: 0 | I671: 0 | J671: 1 | K671: 0 | L671: =vlookup(A671,salesx_all!B:E,2,0) -> #N/A | M671: =vlookup(A671,salesx_all!B:D,3,0) -> #N/A | N671: =vlookup(A671,salesx_all!B:E,4,0) -> #N/A

Sheet salesx_all
A1: Address | C1: H1-1 | D1: H2-1 | E1: H2-2 | F1: Content Type | G1: Status Code | H1: Status | I1: Indexability | J1: Indexability Status | K1: Title 1 | L1: Title 1 Length | M1: Title 1 Pixel Width | N1: Title 2 | O1: Title 2 Length | P1: Title 2 Pixel Width | Q1: Meta Description 1 | R1: Meta Description 1 Length | S1: Meta Description 1 Pixel Width | T1: Meta Keywords 1 | U1: Meta Keywords 1 Length | V1: H1-1 | W1: H1-1 Length | X1: H1-2 | Y1: H1-2 Length | Z1: H2-1 | AA1: H2-1 Length | AB1: H2-2 | AC1: H2-2 Length | AD1: Meta Robots 1 | AE1: X-Robots-Tag 1 | AF1: Meta Refresh 1 | AG1: Canonical Link Element 1 | AH1: rel="next" 1 | AI1: rel="prev" 1 | AJ1: HTTP rel="next" 1 | AK1: HTTP rel="prev" 1 | AL1: amphtml Link Element | AM1: Size (bytes) | AN1: Transferred (bytes) | AO1: Total Transferred (bytes) | AP1: CO2 (mg) | AQ1: Carbon Rating | AR1: Word Count | AS1: Sentence Count | AT1: Average Words Per Sentence | AU1: Flesch Reading Ease Score | AV1: Readability | AW1: Text Ratio | AX1: Crawl Depth | AY1: Folder Depth | AZ1: Link Score | BA1: Inlinks | BB1: Unique Inlinks | BC1: Unique JS Inlinks | BD1: % of Total | BE1: Outlinks | BF1: Unique Outlinks | BG1: Unique JS Outlinks | BH1: External Outlinks | BI1: Unique External Outlinks | BJ1: Unique External JS Outlinks | BK1: Closest Near Duplicate Match | BL1: No. Near Duplicates | BM1: Spelling Errors | BN1: Grammar Errors | BO1: Hash | BP1: Response Time | BQ1: Last Modified | BR1: Redirect URL | BS1: Redirect Type | BT1: Cookies | BU1: Language | BV1: HTTP Version | BW1: Performance Score | BX1: First Contentful Paint Time (ms) | BY1: Speed Index Time (ms) | BZ1: Largest Contentful Paint Time (ms) | CA1: Time to Interactive (ms) | CB1: Total Blocking Time (ms) | CC1: Cumulative Layout Shift | CD1: Total Size Savings (Bytes) | CE1: Total Time Savings (ms) | CF1: Total Requests | CG1: Total Page Size (Bytes) | CH1: HTML Size (Bytes) | CI1: HTML Count | CJ1: Image Size (Bytes) | CK1: Image Count | CL1: CSS Size (Bytes) | CM1: CSS Count | CN1: JavaScript Size (Bytes) | CO1: JavaScript Count | CP1: Font Size (Bytes) | CQ1: Font Count | CR1: Media Size (Bytes) | CS1: Media Count | CT1: Other Size (Bytes) | CU1: Other Count | CV1: Third Party Size (Bytes) | CW1: Third Party Count | CX1: Core Web Vitals Assessment | CY1: CrUX Largest Contentful Paint Time (ms) | CZ1: CrUX Interaction to Next Paint (ms) | DA1: CrUX Cumulative Layout Shift | DB1: CrUX First Contentful Paint Time (ms) | DC1: Minify CSS Savings (ms) | DD1: Minify CSS Savings (Bytes) | DE1: Minify JavaScript Savings (ms) | DF1: Minify JavaScript Savings (Bytes) | DG1: Reduce Unused CSS Savings (ms) | DH1: Reduce Unused CSS Savings (Bytes) | DI1: Reduce Unused JavaScript Savings (ms) | DJ1: Reduce Unused JavaScript Savings (Bytes) | DK1: JavaScript Execution Time (ms) | DL1: JavaScript Execution Time Category | DM1: Minimize Main-Thread Work (ms) | DN1: Minimize Main-Thread Work Category | DO1: Network Payload Size (Bytes) | DP1: User Timing Marks and Measures | DQ1: Number of Redirects | DR1: Server Responds Quickly | DS1: Applies Text Compression | DT1: LCP Request Discovery | DU1: LCP Breakdown | DV1: Render Blocking Requests Savings (ms) | DW1: Preconnect Candidates Savings (ms) | DX1: Maximum Critical Path Latency (ms) | DY1: Use Efficient Cache Lifetimes Savings (Bytes) | DZ1: Layout Shift Culprits | EA1: DOM Size | EB1: Improve Image Delivery Savings (Bytes) | EC1: Forced Reflow Savings (ms) | ED1: Legacy JavaScript Savings (Bytes) | EE1: Duplicated JavaScript (Bytes) | EF1: Font Display Savings (ms) | EG1: 3rd Parties | EH1: Target Size | EI1: Content Width | EJ1: Font Display Size | EK1: Viewport | EL1: Mobile Alternate Link | EM1: Closest Semantically Similar Address | EN1: Semantic Similarity Score | EO1: No. Semantically Similar | EP1: Semantic Relevance Score | EQ1: URL Encoded Address | ER1: Crawl Timestamp
A2: https://salesxceleration.com/ | B2: =IFERROR(__xludf.DUMMYFUNCTION("REGEXREPLACE(A2, ""^https?://[^/]+"", """")"),"/") -> / | C2: Fractional Sales Leadership. Full-Time Results. | D2: Fractional Sales Leaders | E2: A Sales System That Works | F2: text/html; charset=UTF-8 | G2: 200 | H2: OK | I2: Indexable | K2: Sales Xceleration | Outsourced & Fractional Sales Leadership | L2: 60 | M2: 543 | O2: 0 | P2: 0 | Q2: Sales Xceleration offers expert sales outsourcing services. Our outsourced VPs of Sales implement custom strategies to drive growth and improve sales performance. | R2: 162 | S2: 1020 | U2: 0 | V2: Fractional Sales Leadership. Full-Time Results. | W2: 47 | X2: Case Studies | Y2: 12 | Z2: Fractional Sales Leaders | AA2: 24 | AB2: A Sales System That Works | AC2: 25 | AD2: follow, index, max-snippet:-1, max-video-preview:-1, max-image-preview:large | AG2: https://salesxceleration.com/ | AM2: 749412 | AN2: 234736 | AO2: 234736 | AP2: 89.923 | AR2: 1084 | AS2: 188 | AT2: 5.766 | AU2: 54.571 | AV2: Fairly Hard | AW2: 1.671 | AX2: 0 | AY2: 0 | AZ2: 51 | BA2: 833 | BB2: 754 | BC2: 0 | BD2: 100 | BE2: 155 | BF2: 49 | BG2: 0 | BH2: 23 | BI2: 15 | BJ2: 0 | BO2: 527b62052cd29133fd46d9a8ac7da70c | BP2: 1.503 | BU2: en-US | BV2: 1.1 | BW2: 46 | BX2: 3483.699 | BY2: 11076.143 | BZ2: 8477.052 | CA2: 18820.639 | CB2: 547.5 | CC2: 0 | CD2: 640679 | CE2: 1200 | CF2: 193 | CG2: 3456960 | CH2: 223563 | CI2: 2 | CJ2: 1087842 | CK2: 44 | CL2: 118644 | CM2: 42 | CN2: 1756303 | CO2: 70 | CP2: 244245 | CQ2: 5 | CR2: 0 | CS2: 0 | CT2: 26363 | CU2: 30 | CV2: 1505251 | CW2: 90 | DC2: 0 | DD2: 5075 | DE2: 0 | DF2: 3395 | DG2: 150 | DH2: 40137 | DI2: 1050 | DJ2: 592072 | DK2: 2259.466 | DL2: Poor | DM2: 8762.409 | DN2: Poor | DO2: 3456624 | DP2: 1 | DQ2: Avoids redirects | DR2: Server responded slowly (observed 666 ms) | DS2: Applies text compression | DT2: 1 issue found | DU2: 4 resources found | DV2: 14509 | DX2: 6584 | DY2: 1014690 | DZ2: 1 resource found | EA2: 1885 | EB2: 493678 | EC2: 70 | ED2: 26482 | EF2: 245 | EG2: 21 resources found | EH2: 100 | EK2: 100 | EQ2: https://salesxceleration.com/ | ER2: 46045.298
A3: https://salesxceleration.com/wp-includes/js/jquery/ui/core.min.js?ver=1.13.3 | B3: =IFERROR(__xludf.DUMMYFUNCTION("REGEXREPLACE(A3, ""^https?://[^/]+"", """")"),"/wp-includes/js/jquery/ui/core.min.js?ver=1.13.3") -> /wp-includes/js/jquery/ui/core.min.js?ver=1.13.3 | F3: application/javascript | G3: 200 | H3: OK | I3: Indexable | L3: 0 | M3: 0 | O3: 0 | P3: 0 | R3: 0 | S3: 0 | U3: 0 | W3: 0 | Y3: 0 | AA3: 0 | AC3: 0 | AM3: 7106 | AN3: 7106 | AO3: 7106 | AP3: 2.722 | AR3: 0 | AW3: 0 | AX3: 1 | AY3: 4 | BA3: 0 | BB3: 0 | BC3: 0 | BD3: 0 | BE3: 0 | BF3: 0 | BG3: 0 | BH3: 0 | BI3: 0 | BJ3: 0 | BP3: 0.277 | BQ3: Mon, 30 Jun 2025 09:09:57 GMT | BV3: 1.1 | EQ3: https://salesxceleration.com/wp-includes/js/jquery/ui/core.min.js?ver=1.13.3 | ER3: 46045.298
A4: https://salesxceleration.com/privacy-policy/ | B4: =IFERROR(__xludf.DUMMYFUNCTION("REGEXREPLACE(A4, ""^https?://[^/]+"", """")"),"/privacy-policy/") -> /privacy-policy/ | C4: Privacy Policy | F4: text/html; charset=UTF-8 | G4: 200 | H4: OK | I4: Indexable | K4: Privacy Policy | Sales Xceleration | L4: 34 | M4: 294 | O4: 0 | P4: 0 | Q4: Sales Xceleration Privacy Policy | R4: 32 | S4: 195 | U4: 0 | V4: Privacy Policy | W4: 14 | Y4: 0 | AA4: 0 | AC4: 0 | AD4: follow, index, max-snippet:-1, max-video-preview:-1, max-image-preview:large | AG4: https://salesxceleration.com/privacy-policy/ | AM4: 155868 | AN4: 31691 | AO4: 31691 | AP4: 12.14 | AR4: 1736 | AS4: 248 | AT4: 7 | AU4: 60.159 | AV4: Normal | AW4: 8.422 | AX4: 1 | AY4: 1 | AZ4: 51 | BA4: 754 | BB4: 754 | BC4: 0 | BD4: 100 | BE4: 122 | BF4: 42 | BG4: 0 | BH4: 17 | BI4: 9 | BJ4: 0 | BO4: 90fff5e7b8045ce60a195168030ee65 | BP4: 1.377 | BU4: en-US | BV4: 1.1 | BW4: 63 | BX4: 3301.045 | BY4: 9498.224 | BZ4: 5851.083 | CA4: 17963.547 | CB4: 85.5 | CC4: 0.002 | CD4: 652279 | CE4: 1470 | CF4: 155 | CG4: 2199934 | CH4: 33025 | CI4: 2 | CJ4: 17473 | CK4: 15 | CL4: 110635 | CM4: 36 | CN4: 1747376 | CO4: 67 | CP4: 266182 | CQ4: 6 | CR4: 0 | CS4: 0 | CT4: 25243 | CU4: 29 | CV4: 1526753 | CW4: 66 | DC4: 210 | DD4: 5075 | DE4: 0 | DF4: 3396 | DG4: 510 | DH4: 50541 | DI4: 750 | DJ4: 593267 | DK4: 1147.732 | DL4: Good | DM4: 2122.415 | DN4: Poor | DO4: 2199935 | DP4: 1 | DQ4: Avoids redirects | DR4: Server responds quickly (observed 170 ms) | DS4: Applies text compression | DU4: 2 resources found | DV4: 13503 | DW4: 312 | DX4: 5323 | DY4: 579497 | DZ4: 1 resource found | EA4: 807 | EB4: 4453 | EC4: 0 | ED4: 26491 | EF4: 660 | EG4: 21 resources found | EH4: 100 | EK4: 100 | EQ4: https://salesxceleration.com/privacy-policy/ | ER4: 46045.298
A5: https://salesxceleration.com/blog/ | B5: =IFERROR(__xludf.DUMMYFUNCTION("REGEXREPLACE(A5, ""^https?://[^/]+"", """")"),"/blog/") -> /blog/ | C5: Expert Sales Tips and Insights from Sales Xceleration | D5: Not sure where to start? Here are our top picks: | E5: Complete Library | F5: text/html; charset=UTF-8 | G5: 200 | H5: OK | I5: Indexable | K5: Sales Expert Blog | Sales Tips & Insights | Sales Xceleration | L5: 61 | M5: 525 | O5: 0 | P5: 0 | Q5: Explore Sales Xceleration's expert blog for valuable sales tips & insights. Stay ahead with expert advice from industry leaders. | R5: 128 | S5: 768 | U5: 0 | V5: Expert Sales Tips and Insights from Sales Xceleration | W5: 53 | Y5: 0 | Z5: Not sure where to start? Here are our top picks: | AA5: 48 | AB5: Complete Library | AC5: 16 | AD5: follow, index, max-snippet:-1, max-video-preview:-1, max-image-preview:large | AG5: https://salesxceleration.com/blog/ | AM5: 187541 | AN5: 33755 | AO5: 33755 | AP5: 12.931 | AR5: 1117 | AS5: 210 | AT5: 5.319 | AU5: 67.152 | AV5: Normal | AW5: 4.895 | AX5: 1 | AY5: 1 | AZ5: 52 | BA5: 3020 | BB5: 754 | BC5: 0 | BD5: 100 | BE5: 149 | BF5: 53 | BG5: 0 | BH5: 16 | BI5: 8 | BJ5: 0 | BO5: ce57e6117f2da7436d8c7e3fda3baf61 | BP5: 1.567 | BU5: en-US | BV5: 1.1 | BW5: 57 | BX5: 3451.025 | BY5: 8592.665 | BZ5: 7502.059 | CA5: 18048.385 | CB5: 191 | CC5: 0 | CD5: 652819 | CE5: 1200 | CF5: 175 | CG5: 2462041 | CH5: 34568 | CI5: 2 | CJ5: 175038 | CK5: 23 | CL5: 119532 | CM5: 42 | CN5: 1765138 | CO5: 71 | CP5: 341323 | CQ5: 8 | CR5: 0 | CS5: 0 | CT5: 26442 | CU5: 29 | CV5: 1527688 | CW5: 72 | DC5: 0 | DD5: 5075 | DE5: 0 | DF5: 3401 | DG5: 150 | DH5: 50545 | DI5: 1050 | DJ5: 593798 | DK5: 1132.225 | DL5: Good | DM5: 2206.643 | DN5: Poor | DO5: 2461125 | DP5: 1 | DQ5: Avoids redirects | DR5: Server responds quickly (observed 181 ms) | DS5: Applies text compression | DU5: 2 resources found | DV5: 14240 | DX5: 5090 | DY5: 683140 | DZ5: 1 resource found | EA5: 990 | EB5: 4453 | EC5: 0 | ED5: 26491 | EF5: 665 | EG5: 21 resources found | EH5: 100 | EK5: 100 | EQ5: https://salesxceleration.com/blog/ | ER5: 46045.298
A6: https://salesxceleration.com/wp-content/uploads/2025/02/Fractional-Sales-Leader-1-1024x929.jpg | B6: =IFERROR(__xludf.DUMMYFUNCTION("REGEXREPLACE(A6, ""^https?://[^/]+"", """")"),"/wp-content/uploads/2025/02/Fractional-Sales-Leader-1-1024x929.jpg") -> /wp-content/uploads/2025/02/Fractional-Sales-Leader-1-1024x929.jpg | F6: image/jpeg | G6: 200 | H6: OK | I6: Indexable | L6: 0 | M6: 0 | O6: 0 | P6: 0 | R6: 0 | S6: 0 | U6: 0 | W6: 0 | Y6: 0 | AA6: 0 | AC6: 0 | AM6: 115655 | AN6: 115655 | AO6: 115655 | AP6: 44.305 | AR6: 0 | AW6: 0 | AX6: 1 | AY6: 4 | BA6: 0 | BB6: 0 | BC6: 0 | BD6: 0 | BE6: 0 | BF6: 0 | BG6: 0 | BH6: 0 | BI6: 0 | BJ6: 0 | BP6: 0.282 | BQ6: Wed, 26 Feb 2025 14:31:07 GMT | BV6: 1.1 | EQ6: https://salesxceleration.com/wp-content/uploads/2025/02/Fractional-Sales-Leader-1-1024x929.jpg | ER6: 46045.298
A7: https://salesxceleration.com/wp-includes/js/dist/hooks.min.js?ver=dd5603f07f9220ed27f1 | B7: =IFERROR(__xludf.DUMMYFUNCTION("REGEXREPLACE(A7, ""^https?://[^/]+"", """")"),"/wp-includes/js/dist/hooks.min.js?ver=dd5603f07f9220ed27f1") -> /wp-includes/js/dist/hooks.min.js?ver=dd5603f07f9220ed27f1 | F7: application/javascript | G7: 200 | H7: OK | I7: Indexable | L7: 0 | M7: 0 | O7: 0 | P7: 0 | R7: 0 | S7: 0 | U7: 0 | W7: 0 | Y7: 0 | AA7: 0 | AC7: 0 | AM7: 1941 | AN7: 1941 | AO7: 1941 | AP7: 0.744 | AR7: 0 | AW7: 0 | AX7: 1 | AY7: 3 | BA7: 0 | BB7: 0 | BC7: 0 | BD7: 0 | BE7: 0 | BF7: 0 | BG7: 0 | BH7: 0 | BI7: 0 | BJ7: 0 | BP7: 0.274 | BQ7: Fri, 02 Jan 2026 17:49:24 GMT | BV7: 1.1 | EQ7: https://salesxceleration.com/wp-includes/js/dist/hooks.min.js?ver=dd5603f07f9220ed27f1 | ER7: 46045.298
A8: https://salesxceleration.com/client-solutions/ | B8: =IFERROR(__xludf.DUMMYFUNCTION("REGEXREPLACE(A8, ""^https?://[^/]+"", """")"),"/client-solutions/") -> /client-solutions/ | C8: Tailored Sales Solutions for Your Business | D8: Fractional Sales Leader: Your Source for Sales Success | E8: Certified Sales Operating Management SystemTM | F8: text/html; charset=UTF-8 | G8: 200 | H8: OK | I8: Indexable | K8: Expert Sales Consulting & Growth Strategies | Sales Xceleration | L8: 63 | M8: 566 | O8: 0 | P8: 0 | Q8: Unlock business success with Sales Xceleration's expert sales consulting and proven sales growth strategies to build a high-performing team and drive revenue growth. | R8: 165 | S8: 1029 | U8: 0 | V8: Tailored Sales Solutions for Your Business | W8: 42 | Y8: 0 | Z8: Fractional Sales Leader: Your Source for Sales Success | AA8: 54 | AB8: Certified Sales Operating Management SystemTM | AC8: 45 | AD8: follow, index, max-snippet:-1, max-video-preview:-1, max-image-preview:large | AG8: https://salesxceleration.com/client-solutions/ | AM8: 185916 | AN8: 32816 | AO8: 32816 | AP8: 12.571 | AR8: 1161 | AS8: 189 | AT8: 6.143 | AU8: 58.07 | AV8: Fairly Hard | AW8: 5.276 | AX8: 1 | AY8: 1 | AZ8: 51 | BA8: 3028 | BB8: 754 | BC8: 0 | BD8: 100 | BE8: 133 | BF8: 42 | BG8: 0 | BH8: 18 | BI8: 9 | BJ8: 0 | BO8: 7fb40fed596000750dd96c59c0d6edf2 | BP8: 2.036 | BU8: en-US | BV8: 1.1 | BW8: 52 | BX8: 3451.03 | BY8: 6824.549 | BZ8: 7651.07 | CA8: 18030.395 | CB8: 423 | CC8: 0.008 | CD8: 652554 | CE8: 1050 | CF8: 165 | CG8: 2580585 | CH8: 34342 | CI8: 2 | CJ8: 342637 | CK8: 22 | CL8: 113095 | CM8: 37 | CN8: 1749022 | CO8: 69 | CP8: 316830 | CQ8: 7 | CR8: 0 | CS8: 0 | CT8: 24659 | CU8: 28 | CV8: 1526775 | CW8: 69 | DC8: 0 | DD8: 5075 | DE8: 0 | DF8: 3396 | DG8: 150 | DH8: 50502 | DI8: 900 | DJ8: 593581 | DK8: 1776.936 | DL8: Poor | DM8: 3219.756 | DN8: Poor | DO8: 2580157 | DP8: 1 | DQ8: Avoids redirects | DR8: Server responds quickly (observed 171 ms) | DS8: Applies text compression | DT8: 1 issue found | DU8: 4 resources found | DV8: 12640 | DX8: 3806 | DY8: 731215 | DZ8: 1 resource found | EA8: 1024 | EB8: 29477 | EC8: 1 | ED8: 26491 | EF8: 260 | EG8: 21 resources found | EH8: 100 | EK8: 100 | EQ8: https://salesxceleration.com/client-solutions/ | ER8: 46045.298
A9: https://salesxceleration.com/wp-content/plugins/elementor/assets/css/frontend.min.css?ver=3.34.0 | B9: =IFERROR(__xludf.DUMMYFUNCTION("REGEXREPLACE(A9, ""^https?://[^/]+"", """")"),"/wp-content/plugins/elementor/assets/css/frontend.min.css?ver=3.34.0") -> /wp-content/plugins/elementor/assets/css/frontend.min.css?ver=3.34.0 | F9: text/css | G9: 200 | H9: OK | I9: Indexable | L9: 0 | M9: 0 | O9: 0 | P9: 0 | R9: 0 | S9: 0 | U9: 0 | W9: 0 | Y9: 0 | AA9: 0 | AC9: 0 | AM9: 7244 | AN9: 7244 | AO9: 7244 | AP9: 2.775 | AR9: 0 | AW9: 0 | AX9: 1 | AY9: 5 | BA9: 0 | BB9: 0 | BC9: 0 | BD9: 0 | BE9: 0 | BF9: 0 | BG9: 0 | BH9: 0 | BI9: 0 | BJ9: 0 | BP9: 0.282 | BQ9: Fri, 02 Jan 2026 17:29:45 GMT | BV9: 1.1 | EQ9: https://salesxceleration.com/wp-content/plugins/elementor/assets/css/frontend.min.css?ver=3.34.0 | ER9: 46045.298
A10: https://salesxceleration.com/sales-team/ | B10: =IFERROR(__xludf.DUMMYFUNCTION("REGEXREPLACE(A10, ""^https?://[^/]+"", """")"),"/sales-team/") -> /sales-team/ | C10: Sales Team Development Services | D10: Your Foundation for Scalable and Efficient Growth | E10: Read Real Success Stories | F10: text/html; charset=UTF-8 | G10: 200 | H10: OK | I10: Indexable | K10: Sales Team Development | Build, Lead & Train High-Performing Sales Teams | L10: 72 | M10: 684 | O10: 0 | P10: 0 | Q10: Develop your sales team with Sales Xceleration’s proven recruiting, leadership, and training solutions from experienced fractional leaders. Get connected today. | R10: 160 | S10: 979 | U10: 0 | V10: Sales Team Development Services | W10: 31 | Y10: 0 | Z10: Your Foundation for Scalable and Efficient Growth | AA10: 49 | AB10: Read Real Success Stories | AC10: 25 | AD10: follow, index, max-snippet:-1, max-video-preview:-1, max-image-preview:large | AG10: https://salesxceleration.com/sales-team/ | AM10: 585622 | AN10: 167805 | AO10: 167805 | AP10: 64.283 | AR10: 1167 | AS10: 193 | AT10: 6.047 | AU10: 58.103 | AV10: Fairly Hard | AW10: 1.87 | AX10: 1 | AY10: 1 | AZ10: 51 | BA10: 2289 | BB10: 754 | BC10: 0 | BD10: 100 | BE10: 134 | BF10: 45 | BG10: 0 | BH10: 16 | BI10: 8 | BJ10: 0 | BO10: fc7092c005ccb140fcb0f92815f24b98 | BP10: 1.037 | BU10: en-US | BV10: 1.1 | BW10: 43 | BX10: 4051.026 | BY10: 8900.939 | BZ10: 6913.624 | CA10: 19438.924 | CB10: 699.031 | CC10: 0.008 | CD10: 664646 | CE10: 1360 | CF10: 179 | CG10: 2394913 | CH10: 159012 | CI10: 2 | CJ10: 17648 | CK10: 23 | CL10: 127574 | CM10: 47 | CN10: 1798717 | CO10: 72 | CP10: 266193 | CQ10: 6 | CR10: 0 | CS10: 0 | CT10: 25769 | CU10: 29 | CV10: 1526933 | CW10: 74 | DC10: 0 | DD10: 5075 | DE10: 0 | DF10: 3396 | DG10: 300 | DH10: 40162 | DI10: 1060 | DJ10: 616013 | DK10: 2127.931 | DL10: Poor | DM10: 5281.125 | DN10: Poor | DO10: 2394746 | DP10: 1 | DQ10: Avoids redirects | DR10: Server responds quickly (observed 516 ms) | DS10: Applies text compression | DU10: 2 resources found | DV10: 14996 | DW10: 321 | DX10: 4067 | DY10: 606926 | DZ10: 1 resource found | EA10: 1711 | EB10: 4453 | EC10: 55 | ED10: 26491 | EF10: 400 | EG10: 21 resources found | EH10: 100 | EK10: 100 | EQ10: https://salesxceleration.com/sales-team/ | ER10: 46045.298
A11: https://salesxceleration.com/state-of-sales/ | B11: =IFERROR(__xludf.DUMMYFUNCTION("REGEXREPLACE(A11, ""^https?://[^/]+"", """")"),"/state-of-sales/") -> /state-of-sales/ | C11: 2025 State of Sales | Small to Mid-Size Businesses | D11: The State of Sales: Crafting High-Performing Sales Organizations | E11: Sales Strategy | F11: text/html; charset=UTF-8 | G11: 200 | H11: OK | I11: Indexable | K11: State of Sales Report | Trends and Insights | Sales Xceleration | L11: 63 | M11: 550 | O11: 0 | P11: 0 | Q11: Get the latest sales performance trends and insights with Sales Xceleration's State of Sales report. Enhance your sales strategy. | R11: 129 | S11: 786 | U11: 0 | V11: 2025 State of Sales | Small to Mid-Size Businesses | W11: 50 | Y11: 0 | Z11: The State of Sales: Crafting High-Performing Sales Organizations | AA11: 64 | AB11: Sales Strategy | AC11: 14 | AD11: follow, index, max-snippet:-1, max-video-preview:-1, max-image-preview:large | AG11: https://salesxceleration.com/state-of-sales/ | AM11: 327338 | AN11: 48949 | AO11: 48949 | AP11: 18.751 | AR11: 1964 | AS11: 332 | AT11: 5.916 | AU11: 58.423 | AV11: Fairly Hard | AW11: 4.576 | AX11: 1 | AY11: 1 | AZ11: 51 | BA11: 2268 | BB11: 754 | BC11: 0 | BD11: 100 | BE11: 139 | BF11: 47 | BG11: 0 | BH11: 18 | BI11: 8 | BJ11: 0 | BO11: cfe8f6e611a808b12a2a28ed209d7de0 | BP11: 1.124 | BU11: en-US | BV11: 1.1 | BW11: 56 | BX11: 3901.013 | BY11: 7851.421 | BZ11: 7051.025 | CA11: 19822.342 | CB11: 264 | CC11: 0 | CD11: 689726 | CE11: 750 | CF11: 213 | CG11: 2595260 | CH11: 49362 | CI11: 2 | CJ11: 151823 | CK11: 34 | CL11: 166879 | CM11: 56 | CN11: 1857672 | CO11: 82 | CP11: 343690 | CQ11: 8 | CR11: 0 | CS11: 1 | CT11: 25834 | CU11: 30 | CV11: 1531214 | CW11: 81 | DC11: 0 | DD11: 5075 | DE11: 0 | DF11: 3396 | DG11: 150 | DH11: 68104 | DI11: 600 | DJ11: 613151 | DK11: 1640.404 | DL11: Poor | DM11: 4453.969 | DN11: Poor | DO11: 2594526 | DP11: 1 | DQ11: Avoids redirects | DR11: Server responds quickly (observed 324 ms) | DS11: Applies text compression | DU11: 2 resources found | DV11: 16557 | DX11: 4531 | DY11: 729205 | EA11: 1645 | EB11: 4453 | EC11: 50 | ED11: 26491 | EF11: 230 | EG11: 22 resources found | EH11: 100 | EK11: 100 | EQ11: https://salesxceleration.com/state-of-sales/ | ER11: 46045.298
A12: https://salesxceleration.com/industries/private-equity/ | B12: =IFERROR(__xludf.DUMMYFUNCTION("REGEXREPLACE(A12, ""^https?://[^/]+"", """")"),"/industries/private-equity/") -> /industries/private-equity/ | C12: Fractional Sales Leadership for Private Equity | D12: Key Sales Challenges in Private Equity | E12: Why Fractional Sales Leadership Fits Private Equity | F12: text/html; charset=UTF-8 | G12: 200 | H12: OK | I12: Indexable | K12: Fractional Sales Leadership for Private Equity | Sales Xceleration | L12: 66 | M12: 576 | O12: 0 | P12: 0 | Q12: Accelerate portfolio company growth with fractional sales leadership. We drive revenue and maximize exit multiples. Schedule a Consultation. | R12: 140 | S12: 870 | U12: 0 | V12: Fractional Sales Leadership for Private Equity | W12: 46 | Y12: 0 | Z12: Key Sales Challenges in Private Equity | AA12: 38 | AB12: Why Fractional Sales Leadership Fits Private Equity | AC12: 51 | AD12: follow, index, max-snippet:-1, max-video-preview:-1, max-image-preview:large | AG12: https://salesxceleration.com/industries/private-equity/ | AM12: 277166 | AN12: 90934 | AO12: 90934 | AP12: 34.835 | AR12: 1569 | AS12: 258 | AT12: 6.081 | AU12: 52.275 | AV12: Fairly Hard | AW12: 6.515 | AX12: 1 | AY12: 2 | AZ12: 51 | BA12: 2250 | BB12: 754 | BC12: 0 | BD12: 100 | BE12: 136 | BF12: 47 | BG12: 0 | BH12: 16 | BI12: 8 | BJ12: 0 | BO12: 5cd596601cdc2f7e876c4bb3fef0d1ef | BP12: 1.096 | BU12: en-US | BV12: 1.1 | BW12: 62 | BX12: 3751.009 | BY12: 7966.564 | BZ12: 6977.017 | CA12: 17927.074 | CB12: 64.5 | CC12: 0.023 | CD12: 672681 | CE12: 750 | CF12: 179 | CG12: 3144053 | CH12: 89262 | CI12: 2 | CJ12: 762997 | CK12: 27 | CL12: 126361 | CM12: 44 | CN12: 1791292 | CO12: 71 | CP12: 348792 | CQ12: 6 | CR12: 0 | CS12: 0 | CT12: 25349 | CU12: 29 | CV12: 1504890 | CW12: 76 | DC12: 0 | DD12: 5075 | DE12: 0 | DF12: 3396 | DG12: 150 | DH12: 50543 | DI12: 600 | DJ12: 613667 | DK12: 1137.666 | DL12: Good | DM12: 2152.411 | DN12: Poor | DO12: 3143891 | DP12: 1 | DQ12: Avoids redirects | DR12: Server responds quickly (observed 339 ms) | DS12: Applies text compression | DU12: 2 resources found | DV12: 13847 | DX12: 3934 | DY12: 943387 | DZ12: 1 resource found | EA12: 1177 | EB12: 499109 | EC12: 50 | ED12: 26491 | EF12: 240 | EG12: 21 resources found | EH12: 100 | EK12: 100 | EQ12: https://salesxceleration.com/industries/private-equity/ | ER12: 46045.298
A13: https://salesxceleration.com/wp-content/plugins/elementor-pro/assets/js/webpack-pro.runtime.min.js?ver=3.34.0 | B13: =IFERROR(__xludf.DUMMYFUNCTION("REGEXREPLACE(A13, ""^https?://[^/]+"", """")"),"/wp-content/plugins/elementor-pro/assets/js/webpack-pro.runtime.min.js?ver=3.34.0") -> /wp-content/plugins/elementor-pro/assets/js/webpack-pro.runtime.min.js?ver=3.34.0 | F13: application/javascript | G13: 200 | H13: OK | I13: Indexable | L13: 0 | M13: 0 | O13: 0 | P13: 0 | R13: 0 | S13: 0 | U13: 0 | W13: 0 | Y13: 0 | AA13: 0 | AC13: 0 | AM13: 2856 | AN13: 2856 | AO13: 2856 | AP13: 1.094 | AR13: 0 | AW13: 0 | AX13: 1 | AY13: 5 | BA13: 0 | BB13: 0 | BC13: 0 | BD13: 0 | BE13: 0 | BF13: 0 | BG13: 0 | BH13: 0 | BI13: 0 | BJ13: 0 | BP13: 0.279 | BQ13: Fri, 02 Jan 2026 17:52:08 GMT | BV13: 1.1 | EQ13: https://salesxceleration.com/wp-content/plugins/elementor-pro/assets/js/webpack-pro.runtime.min.js?ver=3.34.0 | ER13: 46045.298
A14: https://salesxceleration.com/wp-content/uploads/2022/09/ciobulletin-50-best-companies-to-watch-2022-logo.jpg | B14: =IFERROR(__xludf.DUMMYFUNCTION("REGEXREPLACE(A14, ""^https?://[^/]+"", """")"),"/wp-content/uploads/2022/09/ciobulletin-50-best-companies-to-watch-2022-logo.jpg") -> /wp-content/uploads/2022/09/ciobulletin-50-best-companies-to-watch-2022-logo.jpg | F14: image/jpeg | G14: 200 | H14: OK | I14: Indexable | L14: 0 | M14: 0 | O14: 0 | P14: 0 | R14: 0 | S14: 0 | U14: 0 | W14: 0 | Y14: 0 | AA14: 0 | AC14: 0 | AM14: 30241 | AN14: 30241 | AO14: 30241 | AP14: 11.585 | AR14: 0 | AW14: 0 | AX14: 1 | AY14: 4 | BA14: 0 | BB14: 0 | BC14: 0 | BD14: 0 | BE14: 0 | BF14: 0 | BG14: 0 | BH14: 0 | BI14: 0 | BJ14: 0 | BP14: 0.267 | BQ14: Thu, 22 Sep 2022 17:13:23 GMT | BV14: 1.1 | EQ14: https://salesxceleration.com/wp-content/uploads/2022/09/ciobulletin-50-best-companies-to-watch-2022-logo.jpg | ER14: 46045.298
A15: https://salesxceleration.com/wp-content/themes/salesxceleratione/assets/js/jquery.mixitup.js?ver=2.1.11 | B15: =IFERROR(__xludf.DUMMYFUNCTION("REGEXREPLACE(A15, ""^https?://[^/]+"", """")"),"/wp-content/themes/salesxceleratione/assets/js/jquery.mixitup.js?ver=2.1.11") -> /wp-content/themes/salesxceleratione/assets/js/jquery.mixitup.js?ver=2.1.11 | F15: application/javascript | G15: 200 | H15: OK | I15: Indexable | L15: 0 | M15: 0 | O15: 0 | P15: 0 | R15: 0 | S15: 0 | U15: 0 | W15: 0 | Y15: 0 | AA15: 0 | AC15: 0 | AM15: 11141 | AN15: 11141 | AO15: 11141 | AP15: 4.268 | AR15: 0 | AW15: 0 | AX15: 1 | AY15: 5 | BA15: 0 | BB15: 0 | BC15: 0 | BD15: 0 | BE15: 0 | BF15: 0 | BG15: 0 | BH15: 0 | BI15: 0 | BJ15: 0 | BP15: 0.267 | BQ15: Fri, 12 Nov 2021 15:43:34 GMT | BV15: 1.1 | EQ15: https://salesxceleration.com/wp-content/themes/salesxceleratione/assets/js/jquery.mixitup.js?ver=2.1.11 | ER15: 46045.298
A16: https://salesxceleration.com/wp-content/uploads/2025/04/logo-eos-300x198-1.png | B16: =IFERROR(__xludf.DUMMYFUNCTION("REGEXREPLACE(A16, ""^https?://[^/]+"", """")"),"/wp-content/uploads/2025/04/logo-eos-300x198-1.png") -> /wp-content/uploads/2025/04/logo-eos-300x198-1.png | F16: image/png | G16: 200 | H16: OK | I16: Indexable | L16: 0 | M16: 0 | O16: 0 | P16: 0 | R16: 0 | S16: 0 | U16: 0 | W16: 0 | Y16: 0 | AA16: 0 | AC16: 0 | AM16: 38512 | AN16: 38512 | AO16: 38512 | AP16: 14.753 | AR16: 0 | AW16: 0 | AX16: 1 | AY16: 4 | BA16: 0 | BB16: 0 | BC16: 0 | BD16: 0 | BE16: 0 | BF16: 0 | BG16: 0 | BH16: 0 | BI16: 0 | BJ16: 0 | BP16: 0.318 | BQ16: Wed, 16 Apr 2025 14:18:45 GMT | BV16: 1.1 | EQ16: https://salesxceleration.com/wp-content/uploads/2025/04/logo-eos-300x198-1.png | ER16: 46045.298
A17: https://salesxceleration.com/case-study/electrical-manufacturing-sales-strategy-and-processes-provide-immediate-growth/ | B17: =IFERROR(__xludf.DUMMYFUNCTION("REGEXREPLACE(A17, ""^https?://[^/]+"", """")"),"/case-study/electrical-manufacturing-sales-strategy-and-processes-provide-immediate-growth/") -> /case-study/electrical-manufacturing-sales-strategy-and-processes-provide-immediate-growth/ | C17: Electrical Manufacturing: Sales Strategy and Processes Provide Immediate Growth | D17: Executive Summary | E17: The Big Win | F17: text/html; charset=UTF-8 | G17: 200 | H17: OK | I17: Indexable | K17: Case Study - Electrical Manufacturer Grows 65%+ with Sales Strategy | L17: 67 | M17: 616 | O17: 0 | P17: 0 | Q17: With expert guidance from an Outsourced VP of Sales, an electrical manufacturer achieved 20% quarterly growth, setting the stage for 65% year-over-year gains. | R17: 158 | S17: 987 | U17: 0 | V17: Electrical Manufacturing: Sales Strategy and Processes Provide Immediate Growth | W17: 79 | Y17: 0 | Z17: Executive Summary | AA17: 17 | AB17: The Big Win | AC17: 11 | AD17: follow, index, max-snippet:-1, max-video-preview:-1, max-image-preview:large | AG17: https://salesxceleration.com/case-study/electrical-manufacturing-sales-strategy-and-processes-provide-immediate-growth/ | AM17: 184741 | AN17: 31627 | AO17: 31627 | AP17: 12.116 | AR17: 895 | AS17: 144 | AT17: 6.215 | AU17: 60.629 | AV17: Normal | AW17: 4.31 | AX17: 1 | AY17: 2 | AZ17: 3 | BA17: 6 | BB17: 4 | BC17: 0 | BD17: 0.53 | BE17: 129 | BF17: 48 | BG17: 0 | BH17: 16 | BI17: 8 | BJ17: 0 | BO17: 32d1911981741b746084633baa3673fa | BP17: 0.99 | BU17: en-US | BV17: 1.1 | BW17: 53 | BX17: 3751.032 | BY17: 8026.796 | BZ17: 9901.088 | CA17: 18141.576 | CB17: 314.345 | CC17: 0 | CD17: 652646 | CE17: 1350 | CF17: 166 | CG17: 2308729 | CH17: 32604 | CI17: 2 | CJ17: 98677 | CK17: 19 | CL17: 119133 | CM17: 43 | CN17: 1747804 | CO17: 68 | CP17: 284714 | CQ17: 6 | CR17: 0 | CS17: 0 | CT17: 25797 | CU17: 28 | CV17: 1505043 | CW17: 65 | DC17: 150 | DD17: 5075 | DE17: 0 | DF17: 3396 | DG17: 150 | DH17: 50530 | DI17: 1050 | DJ17: 593645 | DK17: 1480.596 | DL17: Poor | DM17: 2748.634 | DN17: Poor | DO17: 2307948 | DP17: 1 | DQ17: Avoids redirects | DR17: Server responds quickly (observed 169 ms) | DS17: Applies text compression | DT17: 1 issue found | DU17: 4 resources found | DV17: 14547 | DW17: 314 | DX17: 4898 | DY17: 631708 | EA17: 928 | EB17: 4453 | EC17: 1 | ED17: 26491 | EF17: 245 | EG17: 21 resources found | EH17: 100 | EK17: 100 | EQ17: https://salesxceleration.com/case-study/electrical-manufacturing-sales-strategy-and-processes-provide-immediate-growth/ | ER17: 46045.298
A18: https://salesxceleration.com/wp-content/plugins/elementor/assets/css/widget-video.min.css?ver=3.34.0 | B18: =IFERROR(__xludf.DUMMYFUNCTION("REGEXREPLACE(A18, ""^https?://[^/]+"", """")"),"/wp-content/plugins/elementor/assets/css/widget-video.min.css?ver=3.34.0") -> /wp-content/plugins/elementor/assets/css/widget-video.min.css?ver=3.34.0 | F18: text/css | G18: 200 | H18: OK | I18: Indexable | L18: 0 | M18: 0 | O18: 0 | P18: 0 | R18: 0 | S18: 0 | U18: 0 | W18: 0 | Y18: 0 | AA18: 0 | AC18: 0 | AM18: 404 | AN18: 404 | AO18: 404 | AP18: 0.155 | AR18: 0 | AW18: 0 | AX18: 1 | AY18: 5 | BA18: 0 | BB18: 0 | BC18: 0 | BD18: 0 | BE18: 0 | BF18: 0 | BG18: 0 | BH18: 0 | BI18: 0 | BJ18: 0 | BP18: 0.265 | BQ18: Fri, 02 Jan 2026 17:29:45 GMT | BV18: 1.1 | EQ18: https://salesxceleration.com/wp-content/plugins/elementor/assets/css/widget-video.min.css?ver=3.34.0 | ER18: 46045.298
A19: https://salesxceleration.com/wp-content/uploads/elementor/google-fonts/css/robotoslab.css?ver=1744026309 | B19: =IFERROR(__xludf.DUMMYFUNCTION("REGEXREPLACE(A19, ""^https?://[^/]+"", """")"),"/wp-content/uploads/elementor/google-fonts/css/robotoslab.css?ver=1744026309") -> /wp-content/uploads/elementor/google-fonts/css/robotoslab.css?ver=1744026309 | F19: text/css | G19: 200 | H19: OK | I19: Indexable | L19: 0 | M19: 0 | O19: 0 | P19: 0 | R19: 0 | S19: 0 | U19: 0 | W19: 0 | Y19: 0 | AA19: 0 | AC19: 0 | AM19: 944 | AN19: 944 | AO19: 944 | AP19: 0.362 | AR19: 0 | AW19: 0 | AX19: 1 | AY19: 5 | BA19: 0 | BB19: 0 | BC19: 0 | BD19: 0 | BE19: 0 | BF19: 0 | BG19: 0 | BH19: 0 | BI19: 0 | BJ19: 0 | BP19: 0.265 | BQ19: Mon, 07 Apr 2025 11:45:09 GMT | BV19: 1.1 | EQ19: https://salesxceleration.com/wp-content/uploads/elementor/google-fonts/css/robotoslab.css?ver=1744026309 | ER19: 46045.298
A20: https://salesxceleration.com/case-study/healthcare-consulting-driving-growth-through-effective-strategy-execution-and-training/ | B20: =IFERROR(__xludf.DUMMYFUNCTION("REGEXREPLACE(A20, ""^https?://[^/]+"", """")"),"/case-study/healthcare-consulting-driving-growth-through-effective-strategy-execution-and-training/") -> /case-study/healthcare-consulting-driving-growth-through-effective-strategy-execution-and-training/ | C20: Healthcare Consulting: Driving Growth Through Effective Strategy, Execution, and Training | D20: Executive Summary | E20: The Big Win | F20: text/html; charset=UTF-8 | G20: 200 | H20: OK | I20: Indexable | K20: Case Study - Healthcare Company Grows 45% with Sales Strategy | L20: 61 | M20: 584 | O20: 0 | P20: 0 | Q20: See how a healthcare consulting company partnered with an Outsourced VP of Sales to improve strategy execution, train teams, and drive sustainable growth. | R20: 154 | S20: 977 | U20: 0 | V20: Healthcare Consulting: Driving Growth Through Effective Strategy, Execution, and Training | W20: 89 | Y20: 0 | Z20: Executive Summary | AA20: 17 | AB20: The Big Win | AC20: 11 | AD20: follow, index, max-snippet:-1, max-video-preview:-1, max-image-preview:large | AG20: https://salesxceleration.com/case-study/healthcare-consulting-driving-growth-through-effective-strategy-execution-and-training/ | AM20: 181876 | AN20: 31797 | AO20: 31797 | AP20: 12.181 | AR20: 922 | AS20: 150 | AT20: 6.147 | AU20: 59.29 | AV20: Fairly Hard | AW20: 4.508 | AX20: 1 | AY20: 2 | AZ20: 2 | BA20: 8 | BB20: 4 | BC20: 0 | BD20: 0.53 | BE20: 131 | BF20: 48 | BG20: 0 | BH20: 16 | BI20: 8 | BJ20: 0 | BO20: 69d96f70d37d737e457b09b1cd80ef2 | BP20: 1.003 | BU20: en-US | BV20: 1.1 | BW20: 59 | BX20: 4201.043 | BY20: 6201.606 | BZ20: 9151.098 | CA20: 18472.811 | CB20: 166.5 | CC20: 0 | CD20: 651545 | CE20: 1500 | CF20: 167 | CG20: 2311614 | CH20: 32923 | CI20: 2 | CJ20: 100556 | CK20: 19 | CL20: 119156 | CM20: 43 | CN20: 1748093 | CO20: 68 | CP20: 284714 | CQ20: 6 | CR20: 0 | CS20: 0 | CT20: 26172 | CU20: 29 | CV20: 1506101 | CW20: 65 | DC20: 150 | DD20: 5075 | DE20: 0 | DF20: 3396 | DG20: 300 | DH20: 50530 | DI20: 1050 | DJ20: 592544 | DK20: 1201.831 | DL20: Good | DM20: 2287.766 | DN20: Poor | DO20: 2310938 | DP20: 1 | DQ20: Avoids redirects | DR20: Server responds quickly (observed 173 ms) | DS20: Applies text compression | DT20: 1 issue found | DU20: 4 resources found | DV20: 13876 | DX20: 3757 | DY20: 632077 | EA20: 928 | EB20: 4453 | EC20: 0 | ED20: 26491 | EF20: 235 | EG20: 21 resources found | EH20: 100 | EK20: 100 | EQ20: https://salesxceleration.com/case-study/healthcare-consulting-driving-growth-through-effective-strategy-execution-and-training/ | ER20: 46045.298
A21: https://salesxceleration.com/wp-content/plugins/elementor/assets/js/webpack.runtime.min.js?ver=3.34.0 | B21: =IFERROR(__xludf.DUMMYFUNCTION("REGEXREPLACE(A21, ""^https?://[^/]+"", """")"),"/wp-content/plugins/elementor/assets/js/webpack.runtime.min.js?ver=3.34.0") -> /wp-content/plugins/elementor/assets/js/webpack.runtime.min.js?ver=3.34.0 | F21: application/javascript | G21: 200 | H21: OK | I21: Indexable | L21: 0 | M21: 0 | O21: 0 | P21: 0 | R21: 0 | S21: 0 | U21: 0 | W21: 0 | Y21: 0 | AA21: 0 | AC21: 0 | AM21: 2476 | AN21: 2476 | AO21: 2476 | AP21: 0.949 | AR21: 0 | AW21: 0 | AX21: 1 | AY21: 5 | BA21: 0 | BB21: 0 | BC21: 0 | BD21: 0 | BE21: 0 | BF21: 0 | BG21: 0 | BH21: 0 | BI21: 0 | BJ21: 0 | BP21: 0.259 | BQ21: Fri, 02 Jan 2026 17:29:45 GMT | BV21: 1.1 | EQ21: https://salesxceleration.com/wp-content/plugins/elementor/assets/js/webpack.runtime.min.js?ver=3.34.0 | ER21: 46045.298
A22: https://salesxceleration.com/wp-content/uploads/2023/05/spring23.png | B22: =IFERROR(__xludf.DUMMYFUNCTION("REGEXREPLACE(A22, ""^https?://[^/]+"", """")"),"/wp-content/uploads/2023/05/spring23.png") -> /wp-content/uploads/2023/05/spring23.png | F22: image/png | G22: 200 | H22: OK | I22: Indexable | L22: 0 | M22: 0 | O22: 0 | P22: 0 | R22: 0 | S22: 0 | U22: 0 | W22: 0 | Y22: 0 | AA22: 0 | AC22: 0 | AM22: 24222 | AN22: 24222 | AO22: 24222 | AP22: 9.279 | AR22: 0 | AW22: 0 | AX22: 1 | AY22: 4 | BA22: 0 | BB22: 0 | BC22: 0 | BD22: 0 | BE22: 0 | BF22: 0 | BG22: 0 | BH22: 0 | BI22: 0 | BJ22: 0 | BP22: 1.157 | BQ22: Mon, 15 May 2023 14:07:42 GMT | BV22: 1.1 | EQ22: https://salesxceleration.com/wp-content/uploads/2023/05/spring23.png | ER22: 46045.298
A23: https://salesxceleration.com/wp-content/plugins/elementor/assets/lib/font-awesome/css/fontawesome.min.css?ver=5.15.3 | B23: =IFERROR(__xludf.DUMMYFUNCTION("REGEXREPLACE(A23, ""^https?://[^/]+"", """")"),"/wp-content/plugins/elementor/assets/lib/font-awesome/css/fontawesome.min.css?ver=5.15.3") -> /wp-content/plugins/elementor/assets/lib/font-awesome/css/fontawesome.min.css?ver=5.15.3 | F23: text/css | G23: 200 | H23: OK | I23: Indexable | L23: 0 | M23: 0 | O23: 0 | P23: 0 | R23: 0 | S23: 0 | U23: 0 | W23: 0 | Y23: 0 | AA23: 0 | AC23: 0 | AM23: 12617 | AN23: 12617 | AO23: 12617 | AP23: 4.833 | AR23: 0 | AW23: 0 | AX23: 1 | AY23: 7 | BA23: 0 | BB23: 0 | BC23: 0 | BD23: 0 | BE23: 0 | BF23: 0 | BG23: 0 | BH23: 0 | BI23: 0 | BJ23: 0 | BP23: 0.265 | BQ23: Fri, 02 Jan 2026 17:29:45 GMT | BV23: 1.1 | EQ23: https://salesxceleration.com/wp-content/plugins/elementor/assets/lib/font-awesome/css/fontawesome.min.css?ver=5.15.3 | ER23: 46045.298
A24: https://salesxceleration.com/industries/professional-services/ | B24: =IFERROR(__xludf.DUMMYFUNCTION("REGEXREPLACE(A24, ""^https?://[^/]+"", """")"),"/industries/professional-services/") -> /industries/professional-services/ | C24: Fractional Sales Leadership for Professional Services | D24: Scale Revenue in Competitive Markets | E24: Key Sales Challenges in Professional Services | F24: text/html; charset=UTF-8 | G24: 200 | H24: OK | I24: Indexable | K24: Fractional Sales Leadership for Professional Services | Sales Xceleration | L24: 73 | M24: 646 | N24: Sales Xceleration Infographic | O24: 29 | P24: 261 | Q24: Build a scalable growth engine for your professional services firm with Sales Xceleration. Reduce referral reliance, boost win rates, and forecast clarity. | R24: 155 | S24: 924 | U24: 0 | V24: Fractional Sales Leadership for Professional Services | W24: 53 | Y24: 0 | Z24: Scale Revenue in Competitive Markets | AA24: 36 | AB24: Key Sales Challenges in Professional Services | AC24: 45 | AD24: follow, index, max-snippet:-1, max-video-preview:-1, max-image-preview:large | AG24: https://salesxceleration.com/industries/professional-services/ | AM24: 280626 | AN24: 88706 | AO24: 88706 | AP24: 33.982 | AR24: 1819 | AS24: 312 | AT24: 5.83 | AU24: 46.042 | AV24: Hard | AW24: 7.334 | AX24: 1 | AY24: 2 | AZ24: 51 | BA24: 2250 | BB24: 754 | BC24: 0 | BD24: 100 | BE24: 135 | BF24: 47 | BG24: 0 | BH24: 16 | BI24: 8 | BJ24: 0 | BO24: f6bb664fc3313b13b83cd42e4b1ff7d8 | BP24: 1.074 | BU24: en-US | BV24: 1.1 | BW24: 49 | BX24: 4201.008 | BY24: 7227.322 | BZ24: 9752.021 | CA24: 19188.123 | CB24: 423.5 | CC24: 0.038 | CD24: 673030 | CE24: 1050 | CF24: 179 | CG24: 3185542 | CH24: 86177 | CI24: 2 | CJ24: 762833 | CK24: 25 | CL24: 127226 | CM24: 45 | CN24: 1791090 | CO24: 71 | CP24: 392582 | CQ24: 7 | CR24: 0 | CS24: 0 | CT24: 25634 | CU24: 29 | CV24: 1550132 | CW24: 76 | DC24: 0 | DD24: 5075 | DE24: 0 | DF24: 3396 | DG24: 450 | DH24: 50543 | DI24: 600 | DJ24: 614016 | DK24: 1835.702 | DL24: Poor | DM24: 3379.479 | DN24: Poor | DO24: 3185543 | DP24: 1 | DQ24: Avoids redirects | DR24: Server responds quickly (observed 332 ms) | DS24: Applies text compression | DU24: 2 resources found | DV24: 15651 | DX24: 3965 | DY24: 943111 | DZ24: 1 resource found | EA24: 1250 | EB24: 499109 | EC24: 32 | ED24: 26491 | EF24: 235 | EG24: 21 resources found | EH24: 100 | EK24: 100 | EQ24: https://salesxceleration.com/industries/professional-services/ | ER24: 46045.298
A25: https://salesxceleration.com/wp-content/uploads/2025/04/australia.png | B25: =IFERROR(__xludf.DUMMYFUNCTION("REGEXREPLACE(A25, ""^https?://[^/]+"", """")"),"/wp-content/uploads/2025/04/australia.png") -> /wp-content/uploads/2025/04/australia.png | F25: image/png | G25: 200 | H25: OK | I25: Indexable | L25: 0 | M25: 0 | O25: 0 | P25: 0 | R25: 0 | S25: 0 | U25: 0 | W25: 0 | Y25: 0 | AA25: 0 | AC25: 0 | AM25: 150307 | AN25: 150307 | AO25: 150307 | AP25: 57.58 | AR25: 0 | AW25: 0 | AX25: 1 | AY25: 4 | BA25: 0 | BB25: 0 | BC25: 0 | BD25: 0 | BE25: 0 | BF25: 0 | BG25: 0 | BH25: 0 | BI25: 0 | BJ25: 0 | BP25: 0.668 | BQ25: Fri, 11 Apr 2025 19:54:18 GMT | BV25: 1.1 | EQ25: https://salesxceleration.com/wp-content/uploads/2025/04/australia.png | ER25: 46045.298
A26: https://salesxceleration.com/ai-statement/ | B26: =IFERROR(__xludf.DUMMYFUNCTION("REGEXREPLACE(A26, ""^https?://[^/]+"", """")"),"/ai-statement/") -> /ai-statement/ | C26: AI Statement | F26: text/html; charset=UTF-8 | G26: 200 | H26: OK | I26: Indexable | K26: AI Statement | Sales Xceleration | L26: 32 | M26: 289 | O26: 0 | P26: 0 | Q26: In a world where AI is transforming businesses globally, Sales Xceleration recognizes its responsibility to share how we are harnessing this technology in an | R26: 157 | S26: 955 | U26: 0 | V26: AI Statement | W26: 12 | Y26: 0 | AA26: 0 | AC26: 0 | AD26: follow, index, max-snippet:-1, max-video-preview:-1, max-image-preview:large | AG26: https://salesxceleration.com/ai-statement/ | AM26: 149344 | AN26: 29324 | AO26: 29324 | AP26: 11.233 | AR26: 699 | AS26: 125 | AT26: 5.592 | AU26: 58.707 | AV26: Fairly Hard | AW26: 4.497 | AX26: 1 | AY26: 1 | AZ26: 47 | BA26: 748 | BB26: 747 | BC26: 0 | BD26: 99.07 | BE26: 122 | BF26: 42 | BG26: 0 | BH26: 16 | BI26: 8 | BJ26: 0 | BO26: 261a75fa614f3cdeb6c4fbb8c31d558a | BP26: 0.941 | BU26: en-US | BV26: 1.1 | BW26: 50 | BX26: 3001.043 | BY26: 6922.009 | BZ26: 5701.087 | CA26: 17468.092 | CB26: 672 | CC26: 0 | CD26: 651265 | CE26: 1200 | CF26: 163 | CG26: 2238257 | CH26: 30711 | CI26: 2 | CJ26: 78722 | CK26: 23 | CL26: 110645 | CM26: 36 | CN26: 1747211 | CO26: 67 | CP26: 244248 | CQ26: 5 | CR26: 0 | CS26: 0 | CT26: 26720 | CU26: 30 | CV26: 1505551 | CW26: 67 | DC26: 0 | DD26: 5075 | DE26: 0 | DF26: 3396 | DG26: 600 | DH26: 50517 | DI26: 600 | DJ26: 592277 | DK26: 2081.556 | DL26: Poor | DM26: 3544.882 | DN26: Poor | DO26: 2238175 | DP26: 1 | DQ26: Avoids redirects | DR26: Server responds quickly (observed 168 ms) | DS26: Applies text compression | DU26: 2 resources found | DV26: 12189 | DX26: 3893 | DY26: 604193 | DZ26: 1 resource found | EA26: 765 | EB26: 27429 | EC26: 1 | ED26: 26492 | EF26: 235 | EG26: 21 resources found | EH26: 100 | EK26: 100 | EQ26: https://salesxceleration.com/ai-statement/ | ER26: 46045.298
A27: https://salesxceleration.com/podcasts/ | B27: =IFERROR(__xludf.DUMMYFUNCTION("REGEXREPLACE(A27, ""^https?://[^/]+"", """")"),"/podcasts/") -> /podcasts/ | C27: Sales Against The Odds | D27: Latest Episode | E27: Episode Library | F27: text/html; charset=UTF-8 | G27: 200 | H27: OK | I27: Indexable | K27: Sales Against The Odds Podcast | Sales Xceleration | L27: 50 | M27: 461 | O27: 0 | P27: 0 | Q27: Tune into Sales Against The Odds, the podcast for SMB leaders. Host Lee Brumbaugh and expert guests share proven sales strategies to help you grow, even when the odds are stacked against you. | R27: 191 | S27: 1215 | U27: 0 | V27: Sales Against The Odds | W27: 22 | Y27: 0 | Z27: Latest Episode | AA27: 14 | AB27: Episode Library | AC27: 15 | AD27: follow, index, max-snippet:-1, max-video-preview:-1, max-image-preview:large | AG27: https://salesxceleration.com/podcasts/ | AM27: 205629 | AN27: 33795 | AO27: 33795 | AP27: 12.946 | AR27: 1059 | AS27: 174 | AT27: 6.086 | AU27: 65.17 | AV27: Normal | AW27: 4.349 | AX27: 1 | AY27: 1 | AZ27: 51 | BA27: 2983 | BB27: 754 | BC27: 0 | BD27: 100 | BE27: 129 | BF27: 48 | BG27: 0 | BH27: 20 | BI27: 12 | BJ27: 0 | BO27: 1f250ab77ababefcca6cb53f7689af3c | BP27: 1.244 | BU27: en-US | BV27: 1.1 | BW27: 48 | BX27: 3451.031 | BY27: 9182.46 | BZ27: 10351.098 | CA27: 18592.801 | CB27: 269 | CC27: 0.16 | CD27: 653070 | CE27: 900 | CF27: 173 | CG27: 2343917 | CH27: 34723 | CI27: 2 | CJ27: 92532 | CK27: 19 | CL27: 122883 | CM27: 43 | CN27: 1762525 | CO27: 74 | CP27: 306666 | CQ27: 7 | CR27: 0 | CS27: 0 | CT27: 24588 | CU27: 28 | CV27: 1526076 | CW27: 67 | DC27: 0 | DD27: 5075 | DE27: 0 | DF27: 3396 | DG27: 0 | DH27: 50559 | DI27: 900 | DJ27: 594040 | DK27: 1476.443 | DL27: Poor | DM27: 2628.768 | DN27: Poor | DO27: 2343794 | DP27: 1 | DQ27: Avoids redirects | DR27: Server responds quickly (observed 173 ms) | DS27: Applies text compression | DT27: 3 issues found | DU27: 4 resources found | DV27: 14396 | DX27: 5353 | DY27: 636710 | DZ27: 2 resources found | EA27: 978 | EB27: 4453 | EC27: 1 | ED27: 26492 | EF27: 240 | EG27: 21 resources found | EH27: 100 | EK27: 100 | EQ27: https://salesxceleration.com/podcasts/ | ER27: 46045.298
A28: https://salesxceleration.com/careers/ | B28: =IFERROR(__xludf.DUMMYFUNCTION("REGEXREPLACE(A28, ""^https?://[^/]+"", """")"),"/careers/") -> /careers/ | C28: VP of Sales Career Opportunities at Sales Xceleration | D28: Candidates Must Have the Following Background: | E28: We are currently hiring in the following cities: | F28: text/html; charset=UTF-8 | G28: 200 | H28: OK | I28: Indexable | K28: VP of Sales Careers | Sales Leadership Opportunities | Sales Xceleration | L28: 72 | M28: 643 | O28: 0 | P28: 0 | Q28: Discover VP of Sales careers at Sales Xceleration. Explore great leadership opportunities and join our team of sales experts. | R28: 125 | S28: 757 | U28: 0 | V28: VP of Sales Career Opportunities at Sales Xceleration | W28: 53 | Y28: 0 | Z28: Candidates Must Have the Following Background: | AA28: 46 | AB28: We are currently hiring in the following cities: | AC28: 48 | AD28: follow, index, max-snippet:-1, max-video-preview:-1, max-image-preview:large | AG28: https://salesxceleration.com/careers/ | AM28: 172876 | AN28: 30562 | AO28: 30562 | AP28: 11.708 | AR28: 912 | AS28: 157 | AT28: 5.809 | AU28: 63.464 | AV28: Normal | AW28: 4.629 | AX28: 1 | AY28: 1 | AZ28: 51 | BA28: 767 | BB28: 754 | BC28: 0 | BD28: 100 | BE28: 130 | BF28: 50 | BG28: 0 | BH28: 25 | BI28: 17 | BJ28: 0 | BO28: 3b06b135b8384a49615bd0a482c6c6df | BP28: 1.014 | BU28: en-US | BV28: 1.1 | BW28: 48 | BX28: 3751.051 | BY28: 7370.9 | BZ28: 6601.092 | CA28: 18120.941 | CB28: 579.5 | CC28: 0 | CD28: 667240 | CE28: 900 | CF28: 167 | CG28: 2321065 | CH28: 31812 | CI28: 2 | CJ28: 98685 | CK28: 22 | CL28: 132713 | CM28: 40 | CN28: 1747867 | CO28: 68 | CP28: 284718 | CQ28: 6 | CR28: 0 | CS28: 0 | CT28: 25270 | CU28: 29 | CV28: 1503740 | CW28: 67 | DC28: 0 | DD28: 5075 | DE28: 0 | DF28: 3396 | DG28: 300 | DH28: 65073 | DI28: 600 | DJ28: 593696 | DK28: 1960.835 | DL28: Poor | DM28: 3538.433 | DN28: Poor | DO28: 2321066 | DP28: 1 | DQ28: Avoids redirects | DR28: Server responds quickly (observed 170 ms) | DS28: Applies text compression | DT28: 1 issue found | DU28: 4 resources found | DV28: 13543 | DX28: 3821 | DY28: 637662 | DZ28: 1 resource found | EA28: 965 | EB28: 4453 | EC28: 23 | ED28: 26492 | EF28: 235 | EG28: 21 resources found | EH28: 100 | EK28: 100 | EQ28: https://salesxceleration.com/careers/ | ER28: 46045.298
A29: https://salesxceleration.com/sales-recruiting/ | B29: =IFERROR(__xludf.DUMMYFUNCTION("REGEXREPLACE(A29, ""^https?://[^/]+"", """")"),"/sales-recruiting/") -> /sales-recruiting/ | C29: Expert Sales Recruiting Services | D29: Our 6-Month Guarantee | E29: Why Sales Xceleration Recruiting? | F29: text/html; charset=UTF-8 | G29: 200 | H29: OK | I29: Indexable | K29: Sales Recruiting Services | Sales Xceleration | L29: 45 | M29: 396 | O29: 0 | P29: 0 | Q29: Find top talent and build a high-performing sales team with expert guidance from fractional sales leaders, guaranteed results in 6-months. | R29: 138 | S29: 849 | U29: 0 | V29: Expert Sales Recruiting Services | W29: 32 | Y29: 0 | Z29: Our 6-Month Guarantee | AA29: 21 | AB29: Why Sales Xceleration Recruiting? | AC29: 33 | AD29: follow, index, max-snippet:-1, max-video-preview:-1, max-image-preview:large | AG29: https://salesxceleration.com/sales-recruiting/ | AM29: 251047 | AN29: 86158 | AO29: 86158 | AP29: 33.005 | AR29: 1186 | AS29: 194 | AT29: 6.113 | AU29: 54.185 | AV29: Fairly Hard | AW29: 5.734 | AX29: 1 | AY29: 1 | AZ29: 51 | BA29: 3036 | BB29: 754 | BC29: 0 | BD29: 100 | BE29: 127 | BF29: 43 | BG29: 0 | BH29: 16 | BI29: 8 | BJ29: 0 | BO29: 289c90a1e708b59d42b5d24280234205 | BP29: 1.023 | BU29: en-US | BV29: 1.1 | BW29: 48 | BX29: 3601.007 | BY29: 8270.616 | BZ29: 5851.012 | CA29: 18612.473 | CB29: 637 | CC29: 0 | CD29: 694239 | CE29: 1220 | CF29: 173 | CG29: 2366105 | CH29: 84224 | CI29: 2 | CJ29: 58086 | CK29: 21 | CL29: 126857 | CM29: 44 | CN29: 1805486 | CO29: 72 | CP29: 266196 | CQ29: 6 | CR29: 0 | CS29: 0 | CT29: 25256 | CU29: 28 | CV29: 1525525 | CW29: 70 | DC29: 10 | DD29: 5074 | DE29: 0 | DF29: 7389 | DG29: 610 | DH29: 50540 | DI29: 600 | DJ29: 631236 | DK29: 2008.258 | DL29: Poor | DM29: 3751.888 | DN29: Poor | DO29: 2366106 | DP29: 1 | DQ29: Avoids redirects | DR29: Server responds quickly (observed 329 ms) | DS29: Applies text compression | DU29: 2 resources found | DV29: 13605 | DX29: 4350 | DY29: 623705 | DZ29: 1 resource found | EA29: 1059 | EB29: 17282 | EC29: 1 | ED29: 26492 | EF29: 235 | EG29: 21 resources found | EH29: 100 | EK29: 100 | EQ29: https://salesxceleration.com/sales-recruiting/ | ER29: 46045.298
A30: https://salesxceleration.com/wp-content/plugins/elementor/assets/lib/animations/styles/slideInLeft.min.css?ver=3.34.0 | B30: =IFERROR(__xludf.DUMMYFUNCTION("REGEXREPLACE(A30, ""^https?://[^/]+"", """")"),"/wp-content/plugins/elementor/assets/lib/animations/styles/slideInLeft.min.css?ver=3.34.0") -> /wp-content/plugins/elementor/assets/lib/animations/styles/slideInLeft.min.css?ver=3.34.0 | F30: text/css | G30: 200 | H30: OK | I30: Indexable | L30: 0 | M30: 0 | O30: 0 | P30: 0 | R30: 0 | S30: 0 | U30: 0 | W30: 0 | Y30: 0 | AA30: 0 | AC30: 0 | AM30: 123 | AN30: 123 | AO30: 123 | AP30: 0.047 | AR30: 0 | AW30: 0 | AX30: 1 | AY30: 7 | BA30: 0 | BB30: 0 | BC30: 0 | BD30: 0 | BE30: 0 | BF30: 0 | BG30: 0 | BH30: 0 | BI30: 0 | BJ30: 0 | BP30: 0.256 | BQ30: Fri, 02 Jan 2026 17:29:45 GMT | BV30: 1.1 | EQ30: https://salesxceleration.com/wp-content/plugins/elementor/assets/lib/animations/styles/slideInLeft.min.css?ver=3.34.0 | ER30: 46045.298
A31: https://salesxceleration.com/sales-connection/ | B31: =IFERROR(__xludf.DUMMYFUNCTION("REGEXREPLACE(A31, ""^https?://[^/]+"", """")"),"/sales-connection/") -> /sales-connection/ | C31: Sales Connection | F31: text/html; charset=UTF-8 | G31: 200 | H31: OK | I31: Indexable | K31: Sales Connection | Sales Xceleration | L31: 36 | M31: 326 | O31: 0 | P31: 0 | Q31: SalesXceleration offers expert sales leadership strategies to boost growth and performance. Practical advice to elevate your business success. | R31: 142 | S31: 879 | U31: 0 | V31: Sales Connection | W31: 16 | Y31: 0 | AA31: 0 | AC31: 0 | AD31: follow, index, max-snippet:-1, max-video-preview:-1, max-image-preview:large | AG31: https://salesxceleration.com/sales-connection/ | AM31: 144278 | AN31: 27737 | AO31: 27737 | AP31: 10.626 | AR31: 526 | AS31: 91 | AT31: 5.78 | AU31: 60.879 | AV31: Normal | AW31: 3.904 | AX31: 1 | AY31: 1 | AZ31: 47 | BA31: 747 | BB31: 747 | BC31: 0 | BD31: 99.07 | BE31: 122 | BF31: 42 | BG31: 0 | BH31: 16 | BI31: 8 | BJ31: 0 | BO31: 65060063aacbe4c73eb5aeaddcb2d79e | BP31: 1.456 | BU31: en-US | BV31: 1.1 | BW31: 28 | BX31: 3451.028 | BY31: 7755.555 | BZ31: 11026.096 | CA31: 20829.549 | CB31: 844.174 | CC31: 0.246 | CD31: 1173495 | CE31: 2550 | CF31: 184 | CG31: 3622208 | CH31: 83531 | CI31: 4 | CJ31: 119902 | CK31: 29 | CL31: 198357 | CM31: 39 | CN31: 2487611 | CO31: 75 | CP31: 315208 | CQ31: 7 | CR31: 0 | CS31: 0 | CT31: 417599 | CU31: 30 | CV31: 2891301 | CW31: 87 | DC31: 450 | DD31: 5075 | DE31: 450 | DF31: 3401 | DG31: 450 | DH31: 50525 | DI31: 1200 | DJ31: 1114494 | DK31: 3027.114 | DL31: Poor | DM31: 4518.071 | DN31: Poor | DO31: 3622126 | DP31: 1 | DQ31: Avoids redirects | DR31: Server responds quickly (observed 167 ms) | DS31: Applies text compression | DU31: 2 resources found | DV31: 12189 | DW31: 627 | DX31: 3735 | DY31: 604884 | DZ31: 3 resources found | EA31: 791 | EB31: 31882 | EC31: 10 | ED31: 26492 | EF31: 230 | EG31: 22 resources found | EH31: 100 | EK31: 100 | EQ31: https://salesxceleration.com/sales-connection/ | ER31: 46045.298
A32: https://salesxceleration.com/wp-content/themes/salesxceleratione/style.css?ver=6.9 | B32: =IFERROR(__xludf.DUMMYFUNCTION("REGEXREPLACE(A32, ""^https?://[^/]+"", """")"),"/wp-content/themes/salesxceleratione/style.css?ver=6.9") -> /wp-content/themes/salesxceleratione/style.css?ver=6.9 | F32: text/css | G32: 200 | H32: OK | I32: Indexable | L32: 0 | M32: 0 | O32: 0 | P32: 0 | R32: 0 | S32: 0 | U32: 0 | W32: 0 | Y32: 0 | AA32: 0 | AC32: 0 | AM32: 4607 | AN32: 4607 | AO32: 4607 | AP32: 1.765 | AR32: 0 | AW32: 0 | AX32: 1 | AY32: 3 | BA32: 0 | BB32: 0 | BC32: 0 | BD32: 0 | BE32: 0 | BF32: 0 | BG32: 0 | BH32: 0 | BI32: 0 | BJ32: 0 | BP32: 0.259 | BQ32: Mon, 21 Apr 2025 18:05:17 GMT | BV32: 1.1 | EQ32: https://salesxceleration.com/wp-content/themes/salesxceleratione/style.css?ver=6.9 | ER32: 46045.298
A33: https://salesxceleration.com/consultants/ | B33: =IFERROR(__xludf.DUMMYFUNCTION("REGEXREPLACE(A33, ""^https?://[^/]+"", """")"),"/consultants/") -> /consultants/ | C33: Meet Our Outsourced VP of Sales | F33: text/html; charset=UTF-8 | G33: 200 | H33: OK | I33: Indexable | K33: Expert Sales Consultants | Outsourced Sales Leadership | Sales Xceleration | L33: 74 | M33: 670 | O33: 0 | P33: 0 | Q33: Find expert sales consultants at Sales Xceleration. Discover how our fractional VP of Sales can drive your sales strategy and leadership success. | R33: 145 | S33: 887 | U33: 0 | V33: Meet Our Outsourced VP of Sales | W33: 31 | Y33: 0 | AA33: 0 | AC33: 0 | AD33: follow, index, max-snippet:-1, max-video-preview:-1, max-image-preview:large | AG33: https://salesxceleration.com/consultants/ | AM33: 853850 | AN33: 91305 | AO33: 91305 | AP33: 34.977 | AR33: 8605 | AS33: 1399 | AT33: 6.151 | AU33: 47.388 | AV33: Hard | AW33: 7.192 | AX33: 1 | AY33: 1 | AZ33: 51 | BA33: 2287 | BB33: 754 | BC33: 0 | BD33: 100 | BE33: 347 | BF33: 47 | BG33: 0 | BH33: 669 | BI33: 448 | BJ33: 0 | BO33: ce33f07d8141fd211e1f595e694fefbf | BP33: 4.531 | BU33: en-US | BV33: 1.1 | BW33: 44 | BX33: 3901.01 | BY33: 12364.046 | BZ33: 9001.023 | CA33: 17936.635 | CB33: 559.5 | CC33: 0 | CD33: 651234 | CE33: 1350 | CF33: 162 | CG33: 2295711 | CH33: 87346 | CI33: 2 | CJ33: 80283 | CK33: 21 | CL33: 111425 | CM33: 38 | CN33: 1747765 | CO33: 68 | CP33: 244248 | CQ33: 5 | CR33: 0 | CS33: 0 | CT33: 24644 | CU33: 28 | CV33: 1502989 | CW33: 65 | DC33: 0 | DD33: 5075 | DE33: 0 | DF33: 3396 | DG33: 0 | DH33: 50494 | DI33: 1350 | DJ33: 592269 | DK33: 1909.602 | DL33: Poor | DM33: 4263.087 | DN33: Poor | DO33: 2295712 | DP33: 1 | DQ33: Avoids redirects | DR33: Server responds quickly (observed 347 ms) | DS33: Applies text compression | DT33: 1 issue found | DU33: 4 resources found | DV33: 12791 | DX33: 7075 | DY33: 605596 | DZ33: 1 resource found | EA33: 3969 | EB33: 4453 | EC33: 608 | ED33: 26492 | EF33: 235 | EG33: 21 resources found | EH33: 100 | EK33: 100 | EQ33: https://salesxceleration.com/consultants/ | ER33: 46045.298
A34: https://salesxceleration.com/ai-sales-tools-readiness-assessment/ | B34: =IFERROR(__xludf.DUMMYFUNCTION("REGEXREPLACE(A34, ""^https?://[^/]+"", """")"),"/ai-sales-tools-readiness-assessment/") -> /ai-sales-tools-readiness-assessment/ | C34: AI Readiness Check: Is Your Sales Organization Ready to Transform? | F34: text/html; charset=UTF-8 | G34: 200 | H34: OK | I34: Indexable | K34: AI Readiness Check: Is Your Sales Organization Ready to Transform? | Sales Xceleration | L34: 86 | M34: 780 | O34: 0 | P34: 0 | Q34: Is your sales team leveraging AI effectively to support your sales efforts? Take this quick 10-question assessment to get your readiness score and a list of AI tools designed to address common sales challenges and enhance your sales process to drive results. | R34: 258 | S34: 1581 | U34: 0 | V34: AI Readiness Check: Is Your Sales Organization Ready to Transform? | W34: 66 | Y34: 0 | AA34: 0 | AC34: 0 | AD34: follow, index, max-snippet:-1, max-video-preview:-1, max-image-preview:large | AG34: https://salesxceleration.com/ai-sales-tools-readiness-assessment/ | AM34: 225015 | AN34: 43637 | AO34: 43637 | AP34: 16.717 | AR34: 1336 | AS34: 208 | AT34: 6.423 | AU34: 82.724 | AV34: Easy | AW34: 5.835 | AX34: 1 | AY34: 1 | AZ34: 7 | BA34: 22 | BB34: 12 | BC34: 0 | BD34: 1.59 | BE34: 121 | BF34: 42 | BG34: 0 | BH34: 16 | BI34: 8 | BJ34: 0 | BO34: cda7b5a68fc6c4fe98695b9cc94e690c | BP34: 1.286 | BU34: en-US | BV34: 1.1 | BW34: 32 | BX34: 3751.024 | BY34: 8278.529 | BZ34: 7576.051 | CA34: 21489.891 | CB34: 785.5 | CC34: 0.205 | CD34: 1248083 | CE34: 1250 | CF34: 192 | CG34: 3735956 | CH34: 98188 | CI34: 4 | CJ34: 179884 | CK34: 23 | CL34: 219826 | CM34: 43 | CN34: 2562030 | CO34: 86 | CP34: 284718 | CQ34: 6 | CR34: 0 | CS34: 0 | CT34: 391310 | CU34: 30 | CV34: 2745785 | CW34: 74 | DC34: 0 | DD34: 5075 | DE34: 0 | DF34: 3396 | DG34: 350 | DH34: 62028 | DI34: 900 | DJ34: 1177584 | DK34: 2885.724 | DL34: Poor | DM34: 4674.325 | DN34: Poor | DO34: 3735874 | DP34: 1 | DQ34: Avoids redirects | DR34: Server responds quickly (observed 324 ms) | DS34: Applies text compression | DT34: 1 issue found | DU34: 4 resources found | DV34: 13544 | DX34: 4510 | DY34: 701778 | DZ34: 1 resource found | EA34: 1416 | EB34: 31882 | EC34: 1 | ED34: 26492 | EF34: 660 | EG34: 21 resources found | EH34: 100 | EK34: 100 | EQ34: https://salesxceleration.com/ai-sales-tools-readiness-assessment/ | ER34: 46045.298
A35: https://salesxceleration.com/wp-content/themes/salesxceleratione/assets/js/jquery.fancybox.min.js?ver=3.5.7 | B35: =IFERROR(__xludf.DUMMYFUNCTION("REGEXREPLACE(A35, ""^https?://[^/]+"", """")"),"/wp-content/themes/salesxceleratione/assets/js/jquery.fancybox.min.js?ver=3.5.7") -> /wp-content/themes/salesxceleratione/assets/js/jquery.fancybox.min.js?ver=3.5.7 | F35: application/javascript | G35: 200 | H35: OK | I35: Indexable | L35: 0 | M35: 0 | O35: 0 | P35: 0 | R35: 0 | S35: 0 | U35: 0 | W35: 0 | Y35: 0 | AA35: 0 | AC35: 0 | AM35: 22013 | AN35: 22013 | AO35: 22013 | AP35: 8.433 | AR35: 0 | AW35: 0 | AX35: 1 | AY35: 5 | BA35: 0 | BB35: 0 | BC35: 0 | BD35: 0 | BE35: 0 | BF35: 0 | BG35: 0 | BH35: 0 | BI35: 0 | BJ35: 0 | BP35: 0.265 | BQ35: Fri, 12 Nov 2021 15:43:34 GMT | BV35: 1.1 | EQ35: https://salesxceleration.com/wp-content/themes/salesxceleratione/assets/js/jquery.fancybox.min.js?ver=3.5.7 | ER35: 46045.298
A36: https://salesxceleration.com/wp-content/plugins/elementor-pro/assets/js/elements-handlers.min.js?ver=3.34.0 | B36: =IFERROR(__xludf.DUMMYFUNCTION("REGEXREPLACE(A36, ""^https?://[^/]+"", """")"),"/wp-content/plugins/elementor-pro/assets/js/elements-handlers.min.js?ver=3.34.0") -> /wp-content/plugins/elementor-pro/assets/js/elements-handlers.min.js?ver=3.34.0 | F36: application/javascript | G36: 200 | H36: OK | I36: Indexable | L36: 0 | M36: 0 | O36: 0 | P36: 0 | R36: 0 | S36: 0 | U36: 0 | W36: 0 | Y36: 0 | AA36: 0 | AC36: 0 | AM36: 10568 | AN36: 10568 | AO36: 10568 | AP36: 4.048 | AR36: 0 | AW36: 0 | AX36: 1 | AY36: 5 | BA36: 0 | BB36: 0 | BC36: 0 | BD36: 0 | BE36: 0 | BF36: 0 | BG36: 0 | BH36: 0 | BI36: 0 | BJ36: 0 | BP36: 0.272 | BQ36: Fri, 02 Jan 2026 17:52:08 GMT | BV36: 1.1 | EQ36: https://salesxceleration.com/wp-content/plugins/elementor-pro/assets/js/elements-handlers.min.js?ver=3.34.0 | ER36: 46045.298
A37: https://salesxceleration.com/wp-content/plugins/advanced-iframe/js/ai.min.js?ver=502409 | B37: =IFERROR(__xludf.DUMMYFUNCTION("REGEXREPLACE(A37, ""^https?://[^/]+"", """")"),"/wp-content/plugins/advanced-iframe/js/ai.min.js?ver=502409") -> /wp-content/plugins/advanced-iframe/js/ai.min.js?ver=502409 | F37: application/javascript | G37: 200 | H37: OK | I37: Indexable | L37: 0 | M37: 0 | O37: 0 | P37: 0 | R37: 0 | S37: 0 | U37: 0 | W37: 0 | Y37: 0 | AA37: 0 | AC37: 0 | AM37: 13089 | AN37: 13089 | AO37: 13089 | AP37: 5.014 | AR37: 0 | AW37: 0 | AX37: 1 | AY37: 4 | BA37: 0 | BB37: 0 | BC37: 0 | BD37: 0 | BE37: 0 | BF37: 0 | BG37: 0 | BH37: 0 | BI37: 0 | BJ37: 0 | BP37: 0.27 | BQ37: Fri, 02 Jan 2026 17:29:26 GMT | BV37: 1.1 | EQ37: https://salesxceleration.com/wp-content/plugins/advanced-iframe/js/ai.min.js?ver=502409 | ER37: 46045.298
A38: https://salesxceleration.com/become-a-consultant/ | B38: =IFERROR(__xludf.DUMMYFUNCTION("REGEXREPLACE(A38, ""^https?://[^/]+"", """")"),"/become-a-consultant/") -> /become-a-consultant/ | C38: Empowering You to Build Your Own Sales Consultancy Business | D38: Your Path to Success | E38: Wondering if Sales Xceleration Is the Right Fit? | F38: text/html; charset=UTF-8 | G38: 200 | H38: OK | I38: Indexable | K38: Become an Independent Sales Consultant | Sales Xceleration | L38: 58 | M38: 543 | O38: 0 | P38: 0 | Q38: Ready to become a sales consultant? Join Sales Xceleration and leverage your expertise to help businesses grow with tailored sales strategies and leadership. | R38: 157 | S38: 971 | U38: 0 | V38: Empowering You to Build Your Own Sales Consultancy Business | W38: 59 | Y38: 0 | Z38: Your Path to Success | AA38: 20 | AB38: Wondering if Sales Xceleration Is the Right Fit? | AC38: 48 | AD38: follow, index, max-snippet:-1, max-video-preview:-1, max-image-preview:large | AG38: https://salesxceleration.com/become-a-consultant/ | AM38: 197115 | AN38: 35057 | AO38: 35057 | AP38: 13.43 | AR38: 1288 | AS38: 192 | AT38: 6.708 | AU38: 60.646 | AV38: Normal | AW38: 5.307 | AX38: 1 | AY38: 1 | AZ38: 51 | BA38: 3006 | BB38: 754 | BC38: 0 | BD38: 100 | BE38: 127 | BF38: 45 | BG38: 0 | BH38: 17 | BI38: 9 | BJ38: 0 | BO38: 4c8dc560c67d3ee09bdd1b2fb26ec0bc | BP38: 1 | BU38: en-US | BV38: 1.1 | BW38: 31 | BX38: 3601.029 | BY38: 8277.83 | BZ38: 8326.07 | CA38: 22326.717 | CB38: 642 | CC38: 0.263 | CD38: 977012 | CE38: 1200 | CF38: 191 | CG38: 3242144 | CH38: 54658 | CI38: 3 | CJ38: 308815 | CK38: 21 | CL38: 138160 | CM38: 43 | CN38: 2404304 | CO38: 81 | CP38: 294886 | CQ38: 6 | CR38: 6042 | CS38: 1 | CT38: 35279 | CU38: 36 | CV38: 2196505 | CW38: 89 | DC38: 150 | DD38: 5075 | DE38: 0 | DF38: 3396 | DG38: 150 | DH38: 50458 | DI38: 900 | DJ38: 918083 | DK38: 2507.32 | DL38: Poor | DM38: 4045.76 | DN38: Poor | DO38: 3242145 | DP38: 8 | DQ38: Avoids redirects | DR38: Server responds quickly (observed 191 ms) | DS38: Applies text compression | DT38: 1 issue found | DU38: 4 resources found | DV38: 13395 | DX38: 4453 | DY38: 936701 | DZ38: 2 resources found | EA38: 1090 | EB38: 21715 | EC38: 1 | ED38: 26492 | EF38: 240 | EG38: 23 resources found | EH38: 100 | EK38: 100 | EQ38: https://salesxceleration.com/become-a-consultant/ | ER38: 46045.298
A39: https://salesxceleration.com/news-events/ | B39: =IFERROR(__xludf.DUMMYFUNCTION("REGEXREPLACE(A39, ""^https?://[^/]+"", """")"),"/news-events/") -> /news-events/ | C39: Sales Xceleration News and Upcoming Events | D39: Sales Xceleration Introduces Fractional Sales Leaders in Multiple Key Markets | E39: Top Sales Experts Join Sales Xceleration to Boost Small Business Success | F39: text/html; charset=UTF-8 | G39: 200 | H39: OK | I39: Indexable | K39: Latest News and Events in Sales | Sales Xceleration | L39: 51 | M39: 461 | O39: 0 | P39: 0 | Q39: Stay updated with the latest sales news and events from Sales Xceleration. Learn about our webinars, conferences, and more. | R39: 123 | S39: 776 | U39: 0 | V39: Sales Xceleration News and Upcoming Events | W39: 42 | Y39: 0 | Z39: Sales Xceleration Introduces Fractional Sales Leaders in Multiple Key Markets | AA39: 77 | AB39: Top Sales Experts Join Sales Xceleration to Boost Small Business Success | AC39: 72 | AD39: follow, index, max-snippet:-1, max-video-preview:-1, max-image-preview:large | AG39: https://salesxceleration.com/news-events/ | AM39: 259918 | AN39: 39646 | AO39: 39646 | AP39: 15.188 | AR39: 1721 | AS39: 263 | AT39: 6.544 | AU39: 45.101 | AV39: Hard | AW39: 5.656 | AX39: 1 | AY39: 1 | AZ39: 52 | BA39: 2268 | BB39: 754 | BC39: 0 | BD39: 100 | BE39: 230 | BF39: 150 | BG39: 0 | BH39: 16 | BI39: 8 | BJ39: 0 | BO39: d17a82ea96d68ef1e1aef683bb2ffc7b | BP39: 1.134 | BU39: en-US | BV39: 1.1 | BW39: 55 | BX39: 3601.021 | BY39: 7127.523 | BZ39: 8326.05 | CA39: 18369.211 | CB39: 286.5 | CC39: 0.065 | CD39: 650907 | CE39: 1500 | CF39: 168 | CG39: 2868230 | CH39: 40848 | CI39: 2 | CJ39: 550961 | CK39: 23 | CL39: 113509 | CM39: 39 | CN39: 1747845 | CO39: 68 | CP39: 390051 | CQ39: 8 | CR39: 0 | CS39: 0 | CT39: 25016 | CU39: 28 | CV39: 1551995 | CW39: 65 | DC39: 0 | DD39: 5075 | DE39: 0 | DF39: 3396 | DG39: 450 | DH39: 50573 | DI39: 1050 | DJ39: 591863 | DK39: 1515.808 | DL39: Poor | DM39: 2764.421 | DN39: Poor | DO39: 2868231 | DP39: 1 | DQ39: Avoids redirects | DR39: Server responds quickly (observed 174 ms) | DS39: Applies text compression | DT39: 1 issue found | DU39: 4 resources found | DV39: 12943 | DX39: 3889 | DY39: 833595 | DZ39: 1 resource found | EA39: 1418 | EB39: 70679 | EC39: 1 | ED39: 26492 | EF39: 240 | EG39: 21 resources found | EH39: 100 | EK39: 100 | EQ39: https://salesxceleration.com/news-events/ | ER39: 46045.298
A40: https://salesxceleration.com/wp-content/uploads/2025/02/Regional-partner-24-North-America-bg.png | B40: =IFERROR(__xludf.DUMMYFUNCTION("REGEXREPLACE(A40, ""^https?://[^/]+"", """")"),"/wp-content/uploads/2025/02/Regional-partner-24-North-America-bg.png") -> /wp-content/uploads/2025/02/Regional-partner-24-North-America-bg.png | F40: image/png | G40: 200 | H40: OK | I40: Indexable | L40: 0 | M40: 0 | O40: 0 | P40: 0 | R40: 0 | S40: 0 | U40: 0 | W40: 0 | Y40: 0 | AA40: 0 | AC40: 0 | AM40: 53452 | AN40: 53452 | AO40: 53452 | AP40: 20.476 | AR40: 0 | AW40: 0 | AX40: 1 | AY40: 4 | BA40: 0 | BB40: 0 | BC40: 0 | BD40: 0 | BE40: 0 | BF40: 0 | BG40: 0 | BH40: 0 | BI40: 0 | BJ40: 0 | BP40: 0.279 | BQ40: Thu, 13 Feb 2025 19:47:31 GMT | BV40: 1.1 | EQ40: https://salesxceleration.com/wp-content/uploads/2025/02/Regional-partner-24-North-America-bg.png | ER40: 46045.298
A41: https://salesxceleration.com/private-equity-solutions/portfolio-company/ | B41: =IFERROR(__xludf.DUMMYFUNCTION("REGEXREPLACE(A41, ""^https?://[^/]+"", """")"),"/private-equity-solutions/portfolio-company/") -> /private-equity-solutions/portfolio-company/ | C41: Accelerate Your Sales Success with Proven Expertise | D41: Maximizing Sales Growth | E41: Certified Sales Leadership | F41: text/html; charset=UTF-8 | G41: 200 | H41: OK | I41: Indexable | K41: Portfolio Company | Sales Xceleration | L41: 37 | M41: 337 | O41: 0 | P41: 0 | Q41: Over 6,000 small to mid-sized privately held and portfolio companies have trusted us to enhance their sales operations and drive revenue growth. | R41: 144 | S41: 891 | U41: 0 | V41: Accelerate Your Sales Success with Proven Expertise | W41: 51 | Y41: 0 | Z41: Maximizing Sales Growth | AA41: 23 | AB41: Certified Sales Leadership | AC41: 26 | AD41: follow, index, max-snippet:-1, max-video-preview:-1, max-image-preview:large | AG41: https://salesxceleration.com/private-equity-solutions/portfolio-company/ | AM41: 191293 | AN41: 38134 | AO41: 38134 | AP41: 14.608 | AR41: 972 | AS41: 160 | AT41: 6.075 | AU41: 50.878 | AV41: Fairly Hard | AW41: 5.079 | AX41: 1 | AY41: 2 | AZ41: 51 | BA41: 2279 | BB41: 754 | BC41: 0 | BD41: 100 | BE41: 111 | BF41: 44 | BG41: 0 | BH41: 7 | BI41: 6 | BJ41: 0 | BO41: 4c342d25a7565031715af76beba6d136 | BP41: 0.979 | BU41: en-US | BV41: 1.1 | BW41: 51 | BX41: 4051.016 | BY41: 8556.965 | BZ41: 8476.034 | CA41: 17915.789 | CB41: 360.5 | CC41: 0 | CD41: 653213 | CE41: 1050 | CF41: 168 | CG41: 2539564 | CH41: 39863 | CI41: 2 | CJ41: 285398 | CK41: 15 | CL41: 121465 | CM41: 45 | CN41: 1765315 | CO41: 71 | CP41: 301523 | CQ41: 6 | CR41: 0 | CS41: 0 | CT41: 26000 | CU41: 29 | CV41: 1504591 | CW41: 63 | DC41: 0 | DD41: 5075 | DE41: 0 | DF41: 3396 | DG41: 150 | DH41: 50962 | DI41: 900 | DJ41: 593780 | DK41: 1750.25 | DL41: Poor | DM41: 3998.525 | DN41: Poor | DO41: 2539565 | DP41: 1 | DQ41: Avoids redirects | DR41: Server responds quickly (observed 171 ms) | DS41: Applies text compression | DT41: 1 issue found | DU41: 4 resources found | DV41: 13998 | DX41: 3698 | DY41: 721462 | DZ41: 1 resource found | EA41: 837 | EB41: 83768 | EC41: 1 | ED41: 26492 | EF41: 235 | EG41: 21 resources found | EH41: 100 | EK41: 100 | EQ41: https://salesxceleration.com/private-equity-solutions/portfolio-company/ | ER41: 46045.298
A42: https://salesxceleration.com/wp-content/plugins/cookie-law-info/legacy/public/css/cookie-law-info-public.css?ver=3.3.9.1 | B42: =IFERROR(__xludf.DUMMYFUNCTION("REGEXREPLACE(A42, ""^https?://[^/]+"", """")"),"/wp-content/plugins/cookie-law-info/legacy/public/css/cookie-law-info-public.css?ver=3.3.9.1") -> /wp-content/plugins/cookie-law-info/legacy/public/css/cookie-law-info-public.css?ver=3.3.9.1 | F42: text/css | G42: 200 | H42: OK | I42: Indexable | L42: 0 | M42: 0 | O42: 0 | P42: 0 | R42: 0 | S42: 0 | U42: 0 | W42: 0 | Y42: 0 | AA42: 0 | AC42: 0 | AM42: 953 | AN42: 953 | AO42: 953 | AP42: 0.365 | AR42: 0 | AW42: 0 | AX42: 1 | AY42: 6 | BA42: 0 | BB42: 0 | BC42: 0 | BD42: 0 | BE42: 0 | BF42: 0 | BG42: 0 | BH42: 0 | BI42: 0 | BJ42: 0 | BP42: 0.257 | BQ42: Fri, 02 Jan 2026 17:29:34 GMT | BV42: 1.1 | EQ42: https://salesxceleration.com/wp-content/plugins/cookie-law-info/legacy/public/css/cookie-law-info-public.css?ver=3.3.9.1 | ER42: 46045.298
A43: https://salesxceleration.com/wp-content/uploads/elementor/thumbs/Flag_of_Australia.svg-r4g46qz9ltlqws3p70qavt5l3jm99riysjikntibkm.png | B43: =IFERROR(__xludf.DUMMYFUNCTION("REGEXREPLACE(A43, ""^https?://[^/]+"", """")"),"/wp-content/uploads/elementor/thumbs/Flag_of_Australia.svg-r4g46qz9ltlqws3p70qavt5l3jm99riysjikntibkm.png") -> /wp-content/uploads/elementor/thumbs/Flag_of_Australia.svg-r4g46qz9ltlqws3p70qavt5l3jm99riysjikntibkm.png | F43: image/png | G43: 200 | H43: OK | I43: Indexable | L43: 0 | M43: 0 | O43: 0 | P43: 0 | R43: 0 | S43: 0 | U43: 0 | W43: 0 | Y43: 0 | AA43: 0 | AC43: 0 | AM43: 621 | AN43: 621 | AO43: 621 | AP43: 0.238 | AR43: 0 | AW43: 0 | AX43: 1 | AY43: 4 | BA43: 0 | BB43: 0 | BC43: 0 | BD43: 0 | BE43: 0 | BF43: 0 | BG43: 0 | BH43: 0 | BI43: 0 | BJ43: 0 | BP43: 0.271 | BQ43: Wed, 16 Apr 2025 14:24:41 GMT | BV43: 1.1 | EQ43: https://salesxceleration.com/wp-content/uploads/elementor/thumbs/Flag_of_Australia.svg-r4g46qz9ltlqws3p70qavt5l3jm99riysjikntibkm.png | ER43: 46045.298
A44: https://salesxceleration.com/free-sales-resources/ | B44: =IFERROR(__xludf.DUMMYFUNCTION("REGEXREPLACE(A44, ""^https?://[^/]+"", """")"),"/free-sales-resources/") -> /free-sales-resources/ | C44: Free Sales Tools and Resources | D44: Not sure where to start? Here are our top picks: | E44: The AI Security Playbook: 6 Essentials Every Sales Organization Needs | F44: text/html; charset=UTF-8 | G44: 200 | H44: OK | I44: Indexable | K44: Free Sales Resources & Tools | Sales Xceleration | L44: 48 | M44: 434 | O44: 0 | P44: 0 | Q44: Access a wide range of free sales resources and tools to enhance your sales strategies and performance. Download guides, templates, and more. | R44: 141 | S44: 893 | U44: 0 | V44: Free Sales Tools and Resources | W44: 30 | Y44: 0 | Z44: Not sure where to start? Here are our top picks: | AA44: 48 | AB44: The AI Security Playbook: 6 Essentials Every Sales Organization Needs | AC44: 69 | AD44: follow, index, max-snippet:-1, max-video-preview:-1, max-image-preview:large | AG44: https://salesxceleration.com/free-sales-resources/ | AM44: 193757 | AN44: 32419 | AO44: 32419 | AP44: 12.419 | AR44: 924 | AS44: 170 | AT44: 5.435 | AU44: 53.726 | AV44: Fairly Hard | AW44: 4.29 | AX44: 1 | AY44: 1 | AZ44: 51 | BA44: 2270 | BB44: 754 | BC44: 0 | BD44: 100 | BE44: 155 | BF44: 50 | BG44: 0 | BH44: 16 | BI44: 8 | BJ44: 0 | BO44: 1c4392bfe9c334cf8b16774fca19541a | BP44: 1.257 | BU44: en-US | BV44: 1.1 | BW44: 59 | BX44: 4201.036 | BY44: 7644.341 | BZ44: 6901.06 | CA44: 18144.234 | CB44: 162 | CC44: 0 | CD44: 652007 | CE44: 750 | CF44: 171 | CG44: 2333367 | CH44: 33246 | CI44: 2 | CJ44: 49917 | CK44: 22 | CL44: 118401 | CM44: 40 | CN44: 1764893 | CO44: 71 | CP44: 341338 | CQ44: 8 | CR44: 0 | CS44: 0 | CT44: 25572 | CU44: 28 | CV44: 1526039 | CW44: 69 | DC44: 0 | DD44: 5075 | DE44: 0 | DF44: 3396 | DG44: 150 | DH44: 50545 | DI44: 600 | DJ44: 592991 | DK44: 1139.394 | DL44: Good | DM44: 2139.066 | DN44: Poor | DO44: 2332913 | DP44: 1 | DQ44: Avoids redirects | DR44: Server responds quickly (observed 190 ms) | DS44: Applies text compression | DU44: 2 resources found | DV44: 13394 | DW44: 310 | DX44: 3989 | DY44: 633010 | DZ44: 1 resource found | EA44: 980 | EB44: 4453 | EC44: 1 | ED44: 26492 | EF44: 235 | EG44: 21 resources found | EH44: 100 | EK44: 100 | EQ44: https://salesxceleration.com/free-sales-resources/ | ER44: 46045.298
A45: https://salesxceleration.com/about-sales-xceleration/ | B45: =IFERROR(__xludf.DUMMYFUNCTION("REGEXREPLACE(A45, ""^https?://[^/]+"", """")"),"/about-sales-xceleration/") -> /about-sales-xceleration/ | C45: About Sales Xceleration | D45: Meet Our Leadership Team | F45: text/html; charset=UTF-8 | G45: 200 | H45: OK | I45: Indexable | K45: The Story of Sales Xceleration | Sales Xceleration | L45: 50 | M45: 440 | O45: 0 | P45: 0 | Q45: Discover the history of Sales Xceleration, from its groundbreaking vision to becoming a leader in outsourced sales leadership. Learn about our journey and growth. | R45: 162 | S45: 999 | U45: 0 | V45: About Sales Xceleration | W45: 23 | Y45: 0 | Z45: Meet Our Leadership Team | AA45: 24 | AC45: 0 | AD45: follow, index, max-snippet:-1, max-video-preview:-1, max-image-preview:large | AG45: https://salesxceleration.com/about-sales-xceleration/ | AM45: 179146 | AN45: 32824 | AO45: 32824 | AP45: 12.574 | AR45: 1187 | AS45: 183 | AT45: 6.486 | AU45: 45.591 | AV45: Hard | AW45: 5.798 | AX45: 1 | AY45: 1 | AZ45: 51 | BA45: 3011 | BB45: 754 | BC45: 0 | BD45: 100 | BE45: 122 | BF45: 42 | BG45: 0 | BH45: 16 | BI45: 8 | BJ45: 0 | BO45: fe8ee084992d3963ec9620f308ca1dc5 | BP45: 0.994 | BU45: en-US | BV45: 1.1 | BW45: 44 | BX45: 3301.022 | BY45: 7278.542 | BZ45: 8252.06 | CA45: 17953.762 | CB45: 745.5 | CC45: 0 | CD45: 651345 | CE45: 1650 | CF45: 168 | CG45: 2339571 | CH45: 34024 | CI45: 2 | CJ45: 175135 | CK45: 26 | CL45: 112984 | CM45: 38 | CN45: 1747318 | CO45: 67 | CP45: 244248 | CQ45: 5 | CR45: 0 | CS45: 0 | CT45: 25862 | CU45: 30 | CV45: 1505949 | CW45: 72 | DC45: 150 | DD45: 5075 | DE45: 0 | DF45: 3396 | DG45: 150 | DH45: 50486 | DI45: 1350 | DJ45: 592388 | DK45: 2201.062 | DL45: Poor | DM45: 4026.114 | DN45: Poor | DO45: 2338859 | DP45: 1 | DQ45: Avoids redirects | DR45: Server responds quickly (observed 168 ms) | DS45: Applies text compression | DT45: 1 issue found | DU45: 4 resources found | DV45: 12641 | DX45: 3746 | DY45: 643270 | DZ45: 1 resource found | EA45: 891 | EB45: 4453 | EC45: 0 | ED45: 26492 | EF45: 295 | EG45: 21 resources found | EH45: 100 | EK45: 100 | EQ45: https://salesxceleration.com/about-sales-xceleration/ | ER45: 46045.298
A46: https://salesxceleration.com/wp-content/plugins/elementor/assets/css/widget-social-icons.min.css?ver=3.34.0 | B46: =IFERROR(__xludf.DUMMYFUNCTION("REGEXREPLACE(A46, ""^https?://[^/]+"", """")"),"/wp-content/plugins/elementor/assets/css/widget-social-icons.min.css?ver=3.34.0") -> /wp-content/plugins/elementor/assets/css/widget-social-icons.min.css?ver=3.34.0 | F46: text/css | G46: 200 | H46: OK | I46: Indexable | L46: 0 | M46: 0 | O46: 0 | P46: 0 | R46: 0 | S46: 0 | U46: 0 | W46: 0 | Y46: 0 | AA46: 0 | AC46: 0 | AM46: 1142 | AN46: 1142 | AO46: 1142 | AP46: 0.437 | AR46: 0 | AW46: 0 | AX46: 1 | AY46: 5 | BA46: 0 | BB46: 0 | BC46: 0 | BD46: 0 | BE46: 0 | BF46: 0 | BG46: 0 | BH46: 0 | BI46: 0 | BJ46: 0 | BP46: 0.257 | BQ46: Fri, 02 Jan 2026 17:29:45 GMT | BV46: 1.1 | EQ46: https://salesxceleration.com/wp-content/plugins/elementor/assets/css/widget-social-icons.min.css?ver=3.34.0 | ER46: 46045.298
A47: https://salesxceleration.com/sales-leadership-training/ | B47: =IFERROR(__xludf.DUMMYFUNCTION("REGEXREPLACE(A47, ""^https?://[^/]+"", """")"),"/sales-leadership-training/") -> /sales-leadership-training/ | C47: Sales Training Consultants | D47: Sales Training Programs | E47: Sales Rep Training and Application Coaching | F47: text/html; charset=UTF-8 | G47: 200 | H47: OK | I47: Indexable | K47: Sales Training Consultants - Sales Mentoring & Coaching Programs | L47: 64 | M47: 598 | O47: 0 | P47: 0 | Q47: SalesXceleration offers expert training programs to grow your sales teams and strengthen your leadership layer for profitability. | R47: 129 | S47: 787 | U47: 0 | V47: Sales Training Consultants | W47: 26 | Y47: 0 | Z47: Sales Training Programs | AA47: 23 | AB47: Sales Rep Training and Application Coaching | AC47: 43 | AD47: follow, index, max-snippet:-1, max-video-preview:-1, max-image-preview:large | AG47: https://salesxceleration.com/sales-leadership-training/ | AM47: 240800 | AN47: 63284 | AO47: 63284 | AP47: 24.243 | AR47: 1628 | AS47: 250 | AT47: 6.512 | AU47: 60.698 | AV47: Normal | AW47: 6.292 | AX47: 1 | AY47: 1 | AZ47: 51 | BA47: 3106 | BB47: 754 | BC47: 0 | BD47: 100 | BE47: 136 | BF47: 45 | BG47: 0 | BH47: 23 | BI47: 12 | BJ47: 0 | BO47: c125920efa6cce5520079e35abe6770d | BP47: 0.994 | BU47: en-US | BV47: 1.1 | BW47: 42 | BX47: 4201.03 | BY47: 8231.943 | BZ47: 9902.073 | CA47: 19206.875 | CB47: 688 | CC47: 0.007 | CD47: 672773 | CE47: 750 | CF47: 176 | CG47: 3120971 | CH47: 61823 | CI47: 2 | CJ47: 771248 | CK47: 25 | CL47: 123807 | CM47: 42 | CN47: 1790075 | CO47: 71 | CP47: 348806 | CQ47: 6 | CR47: 0 | CS47: 0 | CT47: 25212 | CU47: 30 | CV47: 1504692 | CW47: 74 | DC47: 0 | DD47: 5074 | DE47: 0 | DF47: 3396 | DG47: 150 | DH47: 50562 | DI47: 600 | DJ47: 613741 | DK47: 2261.077 | DL47: Poor | DM47: 3964.045 | DN47: Poor | DO47: 3120857 | DP47: 1 | DQ47: Avoids redirects | DR47: Server responds quickly (observed 336 ms) | DS47: Applies text compression | DU47: 2 resources found | DV47: 13545 | DX47: 4140 | DY47: 945218 | DZ47: 1 resource found | EA47: 1065 | EB47: 505125 | EC47: 42 | ED47: 26492 | EF47: 225 | EG47: 21 resources found | EH47: 100 | EK47: 100 | EQ47: https://salesxceleration.com/sales-leadership-training/ | ER47: 46045.298
A48: https://salesxceleration.com/wp-content/plugins/elementor/assets/css/conditionals/apple-webkit.min.css?ver=3.34.0 | B48: =IFERROR(__xludf.DUMMYFUNCTION("REGEXREPLACE(A48, ""^https?://[^/]+"", """")"),"/wp-content/plugins/elementor/assets/css/conditionals/apple-webkit.min.css?ver=3.34.0") -> /wp-content/plugins/elementor/assets/css/conditionals/apple-webkit.min.css?ver=3.34.0 | F48: text/css | G48: 200 | H48: OK | I48: Indexable | L48: 0 | M48: 0 | O48: 0 | P48: 0 | R48: 0 | S48: 0 | U48: 0 | W48: 0 | Y48: 0 | AA48: 0 | AC48: 0 | AM48: 547 | AN48: 547 | AO48: 547 | AP48: 0.21 | AR48: 0 | AW48: 0 | AX48: 1 | AY48: 6 | BA48: 0 | BB48: 0 | BC48: 0 | BD48: 0 | BE48: 0 | BF48: 0 | BG48: 0 | BH48: 0 | BI48: 0 | BJ48: 0 | BP48: 0.257 | BQ48: Fri, 02 Jan 2026 17:29:45 GMT | BV48: 1.1 | EQ48: https://salesxceleration.com/wp-content/plugins/elementor/assets/css/conditionals/apple-webkit.min.css?ver=3.34.0 | ER48: 46045.298
A49: https://salesxceleration.com/html-sitemap/ | B49: =IFERROR(__xludf.DUMMYFUNCTION("REGEXREPLACE(A49, ""^https?://[^/]+"", """")"),"/html-sitemap/") -> /html-sitemap/ | C49: HTML Sitemap | F49: text/html; charset=UTF-8 | G49: 200 | H49: OK | I49: Indexable | K49: HTML Sitemap | Sales Xceleration | L49: 32 | M49: 305 | O49: 0 | P49: 0 | Q49: Sales Xceleration Outsourced VP of Sales | R49: 40 | S49: 255 | U49: 0 | V49: HTML Sitemap | W49: 12 | Y49: 0 | AA49: 0 | AC49: 0 | AD49: follow, index, max-snippet:-1, max-video-preview:-1, max-image-preview:large | AG49: https://salesxceleration.com/html-sitemap/ | AM49: 147949 | AN49: 28763 | AO49: 28763 | AP49: 11.019 | AR49: 602 | AS49: 111 | AT49: 5.423 | AU49: 60.939 | AV49: Normal | AW49: 4.12 | AX49: 1 | AY49: 1 | AZ49: 47 | BA49: 747 | BB49: 747 | BC49: 0 | BD49: 99.07 | BE49: 138 | BF49: 45 | BG49: 0 | BH49: 16 | BI49: 8 | BJ49: 0 | BO49: 2529645dae6935d1cb580efaa37b0b11 | BP49: 0.913 | BU49: en-US | BV49: 1.1 | BW49: 50 | BX49: 3751.027 | BY49: 7498.17 | BZ49: 11401.087 | CA49: 18102.33 | CB49: 416.5 | CC49: 0 | CD49: 652501 | CE49: 1200 | CF49: 160 | CG49: 2224501 | CH49: 30190 | CI49: 2 | CJ49: 66994 | CK49: 22 | CL49: 110646 | CM49: 36 | CN49: 1747401 | CO49: 67 | CP49: 244248 | CQ49: 5 | CR49: 0 | CS49: 0 | CT49: 25022 | CU49: 28 | CV49: 1504618 | CW49: 65 | DC49: 0 | DD49: 5075 | DE49: 0 | DF49: 3396 | DG49: 450 | DH49: 50541 | DI49: 750 | DJ49: 593489 | DK49: 1653.352 | DL49: Poor | DM49: 2958.322 | DN49: Poor | DO49: 2224419 | DP49: 1 | DQ49: Avoids redirects | DR49: Server responds quickly (observed 168 ms) | DS49: Applies text compression | DU49: 2 resources found | DV49: 12791 | DX49: 3978 | DY49: 599330 | DZ49: 1 resource found | EA49: 792 | EB49: 31882 | EC49: 1 | ED49: 26492 | EF49: 215 | EG49: 21 resources found | EH49: 100 | EK49: 100 | EQ49: https://salesxceleration.com/html-sitemap/ | ER49: 46045.298
A50: https://salesxceleration.com/wp-content/plugins/powerpack-elements/assets/lib/tooltipster/tooltipster.min.js?ver=2.12.15 | B50: =IFERROR(__xludf.DUMMYFUNCTION("REGEXREPLACE(A50, ""^https?://[^/]+"", """")"),"/wp-content/plugins/powerpack-elements/assets/lib/tooltipster/tooltipster.min.js?ver=2.12.15") -> /wp-content/plugins/powerpack-elements/assets/lib/tooltipster/tooltipster.min.js?ver=2.12.15 | F50: application/javascript | G50: 200 | H50: OK | I50: Indexable | L50: 0 | M50: 0 | O50: 0 | P50: 0 | R50: 0 | S50: 0 | U50: 0 | W50: 0 | Y50: 0 | AA50: 0 | AC50: 0 | AM50: 9963 | AN50: 9963 | AO50: 9963 | AP50: 3.817 | AR50: 0 | AW50: 0 | AX50: 1 | AY50: 6 | BA50: 0 | BB50: 0 | BC50: 0 | BD50: 0 | BE50: 0 | BF50: 0 | BG50: 0 | BH50: 0 | BI50: 0 | BJ50: 0 | BP50: 0.274 | BQ50: Fri, 02 Jan 2026 17:30:38 GMT | BV50: 1.1 | EQ50: https://salesxceleration.com/wp-content/plugins/powerpack-elements/assets/lib/tooltipster/tooltipster.min.js?ver=2.12.15 | ER50: 46045.298
A51: https://salesxceleration.com/wp-content/uploads/elementor/css/post-40969.css?ver=1768845972 | B51: =IFERROR(__xludf.DUMMYFUNCTION("REGEXREPLACE(A51, ""^https?://[^/]+"", """")"),"/wp-content/uploads/elementor/css/post-40969.css?ver=1768845972") -> /wp-content/uploads/elementor/css/post-40969.css?ver=1768845972 | F51: text/css | G51: 200 | H51: OK | I51: Indexable | L51: 0 | M51: 0 | O51: 0 | P51: 0 | R51: 0 | S51: 0 | U51: 0 | W51: 0 | Y51: 0 | AA51: 0 | AC51: 0 | AM51: 287 | AN51: 287 | AO51: 287 | AP51: 0.11 | AR51: 0 | AW51: 0 | AX51: 1 | AY51: 4 | BA51: 0 | BB51: 0 | BC51: 0 | BD51: 0 | BE51: 0 | BF51: 0 | BG51: 0 | BH51: 0 | BI51: 0 | BJ51: 0 | BP51: 0.261 | BQ51: Mon, 19 Jan 2026 18:06:12 GMT | BV51: 1.1 | EQ51: https://salesxceleration.com/wp-content/uploads/elementor/css/post-40969.css?ver=1768845972 | ER51: 46045.298
A52: https://salesxceleration.com/wp-content/plugins/elementor/assets/css/widget-icon-list.min.css?ver=3.34.0 | B52: =IFERROR(__xludf.DUMMYFUNCTION("REGEXREPLACE(A52, ""^https?://[^/]+"", """")"),"/wp-content/plugins/elementor/assets/css/widget-icon-list.min.css?ver=3.34.0") -> /wp-content/plugins/elementor/assets/css/widget-icon-list.min.css?ver=3.34.0 | F52: text/css | G52: 200 | H52: OK | I52: Indexable | L52: 0 | M52: 0 | O52: 0 | P52: 0 | R52: 0 | S52: 0 | U52: 0 | W52: 0 | Y52: 0 | AA52: 0 | AC52: 0 | AM52: 1023 | AN52: 1023 | AO52: 1023 | AP52: 0.392 | AR52: 0 | AW52: 0 | AX52: 1 | AY52: 5 | BA52: 0 | BB52: 0 | BC52: 0 | BD52: 0 | BE52: 0 | BF52: 0 | BG52: 0 | BH52: 0 | BI52: 0 | BJ52: 0 | BP52: 0.276 | BQ52: Fri, 02 Jan 2026 17:29:45 GMT | BV52: 1.1 | EQ52: https://salesxceleration.com/wp-content/plugins/elementor/assets/css/widget-icon-list.min.css?ver=3.34.0 | ER52: 46045.298
A53: https://salesxceleration.com/wp-content/plugins/elementor/assets/js/frontend-modules.min.js?ver=3.34.0 | B53: =IFERROR(__xludf.DUMMYFUNCTION("REGEXREPLACE(A53, ""^https?://[^/]+"", """")"),"/wp-content/plugins/elementor/assets/js/frontend-modules.min.js?ver=3.34.0") -> /wp-content/plugins/elementor/assets/js/frontend-modules.min.js?ver=3.34.0 | F53: application/javascript | G53: 200 | H53: OK | I53: Indexable | L53: 0 | M53: 0 | O53: 0 | P53: 0 | R53: 0 | S53: 0 | U53: 0 | W53: 0 | Y53: 0 | AA53: 0 | AC53: 0 | AM53: 25657 | AN53: 25657 | AO53: 25657 | AP53: 9.829 | AR53: 0 | AW53: 0 | AX53: 1 | AY53: 5 | BA53: 0 | BB53: 0 | BC53: 0 | BD53: 0 | BE53: 0 | BF53: 0 | BG53: 0 | BH53: 0 | BI53: 0 | BJ53: 0 | BP53: 0.446 | BQ53: Fri, 02 Jan 2026 17:29:45 GMT | BV53: 1.1 | EQ53: https://salesxceleration.com/wp-content/plugins/elementor/assets/js/frontend-modules.min.js?ver=3.34.0 | ER53: 46045.298
A54: https://salesxceleration.com/sales-management/ | B54: =IFERROR(__xludf.DUMMYFUNCTION("REGEXREPLACE(A54, ""^https?://[^/]+"", """")"),"/sales-management/") -> /sales-management/ | C54: Sales Management Consulting Services | D54: Transform Your Sales with Proven Expertise | E54: How We Build Your Sales Success | F54: text/html; charset=UTF-8 | G54: 200 | H54: OK | I54: Indexable | K54: Sales Management Consulting | Sales Xceleration | L54: 47 | M54: 444 | O54: 0 | P54: 0 | Q54: Elevate your SMB with Sales Xceleration’s fractional sales management solutions. Our expert consultants drive performance, streamline processes, and deliver measurable growth. Request a free consultation today! | R54: 210 | S54: 1320 | U54: 0 | V54: Sales Management Consulting Services | W54: 36 | Y54: 0 | Z54: Transform Your Sales with Proven Expertise | AA54: 42 | AB54: How We Build Your Sales Success | AC54: 31 | AD54: follow, index, max-snippet:-1, max-video-preview:-1, max-image-preview:large | AG54: https://salesxceleration.com/sales-management/ | AM54: 585861 | AN54: 166130 | AO54: 166130 | AP54: 63.641 | AR54: 1546 | AS54: 268 | AT54: 5.769 | AU54: 53.231 | AV54: Fairly Hard | AW54: 2.418 | AX54: 1 | AY54: 1 | AZ54: 51 | BA54: 2375 | BB54: 754 | BC54: 0 | BD54: 100 | BE54: 137 | BF54: 49 | BG54: 0 | BH54: 16 | BI54: 8 | BJ54: 0 | BO54: 69d6e0ac354569abcac4605849a0b4a7 | BP54: 1.173 | BU54: en-US | BV54: 1.1 | BW54: 51 | BX54: 4051.007 | BY54: 7778.126 | BZ54: 10202.019 | CA54: 19152.818 | CB54: 360 | CC54: 0 | CD54: 662955 | CE54: 750 | CF54: 178 | CG54: 3231240 | CH54: 156481 | CI54: 2 | CJ54: 762844 | CK54: 25 | CL54: 124351 | CM54: 43 | CN54: 1791600 | CO54: 71 | CP54: 370754 | CQ54: 7 | CR54: 0 | CS54: 0 | CT54: 25210 | CU54: 30 | CV54: 1526022 | CW54: 76 | DC54: 0 | DD54: 5075 | DE54: 0 | DF54: 3396 | DG54: 150 | DH54: 40154 | DI54: 600 | DJ54: 614330 | DK54: 1684.416 | DL54: Poor | DM54: 3301.812 | DN54: Poor | DO54: 3231241 | DP54: 1 | DQ54: Avoids redirects | DR54: Server responds quickly (observed 514 ms) | DS54: Applies text compression | DU54: 2 resources found | DV54: 13575 | DX54: 4355 | DY54: 942937 | DZ54: 1 resource found | EA54: 1845 | EB54: 499109 | EC54: 22 | ED54: 26492 | EF54: 370 | EG54: 21 resources found | EH54: 100 | EK54: 100 | EQ54: https://salesxceleration.com/sales-management/ | ER54: 46045.298
A55: https://salesxceleration.com/ebooks/ | B55: =IFERROR(__xludf.DUMMYFUNCTION("REGEXREPLACE(A55, ""^https?://[^/]+"", """")"),"/ebooks/") -> /ebooks/ | C55: Sales eBooks for SMBs from Sales Xceleration | D55: Unlock Sales Growth with AI | E55: State of Sales: Small to Mid-Size Business | F55: text/html; charset=UTF-8 | G55: 200 | H55: OK | I55: Indexable | K55: Sales eBooks for SMBs | Sales Xceleration | L55: 41 | M55: 376 | O55: 0 | P55: 0 | Q55: Download free sales eBooks from Sales Xceleration for SMBs. Improve sales strategies and performance with expert insights and training materials. | R55: 145 | S55: 911 | U55: 0 | V55: Sales eBooks for SMBs from Sales Xceleration | W55: 44 | Y55: 0 | Z55: Unlock Sales Growth with AI | AA55: 27 | AB55: State of Sales: Small to Mid-Size Business | AC55: 42 | AD55: follow, index, max-snippet:-1, max-video-preview:-1, max-image-preview:large | AG55: https://salesxceleration.com/ebooks/ | AM55: 200744 | AN55: 32649 | AO55: 32649 | AP55: 12.507 | AR55: 871 | AS55: 143 | AT55: 6.091 | AU55: 58.552 | AV55: Fairly Hard | AW55: 3.903 | AX55: 1 | AY55: 1 | AZ55: 52 | BA55: 2263 | BB55: 754 | BC55: 0 | BD55: 100 | BE55: 132 | BF55: 52 | BG55: 0 | BH55: 16 | BI55: 8 | BJ55: 0 | BO55: e2a882c91091a35f4f3d4aab251d05c8 | BP55: 0.986 | BU55: en-US | BV55: 1.1 | BW55: 59 | BX55: 4051.039 | BY55: 6550.963 | BZ55: 8701.088 | CA55: 18921.574 | CB55: 155.5 | CC55: 0 | CD55: 653150 | CE55: 1200 | CF55: 163 | CG55: 2419614 | CH55: 34028 | CI55: 2 | CJ55: 168226 | CK55: 21 | CL55: 114816 | CM55: 37 | CN55: 1748054 | CO55: 68 | CP55: 329251 | CQ55: 7 | CR55: 0 | CS55: 0 | CT55: 25239 | CU55: 28 | CV55: 1504898 | CW55: 67 | DC55: 0 | DD55: 5075 | DE55: 0 | DF55: 3396 | DG55: 150 | DH55: 50573 | DI55: 1050 | DJ55: 594106 | DK55: 1016.389 | DL55: Good | DM55: 1885.619 | DN55: Good | DO55: 2419250 | DP55: 1 | DQ55: Avoids redirects | DR55: Server responds quickly (observed 167 ms) | DS55: Applies text compression | DT55: 1 issue found | DU55: 4 resources found | DV55: 12970 | DX55: 3070 | DY55: 675643 | EA55: 986 | EB55: 4453 | EC55: 0 | ED55: 26492 | EF55: 235 | EG55: 21 resources found | EH55: 100 | EK55: 100 | EQ55: https://salesxceleration.com/ebooks/ | ER55: 46045.298
A56: https://salesxceleration.com/industries/technology/ | B56: =IFERROR(__xludf.DUMMYFUNCTION("REGEXREPLACE(A56, ""^https?://[^/]+"", """")"),"/industries/technology/") -> /industries/technology/ | C56: Fractional Sales Leadership for Tech Companies | D56: Scale Revenue in Competitive Markets | E56: Key Sales Challenges in the Tech Space | F56: text/html; charset=UTF-8 | G56: 200 | H56: OK | I56: Non-Indexable | J56: Canonicalised | K56: Fractional Sales Leadership for Tech Businesses | Sales Xceleration | Sales Xceleration | L56: 87 | M56: 774 | N56: Sales Xceleration Infographic | O56: 29 | P56: 261 | Q56: Tailored systems designed to overcome the unique challenges in the tech industry, delivering measurable revenue growth and scalable systems. | R56: 140 | S56: 883 | U56: 0 | V56: Fractional Sales Leadership for Tech Companies | W56: 46 | Y56: 0 | Z56: Scale Revenue in Competitive Markets | AA56: 36 | AB56: Key Sales Challenges in the Tech Space | AC56: 38 | AD56: follow, index, max-snippet:-1, max-video-preview:-1, max-image-preview:large | AG56: https://salesxceleration.com/technology/ | AM56: 276692 | AN56: 87189 | AO56: 87189 | AP56: 33.4 | AR56: 1623 | AS56: 270 | AT56: 6.011 | AU56: 54.156 | AV56: Fairly Hard | AW56: 6.535 | AX56: 1 | AY56: 2 | BA56: 2250 | BB56: 754 | BC56: 0 | BD56: 100 | BE56: 131 | BF56: 46 | BG56: 0 | BH56: 16 | BI56: 8 | BJ56: 0 | BO56: 541e4100bff0435a3a752569c0c7a46e | BP56: 1.048 | BU56: en-US | BV56: 1.1 | BW56: 53 | BX56: 4201.009 | BY56: 8812.093 | BZ56: 9752.021 | CA56: 19673.188 | CB56: 274.5 | CC56: 0.006 | CD56: 672445 | CE56: 900 | CF56: 179 | CG56: 3185469 | CH56: 85236 | CI56: 2 | CJ56: 762839 | CK56: 25 | CL56: 128104 | CM56: 45 | CN56: 1791361 | CO56: 71 | CP56: 392582 | CQ56: 7 | CR56: 0 | CS56: 0 | CT56: 25347 | CU56: 29 | CV56: 1550978 | CW56: 76 | DC56: 0 | DD56: 5075 | DE56: 0 | DF56: 3397 | DG56: 300 | DH56: 50542 | DI56: 600 | DJ56: 613431 | DK56: 1624.397 | DL56: Poor | DM56: 3130.577 | DN56: Poor | DO56: 3185470 | DP56: 1 | DQ56: Avoids redirects | DR56: Server responds quickly (observed 339 ms) | DS56: Applies text compression | DU56: 2 resources found | DV56: 14749 | DX56: 4385 | DY56: 943125 | DZ56: 1 resource found | EA56: 1227 | EB56: 499109 | EC56: 74 | ED56: 26492 | EF56: 235 | EG56: 21 resources found | EH56: 100 | EK56: 100 | EQ56: https://salesxceleration.com/industries/technology/ | ER56: 46045.298
A57: https://salesxceleration.com/wp-content/plugins/elementor/assets/js/frontend.min.js?ver=3.34.0 | B57: =IFERROR(__xludf.DUMMYFUNCTION("REGEXREPLACE(A57, ""^https?://[^/]+"", """")"),"/wp-content/plugins/elementor/assets/js/frontend.min.js?ver=3.34.0") -> /wp-content/plugins/elementor/assets/js/frontend.min.js?ver=3.34.0 | F57: application/javascript | G57: 200 | H57: OK | I57: Indexable | L57: 0 | M57: 0 | O57: 0 | P57: 0 | R57: 0 | S57: 0 | U57: 0 | W57: 0 | Y57: 0 | AA57: 0 | AC57: 0 | AM57: 10325 | AN57: 10325 | AO57: 10325 | AP57: 3.955 | AR57: 0 | AW57: 0 | AX57: 1 | AY57: 5 | BA57: 0 | BB57: 0 | BC57: 0 | BD57: 0 | BE57: 0 | BF57: 0 | BG57: 0 | BH57: 0 | BI57: 0 | BJ57: 0 | BP57: 0.281 | BQ57: Fri, 02 Jan 2026 17:29:45 GMT | BV57: 1.1 | EQ57: https://salesxceleration.com/wp-content/plugins/elementor/assets/js/frontend.min.js?ver=3.34.0 | ER57: 46045.298
A58: https://salesxceleration.com/wp-content/uploads/2024/04/Revitalizing-Sales-Strategy-for-Sustained-Growth-Cover.jpg | B58: =IFERROR(__xludf.DUMMYFUNCTION("REGEXREPLACE(A58, ""^https?://[^/]+"", """")"),"/wp-content/uploads/2024/04/Revitalizing-Sales-Strategy-for-Sustained-Growth-Cover.jpg") -> /wp-content/uploads/2024/04/Revitalizing-Sales-Strategy-for-Sustained-Growth-Cover.jpg | F58: image/jpeg | G58: 200 | H58: OK | I58: Indexable | L58: 0 | M58: 0 | O58: 0 | P58: 0 | R58: 0 | S58: 0 | U58: 0 | W58: 0 | Y58: 0 | AA58: 0 | AC58: 0 | AM58: 50775 | AN58: 50775 | AO58: 50775 | AP58: 19.451 | AR58: 0 | AW58: 0 | AX58: 1 | AY58: 4 | BA58: 0 | BB58: 0 | BC58: 0 | BD58: 0 | BE58: 0 | BF58: 0 | BG58: 0 | BH58: 0 | BI58: 0 | BJ58: 0 | BP58: 0.269 | BQ58: Wed, 08 May 2024 18:13:36 GMT | BV58: 1.1 | EQ58: https://salesxceleration.com/wp-content/uploads/2024/04/Revitalizing-Sales-Strategy-for-Sustained-Growth-Cover.jpg | ER58: 46045.298
A59: https://salesxceleration.com/wp-content/plugins/elementor/assets/lib/animations/styles/fadeInUp.min.css?ver=3.34.0 | B59: =IFERROR(__xludf.DUMMYFUNCTION("REGEXREPLACE(A59, ""^https?://[^/]+"", """")"),"/wp-content/plugins/elementor/assets/lib/animations/styles/fadeInUp.min.css?ver=3.34.0") -> /wp-content/plugins/elementor/assets/lib/animations/styles/fadeInUp.min.css?ver=3.34.0 | F59: text/css | G59: 200 | H59: OK | I59: Indexable | L59: 0 | M59: 0 | O59: 0 | P59: 0 | R59: 0 | S59: 0 | U59: 0 | W59: 0 | Y59: 0 | AA59: 0 | AC59: 0 | AM59: 117 | AN59: 117 | AO59: 117 | AP59: 0.045 | AR59: 0 | AW59: 0 | AX59: 1 | AY59: 7 | BA59: 0 | BB59: 0 | BC59: 0 | BD59: 0 | BE59: 0 | BF59: 0 | BG59: 0 | BH59: 0 | BI59: 0 | BJ59: 0 | BP59: 0.268 | BQ59: Fri, 02 Jan 2026 17:29:45 GMT | BV59: 1.1 | EQ59: https://salesxceleration.com/wp-content/plugins/elementor/assets/lib/animations/styles/fadeInUp.min.css?ver=3.34.0 | ER59: 46045.298
A60: https://salesxceleration.com/wp-content/plugins/elementor/assets/css/widget-divider.min.css?ver=3.34.0 | B60: =IFERROR(__xludf.DUMMYFUNCTION("REGEXREPLACE(A60, ""^https?://[^/]+"", """")"),"/wp-content/plugins/elementor/assets/css/widget-divider.min.css?ver=3.34.0") -> /wp-content/plugins/elementor/assets/css/widget-divider.min.css?ver=3.34.0 | F60: text/css | G60: 200 | H60: OK | I60: Indexable | L60: 0 | M60: 0 | O60: 0 | P60: 0 | R60: 0 | S60: 0 | U60: 0 | W60: 0 | Y60: 0 | AA60: 0 | AC60: 0 | AM60: 741 | AN60: 741 | AO60: 741 | AP60: 0.284 | AR60: 0 | AW60: 0 | AX60: 1 | AY60: 5 | BA60: 0 | BB60: 0 | BC60: 0 | BD60: 0 | BE60: 0 | BF60: 0 | BG60: 0 | BH60: 0 | BI60: 0 | BJ60: 0 | BP60: 0.25 | BQ60: Fri, 02 Jan 2026 17:29:45 GMT | BV60: 1.1 | EQ60: https://salesxceleration.com/wp-content/plugins/elementor/assets/css/widget-divider.min.css?ver=3.34.0 | ER60: 46045.298
A61: https://salesxceleration.com/industries/manufacturing/ | B61: =IFERROR(__xludf.DUMMYFUNCTION("REGEXREPLACE(A61, ""^https?://[^/]+"", """")"),"/industries/manufacturing/") -> /industries/manufacturing/ | C61: Fractional Sales Leadership for Manufacturing Companies | D61: Scale Revenue in Competitive Markets | E61: Key Sales Challenges in Manufacturing | F61: text/html; charset=UTF-8 | G61: 200 | H61: OK | I61: Indexable | K61: Fractional VP of Sales for Manufacturing | Sales Xceleration | L61: 60 | M61: 533 | N61: Sales Xceleration Infographic | O61: 29 | P61: 261 | Q61: Tailored systems designed to overcome the unique challenges in the manufacturing industry, delivering measurable revenue growth and scalable systems. | R61: 149 | S61: 949 | U61: 0 | V61: Fractional Sales Leadership for Manufacturing Companies | W61: 55 | Y61: 0 | Z61: Scale Revenue in Competitive Markets | AA61: 36 | AB61: Key Sales Challenges in Manufacturing | AC61: 37 | AD61: follow, index, max-snippet:-1, max-video-preview:-1, max-image-preview:large | AG61: https://salesxceleration.com/industries/manufacturing/ | AM61: 274302 | AN61: 86402 | AO61: 86402 | AP61: 33.099 | AR61: 1490 | AS61: 248 | AT61: 6.008 | AU61: 42.438 | AV61: Hard | AW61: 6.422 | AX61: 1 | AY61: 2 | AZ61: 51 | BA61: 2250 | BB61: 754 | BC61: 0 | BD61: 100 | BE61: 133 | BF61: 44 | BG61: 0 | BH61: 16 | BI61: 8 | BJ61: 0 | BO61: 48e379aaabf01c717361394b310220fc | BP61: 1.059 | BU61: en-US | BV61: 1.1 | BW61: 53 | BX61: 3901.014 | BY61: 6751.641 | BZ61: 9451.035 | CA61: 20933.252 | CB61: 363.5 | CC61: 0 | CD61: 675828 | CE61: 900 | CF61: 175 | CG61: 3082575 | CH61: 84567 | CI61: 2 | CJ61: 762834 | CK61: 22 | CL61: 124136 | CM61: 46 | CN61: 1791115 | CO61: 71 | CP61: 294886 | CQ61: 6 | CR61: 0 | CS61: 0 | CT61: 25037 | CU61: 28 | CV61: 1502504 | CW61: 72 | DC61: 0 | DD61: 5075 | DE61: 0 | DF61: 3396 | DG61: 300 | DH61: 50543 | DI61: 600 | DJ61: 616814 | DK61: 1704.545 | DL61: Poor | DM61: 3160.757 | DN61: Poor | DO61: 3082576 | DP61: 1 | DQ61: Avoids redirects | DR61: Server responds quickly (observed 337 ms) | DS61: Applies text compression | DU61: 2 resources found | DV61: 15508 | DX61: 3632 | DY61: 921630 | EA61: 1189 | EB61: 499109 | EC61: 3 | ED61: 26492 | EF61: 235 | EG61: 21 resources found | EH61: 100 | EK61: 100 | EQ61: https://salesxceleration.com/industries/manufacturing/ | ER61: 46045.298
A62: https://salesxceleration.com/wp-content/themes/salesxceleratione/assets/js/slick-1.8.1.min.js?ver=1.8.1 | B62: =IFERROR(__xludf.DUMMYFUNCTION("REGEXREPLACE(A62, ""^https?://[^/]+"", """")"),"/wp-content/themes/salesxceleratione/assets/js/slick-1.8.1.min.js?ver=1.8.1") -> /wp-content/themes/salesxceleratione/assets/js/slick-1.8.1.min.js?ver=1.8.1 | F62: application/javascript | G62: 200 | H62: OK | I62: Indexable | L62: 0 | M62: 0 | O62: 0 | P62: 0 | R62: 0 | S62: 0 | U62: 0 | W62: 0 | Y62: 0 | AA62: 0 | AC62: 0 | AM62: 10718 | AN62: 10718 | AO62: 10718 | AP62: 4.106 | AR62: 0 | AW62: 0 | AX62: 1 | AY62: 5 | BA62: 0 | BB62: 0 | BC62: 0 | BD62: 0 | BE62: 0 | BF62: 0 | BG62: 0 | BH62: 0 | BI62: 0 | BJ62: 0 | BP62: 0.259 | BQ62: Fri, 12 Nov 2021 15:43:34 GMT | BV62: 1.1 | EQ62: https://salesxceleration.com/wp-content/themes/salesxceleratione/assets/js/slick-1.8.1.min.js?ver=1.8.1 | ER62: 46045.298
A63: https://salesxceleration.com/wp-content/plugins/powerpack-elements/assets/css/min/extensions.min.css?ver=2.12.15 | B63: =IFERROR(__xludf.DUMMYFUNCTION("REGEXREPLACE(A63, ""^https?://[^/]+"", """")"),"/wp-content/plugins/powerpack-elements/assets/css/min/extensions.min.css?ver=2.12.15") -> /wp-content/plugins/powerpack-elements/assets/css/min/extensions.min.css?ver=2.12.15 | F63: text/css | G63: 200 | H63: OK | I63: Indexable | L63: 0 | M63: 0 | O63: 0 | P63: 0 | R63: 0 | S63: 0 | U63: 0 | W63: 0 | Y63: 0 | AA63: 0 | AC63: 0 | AM63: 394 | AN63: 394 | AO63: 394 | AP63: 0.151 | AR63: 0 | AW63: 0 | AX63: 1 | AY63: 6 | BA63: 0 | BB63: 0 | BC63: 0 | BD63: 0 | BE63: 0 | BF63: 0 | BG63: 0 | BH63: 0 | BI63: 0 | BJ63: 0 | BP63: 0.265 | BQ63: Fri, 02 Jan 2026 17:30:38 GMT | BV63: 1.1 | EQ63: https://salesxceleration.com/wp-content/plugins/powerpack-elements/assets/css/min/extensions.min.css?ver=2.12.15 | ER63: 46045.298
A64: https://salesxceleration.com/wp-content/uploads/2021/02/thumb-consulting-cs.jpg | B64: =IFERROR(__xludf.DUMMYFUNCTION("REGEXREPLACE(A64, ""^https?://[^/]+"", """")"),"/wp-content/uploads/2021/02/thumb-consulting-cs.jpg") -> /wp-content/uploads/2021/02/thumb-consulting-cs.jpg | F64: image/jpeg | G64: 200 | H64: OK | I64: Indexable | L64: 0 | M64: 0 | O64: 0 | P64: 0 | R64: 0 | S64: 0 | U64: 0 | W64: 0 | Y64: 0 | AA64: 0 | AC64: 0 | AM64: 106825 | AN64: 106825 | AO64: 106825 | AP64: 40.923 | AR64: 0 | AW64: 0 | AX64: 1 | AY64: 4 | BA64: 0 | BB64: 0 | BC64: 0 | BD64: 0 | BE64: 0 | BF64: 0 | BG64: 0 | BH64: 0 | BI64: 0 | BJ64: 0 | BP64: 0.27 | BQ64: Mon, 03 Jan 2022 14:44:53 GMT | BV64: 1.1 | EQ64: https://salesxceleration.com/wp-content/uploads/2021/02/thumb-consulting-cs.jpg | ER64: 46045.298
A65: https://salesxceleration.com/wp-content/uploads/elementor/css/post-68977.css?ver=1768845999 | B65: =IFERROR(__xludf.DUMMYFUNCTION("REGEXREPLACE(A65, ""^https?://[^/]+"", """")"),"/wp-content/uploads/elementor/css/post-68977.css?ver=1768845999") -> /wp-content/uploads/elementor/css/post-68977.css?ver=1768845999 | F65: text/css | G65: 200 | H65: OK | I65: Indexable | L65: 0 | M65: 0 | O65: 0 | P65: 0 | R65: 0 | S65: 0 | U65: 0 | W65: 0 | Y65: 0 | AA65: 0 | AC65: 0 | AM65: 2156 | AN65: 2156 | AO65: 2156 | AP65: 0.826 | AR65: 0 | AW65: 0 | AX65: 1 | AY65: 4 | BA65: 0 | BB65: 0 | BC65: 0 | BD65: 0 | BE65: 0 | BF65: 0 | BG65: 0 | BH65: 0 | BI65: 0 | BJ65: 0 | BP65: 0.254 | BQ65: Mon, 19 Jan 2026 18:06:39 GMT | BV65: 1.1 | EQ65: https://salesxceleration.com/wp-content/uploads/elementor/css/post-68977.css?ver=1768845999 | ER65: 46045.298
A66: https://salesxceleration.com/wp-content/uploads/2021/06/logo-sales-xceleration-ko-1024x231.png | B66: =IFERROR(__xludf.DUMMYFUNCTION("REGEXREPLACE(A66, ""^https?://[^/]+"", """")"),"/wp-content/uploads/2021/06/logo-sales-xceleration-ko-1024x231.png") -> /wp-content/uploads/2021/06/logo-sales-xceleration-ko-1024x231.png | F66: image/png | G66: 200 | H66: OK | I66: Indexable | L66: 0 | M66: 0 | O66: 0 | P66: 0 | R66: 0 | S66: 0 | U66: 0 | W66: 0 | Y66: 0 | AA66: 0 | AC66: 0 | AM66: 18676 | AN66: 18676 | AO66: 18676 | AP66: 7.154 | AR66: 0 | AW66: 0 | AX66: 1 | AY66: 4 | BA66: 0 | BB66: 0 | BC66: 0 | BD66: 0 | BE66: 0 | BF66: 0 | BG66: 0 | BH66: 0 | BI66: 0 | BJ66: 0 | BP66: 0.373 | BQ66: Mon, 19 Jan 2026 16:38:16 GMT | BV66: 1.1 | EQ66: https://salesxceleration.com/wp-content/uploads/2021/06/logo-sales-xceleration-ko-1024x231.png | ER66: 46045.298
A67: https://salesxceleration.com/wp-includes/js/dist/i18n.min.js?ver=c26c3dc7bed366793375 | B67: =IFERROR(__xludf.DUMMYFUNCTION("REGEXREPLACE(A67, ""^https?://[^/]+"", """")"),"/wp-includes/js/dist/i18n.min.js?ver=c26c3dc7bed366793375") -> /wp-includes/js/dist/i18n.min.js?ver=c26c3dc7bed366793375 | F67: application/javascript | G67: 200 | H67: OK | I67: Indexable | L67: 0 | M67: 0 | O67: 0 | P67: 0 | R67: 0 | S67: 0 | U67: 0 | W67: 0 | Y67: 0 | AA67: 0 | AC67: 0 | AM67: 2229 | AN67: 2229 | AO67: 2229 | AP67: 0.854 | AR67: 0 | AW67: 0 | AX67: 1 | AY67: 3 | BA67: 0 | BB67: 0 | BC67: 0 | BD67: 0 | BE67: 0 | BF67: 0 | BG67: 0 | BH67: 0 | BI67: 0 | BJ67: 0 | BP67: 0.276 | BQ67: Fri, 02 Jan 2026 17:49:24 GMT | BV67: 1.1 | EQ67: https://salesxceleration.com/wp-includes/js/dist/i18n.min.js?ver=c26c3dc7bed366793375 | ER67: 46045.298
A68: https://salesxceleration.com/industries/franchises/ | B68: =IFERROR(__xludf.DUMMYFUNCTION("REGEXREPLACE(A68, ""^https?://[^/]+"", """")"),"/industries/franchises/") -> /industries/franchises/ | C68: Fractional Sales Leadership for Franchises | D68: Key Sales Challenges in Franchising | E68: Why Fractional Sales Leadership Fits Franchises | F68: text/html; charset=UTF-8 | G68: 200 | H68: OK | I68: Indexable | K68: Fractional Sales Leadership for Franchises | Sales Xceleration | L68: 62 | M68: 550 | O68: 0 | P68: 0 | Q68: Scale your franchise network with proven sales leadership. We standardize franchisee recruitment, build repeatable sales playbooks, and drive unit-level revenue growth. | R68: 168 | S68: 1035 | U68: 0 | V68: Fractional Sales Leadership for Franchises | W68: 42 | Y68: 0 | Z68: Key Sales Challenges in Franchising | AA68: 35 | AB68: Why Fractional Sales Leadership Fits Franchises | AC68: 47 | AD68: follow, index, max-snippet:-1, max-video-preview:-1, max-image-preview:large | AG68: https://salesxceleration.com/industries/franchises/ | AM68: 275732 | AN68: 90946 | AO68: 90946 | AP68: 34.84 | AR68: 1537 | AS68: 258 | AT68: 5.957 | AU68: 52.394 | AV68: Fairly Hard | AW68: 6.524 | AX68: 1 | AY68: 2 | AZ68: 51 | BA68: 2250 | BB68: 754 | BC68: 0 | BD68: 100 | BE68: 134 | BF68: 46 | BG68: 0 | BH68: 16 | BI68: 8 | BJ68: 0 | BO68: 84252576710167807ae2fae92523048c | BP68: 1.068 | BU68: en-US | BV68: 1.1 | BW68: 49 | BX68: 3601.009 | BY68: 7740.616 | BZ68: 9452.025 | CA68: 21049.211 | CB68: 464.5 | CC68: 0 | CD68: 672886 | CE68: 750 | CF68: 179 | CG68: 3142447 | CH68: 89016 | CI68: 2 | CJ68: 762998 | CK68: 26 | CL68: 124658 | CM68: 44 | CN68: 1791458 | CO68: 71 | CP68: 348806 | CQ68: 6 | CR68: 0 | CS68: 0 | CT68: 25511 | CU68: 30 | CV68: 1503233 | CW68: 76 | DC68: 0 | DD68: 5075 | DE68: 0 | DF68: 3396 | DG68: 150 | DH68: 50543 | DI68: 600 | DJ68: 613872 | DK68: 1922.089 | DL68: Poor | DM68: 3552.398 | DN68: Poor | DO68: 3142285 | DP68: 1 | DQ68: Avoids redirects | DR68: Server responds quickly (observed 333 ms) | DS68: Applies text compression | DU68: 2 resources found | DV68: 13547 | DW68: 313 | DX68: 4098 | DY68: 943409 | DZ68: 1 resource found | EA68: 1161 | EB68: 499109 | EC68: 1 | ED68: 26492 | EF68: 235 | EG68: 21 resources found | EH68: 100 | EK68: 100 | EQ68: https://salesxceleration.com/industries/franchises/ | ER68: 46045.298
A69: https://salesxceleration.com/private-equity-solutions/ | B69: =IFERROR(__xludf.DUMMYFUNCTION("REGEXREPLACE(A69, ""^https?://[^/]+"", """")"),"/private-equity-solutions/") -> /private-equity-solutions/ | C69: Creating Scalable, Profitable Revenue Growth | D69: Our Advisors have a proven track record of collaborating with PE Firms | E69: Maximize Your Return on Investment | F69: text/html; charset=UTF-8 | G69: 200 | H69: OK | I69: Indexable | K69: Improve Sales Performance & Quality | Sales Xceleration | L69: 55 | M69: 504 | O69: 0 | P69: 0 | Q69: Boost sales with Sales Xceleration's Quality of Sales program. Our strategies drive revenue growth and enterprise value for private equity and portfolio companies. | R69: 163 | S69: 998 | U69: 0 | V69: Creating Scalable, Profitable Revenue Growth | W69: 44 | Y69: 0 | Z69: Our Advisors have a proven track record of collaborating with PE Firms | AA69: 70 | AB69: Maximize Your Return on Investment | AC69: 34 | AD69: follow, index, max-snippet:-1, max-video-preview:-1, max-image-preview:large | AG69: https://salesxceleration.com/private-equity-solutions/ | AM69: 239938 | AN69: 49275 | AO69: 49275 | AP69: 18.876 | AR69: 1083 | AS69: 177 | AT69: 6.119 | AU69: 50.172 | AV69: Fairly Hard | AW69: 4.962 | AX69: 1 | AY69: 1 | AZ69: 51 | BA69: 2296 | BB69: 754 | BC69: 0 | BD69: 100 | BE69: 114 | BF69: 44 | BG69: 0 | BH69: 7 | BI69: 6 | BJ69: 0 | BO69: 5c5915357c222e3fe4dd0b49fb6b8aeb | BP69: 0.994 | BU69: en-US | BV69: 1.1 | BW69: 47 | BX69: 3601.02 | BY69: 9977.16 | BZ69: 9752.058 | CA69: 20192.814 | CB69: 462.5 | CC69: 0 | CD69: 673075 | CE69: 1050 | CF69: 207 | CG69: 2974253 | CH69: 50836 | CI69: 2 | CJ69: 659918 | CK69: 48 | CL69: 128158 | CM69: 45 | CN69: 1822178 | CO69: 77 | CP69: 287902 | CQ69: 5 | CR69: 0 | CS69: 0 | CT69: 25261 | CU69: 30 | CV69: 1504769 | CW69: 79 | DC69: 0 | DD69: 5074 | DE69: 0 | DF69: 3396 | DG69: 150 | DH69: 50755 | DI69: 900 | DJ69: 613850 | DK69: 2430.224 | DL69: Poor | DM69: 6209.114 | DN69: Poor | DO69: 2974075 | DP69: 1 | DQ69: Avoids redirects | DR69: Server responds quickly (observed 332 ms) | DS69: Applies text compression | DT69: 1 issue found | DU69: 4 resources found | DV69: 13698 | DX69: 4432 | DY69: 890869 | DZ69: 2 resources found | EA69: 1049 | EB69: 87764 | EC69: 57 | ED69: 26492 | EF69: 670 | EG69: 21 resources found | EH69: 100 | EK69: 100 | EQ69: https://salesxceleration.com/private-equity-solutions/ | ER69: 46045.298
A70: https://salesxceleration.com/ai-for-sales/ | B70: =IFERROR(__xludf.DUMMYFUNCTION("REGEXREPLACE(A70, ""^https?://[^/]+"", """")"),"/ai-for-sales/") -> /ai-for-sales/ | C70: Artificial Intelligence (AI) for Sales | D70: Embrace AI to Enhance Sales Strategies | F70: text/html; charset=UTF-8 | G70: 200 | H70: OK | I70: Indexable | K70: AI for Sales | Sales Xceleration | L70: 32 | M70: 273 | O70: 0 | P70: 0 | Q70: Discover how AI for sales can revolutionize your sales processes. Learn how AI-driven tools can enhance lead generation, forecasting, and team performance. | R70: 155 | S70: 970 | U70: 0 | V70: Artificial Intelligence (AI) for Sales | W70: 38 | Y70: 0 | Z70: Embrace AI to Enhance Sales Strategies | AA70: 38 | AC70: 0 | AD70: follow, index, max-snippet:-1, max-video-preview:-1, max-image-preview:large | AG70: https://salesxceleration.com/ai-for-sales/ | AM70: 247488 | AN70: 41150 | AO70: 41150 | AP70: 15.764 | AR70: 1947 | AS70: 346 | AT70: 5.627 | AU70: 53.562 | AV70: Fairly Hard | AW70: 6.056 | AX70: 1 | AY70: 1 | AZ70: 52 | BA70: 2264 | BB70: 754 | BC70: 0 | BD70: 100 | BE70: 155 | BF70: 57 | BG70: 0 | BH70: 59 | BI70: 48 | BJ70: 0 | BO70: 25cf8f6e65e2dbd7ea16d2e42e8d37fc | BP70: 1.27 | BU70: en-US | BV70: 1.1 | BW70: 44 | BX70: 3451.058 | BY70: 7273.664 | BZ70: 6151.107 | CA70: 19155.137 | CB70: 872.5 | CC70: 0.01 | CD70: 673033 | CE70: 750 | CF70: 201 | CG70: 11190502 | CH70: 41890 | CI70: 2 | CJ70: 276003 | CK70: 35 | CL70: 132168 | CM70: 49 | CN70: 1809417 | CO70: 76 | CP70: 399444 | CQ70: 7 | CR70: 8506326 | CS70: 3 | CT70: 25254 | CU70: 29 | CV70: 1504965 | CW70: 80 | DC70: 0 | DD70: 5075 | DE70: 0 | DF70: 3396 | DG70: 150 | DH70: 50516 | DI70: 600 | DJ70: 614046 | DK70: 2608.594 | DL70: Poor | DM70: 5520.6 | DN70: Poor | DO70: 11189332 | DP70: 1 | DQ70: Avoids redirects | DR70: Server responds quickly (observed 329 ms) | DS70: Applies text compression | DT70: 1 issue found | DU70: 4 resources found | DV70: 14029 | DX70: 4756 | DY70: 778387 | DZ70: 1 resource found | EA70: 1396 | EB70: 19075 | EC70: 201 | ED70: 26492 | EF70: 245 | EG70: 21 resources found | EH70: 100 | EK70: 100 | EQ70: https://salesxceleration.com/ai-for-sales/ | ER70: 46045.298
A71: https://salesxceleration.com/how-we-serve/ | B71: =IFERROR(__xludf.DUMMYFUNCTION("REGEXREPLACE(A71, ""^https?://[^/]+"", """")"),"/how-we-serve/") -> /how-we-serve/ | C71: How We Serve | D71: “Integrity, character and ethics, lived out in service for others" | E71: Sales Xceleration Day of Giving | F71: text/html; charset=UTF-8 | G71: 200 | H71: OK | I71: Indexable | K71: Our Sales Consulting Services | Sales Xceleration | L71: 49 | M71: 438 | O71: 0 | P71: 0 | Q71: Discover how Sales Xceleration provides expert sales consulting services, including strategy, leadership, and support to drive your business growth. | R71: 148 | S71: 905 | U71: 0 | V71: How We Serve | W71: 12 | Y71: 0 | Z71: “Integrity, character and ethics, lived out in service for others" | AA71: 66 | AB71: Sales Xceleration Day of Giving | AC71: 31 | AD71: follow, index, max-snippet:-1, max-video-preview:-1, max-image-preview:large | AG71: https://salesxceleration.com/how-we-serve/ | AM71: 207188 | AN71: 36762 | AO71: 36762 | AP71: 14.083 | AR71: 1340 | AS71: 224 | AT71: 5.982 | AU71: 73.169 | AV71: Fairly Easy | AW71: 4.949 | AX71: 1 | AY71: 1 | AZ71: 51 | BA71: 2263 | BB71: 754 | BC71: 0 | BD71: 100 | BE71: 130 | BF71: 50 | BG71: 0 | BH71: 70 | BI71: 58 | BJ71: 0 | BO71: c9cf04a6fbb9364a2a2e1ebd9589d929 | BP71: 1.138 | BU71: en-US | BV71: 1.1 | BW71: 45 | BX71: 4051.036 | BY71: 8262.512 | BZ71: 11851.111 | CA71: 19145.797 | CB71: 573.5 | CC71: 0.007 | CD71: 673099 | CE71: 1500 | CF71: 185 | CG71: 2635546 | CH71: 37754 | CI71: 2 | CJ71: 153322 | CK71: 23 | CL71: 129404 | CM71: 47 | CN71: 1805335 | CO71: 75 | CP71: 484453 | CQ71: 9 | CR71: 0 | CS71: 0 | CT71: 25278 | CU71: 29 | CV71: 1504120 | CW71: 70 | DC71: 0 | DD71: 5075 | DE71: 0 | DF71: 3396 | DG71: 300 | DH71: 50541 | DI71: 1200 | DJ71: 614087 | DK71: 2082.366 | DL71: Poor | DM71: 3984.78 | DN71: Poor | DO71: 2635221 | DP71: 1 | DQ71: Avoids redirects | DR71: Server responds quickly (observed 178 ms) | DS71: Applies text compression | DU71: 4 resources found | DV71: 14148 | DX71: 4077 | DY71: 760914 | DZ71: 1 resource found | EA71: 1164 | EB71: 12082 | EC71: 1 | ED71: 26492 | EF71: 240 | EG71: 21 resources found | EH71: 100 | EK71: 100 | EQ71: https://salesxceleration.com/how-we-serve/ | ER71: 46045.298
A72: https://salesxceleration.com/wp-content/uploads/2021/11/Canda-shadow.png | B72: =IFERROR(__xludf.DUMMYFUNCTION("REGEXREPLACE(A72, ""^https?://[^/]+"", """")"),"/wp-content/uploads/2021/11/Canda-shadow.png") -> /wp-content/uploads/2021/11/Canda-shadow.png | F72: image/png | G72: 200 | H72: OK | I72: Indexable | L72: 0 | M72: 0 | O72: 0 | P72: 0 | R72: 0 | S72: 0 | U72: 0 | W72: 0 | Y72: 0 | AA72: 0 | AC72: 0 | AM72: 68364 | AN72: 68364 | AO72: 68364 | AP72: 26.189 | AR72: 0 | AW72: 0 | AX72: 1 | AY72: 4 | BA72: 0 | BB72: 0 | BC72: 0 | BD72: 0 | BE72: 0 | BF72: 0 | BG72: 0 | BH72: 0 | BI72: 0 | BJ72: 0 | BP72: 0.273 | BQ72: Mon, 03 Jan 2022 14:07:50 GMT | BV72: 1.1 | EQ72: https://salesxceleration.com/wp-content/uploads/2021/11/Canda-shadow.png | ER72: 46045.298
A73: https://salesxceleration.com/wp-content/plugins/elementor/assets/css/widget-heading.min.css?ver=3.34.0 | B73: =IFERROR(__xludf.DUMMYFUNCTION("REGEXREPLACE(A73, ""^https?://[^/]+"", """")"),"/wp-content/plugins/elementor/assets/css/widget-heading.min.css?ver=3.34.0") -> /wp-content/plugins/elementor/assets/css/widget-heading.min.css?ver=3.34.0 | F73: text/css | G73: 200 | H73: OK | I73: Indexable | L73: 0 | M73: 0 | O73: 0 | P73: 0 | R73: 0 | S73: 0 | U73: 0 | W73: 0 | Y73: 0 | AA73: 0 | AC73: 0 | AM73: 160 | AN73: 160 | AO73: 160 | AP73: 0.061 | AR73: 0 | AW73: 0 | AX73: 1 | AY73: 5 | BA73: 0 | BB73: 0 | BC73: 0 | BD73: 0 | BE73: 0 | BF73: 0 | BG73: 0 | BH73: 0 | BI73: 0 | BJ73: 0 | BP73: 0.256 | BQ73: Fri, 02 Jan 2026 17:29:45 GMT | BV73: 1.1 | EQ73: https://salesxceleration.com/wp-content/plugins/elementor/assets/css/widget-heading.min.css?ver=3.34.0 | ER73: 46045.298
A74: https://salesxceleration.com/wp-content/uploads/2025/03/nomask-1024x578.jpg | B74: =IFERROR(__xludf.DUMMYFUNCTION("REGEXREPLACE(A74, ""^https?://[^/]+"", """")"),"/wp-content/uploads/2025/03/nomask-1024x578.jpg") -> /wp-content/uploads/2025/03/nomask-1024x578.jpg | F74: image/jpeg | G74: 200 | H74: OK | I74: Indexable | L74: 0 | M74: 0 | O74: 0 | P74: 0 | R74: 0 | S74: 0 | U74: 0 | W74: 0 | Y74: 0 | AA74: 0 | AC74: 0 | AM74: 47222 | AN74: 47222 | AO74: 47222 | AP74: 18.09 | AR74: 0 | AW74: 0 | AX74: 1 | AY74: 4 | BA74: 0 | BB74: 0 | BC74: 0 | BD74: 0 | BE74: 0 | BF74: 0 | BG74: 0 | BH74: 0 | BI74: 0 | BJ74: 0 | BP74: 0.26 | BQ74: Mon, 17 Mar 2025 18:22:48 GMT | BV74: 1.1 | EQ74: https://salesxceleration.com/wp-content/uploads/2025/03/nomask-1024x578.jpg | ER74: 46045.298
A75: https://salesxceleration.com/wp-content/uploads/2025/02/SX-2-1024x684.jpg | B75: =IFERROR(__xludf.DUMMYFUNCTION("REGEXREPLACE(A75, ""^https?://[^/]+"", """")"),"/wp-content/uploads/2025/02/SX-2-1024x684.jpg") -> /wp-content/uploads/2025/02/SX-2-1024x684.jpg | F75: image/jpeg | G75: 200 | H75: OK | I75: Indexable | L75: 0 | M75: 0 | O75: 0 | P75: 0 | R75: 0 | S75: 0 | U75: 0 | W75: 0 | Y75: 0 | AA75: 0 | AC75: 0 | AM75: 52252 | AN75: 52252 | AO75: 52252 | AP75: 20.017 | AR75: 0 | AW75: 0 | AX75: 1 | AY75: 4 | BA75: 0 | BB75: 0 | BC75: 0 | BD75: 0 | BE75: 0 | BF75: 0 | BG75: 0 | BH75: 0 | BI75: 0 | BJ75: 0 | BP75: 0.268 | BQ75: Wed, 26 Feb 2025 14:22:07 GMT | BV75: 1.1 | EQ75: https://salesxceleration.com/wp-content/uploads/2025/02/SX-2-1024x684.jpg | ER75: 46045.298
A76: https://salesxceleration.com/frequently-asked-questions/ | B76: =IFERROR(__xludf.DUMMYFUNCTION("REGEXREPLACE(A76, ""^https?://[^/]+"", """")"),"/frequently-asked-questions/") -> /frequently-asked-questions/ | C76: Frequently Asked Questions | D76: General Questions | E76: Engagement & Pricing | F76: text/html; charset=UTF-8 | G76: 200 | H76: OK | I76: Indexable | K76: Frequently Asked Questions | Sales Xceleration | L76: 46 | M76: 420 | O76: 0 | P76: 0 | Q76: What does Sales Xceleration do? | R76: 31 | S76: 201 | U76: 0 | V76: Frequently Asked Questions | W76: 26 | Y76: 0 | Z76: General Questions | AA76: 17 | AB76: Engagement & Pricing | AC76: 20 | AD76: follow, index, max-snippet:-1, max-video-preview:-1, max-image-preview:large | AG76: https://salesxceleration.com/frequently-asked-questions/ | AM76: 165559 | AN76: 32316 | AO76: 32316 | AP76: 12.38 | AR76: 1126 | AS76: 164 | AT76: 6.866 | AU76: 58.691 | AV76: Fairly Hard | AW76: 5.708 | AX76: 1 | AY76: 1 | AZ76: 51 | BA76: 2249 | BB76: 754 | BC76: 0 | BD76: 100 | BE76: 123 | BF76: 42 | BG76: 0 | BH76: 16 | BI76: 8 | BJ76: 0 | BO76: 281a129dc721c9e412725769713995ef | BP76: 1.003 | BU76: en-US | BV76: 1.1 | BW76: 53 | BX76: 3451.072 | BY76: 6752.793 | BZ76: 6151.133 | CA76: 18040.514 | CB76: 474.5 | CC76: 0 | CD76: 651667 | CE76: 1350 | CF76: 166 | CG76: 2353987 | CH76: 31771 | CI76: 2 | CJ76: 191627 | CK76: 24 | CL76: 112033 | CM76: 38 | CN76: 1748987 | CO76: 69 | CP76: 244251 | CQ76: 5 | CR76: 0 | CS76: 0 | CT76: 25318 | CU76: 28 | CV76: 1503514 | CW76: 65 | DC76: 150 | DD76: 5075 | DE76: 0 | DF76: 3396 | DG76: 600 | DH76: 50560 | DI76: 600 | DJ76: 592636 | DK76: 1739.957 | DL76: Poor | DM76: 3105.097 | DN76: Poor | DO76: 2353905 | DP76: 1 | DQ76: Avoids redirects | DR76: Server responds quickly (observed 173 ms) | DS76: Applies text compression | DT76: 1 issue found | DU76: 4 resources found | DV76: 12791 | DX76: 3945 | DY76: 650971 | DZ76: 1 resource found | EA76: 902 | EB76: 27429 | EC76: 1 | ED76: 26492 | EF76: 235 | EG76: 21 resources found | EH76: 100 | EK76: 100 | EQ76: https://salesxceleration.com/frequently-asked-questions/ | ER76: 46045.298
A77: https://salesxceleration.com/wp-content/uploads/elementor/css/post-51707.css?ver=1768845927 | B77: =IFERROR(__xludf.DUMMYFUNCTION("REGEXREPLACE(A77, ""^https?://[^/]+"", """")"),"/wp-content/uploads/elementor/css/post-51707.css?ver=1768845927") -> /wp-content/uploads/elementor/css/post-51707.css?ver=1768845927 | F77: text/css | G77: 200 | H77: OK | I77: Indexable | L77: 0 | M77: 0 | O77: 0 | P77: 0 | R77: 0 | S77: 0 | U77: 0 | W77: 0 | Y77: 0 | AA77: 0 | AC77: 0 | AM77: 1602 | AN77: 1602 | AO77: 1602 | AP77: 0.614 | AR77: 0 | AW77: 0 | AX77: 1 | AY77: 4 | BA77: 0 | BB77: 0 | BC77: 0 | BD77: 0 | BE77: 0 | BF77: 0 | BG77: 0 | BH77: 0 | BI77: 0 | BJ77: 0 | BP77: 0.257 | BQ77: Mon, 19 Jan 2026 18:05:27 GMT | BV77: 1.1 | EQ77: https://salesxceleration.com/wp-content/uploads/elementor/css/post-51707.css?ver=1768845927 | ER77: 46045.298
A78: https://salesxceleration.com/wp-content/plugins/powerpack-elements/assets/js/min/pp-bg-effects.min.js?ver=1.0.0 | B78: =IFERROR(__xludf.DUMMYFUNCTION("REGEXREPLACE(A78, ""^https?://[^/]+"", """")"),"/wp-content/plugins/powerpack-elements/assets/js/min/pp-bg-effects.min.js?ver=1.0.0") -> /wp-content/plugins/powerpack-elements/assets/js/min/pp-bg-effects.min.js?ver=1.0.0 | F78: application/javascript | G78: 200 | H78: OK | I78: Indexable | L78: 0 | M78: 0 | O78: 0 | P78: 0 | R78: 0 | S78: 0 | U78: 0 | W78: 0 | Y78: 0 | AA78: 0 | AC78: 0 | AM78: 2051 | AN78: 2051 | AO78: 2051 | AP78: 0.786 | AR78: 0 | AW78: 0 | AX78: 1 | AY78: 6 | BA78: 0 | BB78: 0 | BC78: 0 | BD78: 0 | BE78: 0 | BF78: 0 | BG78: 0 | BH78: 0 | BI78: 0 | BJ78: 0 | BP78: 0.264 | BQ78: Fri, 02 Jan 2026 17:30:38 GMT | BV78: 1.1 | EQ78: https://salesxceleration.com/wp-content/plugins/powerpack-elements/assets/js/min/pp-bg-effects.min.js?ver=1.0.0 | ER78: 46045.298
A79: https://salesxceleration.com/wp-content/plugins/elementor/assets/css/widget-image.min.css?ver=3.34.0 | B79: =IFERROR(__xludf.DUMMYFUNCTION("REGEXREPLACE(A79, ""^https?://[^/]+"", """")"),"/wp-content/plugins/elementor/assets/css/widget-image.min.css?ver=3.34.0") -> /wp-content/plugins/elementor/assets/css/widget-image.min.css?ver=3.34.0 | F79: text/css | G79: 200 | H79: OK | I79: Indexable | L79: 0 | M79: 0 | O79: 0 | P79: 0 | R79: 0 | S79: 0 | U79: 0 | W79: 0 | Y79: 0 | AA79: 0 | AC79: 0 | AM79: 135 | AN79: 135 | AO79: 135 | AP79: 0.052 | AR79: 0 | AW79: 0 | AX79: 1 | AY79: 5 | BA79: 0 | BB79: 0 | BC79: 0 | BD79: 0 | BE79: 0 | BF79: 0 | BG79: 0 | BH79: 0 | BI79: 0 | BJ79: 0 | BP79: 0.699 | BQ79: Fri, 02 Jan 2026 17:29:45 GMT | BV79: 1.1 | EQ79: https://salesxceleration.com/wp-content/plugins/elementor/assets/css/widget-image.min.css?ver=3.34.0 | ER79: 46045.298
A80: https://salesxceleration.com/wp-content/uploads/2025/02/Untitled-design-13.png | B80: =IFERROR(__xludf.DUMMYFUNCTION("REGEXREPLACE(A80, ""^https?://[^/]+"", """")"),"/wp-content/uploads/2025/02/Untitled-design-13.png") -> /wp-content/uploads/2025/02/Untitled-design-13.png | F80: image/png | G80: 200 | H80: OK | I80: Indexable | L80: 0 | M80: 0 | O80: 0 | P80: 0 | R80: 0 | S80: 0 | U80: 0 | W80: 0 | Y80: 0 | AA80: 0 | AC80: 0 | AM80: 462605 | AN80: 462605 | AO80: 462605 | AP80: 177.215 | AR80: 0 | AW80: 0 | AX80: 1 | AY80: 4 | BA80: 0 | BB80: 0 | BC80: 0 | BD80: 0 | BE80: 0 | BF80: 0 | BG80: 0 | BH80: 0 | BI80: 0 | BJ80: 0 | BP80: 0.26 | BQ80: Wed, 26 Feb 2025 14:56:11 GMT | BV80: 1.1 | EQ80: https://salesxceleration.com/wp-content/uploads/2025/02/Untitled-design-13.png | ER80: 46045.298
A81: https://salesxceleration.com/wp-content/uploads/2025/03/mask-1024x978.png | B81: =IFERROR(__xludf.DUMMYFUNCTION("REGEXREPLACE(A81, ""^https?://[^/]+"", """")"),"/wp-content/uploads/2025/03/mask-1024x978.png") -> /wp-content/uploads/2025/03/mask-1024x978.png | F81: image/png | G81: 200 | H81: OK | I81: Indexable | L81: 0 | M81: 0 | O81: 0 | P81: 0 | R81: 0 | S81: 0 | U81: 0 | W81: 0 | Y81: 0 | AA81: 0 | AC81: 0 | AM81: 702076 | AN81: 702076 | AO81: 702076 | AP81: 268.952 | AR81: 0 | AW81: 0 | AX81: 1 | AY81: 4 | BA81: 0 | BB81: 0 | BC81: 0 | BD81: 0 | BE81: 0 | BF81: 0 | BG81: 0 | BH81: 0 | BI81: 0 | BJ81: 0 | BP81: 0.27 | BQ81: Mon, 17 Mar 2025 18:22:11 GMT | BV81: 1.1 | EQ81: https://salesxceleration.com/wp-content/uploads/2025/03/mask-1024x978.png | ER81: 46045.298
A82: https://salesxceleration.com/wp-includes/js/jquery/jquery-migrate.min.js?ver=3.4.1 | B82: =IFERROR(__xludf.DUMMYFUNCTION("REGEXREPLACE(A82, ""^https?://[^/]+"", """")"),"/wp-includes/js/jquery/jquery-migrate.min.js?ver=3.4.1") -> /wp-includes/js/jquery/jquery-migrate.min.js?ver=3.4.1 | F82: application/javascript | G82: 200 | H82: OK | I82: Indexable | L82: 0 | M82: 0 | O82: 0 | P82: 0 | R82: 0 | S82: 0 | U82: 0 | W82: 0 | Y82: 0 | AA82: 0 | AC82: 0 | AM82: 4872 | AN82: 4872 | AO82: 4872 | AP82: 1.866 | AR82: 0 | AW82: 0 | AX82: 1 | AY82: 3 | BA82: 0 | BB82: 0 | BC82: 0 | BD82: 0 | BE82: 0 | BF82: 0 | BG82: 0 | BH82: 0 | BI82: 0 | BJ82: 0 | BP82: 0.26 | BQ82: Wed, 04 Oct 2023 20:05:04 GMT | BV82: 1.1 | EQ82: https://salesxceleration.com/wp-includes/js/jquery/jquery-migrate.min.js?ver=3.4.1 | ER82: 46045.298
A83: https://salesxceleration.com/wp-content/uploads/elementor/css/post-208.css?ver=1768845927 | B83: =IFERROR(__xludf.DUMMYFUNCTION("REGEXREPLACE(A83, ""^https?://[^/]+"", """")"),"/wp-content/uploads/elementor/css/post-208.css?ver=1768845927") -> /wp-content/uploads/elementor/css/post-208.css?ver=1768845927 | F83: text/css | G83: 200 | H83: OK | I83: Indexable | L83: 0 | M83: 0 | O83: 0 | P83: 0 | R83: 0 | S83: 0 | U83: 0 | W83: 0 | Y83: 0 | AA83: 0 | AC83: 0 | AM83: 1136 | AN83: 1136 | AO83: 1136 | AP83: 0.435 | AR83: 0 | AW83: 0 | AX83: 1 | AY83: 4 | BA83: 0 | BB83: 0 | BC83: 0 | BD83: 0 | BE83: 0 | BF83: 0 | BG83: 0 | BH83: 0 | BI83: 0 | BJ83: 0 | BP83: 0.258 | BQ83: Mon, 19 Jan 2026 18:05:27 GMT | BV83: 1.1 | EQ83: https://salesxceleration.com/wp-content/uploads/elementor/css/post-208.css?ver=1768845927 | ER83: 46045.298
A84: https://salesxceleration.com/private-equity-solutions/private-equity/ | B84: =IFERROR(__xludf.DUMMYFUNCTION("REGEXREPLACE(A84, ""^https?://[^/]+"", """")"),"/private-equity-solutions/private-equity/") -> /private-equity-solutions/private-equity/ | C84: Private Equity Growth with Expert Sales Strategies | D84: Accelerate Growth. Maximize Returns. | E84: Maximizing Organic Growth | F84: text/html; charset=UTF-8 | G84: 200 | H84: OK | I84: Indexable | K84: Private Equity Sales Solutions | Sales Xceleration | L84: 50 | M84: 436 | O84: 0 | P84: 0 | Q84: Discover Sales Xceleration’s private equity solutions, designed to maximize sales potential, drive growth, and improve portfolio company value in any market. | R84: 157 | S84: 963 | U84: 0 | V84: Private Equity Growth with Expert Sales Strategies | W84: 50 | Y84: 0 | Z84: Accelerate Growth. Maximize Returns. | AA84: 36 | AB84: Maximizing Organic Growth | AC84: 25 | AD84: follow, index, max-snippet:-1, max-video-preview:-1, max-image-preview:large | AG84: https://salesxceleration.com/private-equity-solutions/private-equity/ | AM84: 161899 | AN84: 29280 | AO84: 29280 | AP84: 11.217 | AR84: 976 | AS84: 152 | AT84: 6.421 | AU84: 47.587 | AV84: Hard | AW84: 5.25 | AX84: 1 | AY84: 2 | AZ84: 51 | BA84: 2278 | BB84: 754 | BC84: 0 | BD84: 100 | BE84: 110 | BF84: 42 | BG84: 0 | BH84: 7 | BI84: 6 | BJ84: 0 | BO84: a7641d21b0d12ddde1ccc184e1c2b6a1 | BP84: 0.96 | BU84: en-US | BV84: 1.1 | BW84: 52 | BX84: 3751.032 | BY84: 9131.671 | BZ84: 8401.075 | CA84: 18176.943 | CB84: 338 | CC84: 0 | CD84: 651976 | CE84: 1650 | CF84: 173 | CG84: 2531105 | CH84: 32034 | CI84: 2 | CJ84: 300993 | CK84: 22 | CL84: 117572 | CM84: 42 | CN84: 1767227 | CO84: 72 | CP84: 287905 | CQ84: 5 | CR84: 0 | CS84: 1 | CT84: 25374 | CU84: 29 | CV84: 1505245 | CW84: 70 | DC84: 150 | DD84: 5075 | DE84: 0 | DF84: 3397 | DG84: 300 | DH84: 51025 | DI84: 1200 | DJ84: 592479 | DK84: 2023.415 | DL84: Poor | DM84: 7750.167 | DN84: Poor | DO84: 2530927 | DP84: 1 | DQ84: Avoids redirects | DR84: Server responds quickly (observed 176 ms) | DS84: Applies text compression | DT84: 1 issue found | DU84: 4 resources found | DV84: 13395 | DX84: 3715 | DY84: 720941 | DZ84: 1 resource found | EA84: 757 | EB84: 0 | EC84: 2 | ED84: 26492 | EF84: 275 | EG84: 21 resources found | EH84: 100 | EK84: 100 | EQ84: https://salesxceleration.com/private-equity-solutions/private-equity/ | ER84: 46045.298
A85: https://salesxceleration.com/wp-content/plugins/wp-job-manager/assets/dist/css/job-listings.css?ver=598383a28ac5f9f156e4 | B85: =IFERROR(__xludf.DUMMYFUNCTION("REGEXREPLACE(A85, ""^https?://[^/]+"", """")"),"/wp-content/plugins/wp-job-manager/assets/dist/css/job-listings.css?ver=598383a28ac5f9f156e4") -> /wp-content/plugins/wp-job-manager/assets/dist/css/job-listings.css?ver=598383a28ac5f9f156e4 | F85: text/css | G85: 200 | H85: OK | I85: Indexable | L85: 0 | M85: 0 | O85: 0 | P85: 0 | R85: 0 | S85: 0 | U85: 0 | W85: 0 | Y85: 0 | AA85: 0 | AC85: 0 | AM85: 1315 | AN85: 1315 | AO85: 1315 | AP85: 0.504 | AR85: 0 | AW85: 0 | AX85: 1 | AY85: 6 | BA85: 0 | BB85: 0 | BC85: 0 | BD85: 0 | BE85: 0 | BF85: 0 | BG85: 0 | BH85: 0 | BI85: 0 | BJ85: 0 | BP85: 0.27 | BQ85: Mon, 04 Nov 2024 07:39:17 GMT | BV85: 1.1 | EQ85: https://salesxceleration.com/wp-content/plugins/wp-job-manager/assets/dist/css/job-listings.css?ver=598383a28ac5f9f156e4 | ER85: 46045.298
A86: https://salesxceleration.com/wp-content/plugins/elementor/assets/lib/font-awesome/css/solid.min.css?ver=5.15.3 | B86: =IFERROR(__xludf.DUMMYFUNCTION("REGEXREPLACE(A86, ""^https?://[^/]+"", """")"),"/wp-content/plugins/elementor/assets/lib/font-awesome/css/solid.min.css?ver=5.15.3") -> /wp-content/plugins/elementor/assets/lib/font-awesome/css/solid.min.css?ver=5.15.3 | F86: text/css | G86: 200 | H86: OK | I86: Indexable | L86: 0 | M86: 0 | O86: 0 | P86: 0 | R86: 0 | S86: 0 | U86: 0 | W86: 0 | Y86: 0 | AA86: 0 | AC86: 0 | AM86: 309 | AN86: 309 | AO86: 309 | AP86: 0.118 | AR86: 0 | AW86: 0 | AX86: 1 | AY86: 7 | BA86: 0 | BB86: 0 | BC86: 0 | BD86: 0 | BE86: 0 | BF86: 0 | BG86: 0 | BH86: 0 | BI86: 0 | BJ86: 0 | BP86: 0.252 | BQ86: Fri, 02 Jan 2026 17:29:45 GMT | BV86: 1.1 | EQ86: https://salesxceleration.com/wp-content/plugins/elementor/assets/lib/font-awesome/css/solid.min.css?ver=5.15.3 | ER86: 46045.298
A87: https://salesxceleration.com/wp-content/plugins/powerpack-elements/assets/css/min/tooltip.min.css?ver=2.12.15 | B87: =IFERROR(__xludf.DUMMYFUNCTION("REGEXREPLACE(A87, ""^https?://[^/]+"", """")"),"/wp-content/plugins/powerpack-elements/assets/css/min/tooltip.min.css?ver=2.12.15") -> /wp-content/plugins/powerpack-elements/assets/css/min/tooltip.min.css?ver=2.12.15 | F87: text/css | G87: 200 | H87: OK | I87: Indexable | L87: 0 | M87: 0 | O87: 0 | P87: 0 | R87: 0 | S87: 0 | U87: 0 | W87: 0 | Y87: 0 | AA87: 0 | AC87: 0 | AM87: 1073 | AN87: 1073 | AO87: 1073 | AP87: 0.411 | AR87: 0 | AW87: 0 | AX87: 1 | AY87: 6 | BA87: 0 | BB87: 0 | BC87: 0 | BD87: 0 | BE87: 0 | BF87: 0 | BG87: 0 | BH87: 0 | BI87: 0 | BJ87: 0 | BP87: 0.257 | BQ87: Fri, 02 Jan 2026 17:30:38 GMT | BV87: 1.1 | EQ87: https://salesxceleration.com/wp-content/plugins/powerpack-elements/assets/css/min/tooltip.min.css?ver=2.12.15 | ER87: 46045.298
A88: https://salesxceleration.com/case-studies | B88: =IFERROR(__xludf.DUMMYFUNCTION("REGEXREPLACE(A88, ""^https?://[^/]+"", """")"),"/case-studies") -> /case-studies | F88: text/html; charset=UTF-8 | G88: 301 | H88: Moved Permanently | I88: Non-Indexable | J88: Redirected | L88: 0 | M88: 0 | O88: 0 | P88: 0 | R88: 0 | S88: 0 | U88: 0 | W88: 0 | Y88: 0 | AA88: 0 | AC88: 0 | AM88: 0 | AN88: 0 | AO88: 0 | AP88: 0 | AR88: 0 | AW88: 0 | AX88: 1 | AY88: 0 | BA88: 2 | BB88: 2 | BC88: 0 | BD88: 0.27 | BE88: 0 | BF88: 0 | BG88: 0 | BH88: 0 | BI88: 0 | BJ88: 0 | BP88: 0.542 | BR88: https://salesxceleration.com/case-studies/ | BS88: HTTP Redirect | BV88: 1.1 | EQ88: https://salesxceleration.com/case-studies | ER88: 46045.298
A89: https://salesxceleration.com/wp-content/uploads/2023/05/2023-logo.png | B89: =IFERROR(__xludf.DUMMYFUNCTION("REGEXREPLACE(A89, ""^https?://[^/]+"", """")"),"/wp-content/uploads/2023/05/2023-logo.png") -> /wp-content/uploads/2023/05/2023-logo.png | F89: image/png | G89: 200 | H89: OK | I89: Indexable | L89: 0 | M89: 0 | O89: 0 | P89: 0 | R89: 0 | S89: 0 | U89: 0 | W89: 0 | Y89: 0 | AA89: 0 | AC89: 0 | AM89: 30779 | AN89: 30779 | AO89: 30779 | AP89: 11.791 | AR89: 0 | AW89: 0 | AX89: 1 | AY89: 4 | BA89: 0 | BB89: 0 | BC89: 0 | BD89: 0 | BE89: 0 | BF89: 0 | BG89: 0 | BH89: 0 | BI89: 0 | BJ89: 0 | BP89: 0.271 | BQ89: Wed, 17 May 2023 21:02:07 GMT | BV89: 1.1 | EQ89: https://salesxceleration.com/wp-content/uploads/2023/05/2023-logo.png | ER89: 46045.298
A90: https://salesxceleration.com/sales-infrastructure/ | B90: =IFERROR(__xludf.DUMMYFUNCTION("REGEXREPLACE(A90, ""^https?://[^/]+"", """")"),"/sales-infrastructure/") -> /sales-infrastructure/ | C90: Sales Infrastructure Consulting Services | D90: What is Sales Infrastructure? | E90: Your Foundation for Scalable and Efficient Growth | F90: text/html; charset=UTF-8 | G90: 200 | H90: OK | I90: Indexable | K90: Sales Infrastructure Consulting Services | Sales Xceleration | L90: 60 | M90: 528 | O90: 0 | P90: 0 | Q90: Build a foundation for growth with our sales infrastructure consulting services. Our fractional sales leaders design scalable systems to drive predictable revenue. | R90: 163 | S90: 988 | U90: 0 | V90: Sales Infrastructure Consulting Services | W90: 40 | Y90: 0 | Z90: What is Sales Infrastructure? | AA90: 29 | AB90: Your Foundation for Scalable and Efficient Growth | AC90: 49 | AD90: follow, index, max-snippet:-1, max-video-preview:-1, max-image-preview:large | AG90: https://salesxceleration.com/sales-infrastructure/ | AM90: 588206 | AN90: 176651 | AO90: 176651 | AP90: 67.672 | AR90: 1306 | AS90: 217 | AT90: 6.018 | AU90: 53.421 | AV90: Fairly Hard | AW90: 2.109 | AX90: 1 | AY90: 1 | AZ90: 51 | BA90: 2343 | BB90: 754 | BC90: 0 | BD90: 100 | BE90: 131 | BF90: 45 | BG90: 0 | BH90: 16 | BI90: 8 | BJ90: 0 | BO90: e251459dede262c2dd912141b05087d0 | BP90: 1.046 | BU90: en-US | BV90: 1.1 | BW90: 57 | BX90: 4501.005 | BY90: 8604.943 | BZ90: 12301.015 | CA90: 18690.762 | CB90: 48.5 | CC90: 0.007 | CD90: 664566 | CE90: 1650 | CF90: 174 | CG90: 3116358 | CH90: 168056 | CI90: 2 | CJ90: 762841 | CK90: 24 | CL90: 124264 | CM90: 43 | CN90: 1791635 | CO90: 71 | CP90: 244251 | CQ90: 5 | CR90: 0 | CS90: 0 | CT90: 25311 | CU90: 29 | CV90: 1504185 | CW90: 73 | DC90: 150 | DD90: 5075 | DE90: 0 | DF90: 3396 | DG90: 300 | DH90: 40124 | DI90: 1200 | DJ90: 615971 | DK90: 777.083 | DL90: Good | DM90: 1699.82 | DN90: Good | DO90: 3116359 | DP90: 1 | DQ90: Avoids redirects | DR90: Server responds quickly (observed 518 ms) | DS90: Applies text compression | DU90: 2 resources found | DV90: 13997 | DW90: 312 | DX90: 4084 | DY90: 901087 | DZ90: 1 resource found | EA90: 1760 | EB90: 499109 | EC90: 31 | ED90: 26492 | EF90: 225 | EG90: 21 resources found | EH90: 100 | EK90: 100 | EQ90: https://salesxceleration.com/sales-infrastructure/ | ER90: 46045.298
A91: https://salesxceleration.com/wp-content/plugins/elementor-pro/assets/js/frontend.min.js?ver=3.34.0 | B91: =IFERROR(__xludf.DUMMYFUNCTION("REGEXREPLACE(A91, ""^https?://[^/]+"", """")"),"/wp-content/plugins/elementor-pro/assets/js/frontend.min.js?ver=3.34.0") -> /wp-content/plugins/elementor-pro/assets/js/frontend.min.js?ver=3.34.0 | F91: application/javascript | G91: 200 | H91: OK | I91: Indexable | L91: 0 | M91: 0 | O91: 0 | P91: 0 | R91: 0 | S91: 0 | U91: 0 | W91: 0 | Y91: 0 | AA91: 0 | AC91: 0 | AM91: 6434 | AN91: 6434 | AO91: 6434 | AP91: 2.465 | AR91: 0 | AW91: 0 | AX91: 1 | AY91: 5 | BA91: 0 | BB91: 0 | BC91: 0 | BD91: 0 | BE91: 0 | BF91: 0 | BG91: 0 | BH91: 0 | BI91: 0 | BJ91: 0 | BP91: 0.271 | BQ91: Fri, 02 Jan 2026 17:52:08 GMT | BV91: 1.1 | EQ91: https://salesxceleration.com/wp-content/plugins/elementor-pro/assets/js/frontend.min.js?ver=3.34.0 | ER91: 46045.298
A92: https://salesxceleration.com/sales-strategy/ | B92: =IFERROR(__xludf.DUMMYFUNCTION("REGEXREPLACE(A92, ""^https?://[^/]+"", """")"),"/sales-strategy/") -> /sales-strategy/ | C92: Sales Strategy Consulting Services | D92: Transform Your Sales with Proven Expertise | E92: Build Your Sales Strategy with Our Proven Framework | F92: text/html; charset=UTF-8 | G92: 200 | H92: OK | I92: Indexable | K92: Sales Strategy Consultants | Sales Xceleration | L92: 46 | M92: 412 | O92: 0 | P92: 0 | Q92: Unlock up to 32% sales growth with SalesXceleration's tailored strategies from experienced fractional VPs. | R92: 106 | S92: 654 | U92: 0 | V92: Sales Strategy Consulting Services | W92: 34 | Y92: 0 | Z92: Transform Your Sales with Proven Expertise | AA92: 42 | AB92: Build Your Sales Strategy with Our Proven Framework | AC92: 51 | AD92: follow, index, max-snippet:-1, max-video-preview:-1, max-image-preview:large | AG92: https://salesxceleration.com/sales-strategy/ | AM92: 613729 | AN92: 184332 | AO92: 184332 | AP92: 70.614 | AR92: 1553 | AS92: 267 | AT92: 5.816 | AU92: 58.37 | AV92: Fairly Hard | AW92: 2.373 | AX92: 1 | AY92: 1 | AZ92: 51 | BA92: 2424 | BB92: 754 | BC92: 0 | BD92: 100 | BE92: 140 | BF92: 50 | BG92: 0 | BH92: 17 | BI92: 9 | BJ92: 0 | BO92: a689d1d05fabbee31fe683518d34812e | BP92: 1.123 | BU92: en-US | BV92: 1.1 | BW92: 55 | BX92: 4951.008 | BY92: 8343.017 | BZ92: 11852.021 | CA92: 19171.119 | CB92: 196 | CC92: 0 | CD92: 662925 | CE92: 750 | CF92: 178 | CG92: 3279481 | CH92: 175876 | CI92: 2 | CJ92: 762848 | CK92: 26 | CL92: 124482 | CM92: 43 | CN92: 1791385 | CO92: 71 | CP92: 399448 | CQ92: 7 | CR92: 0 | CS92: 0 | CT92: 25442 | CU92: 29 | CV92: 1503572 | CW92: 75 | DC92: 0 | DD92: 5075 | DE92: 0 | DF92: 3396 | DG92: 150 | DH92: 40156 | DI92: 600 | DJ92: 614298 | DK92: 1442.965 | DL92: Poor | DM92: 2714.519 | DN92: Poor | DO92: 3279482 | DP92: 1 | DQ92: Avoids redirects | DR92: Server responds quickly (observed 523 ms) | DS92: Applies text compression | DT92: 1 issue found | DU92: 4 resources found | DV92: 13875 | DX92: 4333 | DY92: 963251 | EA92: 1817 | EB92: 499109 | EC92: 55 | ED92: 26492 | EF92: 235 | EG92: 21 resources found | EH92: 100 | EK92: 100 | EQ92: https://salesxceleration.com/sales-strategy/ | ER92: 46045.298
A93: https://salesxceleration.com/news-events/sales-xceleration-recognized-as-pipedrives-regional-partner-of-the-year-north-america-2024/ | B93: =IFERROR(__xludf.DUMMYFUNCTION("REGEXREPLACE(A93, ""^https?://[^/]+"", """")"),"/news-events/sales-xceleration-recognized-as-pipedrives-regional-partner-of-the-year-north-america-2024/") -> /news-events/sales-xceleration-recognized-as-pipedrives-regional-partner-of-the-year-north-america-2024/ | C93: Sales Xceleration Recognized as Pipedrive’s Regional Partner of the Year North America 2024 | D93: About Sales Xceleration | E93: About Pipedrive | F93: text/html; charset=UTF-8 | G93: 200 | H93: OK | I93: Indexable | K93: Sales Xceleration Recognized as Pipedrive’s Regional Partner of the Year North America 2024 | Sales Xceleration | L93: 111 | M93: 1005 | O93: 0 | P93: 0 | Q93: Indianapolis, 18 February 2025 - Sales Xceleration announced today it has been recognized as the Regional Partner of the Year North America 2024 of Pipedrive, | R93: 158 | S93: 986 | U93: 0 | V93: Sales Xceleration Recognized as Pipedrive’s Regional Partner of the Year North America 2024 | W93: 91 | Y93: 0 | Z93: About Sales Xceleration | AA93: 23 | AB93: About Pipedrive | AC93: 15 | AD93: follow, index, max-snippet:-1, max-video-preview:-1, max-image-preview:large | AG93: https://salesxceleration.com/news-events/sales-xceleration-recognized-as-pipedrives-regional-partner-of-the-year-north-america-2024/ | AM93: 173711 | AN93: 32793 | AO93: 32793 | AP93: 12.562 | AR93: 1056 | AS93: 177 | AT93: 5.966 | AU93: 55.854 | AV93: Fairly Hard | AW93: 5.287 | AX93: 1 | AY93: 2 | AZ93: 3 | BA93: 4 | BB93: 4 | BC93: 0 | BD93: 0.53 | BE93: 127 | BF93: 43 | BG93: 0 | BH93: 28 | BI93: 20 | BJ93: 0 | BO93: 4e9731afbebcbf7c35b10db3e49292e3 | BP93: 0.964 | BU93: en-US | BV93: 1.1 | BW93: 55 | BX93: 4351.027 | BY93: 6848.427 | BZ93: 9976.065 | CA93: 19928.082 | CB93: 272.5 | CC93: 0.02 | CD93: 709192 | CE93: 1200 | CF93: 169 | CG93: 2691154 | CH93: 33538 | CI93: 2 | CJ93: 66736 | CK93: 20 | CL93: 176249 | CM93: 41 | CN93: 1748294 | CO93: 68 | CP93: 640717 | CQ93: 10 | CR93: 0 | CS93: 0 | CT93: 25620 | CU93: 28 | CV93: 1833216 | CW93: 70 | DC93: 0 | DD93: 5075 | DE93: 0 | DF93: 3396 | DG93: 450 | DH93: 108274 | DI93: 750 | DJ93: 592447 | DK93: 1329.92 | DL93: Poor | DM93: 2557.928 | DN93: Poor | DO93: 2690806 | DP93: 1 | DQ93: Avoids redirects | DR93: Server responds quickly (observed 178 ms) | DS93: Applies text compression | DT93: 1 issue found | DU93: 4 resources found | DV93: 17147 | DX93: 3917 | DY93: 652777 | DZ93: 1 resource found | EA93: 848 | EB93: 4453 | EC93: 1 | ED93: 26492 | EF93: 230 | EG93: 22 resources found | EH93: 100 | EK93: 100 | EQ93: https://salesxceleration.com/news-events/sales-xceleration-recognized-as-pipedrives-regional-partner-of-the-year-north-america-2024/ | ER93: 46045.298
A94: https://salesxceleration.com/wp-content/uploads/2022/05/logo-acg.jpg | B94: =IFERROR(__xludf.DUMMYFUNCTION("REGEXREPLACE(A94, ""^https?://[^/]+"", """")"),"/wp-content/uploads/2022/05/logo-acg.jpg") -> /wp-content/uploads/2022/05/logo-acg.jpg | F94: image/jpeg | G94: 200 | H94: OK | I94: Indexable | L94: 0 | M94: 0 | O94: 0 | P94: 0 | R94: 0 | S94: 0 | U94: 0 | W94: 0 | Y94: 0 | AA94: 0 | AC94: 0 | AM94: 29768 | AN94: 29768 | AO94: 29768 | AP94: 11.404 | AR94: 0 | AW94: 0 | AX94: 1 | AY94: 4 | BA94: 0 | BB94: 0 | BC94: 0 | BD94: 0 | BE94: 0 | BF94: 0 | BG94: 0 | BH94: 0 | BI94: 0 | BJ94: 0 | BP94: 0.253 | BQ94: Mon, 09 May 2022 19:36:41 GMT | BV94: 1.1 | EQ94: https://salesxceleration.com/wp-content/uploads/2022/05/logo-acg.jpg | ER94: 46045.298
A95: https://salesxceleration.com/industries/financial-services/ | B95: =IFERROR(__xludf.DUMMYFUNCTION("REGEXREPLACE(A95, ""^https?://[^/]+"", """")"),"/industries/financial-services/") -> /industries/financial-services/ | C95: Fractional Sales Leadership for Financial Services | D95: Scale Revenue in Competitive Markets | E95: Key Sales Challenges in Financial Services | F95: text/html; charset=UTF-8 | G95: 200 | H95: OK | I95: Non-Indexable | J95: Canonicalised | K95: Fractional Sales Leadership for Financial Services | Sales Xceleration | L95: 70 | M95: 614 | N95: Sales Xceleration Infographic | O95: 29 | P95: 261 | Q95: Drive growth in banking, wealth, or fintech. Sales Xceleration offers fractional sales leadership tailored to the challenges of the financial services industry. | R95: 160 | S95: 941 | U95: 0 | V95: Fractional Sales Leadership for Financial Services | W95: 50 | Y95: 0 | Z95: Scale Revenue in Competitive Markets | AA95: 36 | AB95: Key Sales Challenges in Financial Services | AC95: 42 | AD95: follow, index, max-snippet:-1, max-video-preview:-1, max-image-preview:large | AG95: https://salesxceleration.com/technology/ | AM95: 276533 | AN95: 87546 | AO95: 87546 | AP95: 33.537 | AR95: 1636 | AS95: 276 | AT95: 5.928 | AU95: 47.753 | AV95: Hard | AW95: 6.73 | AX95: 1 | AY95: 2 | BA95: 2250 | BB95: 754 | BC95: 0 | BD95: 100 | BE95: 135 | BF95: 46 | BG95: 0 | BH95: 16 | BI95: 8 | BJ95: 0 | BO95: a7a8bfbe1f3db636e094c4897720e4c0 | BP95: 1.053 | BU95: en-US | BV95: 1.1 | BW95: 56 | BX95: 4201.119 | BY95: 6805.319 | BZ95: 9752.289 | CA95: 20953.434 | CB95: 236.5 | CC95: 0.005 | CD95: 672351 | CE95: 900 | CF95: 179 | CG95: 3186128 | CH95: 85787 | CI95: 2 | CJ95: 763002 | CK95: 25 | CL95: 127932 | CM95: 45 | CN95: 1791193 | CO95: 71 | CP95: 392584 | CQ95: 7 | CR95: 0 | CS95: 0 | CT95: 25630 | CU95: 29 | CV95: 1550124 | CW95: 76 | DC95: 0 | DD95: 5075 | DE95: 0 | DF95: 3401 | DG95: 300 | DH95: 50543 | DI95: 600 | DJ95: 613332 | DK95: 1485.792 | DL95: Poor | DM95: 2794.078 | DN95: Poor | DO95: 3185966 | DP95: 1 | DQ95: Avoids redirects | DR95: Server responds quickly (observed 347 ms) | DS95: Applies text compression | DU95: 2 resources found | DV95: 14748 | DX95: 3898 | DY95: 943415 | DZ95: 1 resource found | EA95: 1213 | EB95: 499109 | EC95: 0 | ED95: 26492 | EF95: 215 | EG95: 21 resources found | EH95: 100 | EK95: 100 | EQ95: https://salesxceleration.com/industries/financial-services/ | ER95: 46045.298
A96: https://salesxceleration.com/wp-content/uploads/2025/02/Untitled-design-11.png | B96: =IFERROR(__xludf.DUMMYFUNCTION("REGEXREPLACE(A96, ""^https?://[^/]+"", """")"),"/wp-content/uploads/2025/02/Untitled-design-11.png") -> /wp-content/uploads/2025/02/Untitled-design-11.png | F96: image/png | G96: 200 | H96: OK | I96: Indexable | L96: 0 | M96: 0 | O96: 0 | P96: 0 | R96: 0 | S96: 0 | U96: 0 | W96: 0 | Y96: 0 | AA96: 0 | AC96: 0 | AM96: 611863 | AN96: 611863 | AO96: 611863 | AP96: 234.393 | AR96: 0 | AW96: 0 | AX96: 1 | AY96: 4 | BA96: 0 | BB96: 0 | BC96: 0 | BD96: 0 | BE96: 0 | BF96: 0 | BG96: 0 | BH96: 0 | BI96: 0 | BJ96: 0 | BP96: 0.261 | BQ96: Wed, 26 Feb 2025 14:17:07 GMT | BV96: 1.1 | EQ96: https://salesxceleration.com/wp-content/uploads/2025/02/Untitled-design-11.png | ER96: 46045.298
A97: https://salesxceleration.com/contact-us/ | B97: =IFERROR(__xludf.DUMMYFUNCTION("REGEXREPLACE(A97, ""^https?://[^/]+"", """")"),"/contact-us/") -> /contact-us/ | C97: Contact Us | F97: text/html; charset=UTF-8 | G97: 200 | H97: OK | I97: Non-Indexable | J97: noindex | K97: Contact Us New | Sales Xceleration | L97: 34 | M97: 314 | O97: 0 | P97: 0 | Q97: For vendor inquiries, please send a brief overview to info@salesxceleration.com. | R97: 81 | S97: 492 | U97: 0 | V97: Contact Us | W97: 10 | Y97: 0 | AA97: 0 | AC97: 0 | AD97: follow, noindex | AM97: 178087 | AN97: 35550 | AO97: 35550 | AP97: 13.619 | AR97: 605 | AS97: 110 | AT97: 5.5 | AU97: 63.655 | AV97: Normal | AW97: 3.417 | AX97: 1 | AY97: 1 | AZ97: 47 | BA97: 1606 | BB97: 748 | BC97: 0 | BD97: 99.2 | BE97: 125 | BF97: 43 | BG97: 0 | BH97: 16 | BI97: 8 | BJ97: 0 | BO97: 65bb113a9c7ae8b33523c613b2a97a27 | BP97: 0.928 | BU97: en-US | BV97: 1.1 | BW97: 45 | BX97: 3901.029 | BY97: 7193.344 | BZ97: 15076.603 | CA97: 22071.35 | CB97: 624.5 | CC97: 0 | CD97: 1239461 | CE97: 3720 | CF97: 189 | CG97: 3856948 | CH97: 90572 | CI97: 4 | CJ97: 210812 | CK97: 20 | CL97: 220408 | CM97: 46 | CN97: 2538146 | CO97: 80 | CP97: 406321 | CQ97: 9 | CR97: 0 | CS97: 0 | CT97: 390689 | CU97: 30 | CV97: 2819191 | CW97: 80 | DC97: 0 | DD97: 0 | DE97: 150 | DF97: 3396 | DG97: 870 | DH97: 59568 | DI97: 2700 | DJ97: 1176497 | DK97: 2424.558 | DL97: Poor | DM97: 3863.038 | DN97: Poor | DO97: 3856866 | DP97: 1 | DQ97: Avoids redirects | DR97: Server responds quickly (observed 175 ms) | DS97: Applies text compression | DU97: 2 resources found | DV97: 14148 | DX97: 3926 | DY97: 724536 | DZ97: 1 resource found | EA97: 902 | EB97: 4453 | EC97: 4 | ED97: 26492 | EF97: 240 | EG97: 21 resources found | EH97: 100 | EK97: 100 | EQ97: https://salesxceleration.com/contact-us/ | ER97: 46045.298
A98: https://salesxceleration.com/wp-content/uploads/2022/06/50-Fastest-Companies-2022_Award-Logo.png | B98: =IFERROR(__xludf.DUMMYFUNCTION("REGEXREPLACE(A98, ""^https?://[^/]+"", """")"),"/wp-content/uploads/2022/06/50-Fastest-Companies-2022_Award-Logo.png") -> /wp-content/uploads/2022/06/50-Fastest-Companies-2022_Award-Logo.png | F98: image/png | G98: 200 | H98: OK | I98: Indexable | L98: 0 | M98: 0 | O98: 0 | P98: 0 | R98: 0 | S98: 0 | U98: 0 | W98: 0 | Y98: 0 | AA98: 0 | AC98: 0 | AM98: 58249 | AN98: 58249 | AO98: 58249 | AP98: 22.314 | AR98: 0 | AW98: 0 | AX98: 1 | AY98: 4 | BA98: 0 | BB98: 0 | BC98: 0 | BD98: 0 | BE98: 0 | BF98: 0 | BG98: 0 | BH98: 0 | BI98: 0 | BJ98: 0 | BP98: 0.272 | BQ98: Fri, 24 Jun 2022 16:01:18 GMT | BV98: 1.1 | EQ98: https://salesxceleration.com/wp-content/uploads/2022/06/50-Fastest-Companies-2022_Award-Logo.png | ER98: 46045.298
A99: https://salesxceleration.com/wp-content/themes/salesxceleratione/assets/css/style.css?ver=1769123309 | B99: =IFERROR(__xludf.DUMMYFUNCTION("REGEXREPLACE(A99, ""^https?://[^/]+"", """")"),"/wp-content/themes/salesxceleratione/assets/css/style.css?ver=1769123309") -> /wp-content/themes/salesxceleratione/assets/css/style.css?ver=1769123309 | F99: text/css | G99: 200 | H99: OK | I99: Indexable | L99: 0 | M99: 0 | O99: 0 | P99: 0 | R99: 0 | S99: 0 | U99: 0 | W99: 0 | Y99: 0 | AA99: 0 | AC99: 0 | AM99: 17704 | AN99: 17704 | AO99: 17704 | AP99: 6.782 | AR99: 0 | AW99: 0 | AX99: 1 | AY99: 5 | BA99: 0 | BB99: 0 | BC99: 0 | BD99: 0 | BE99: 0 | BF99: 0 | BG99: 0 | BH99: 0 | BI99: 0 | BJ99: 0 | BP99: 0.28 | BQ99: Thu, 22 Jan 2026 23:08:52 GMT | BV99: 1.1 | EQ99: https://salesxceleration.com/wp-content/themes/salesxceleratione/assets/css/style.css?ver=1769123309 | ER99: 46045.298
A100: https://salesxceleration.com/wp-content/uploads/2025/02/2024-Bronze.png | B100: =IFERROR(__xludf.DUMMYFUNCTION("REGEXREPLACE(A100, ""^https?://[^/]+"", """")"),"/wp-content/uploads/2025/02/2024-Bronze.png") -> /wp-content/uploads/2025/02/2024-Bronze.png | F100: image/png | G100: 200 | H100: OK | I100: Indexable | L100: 0 | M100: 0 | O100: 0 | P100: 0 | R100: 0 | S100: 0 | U100: 0 | W100: 0 | Y100: 0 | AA100: 0 | AC100: 0 | AM100: 129596 | AN100: 129596 | AO100: 129596 | AP100: 49.646 | AR100: 0 | AW100: 0 | AX100: 1 | AY100: 4 | BA100: 0 | BB100: 0 | BC100: 0 | BD100: 0 | BE100: 0 | BF100: 0 | BG100: 0 | BH100: 0 | BI100: 0 | BJ100: 0 | BP100: 0.313 | BQ100: Tue, 04 Feb 2025 22:18:03 GMT | BV100: 1.1 | EQ100: https://salesxceleration.com/wp-content/uploads/2025/02/2024-Bronze.png | ER100: 46045.298
...
