Workbook

Sheet Current Pages
A1: CURRENT IL PAGES (NO BLOGS)
A2: https://www.sterlinglawyers.com/illinois/
A3: https://www.sterlinglawyers.com/illinois/divorce/
A4: https://www.sterlinglawyers.com/illinois/paternity/
A5: https://www.sterlinglawyers.com/illinois/child-custody/
A6: https://www.sterlinglawyers.com/illinois/attorneys/
A7: https://www.sterlinglawyers.com/illinois/locations/
A8: https://www.sterlinglawyers.com/illinois/pricing/
A9: https://www.sterlinglawyers.com/illinois/guardianship/
A10: https://www.sterlinglawyers.com/illinois/child-support/
A11: https://www.sterlinglawyers.com/illinois/property-division/
A12: https://www.sterlinglawyers.com/illinois/spousal-support/
... A229: https://www.sterlinglawyers.com/illinois/property-division/survivorship-marital-property/

Sheet Sterling_Lawyers_IL_Content_Gap
A1: Map ID | B1: Content Phase | C1: Content Category | D1: Content Type | E1: Content Role | F1: Page Title Structure | G1: Idealized URL | H1: Target Seed Keyword | I1: Existing Client URL | J1: Gap Status | K1: Notes | L1: -
A2: AH (Attorney Hub) | B2: Phase 1 | C2: Firm Hub | D2: Attorney Directory | E2: Navigation + Trust | F2: Illinois Family Law Attorneys | Sterling Lawyers | G2: https://www.sterlinglawyers.com/illinois/attorneys/ | H2: Illinois family law attorneys | I2: https://www.sterlinglawyers.com/illinois/attorneys/ | J2: MAPPED | K2: Attorney directory / hub page. Full match to existing page.
A3: LH (Location Hub) | B3: Phase 1 | C3: Firm Hub | D3: Location Directory | E3: Navigation + Trust | F3: Illinois Family Law Office Locations | Sterling Lawyers | G3: https://www.sterlinglawyers.com/illinois/locations/ | H3: Illinois family law office locations | I3: https://www.sterlinglawyers.com/illinois/locations/ | J3: MAPPED | K3: Location directory / hub page. Full match to existing page.
A4: 1 | B4: Phase 1 | C4: Practice Area | D4: Practice Area Hub | E4: Pillar Hub | F4: Illinois Divorce Lawyer | Sterling Lawyers | G4: https://www.sterlinglawyers.com/illinois/divorce/ | H4: illinois divorce lawyer | I4: https://www.sterlinglawyers.com/illinois/divorce/ | J4: MAPPED | K4: Full match to existing page.
A5: 2 | B5: Phase 1 | C5: Practice Area | D5: Practice Area Hub | E5: Pillar Hub | F5: Illinois Child Custody Lawyer | Sterling Lawyers | G5: https://www.sterlinglawyers.com/illinois/child-custody/ | H5: illinois child custody lawyer | I5: https://www.sterlinglawyers.com/illinois/child-custody/ | J5: MAPPED | K5: Full match to existing page.
A6: 3 | B6: Phase 1 | C6: Practice Area | D6: Practice Area Hub | E6: Pillar Hub | F6: Illinois Child Support Lawyer | Sterling Lawyers | G6: https://www.sterlinglawyers.com/illinois/child-support/ | H6: illinois child support lawyer | I6: https://www.sterlinglawyers.com/illinois/child-support/ | J6: MAPPED | K6: Full match to existing page.
A7: 4 | B7: Phase 1 | C7: Practice Area | D7: Practice Area Hub | E7: Pillar Hub | F7: Illinois Alimony Lawyer | Sterling Lawyers | G7: https://www.sterlinglawyers.com/illinois/spousal-support/ | H7: illinois alimony lawyer | I7: https://www.sterlinglawyers.com/illinois/spousal-support/ | J7: MAPPED | K7: Illinois uses 'spousal support' terminology; treat as alimony equivalent. Full match to existing page.
A8: 5 | B8: Phase 1 | C8: Practice Area | D8: Practice Area Hub | E8: Pillar Hub | F8: Illinois Property Division Lawyer | Sterling Lawyers | G8: https://www.sterlinglawyers.com/illinois/property-division/ | H8: illinois property division lawyer | I8: https://www.sterlinglawyers.com/illinois/property-division/ | J8: MAPPED | K8: Full match to existing page.
A9: 6 | B9: Phase 1 | C9: Practice Area | D9: Practice Area Hub | E9: Pillar Hub | F9: Illinois Paternity Lawyer | Sterling Lawyers | G9: https://www.sterlinglawyers.com/illinois/paternity/ | H9: illinois paternity lawyer | I9: https://www.sterlinglawyers.com/illinois/paternity/ | J9: MAPPED | K9: Paternity content also exists under Child Custody section. Full match to existing page.
A10: 7 | B10: Phase 1 | C10: Practice Area | D10: Practice Area Hub | E10: Pillar Hub | F10: Illinois Guardianship Lawyer | Sterling Lawyers | G10: https://www.sterlinglawyers.com/illinois/guardianship/ | H10: illinois guardianship lawyer | I10: https://www.sterlinglawyers.com/illinois/guardianship/ | J10: MAPPED | K10: Full match to existing page.
A11: 8 | B11: Phase 1 | C11: Procedural | D11: Process Page | E11: Cluster Support | F11: Contested Divorce in Illinois | Sterling Lawyers | G11: https://www.sterlinglawyers.com/illinois/divorce/contested/ | H11: illinois contested divorce | I11: https://www.sterlinglawyers.com/illinois/divorce/contested/ | J11: MAPPED | K11: Full match to existing page.
A12: 9 | B12: Phase 1 | C12: Procedural | D12: Process Page | E12: Cluster Support | F12: Uncontested Divorce in Illinois | Sterling Lawyers | G12: https://www.sterlinglawyers.com/illinois/divorce/uncontested-divorce/ | H12: illinois uncontested divorce | I12: https://www.sterlinglawyers.com/illinois/divorce/uncontested-divorce/ | J12: MAPPED | K12: Full match to existing page.
A13: 10 | B13: Phase 2 | C13: Procedural | D13: Process Page | E13: Cluster Support | F13: Child Custody Modification in Illinois | Sterling Lawyers | G13: https://www.sterlinglawyers.com/illinois/child-custody/modify-orders/ | H13: illinois child custody modification | I13: https://www.sterlinglawyers.com/illinois/child-custody/modify-orders/ | J13: MAPPED | K13: Full match to existing page.
A14: 11 | B14: Phase 2 | C14: Procedural | D14: Process Page | E14: Cluster Support | F14: Child Support Modification in Illinois | Sterling Lawyers | G14: https://www.sterlinglawyers.com/illinois/child-support/modify-orders/ | H14: illinois child support modification | I14: https://www.sterlinglawyers.com/illinois/child-support/modify-orders/ | J14: MAPPED | K14: Full match to existing page.
A15: 12 | B15: Phase 2 | C15: Procedural | D15: Process Page | E15: Cluster Support | F15: Child Support Enforcement in Illinois | Sterling Lawyers | G15: https://www.sterlinglawyers.com/illinois/child-support/enforce-orders/ | H15: illinois child support enforcement | I15: https://www.sterlinglawyers.com/illinois/child-support/enforce-orders/ | J15: MAPPED | K15: Full match to existing page.
... A23: 20 | B23: Phase 2 | C23: Procedural | D23: Process Page | E23: Cluster Support | F23: Guardianship of a Minor in Illinois | Sterling Lawyers | G23: https://www.sterlinglawyers.com/illinois/guardianship/minor/ | H23: illinois guardianship of a minor | I23: https://www.sterlinglawyers.com/illinois/guardianship/ | J23: PARTIAL | K23: Guardianship hub appears to focus on minors; no dedicated minor-only page. Partial coverage via https://www.sterlinglawyers.com/illinois/guardianship/ — recommend dedicated page at https://www.sterlinglawyers.com/illinois/guardianship/minor/.
A24: 21 | B24: Phase 2 | C24: Procedural | D24: Process Page | E24: Cluster Support | F24: Adult Guardianship in Illinois | Sterling Lawyers | G24: https://www.sterlinglawyers.com/illinois/guardianship/adult/ | H24: illinois adult guardianship | J24: GAP - MISSING | K24: No adult guardianship content detected; guardianship hub appears focused on minors. No dedicated page found — create at https://www.sterlinglawyers.com/illinois/guardianship/adult/.
A25: 22 | B25: Phase 2 | C25: Procedural | D25: Process Page | E25: Cluster Support | F25: Challenging Paternity in Illinois | Sterling Lawyers | G25: https://www.sterlinglawyers.com/illinois/paternity/challenging-paternity/ | H25: illinois challenging paternity | J25: GAP - MISSING | K25: No paternity challenge/disestablishment page detected. No dedicated page found — create at https://www.sterlinglawyers.com/illinois/paternity/challenging-paternity/.
A26: 23 | B26: Phase 2 | C26: Procedural | D26: Process Page | E26: Cluster Support | F26: Legal Separation in Illinois | Sterling Lawyers | G26: https://www.sterlinglawyers.com/illinois/divorce/separation/ | H26: illinois legal separation | I26: https://www.sterlinglawyers.com/illinois/divorce/separation/ | J26: MAPPED | K26: Full match to existing page.
A27: 24 | B27: Phase 2 | C27: Procedural | D27: Process Page | E27: Cluster Support | F27: Divorce Mediation in Illinois | Sterling Lawyers | G27: https://www.sterlinglawyers.com/illinois/divorce/mediation/ | H27: illinois divorce mediation | I27: https://www.sterlinglawyers.com/illinois/divorce/mediation/ | J27: MAPPED | K27: Full match to existing page.
A28: 25 | B28: Phase 2 | C28: Procedural | D28: Process Page | E28: Cluster Support | F28: Collaborative Divorce in Illinois | Sterling Lawyers | G28: https://www.sterlinglawyers.com/illinois/divorce/collaborative/ | H28: illinois collaborative divorce | I28: https://www.sterlinglawyers.com/illinois/divorce/collaborative/ | J28: MAPPED | K28: Full match to existing page.
A29: 26 | B29: Phase 2 | C29: Procedural | D29: Process Page | E29: Cluster Support | F29: Temporary Guardianship in Illinois | Sterling Lawyers | G29: https://www.sterlinglawyers.com/illinois/guardianship/temporary/ | H29: illinois temporary guardianship | J29: GAP - MISSING | K29: No temporary guardianship page detected. No dedicated page found — create at https://www.sterlinglawyers.com/illinois/guardianship/temporary/.
A30: 27 | B30: Phase 3 | C30: Situational | D30: Situation Page | E30: Cluster Support | F30: High-Conflict Divorce in Illinois | Sterling Lawyers | G30: https://www.sterlinglawyers.com/illinois/divorce/high-conflict/ | H30: illinois high-conflict divorce | I30: https://www.sterlinglawyers.com/illinois/divorce/litigation/ | J30: PARTIAL | K30: Litigation / protective orders likely capture high-conflict intent. Partial coverage via https://www.sterlinglawyers.com/illinois/divorce/litigation/ — recommend dedicated page at https://www.sterlinglawyers.com/illinois/divorce/high-conflict/.
A31: 28 | B31: Phase 3 | C31: Situational | D31: Situation Page | E31: Cluster Support | F31: Relocation / Move-Away Custody Disputes in Illinois | Sterling Lawyers | G31: https://www.sterlinglawyers.com/illinois/child-custody/relocation/ | H31: illinois relocation / move-away custody disputes | I31: https://www.sterlinglawyers.com/illinois/child-custody/ | J31: PARTIAL | K31: Relocation appears addressed within custody/parenting plan content; no dedicated relocation dispute page. Partial coverage via https://www.sterlinglawyers.com/illinois/child-custody/ — recommend dedicated page at https://www.sterlinglawyers.com/illinois/child-custody/relocation/.
A32: 29 | B32: Phase 3 | C32: Situational | D32: Situation Page | E32: Cluster Support | F32: Divorce Involving Business Ownership in Illinois | Sterling Lawyers | G32: https://www.sterlinglawyers.com/illinois/divorce/business-ownership/ | H32: illinois divorce involving business ownership | J32: GAP - MISSING | K32: No business ownership divorce page detected. No dedicated page found — create at https://www.sterlinglawyers.com/illinois/divorce/business-ownership/.
A33: 30 | B33: Phase 3 | C33: Situational | D33: Situation Page | E33: Cluster Support | F33: High-Conflict Custody in Illinois | Sterling Lawyers | G33: https://www.sterlinglawyers.com/illinois/child-custody/high-conflict/ | H33: illinois high-conflict custody | I33: https://www.sterlinglawyers.com/illinois/child-custody/parental-alienation/ | J33: PARTIAL | K33: Covered partially via alienation/narcissist co-parenting pages. Partial coverage via https://www.sterlinglawyers.com/illinois/child-custody/parental-alienation/ — recommend dedicated page at https://www.sterlinglawyers.com/illinois/child-custody/high-conflict/.
A34: 31 | B34: Phase 3 | C34: Situational | D34: Situation Page | E34: Cluster Support | F34: Child Support Disputes After Income Changes in Illinois | Sterling Lawyers | G34: https://www.sterlinglawyers.com/illinois/child-support/income-change/ | H34: illinois child support disputes after income changes | I34: https://www.sterlinglawyers.com/illinois/child-support/modify-orders/ | J34: PARTIAL | K34: Modification page covers income change scenarios; no dedicated income-change dispute page. Partial coverage via https://www.sterlinglawyers.com/illinois/child-support/modify-orders/ — recommend dedicated page at https://www.sterlinglawyers.com/illinois/child-support/income-change/.
A35: 32 | B35: Phase 3 | C35: Situational | D35: Situation Page | E35: Cluster Support | F35: Back Child Support / Arrears in Illinois | Sterling Lawyers | G35: https://www.sterlinglawyers.com/illinois/child-support/arrears/ | H35: illinois back child support / arrears | I35: https://www.sterlinglawyers.com/illinois/child-support/enforce-orders/ | J35: PARTIAL | K35: Enforcement page likely touches arrears; no arrears-focused page detected. Partial coverage via https://www.sterlinglawyers.com/illinois/child-support/enforce-orders/ — recommend dedicated page at https://www.sterlinglawyers.com/illinois/child-support/arrears/.
A36: 33 | B36: Phase 3 | C36: Situational | D36: Situation Page | E36: Cluster Support | F36: Long-Term Marriage Divorce in Illinois | Sterling Lawyers | G36: https://www.sterlinglawyers.com/illinois/divorce/long-term-marriage/ | H36: illinois long-term marriage divorce | J36: GAP - MISSING | K36: No long-term marriage divorce page detected. No dedicated page found — create at https://www.sterlinglawyers.com/illinois/divorce/long-term-marriage/.
A37: 34 | B37: Phase 3 | C37: Situational | D37: Situation Page | E37: Cluster Support | F37: Business Valuation and Division in Illinois | Sterling Lawyers | G37: https://www.sterlinglawyers.com/illinois/property-division/business-valuation/ | H37: illinois business valuation and division | J37: GAP - MISSING | K37: No business valuation page detected. No dedicated page found — create at https://www.sterlinglawyers.com/illinois/property-division/business-valuation/.
A38: 35 | B38: Phase 3 | C38: Situational | D38: Situation Page | E38: Cluster Support | F38: Emergency Guardianship in Illinois | Sterling Lawyers | G38: https://www.sterlinglawyers.com/illinois/guardianship/emergency/ | H38: illinois emergency guardianship | J38: GAP - MISSING | K38: No emergency guardianship page detected. No dedicated page found — create at https://www.sterlinglawyers.com/illinois/guardianship/emergency/.
A39: 36 | B39: Phase 3 | C39: Situational | D39: Situation Page | E39: Cluster Support | F39: Parenting Time Disputes in Illinois | Sterling Lawyers | G39: https://www.sterlinglawyers.com/illinois/child-custody/parenting-time-disputes/ | H39: illinois parenting time disputes | I39: https://www.sterlinglawyers.com/illinois/child-custody/split-orders/ | J39: PARTIAL | K39: Split/enforcement pages partially address parenting time disputes. Partial coverage via https://www.sterlinglawyers.com/illinois/child-custody/split-orders/ — recommend dedicated page at https://www.sterlinglawyers.com/illinois/child-custody/parenting-time-disputes/.
A40: 37 | B40: Phase 3 | C40: Situational | D40: Situation Page | E40: Cluster Support | F40: High-Income Spousal Support Disputes in Illinois | Sterling Lawyers | G40: https://www.sterlinglawyers.com/illinois/spousal-support/high-income/ | H40: illinois high-income spousal support disputes | J40: GAP - MISSING | K40: No high-income spousal support dispute content detected. No dedicated page found — create at https://www.sterlinglawyers.com/illinois/spousal-support/high-income/.
A41: 38 | B41: Phase 3 | C41: Situational | D41: Situation Page | E41: Cluster Support | F41: Self-Employed or Variable Income Support in Illinois | Sterling Lawyers | G41: https://www.sterlinglawyers.com/illinois/child-support/self-employed-income/ | H41: illinois self-employed or variable income support | J41: GAP - MISSING | K41: No self-employed/variable income support page detected. No dedicated page found — create at https://www.sterlinglawyers.com/illinois/child-support/self-employed-income/.
A42: 39 | B42: Phase 3 | C42: Situational | D42: Situation Page | E42: Cluster Support | F42: Supervised Visitation in Illinois | Sterling Lawyers | G42: https://www.sterlinglawyers.com/illinois/child-custody/supervised-visitation/ | H42: illinois supervised visitation | J42: GAP - MISSING | K42: No supervised visitation page detected. No dedicated page found — create at https://www.sterlinglawyers.com/illinois/child-custody/supervised-visitation/.
A43: 40 | B43: Phase 3 | C43: Situational | D43: Situation Page | E43: Cluster Support | F43: Hidden Assets and Financial Misconduct in Illinois | Sterling Lawyers | G43: https://www.sterlinglawyers.com/illinois/property-division/hidden-assets/ | H43: illinois hidden assets and financial misconduct | I43: https://www.sterlinglawyers.com/illinois/property-division/hidden-assets/ | J43: MAPPED | K43: Full match to existing page.

Sheet Performance Summary
A1: Map ID | B1: Page Title | C1: Target Keyword | D1: URL | F1: Status Code | G1: L3M Clicks | H1: Prev 3M Clicks | I1: Δ Clicks % | J1: L3M Impressions | K1: Prev 3M Impressions | L1: Δ Impr % | M1: L3M New Users | N1: Prev 3M New Users | O1: Δ Users % | P1: L3M Key Events | Q1: Prev 3M Key Events | R1: Δ Conv %
A2: 1 | B2: Attorney Hub | C2: family law attorneys texas | D2: https://sbrownlawyer.com/attorneys/ | E2: /attorneys | F2: =vlookup(D2,L3m_search_console_all!A:B,2,0) -> 200 | G2: =vlookup(D2,L3m_search_console_all!A:F,6,0) -> 57 | H2: =vlookup(D2,P3m_search_console!A:F,6,0) -> 101 | I2: =IF(H2>0,(G2-H2)/H2,"N/A") -> -0.43564356 | J2: =vlookup(D2,L3m_search_console_all!A:G,7,0) -> 19373 | K2: =vlookup(D2,P3m_search_console!A:G,7,0) -> 34633 | L2: =IF(K2>0,(J2-K2)/K2,"N/A") -> -0.44062022 | M2: =vlookup(D2,L3m_analytics_all!A:M,13,0) -> 71 | N2: =vlookup(E2,P3M_analytics!A:D,4,0) -> 125 | O2: =IF(N2>0,(M2-N2)/N2,"N/A") -> -0.432 | P2: =vlookup(D2,L3m_analytics_all!A:J,10,0) -> 0 | Q2: =vlookup(E2,P3M_analytics!A:F,6,0) -> 11 | R2: =IF(Q2>0,(P2-Q2)/Q2,"N/A") -> -1
A3: 2 | B3: Location Hub | C3: family law office locations texas | D3: https://sbrownlawyer.com/texas/locations/ | E3: /texas/locations | F3: =vlookup(D3,L3m_search_console_all!A:B,2,0) -> 200 | G3: =vlookup(D3,L3m_search_console_all!A:F,6,0) -> 2 | H3: =vlookup(D3,P3m_search_console!A:F,6,0) -> 0 | I3: =IF(H3>0,(G3-H3)/H3,"N/A") -> N/A | J3: =vlookup(D3,L3m_search_console_all!A:G,7,0) -> 1703 | K3: =vlookup(D3,P3m_search_console!A:G,7,0) -> 300 | L3: =IF(K3>0,(J3-K3)/K3,"N/A") -> 4.6766667 | M3: =vlookup(D3,L3m_analytics_all!A:M,13,0) -> 8 | N3: =vlookup(E3,P3M_analytics!A:D,4,0) -> 11 | O3: =IF(N3>0,(M3-N3)/N3,"N/A") -> -0.27272727 | P3: =vlookup(D3,L3m_analytics_all!A:J,10,0) -> 1 | Q3: =vlookup(E3,P3M_analytics!A:F,6,0) -> 0 | R3: =IF(Q3>0,(P3-Q3)/Q3,"N/A") -> N/A
A4: 3 | B4: Divorce Hub | C4: divorce lawyer texas | D4: https://sbrownlawyer.com/divorce/ | E4: /divorce | F4: =vlookup(D4,L3m_search_console_all!A:B,2,0) -> 200 | G4: =vlookup(D4,L3m_search_console_all!A:F,6,0) -> 7 | H4: =vlookup(D4,P3m_search_console!A:F,6,0) -> 24 | I4: =IF(H4>0,(G4-H4)/H4,"N/A") -> -0.70833333 | J4: =vlookup(D4,L3m_search_console_all!A:G,7,0) -> 12101 | K4: =vlookup(D4,P3m_search_console!A:G,7,0) -> 18218 | L4: =IF(K4>0,(J4-K4)/K4,"N/A") -> -0.33576682 | M4: =vlookup(D4,L3m_analytics_all!A:M,13,0) -> 13 | N4: =vlookup(E4,P3M_analytics!A:D,4,0) -> 32 | O4: =IF(N4>0,(M4-N4)/N4,"N/A") -> -0.59375 | P4: =vlookup(D4,L3m_analytics_all!A:J,10,0) -> 0 | Q4: =vlookup(E4,P3M_analytics!A:F,6,0) -> 1 | R4: =IF(Q4>0,(P4-Q4)/Q4,"N/A") -> -1
A5: 4 | B5: Child Custody Hub | C5: child custody lawyer texas | D5: https://sbrownlawyer.com/child-custody/ | E5: /child-custody | F5: =vlookup(D5,L3m_search_console_all!A:B,2,0) -> 200 | G5: =vlookup(D5,L3m_search_console_all!A:F,6,0) -> 2 | H5: =vlookup(D5,P3m_search_console!A:F,6,0) -> 9 | I5: =IF(H5>0,(G5-H5)/H5,"N/A") -> -0.77777778 | J5: =vlookup(D5,L3m_search_console_all!A:G,7,0) -> 3310 | K5: =vlookup(D5,P3m_search_console!A:G,7,0) -> 28578 | L5: =IF(K5>0,(J5-K5)/K5,"N/A") -> -0.88417664 | M5: =vlookup(D5,L3m_analytics_all!A:M,13,0) -> 5 | N5: =vlookup(E5,P3M_analytics!A:D,4,0) -> 11 | O5: =IF(N5>0,(M5-N5)/N5,"N/A") -> -0.54545455 | P5: =vlookup(D5,L3m_analytics_all!A:J,10,0) -> 1 | Q5: =vlookup(E5,P3M_analytics!A:F,6,0) -> 0 | R5: =IF(Q5>0,(P5-Q5)/Q5,"N/A") -> N/A
A6: 5 | B6: Child Support Hub | C6: child support lawyer texas | D6: https://sbrownlawyer.com/child-support/ | E6: /child-support | F6: =vlookup(D6,L3m_search_console_all!A:B,2,0) -> 200 | G6: =vlookup(D6,L3m_search_console_all!A:F,6,0) -> 1 | H6: =vlookup(D6,P3m_search_console!A:F,6,0) -> 1 | I6: =IF(H6>0,(G6-H6)/H6,"N/A") -> 0 | J6: =vlookup(D6,L3m_search_console_all!A:G,7,0) -> 2110 | K6: =vlookup(D6,P3m_search_console!A:G,7,0) -> 4643 | L6: =IF(K6>0,(J6-K6)/K6,"N/A") -> -0.54555244 | M6: =vlookup(D6,L3m_analytics_all!A:M,13,0) -> 3 | N6: =vlookup(E6,P3M_analytics!A:D,4,0) -> 6 | O6: =IF(N6>0,(M6-N6)/N6,"N/A") -> -0.5 | P6: =vlookup(D6,L3m_analytics_all!A:J,10,0) -> 1 | Q6: =vlookup(E6,P3M_analytics!A:F,6,0) -> 0 | R6: =IF(Q6>0,(P6-Q6)/Q6,"N/A") -> N/A
A7: 6 | B7: Spousal Support / Alimony Hub | C7: alimony lawyer texas | D7: https://sbrownlawyer.com/attorneys-working-to-achieve-your-alimony-goals/ | E7: /attorneys-working-to-achieve-your-alimony-goals | F7: =vlookup(D7,L3m_search_console_all!A:B,2,0) -> 200 | G7: =vlookup(D7,L3m_search_console_all!A:F,6,0) -> 0 | H7: =vlookup(D7,P3m_search_console!A:F,6,0) -> 3 | I7: =IF(H7>0,(G7-H7)/H7,"N/A") -> -1 | J7: =vlookup(D7,L3m_search_console_all!A:G,7,0) -> 535 | K7: =vlookup(D7,P3m_search_console!A:G,7,0) -> 1731 | L7: =IF(K7>0,(J7-K7)/K7,"N/A") -> -0.6909301 | M7: =vlookup(D7,L3m_analytics_all!A:M,13,0) -> 1 | N7: =vlookup(E7,P3M_analytics!A:D,4,0) -> 2 | O7: =IF(N7>0,(M7-N7)/N7,"N/A") -> -0.5 | P7: =vlookup(D7,L3m_analytics_all!A:J,10,0) -> 0 | Q7: =vlookup(E7,P3M_analytics!A:F,6,0) -> 0 | R7: =IF(Q7>0,(P7-Q7)/Q7,"N/A") -> N/A
A8: 7 | B8: Property Division Hub | C8: property division lawyer texas | D8: https://sbrownlawyer.com/division-of-property/ | E8: /division-of-property | F8: =vlookup(D8,L3m_search_console_all!A:B,2,0) -> 200 | G8: =vlookup(D8,L3m_search_console_all!A:F,6,0) -> 2 | H8: =vlookup(D8,P3m_search_console!A:F,6,0) -> 5 | I8: =IF(H8>0,(G8-H8)/H8,"N/A") -> -0.6 | J8: =vlookup(D8,L3m_search_console_all!A:G,7,0) -> 499 | K8: =vlookup(D8,P3m_search_console!A:G,7,0) -> 577 | L8: =IF(K8>0,(J8-K8)/K8,"N/A") -> -0.13518198 | M8: =vlookup(D8,L3m_analytics_all!A:M,13,0) -> 4 | N8: =vlookup(E8,P3M_analytics!A:D,4,0) -> 5 | O8: =IF(N8>0,(M8-N8)/N8,"N/A") -> -0.2 | P8: =vlookup(D8,L3m_analytics_all!A:J,10,0) -> 0 | Q8: =vlookup(E8,P3M_analytics!A:F,6,0) -> 0 | R8: =IF(Q8>0,(P8-Q8)/Q8,"N/A") -> N/A
A9: 8 | B9: Paternity Hub | C9: paternity lawyer texas | D9: https://sbrownlawyer.com/paternity/ | E9: /paternity | F9: =vlookup(D9,L3m_search_console_all!A:B,2,0) -> 200 | G9: =vlookup(D9,L3m_search_console_all!A:F,6,0) -> 0 | H9: =vlookup(D9,P3m_search_console!A:F,6,0) -> 0 | I9: =IF(H9>0,(G9-H9)/H9,"N/A") -> N/A | J9: =vlookup(D9,L3m_search_console_all!A:G,7,0) -> 112 | K9: =vlookup(D9,P3m_search_console!A:G,7,0) -> 356 | L9: =IF(K9>0,(J9-K9)/K9,"N/A") -> -0.68539326 | M9: =vlookup(D9,L3m_analytics_all!A:M,13,0) -> 1 | N9: =vlookup(E9,P3M_analytics!A:D,4,0) -> 1 | O9: =IF(N9>0,(M9-N9)/N9,"N/A") -> 0 | P9: =vlookup(D9,L3m_analytics_all!A:J,10,0) -> 0 | Q9: =vlookup(E9,P3M_analytics!A:F,6,0) -> 0 | R9: =IF(Q9>0,(P9-Q9)/Q9,"N/A") -> N/A
A10: 10 | B10: Contested Divorce | C10: contested divorce texas | D10: https://sbrownlawyer.com/complex-and-contested-divorce-attorneys/ | E10: /complex-and-contested-divorce-attorneys | F10: =vlookup(D10,L3m_search_console_all!A:B,2,0) -> 200 | G10: =vlookup(D10,L3m_search_console_all!A:F,6,0) -> 0 | H10: =vlookup(D10,P3m_search_console!A:F,6,0) -> 0 | I10: =IF(H10>0,(G10-H10)/H10,"N/A") -> N/A | J10: =vlookup(D10,L3m_search_console_all!A:G,7,0) -> 58 | K10: =vlookup(D10,P3m_search_console!A:G,7,0) -> 16 | L10: =IF(K10>0,(J10-K10)/K10,"N/A") -> 2.625 | M10: =vlookup(D10,L3m_analytics_all!A:M,13,0) -> 1 | N10: =vlookup(E10,P3M_analytics!A:D,4,0) -> #N/A | O10: =IF(N10>0,(M10-N10)/N10,"N/A") -> #N/A | P10: =vlookup(D10,L3m_analytics_all!A:J,10,0) -> 0 | Q10: =vlookup(E10,P3M_analytics!A:F,6,0) -> #N/A | R10: =IF(Q10>0,(P10-Q10)/Q10,"N/A") -> #N/A
A11: 11 | B11: Uncontested Divorce | C11: uncontested divorce texas | D11: https://sbrownlawyer.com/uncontested-divorce-lawyer-in-pearland/ | E11: /uncontested-divorce-lawyer-in-pearland | F11: =vlookup(D11,L3m_search_console_all!A:B,2,0) -> 200 | G11: =vlookup(D11,L3m_search_console_all!A:F,6,0) -> 4 | H11: =vlookup(D11,P3m_search_console!A:F,6,0) -> 7 | I11: =IF(H11>0,(G11-H11)/H11,"N/A") -> -0.42857143 | J11: =vlookup(D11,L3m_search_console_all!A:G,7,0) -> 1454 | K11: =vlookup(D11,P3m_search_console!A:G,7,0) -> 1754 | L11: =IF(K11>0,(J11-K11)/K11,"N/A") -> -0.17103763 | M11: =vlookup(D11,L3m_analytics_all!A:M,13,0) -> 6 | N11: =vlookup(E11,P3M_analytics!A:D,4,0) -> 4 | O11: =IF(N11>0,(M11-N11)/N11,"N/A") -> 0.5 | P11: =vlookup(D11,L3m_analytics_all!A:J,10,0) -> 1 | Q11: =vlookup(E11,P3M_analytics!A:F,6,0) -> 0 | R11: =IF(Q11>0,(P11-Q11)/Q11,"N/A") -> N/A
A12: 12 | B12: Child Custody Modification | C12: child custody modification texas | D12: https://sbrownlawyer.com/modification-of-custody/ | E12: /modification-of-custody | F12: =vlookup(D12,L3m_search_console_all!A:B,2,0) -> 200 | G12: =vlookup(D12,L3m_search_console_all!A:F,6,0) -> 1 | H12: =vlookup(D12,P3m_search_console!A:F,6,0) -> 0 | I12: =IF(H12>0,(G12-H12)/H12,"N/A") -> N/A | J12: =vlookup(D12,L3m_search_console_all!A:G,7,0) -> 475 | K12: =vlookup(D12,P3m_search_console!A:G,7,0) -> 563 | L12: =IF(K12>0,(J12-K12)/K12,"N/A") -> -0.15630551 | M12: =vlookup(D12,L3m_analytics_all!A:M,13,0) -> 1 | N12: =vlookup(E12,P3M_analytics!A:D,4,0) -> #N/A | O12: =IF(N12>0,(M12-N12)/N12,"N/A") -> #N/A | P12: =vlookup(D12,L3m_analytics_all!A:J,10,0) -> 0 | Q12: =vlookup(E12,P3M_analytics!A:F,6,0) -> #N/A | R12: =IF(Q12>0,(P12-Q12)/Q12,"N/A") -> #N/A
A13: 13 | B13: Child Support Modification | C13: child support modification texas | D13: https://sbrownlawyer.com/child-support-modifications/ | E13: /child-support-modifications | F13: =vlookup(D13,L3m_search_console_all!A:B,2,0) -> 200 | G13: =vlookup(D13,L3m_search_console_all!A:F,6,0) -> 0 | H13: =vlookup(D13,P3m_search_console!A:F,6,0) -> 0 | I13: =IF(H13>0,(G13-H13)/H13,"N/A") -> N/A | J13: =vlookup(D13,L3m_search_console_all!A:G,7,0) -> 193 | K13: =vlookup(D13,P3m_search_console!A:G,7,0) -> 514 | L13: =IF(K13>0,(J13-K13)/K13,"N/A") -> -0.62451362 | M13: =vlookup(D13,L3m_analytics_all!A:M,13,0) | N13: =vlookup(E13,P3M_analytics!A:D,4,0) -> 2 | O13: =IF(N13>0,(M13-N13)/N13,"N/A") -> -1 | P13: =vlookup(D13,L3m_analytics_all!A:J,10,0) | Q13: =vlookup(E13,P3M_analytics!A:F,6,0) -> 0 | R13: =IF(Q13>0,(P13-Q13)/Q13,"N/A") -> N/A
... A28: 42 | B28: Hidden Assets and Financial Misconduct | C28: hidden assets divorce texas | D28: https://sbrownlawyer.com/hidden-assets/ | E28: /hidden-assets | F28: =vlookup(D28,L3m_search_console_all!A:B,2,0) -> 200 | G28: =vlookup(D28,L3m_search_console_all!A:F,6,0) -> 1 | H28: =vlookup(D28,P3m_search_console!A:F,6,0) -> 0 | I28: =IF(H28>0,(G28-H28)/H28,"N/A") -> N/A | J28: =vlookup(D28,L3m_search_console_all!A:G,7,0) -> 5 | K28: =vlookup(D28,P3m_search_console!A:G,7,0) -> 6 | L28: =IF(K28>0,(J28-K28)/K28,"N/A") -> -0.16666667 | M28: =vlookup(D28,L3m_analytics_all!A:M,13,0) -> 2 | N28: =vlookup(E28,P3M_analytics!A:D,4,0) -> #N/A | O28: =IF(N28>0,(M28-N28)/N28,"N/A") -> #N/A | P28: =vlookup(D28,L3m_analytics_all!A:J,10,0) -> 0 | Q28: =vlookup(E28,P3M_analytics!A:F,6,0) -> #N/A | R28: =IF(Q28>0,(P28-Q28)/Q28,"N/A") -> #N/A

Sheet YoY Comparison
A1: Map ID | B1: Page Title | C1: Target Keyword | D1: URL | E1: L3M Clicks | F1: L3M LY Clicks | G1: YoY Δ % | H1: L3M Impressions | I1: L3M LY Impressions | J1: YoY Δ %
A2: 1 | B2: Attorney Hub | C2: family law attorneys texas | D2: https://sbrownlawyer.com/attorneys/ | E2: =vlookup(D2,L3m_search_console_all!A:F,6,0) -> 57 | F2: =vlookup(D2,L3M_LY_search_console!A:B,2,0) -> 54 | G2: =IF(F2>0,(E2-F2)/F2,"N/A") -> 0.055555556 | H2: =vlookup(D2,L3m_search_console_all!A:G,7,0) -> 19373 | I2: =vlookup(D2,L3M_LY_search_console!A:C,3,0) -> 15958 | J2: =IF(I2>0,(H2-I2)/I2,"N/A") -> 0.21399925
A3: 2 | B3: Location Hub | C3: family law office locations texas | D3: https://sbrownlawyer.com/texas/locations/ | E3: =vlookup(D3,L3m_search_console_all!A:F,6,0) -> 2 | F3: =vlookup(D3,L3M_LY_search_console!A:B,2,0) -> #N/A | G3: =IF(F3>0,(E3-F3)/F3,"N/A") -> #N/A | H3: =vlookup(D3,L3m_search_console_all!A:G,7,0) -> 1703 | I3: =vlookup(D3,L3M_LY_search_console!A:C,3,0) -> #N/A | J3: =IF(I3>0,(H3-I3)/I3,"N/A") -> #N/A
A4: 3 | B4: Divorce Hub | C4: divorce lawyer texas | D4: https://sbrownlawyer.com/divorce/ | E4: =vlookup(D4,L3m_search_console_all!A:F,6,0) -> 7 | F4: =vlookup(D4,L3M_LY_search_console!A:B,2,0) -> 29 | G4: =IF(F4>0,(E4-F4)/F4,"N/A") -> -0.75862069 | H4: =vlookup(D4,L3m_search_console_all!A:G,7,0) -> 12101 | I4: =vlookup(D4,L3M_LY_search_console!A:C,3,0) -> 16016 | J4: =IF(I4>0,(H4-I4)/I4,"N/A") -> -0.24444306
A5: 4 | B5: Child Custody Hub | C5: child custody lawyer texas | D5: https://sbrownlawyer.com/child-custody/ | E5: =vlookup(D5,L3m_search_console_all!A:F,6,0) -> 2 | F5: =vlookup(D5,L3M_LY_search_console!A:B,2,0) -> 2 | G5: =IF(F5>0,(E5-F5)/F5,"N/A") -> 0 | H5: =vlookup(D5,L3m_search_console_all!A:G,7,0) -> 3310 | I5: =vlookup(D5,L3M_LY_search_console!A:C,3,0) -> 8796 | J5: =IF(I5>0,(H5-I5)/I5,"N/A") -> -0.62369259
A6: 5 | B6: Child Support Hub | C6: child support lawyer texas | D6: https://sbrownlawyer.com/child-support/ | E6: =vlookup(D6,L3m_search_console_all!A:F,6,0) -> 1 | F6: =vlookup(D6,L3M_LY_search_console!A:B,2,0) -> 1 | G6: =IF(F6>0,(E6-F6)/F6,"N/A") -> 0 | H6: =vlookup(D6,L3m_search_console_all!A:G,7,0) -> 2110 | I6: =vlookup(D6,L3M_LY_search_console!A:C,3,0) -> 6838 | J6: =IF(I6>0,(H6-I6)/I6,"N/A") -> -0.69143024
A7: 6 | B7: Spousal Support / Alimony Hub | C7: alimony lawyer texas | D7: https://sbrownlawyer.com/attorneys-working-to-achieve-your-alimony-goals/ | E7: =vlookup(D7,L3m_search_console_all!A:F,6,0) -> 0 | F7: =vlookup(D7,L3M_LY_search_console!A:B,2,0) -> 0 | G7: =IF(F7>0,(E7-F7)/F7,"N/A") -> N/A | H7: =vlookup(D7,L3m_search_console_all!A:G,7,0) -> 535 | I7: =vlookup(D7,L3M_LY_search_console!A:C,3,0) -> 892 | J7: =IF(I7>0,(H7-I7)/I7,"N/A") -> -0.40022422
A8: 7 | B8: Property Division Hub | C8: property division lawyer texas | D8: https://sbrownlawyer.com/division-of-property/ | E8: =vlookup(D8,L3m_search_console_all!A:F,6,0) -> 2 | F8: =vlookup(D8,L3M_LY_search_console!A:B,2,0) -> 6 | G8: =IF(F8>0,(E8-F8)/F8,"N/A") -> -0.66666667 | H8: =vlookup(D8,L3m_search_console_all!A:G,7,0) -> 499 | I8: =vlookup(D8,L3M_LY_search_console!A:C,3,0) -> 2126 | J8: =IF(I8>0,(H8-I8)/I8,"N/A") -> -0.76528692
A9: 8 | B9: Paternity Hub | C9: paternity lawyer texas | D9: https://sbrownlawyer.com/paternity/ | E9: =vlookup(D9,L3m_search_console_all!A:F,6,0) -> 0 | F9: =vlookup(D9,L3M_LY_search_console!A:B,2,0) -> 0 | G9: =IF(F9>0,(E9-F9)/F9,"N/A") -> N/A | H9: =vlookup(D9,L3m_search_console_all!A:G,7,0) -> 112 | I9: =vlookup(D9,L3M_LY_search_console!A:C,3,0) -> 476 | J9: =IF(I9>0,(H9-I9)/I9,"N/A") -> -0.76470588
A10: 10 | B10: Contested Divorce | C10: contested divorce texas | D10: https://sbrownlawyer.com/complex-and-contested-divorce-attorneys/ | E10: =vlookup(D10,L3m_search_console_all!A:F,6,0) -> 0 | F10: =vlookup(D10,L3M_LY_search_console!A:B,2,0) -> 0 | G10: =IF(F10>0,(E10-F10)/F10,"N/A") -> N/A | H10: =vlookup(D10,L3m_search_console_all!A:G,7,0) -> 58 | I10: =vlookup(D10,L3M_LY_search_console!A:C,3,0) -> 44 | J10: =IF(I10>0,(H10-I10)/I10,"N/A") -> 0.31818182
A11: 11 | B11: Uncontested Divorce | C11: uncontested divorce texas | D11: https://sbrownlawyer.com/uncontested-divorce-lawyer-in-pearland/ | E11: =vlookup(D11,L3m_search_console_all!A:F,6,0) -> 4 | F11: =vlookup(D11,L3M_LY_search_console!A:B,2,0) -> 8 | G11: =IF(F11>0,(E11-F11)/F11,"N/A") -> -0.5 | H11: =vlookup(D11,L3m_search_console_all!A:G,7,0) -> 1454 | I11: =vlookup(D11,L3M_LY_search_console!A:C,3,0) -> 3452 | J11: =IF(I11>0,(H11-I11)/I11,"N/A") -> -0.5787949
A12: 12 | B12: Child Custody Modification | C12: child custody modification texas | D12: https://sbrownlawyer.com/modification-of-custody/ | E12: =vlookup(D12,L3m_search_console_all!A:F,6,0) -> 1 | F12: =vlookup(D12,L3M_LY_search_console!A:B,2,0) -> 0 | G12: =IF(F12>0,(E12-F12)/F12,"N/A") -> N/A | H12: =vlookup(D12,L3m_search_console_all!A:G,7,0) -> 475 | I12: =vlookup(D12,L3M_LY_search_console!A:C,3,0) -> 396 | J12: =IF(I12>0,(H12-I12)/I12,"N/A") -> 0.19949495
A13: 13 | B13: Child Support Modification | C13: child support modification texas | D13: https://sbrownlawyer.com/child-support-modifications/ | E13: =vlookup(D13,L3m_search_console_all!A:F,6,0) -> 0 | F13: =vlookup(D13,L3M_LY_search_console!A:B,2,0) -> 0 | G13: =IF(F13>0,(E13-F13)/F13,"N/A") -> N/A | H13: =vlookup(D13,L3m_search_console_all!A:G,7,0) -> 193 | I13: =vlookup(D13,L3M_LY_search_console!A:C,3,0) -> 214 | J13: =IF(I13>0,(H13-I13)/I13,"N/A") -> -0.098130841
... A28: 42 | B28: Hidden Assets and Financial Misconduct | C28: hidden assets divorce texas | D28: https://sbrownlawyer.com/hidden-assets/ | E28: =vlookup(D28,L3m_search_console_all!A:F,6,0) -> 1 | F28: =vlookup(D28,L3M_LY_search_console!A:B,2,0) -> 0 | G28: =IF(F28>0,(E28-F28)/F28,"N/A") -> N/A | H28: =vlookup(D28,L3m_search_console_all!A:G,7,0) -> 5 | I28: =vlookup(D28,L3M_LY_search_console!A:C,3,0) -> 316 | J28: =IF(I28>0,(H28-I28)/I28,"N/A") -> -0.98417722

Sheet Top Keyword Rankings
A1: Map ID | B1: Page Title | C1: URL | D1: Top Keyword 1 | E1: Position 1 | F1: Volume 1 | G1: Top Keyword 2 | H1: Position 2 | I1: Volume 2 | J1: Top Keyword 3 | K1: Position 3 | L1: Volume 3
A2: 1 | B2: Attorney Hub | C2: https://sbrownlawyer.com/attorneys/ | D2: =IFERROR(__xludf.DUMMYFUNCTION("IFERROR(INDEX(SORT(FILTER(semrush_keywords!A:D, semrush_keywords!D:D=$C2), 2, 1), 1, 1), """")"),"mary e samaan attorney photos") -> mary e samaan attorney photos | E2: =IFERROR(__xludf.DUMMYFUNCTION("IFERROR(INDEX(SORT(FILTER(semrush_keywords!A:D, semrush_keywords!D:D=$C2), 2, 1), 1, 2), """")"),18.0) -> 18 | F2: =IFERROR(__xludf.DUMMYFUNCTION("IFERROR(INDEX(SORT(FILTER(semrush_keywords!A:D, semrush_keywords!D:D=$C2), 2, 1), 1, 3), """")"),40.0) -> 40 | G2: =IFERROR(__xludf.DUMMYFUNCTION("IFERROR(INDEX(SORT(FILTER(semrush_keywords!A:D, semrush_keywords!D:D=$C2), 2, 1), 2, 1), """")"),"lawyers in texas city tx") -> lawyers in texas city tx | H2: =IFERROR(__xludf.DUMMYFUNCTION("IFERROR(INDEX(SORT(FILTER(semrush_keywords!A:D, semrush_keywords!D:D=$C2), 2, 1), 2, 2), """")"),21.0) -> 21 | I2: =IFERROR(__xludf.DUMMYFUNCTION("IFERROR(INDEX(SORT(FILTER(semrush_keywords!A:D, semrush_keywords!D:D=$C2), 2, 1), 2, 3), """")"),90.0) -> 90 | J2: =IFERROR(__xludf.DUMMYFUNCTION("IFERROR(INDEX(SORT(FILTER(semrush_keywords!$A:$D, semrush_keywords!$D:$D=$C2), 2, 1), 3, 1), """")"),"scott and associates houston") -> scott and associates houston | K2: =IFERROR(__xludf.DUMMYFUNCTION("IFERROR(INDEX(SORT(FILTER(semrush_keywords!$A:$D, semrush_keywords!$D:$D=$C2), 2, 1), 3, 2), """")"),22.0) -> 22 | L2: =IFERROR(__xludf.DUMMYFUNCTION("IFERROR(INDEX(SORT(FILTER(semrush_keywords!$A:$D, semrush_keywords!$D:$D=$C2), 2, 1), 3, 3), """") "),40.0) -> 40
A3: 2 | B3: Location Hub | C3: https://sbrownlawyer.com/texas/locations/ | D3: =IFERROR(__xludf.DUMMYFUNCTION("IFERROR(INDEX(SORT(FILTER(semrush_keywords!A:D, semrush_keywords!D:D=$C3), 2, 1), 1, 1), """")"),"family law attorney angleton tx") -> family law attorney angleton tx | E3: =IFERROR(__xludf.DUMMYFUNCTION("IFERROR(INDEX(SORT(FILTER(semrush_keywords!A:D, semrush_keywords!D:D=$C3), 2, 1), 1, 2), """")"),27.0) -> 27 | F3: =IFERROR(__xludf.DUMMYFUNCTION("IFERROR(INDEX(SORT(FILTER(semrush_keywords!A:D, semrush_keywords!D:D=$C3), 2, 1), 1, 3), """")"),140.0) -> 140 | G3: =IFERROR(__xludf.DUMMYFUNCTION("IFERROR(INDEX(SORT(FILTER(semrush_keywords!A:D, semrush_keywords!D:D=$C3), 2, 1), 2, 1), """")"),"family law attorney angleton tx") -> family law attorney angleton tx | H3: =IFERROR(__xludf.DUMMYFUNCTION("IFERROR(INDEX(SORT(FILTER(semrush_keywords!A:D, semrush_keywords!D:D=$C3), 2, 1), 2, 2), """")"),61.0) -> 61 | I3: =IFERROR(__xludf.DUMMYFUNCTION("IFERROR(INDEX(SORT(FILTER(semrush_keywords!A:D, semrush_keywords!D:D=$C3), 2, 1), 2, 3), """")"),140.0) -> 140 | J3: =IFERROR(__xludf.DUMMYFUNCTION("IFERROR(INDEX(SORT(FILTER(semrush_keywords!$A:$D, semrush_keywords!$D:$D=$C3), 2, 1), 3, 1), """")"),"family attorney angleton") -> family attorney angleton | K3: =IFERROR(__xludf.DUMMYFUNCTION("IFERROR(INDEX(SORT(FILTER(semrush_keywords!$A:$D, semrush_keywords!$D:$D=$C3), 2, 1), 3, 2), """")"),74.0) -> 74 | L3: =IFERROR(__xludf.DUMMYFUNCTION("IFERROR(INDEX(SORT(FILTER(semrush_keywords!$A:$D, semrush_keywords!$D:$D=$C3), 2, 1), 3, 3), """") "),70.0) -> 70
A4: 3 | B4: Divorce Hub | C4: https://sbrownlawyer.com/divorce/ | D4: =IFERROR(__xludf.DUMMYFUNCTION("IFERROR(INDEX(SORT(FILTER(semrush_keywords!A:D, semrush_keywords!D:D=$C4), 2, 1), 1, 1), """")"),"attorneys in brazoria county texas") -> attorneys in brazoria county texas | E4: =IFERROR(__xludf.DUMMYFUNCTION("IFERROR(INDEX(SORT(FILTER(semrush_keywords!A:D, semrush_keywords!D:D=$C4), 2, 1), 1, 2), """")"),15.0) -> 15 | F4: =IFERROR(__xludf.DUMMYFUNCTION("IFERROR(INDEX(SORT(FILTER(semrush_keywords!A:D, semrush_keywords!D:D=$C4), 2, 1), 1, 3), """")"),110.0) -> 110 | G4: =IFERROR(__xludf.DUMMYFUNCTION("IFERROR(INDEX(SORT(FILTER(semrush_keywords!A:D, semrush_keywords!D:D=$C4), 2, 1), 2, 1), """")"),"lawyers in brazoria county tx") -> lawyers in brazoria county tx | H4: =IFERROR(__xludf.DUMMYFUNCTION("IFERROR(INDEX(SORT(FILTER(semrush_keywords!A:D, semrush_keywords!D:D=$C4), 2, 1), 2, 2), """")"),20.0) -> 20 | I4: =IFERROR(__xludf.DUMMYFUNCTION("IFERROR(INDEX(SORT(FILTER(semrush_keywords!A:D, semrush_keywords!D:D=$C4), 2, 1), 2, 3), """")"),140.0) -> 140 | J4: =IFERROR(__xludf.DUMMYFUNCTION("IFERROR(INDEX(SORT(FILTER(semrush_keywords!$A:$D, semrush_keywords!$D:$D=$C4), 2, 1), 3, 1), """")"),"divorce attorney angleton") -> divorce attorney angleton | K4: =IFERROR(__xludf.DUMMYFUNCTION("IFERROR(INDEX(SORT(FILTER(semrush_keywords!$A:$D, semrush_keywords!$D:$D=$C4), 2, 1), 3, 2), """")"),22.0) -> 22 | L4: =IFERROR(__xludf.DUMMYFUNCTION("IFERROR(INDEX(SORT(FILTER(semrush_keywords!$A:$D, semrush_keywords!$D:$D=$C4), 2, 1), 3, 3), """") "),170.0) -> 170
A5: 4 | B5: Child Custody Hub | C5: https://sbrownlawyer.com/child-custody/ | D5: =IFERROR(__xludf.DUMMYFUNCTION("IFERROR(INDEX(SORT(FILTER(semrush_keywords!A:D, semrush_keywords!D:D=$C5), 2, 1), 1, 1), """")"),"child custody lawyer texas") -> child custody lawyer texas | E5: =IFERROR(__xludf.DUMMYFUNCTION("IFERROR(INDEX(SORT(FILTER(semrush_keywords!A:D, semrush_keywords!D:D=$C5), 2, 1), 1, 2), """")"),22.0) -> 22 | F5: =IFERROR(__xludf.DUMMYFUNCTION("IFERROR(INDEX(SORT(FILTER(semrush_keywords!A:D, semrush_keywords!D:D=$C5), 2, 1), 1, 3), """")"),110.0) -> 110 | G5: =IFERROR(__xludf.DUMMYFUNCTION("IFERROR(INDEX(SORT(FILTER(semrush_keywords!A:D, semrush_keywords!D:D=$C5), 2, 1), 2, 1), """")"),"texas parental rights lawyer") -> texas parental rights lawyer | H5: =IFERROR(__xludf.DUMMYFUNCTION("IFERROR(INDEX(SORT(FILTER(semrush_keywords!A:D, semrush_keywords!D:D=$C5), 2, 1), 2, 2), """")"),23.0) -> 23 | I5: =IFERROR(__xludf.DUMMYFUNCTION("IFERROR(INDEX(SORT(FILTER(semrush_keywords!A:D, semrush_keywords!D:D=$C5), 2, 1), 2, 3), """")"),70.0) -> 70 | J5: =IFERROR(__xludf.DUMMYFUNCTION("IFERROR(INDEX(SORT(FILTER(semrush_keywords!$A:$D, semrush_keywords!$D:$D=$C5), 2, 1), 3, 1), """")"),"texas child custody lawyers") -> texas child custody lawyers | K5: =IFERROR(__xludf.DUMMYFUNCTION("IFERROR(INDEX(SORT(FILTER(semrush_keywords!$A:$D, semrush_keywords!$D:$D=$C5), 2, 1), 3, 2), """")"),28.0) -> 28 | L5: =IFERROR(__xludf.DUMMYFUNCTION("IFERROR(INDEX(SORT(FILTER(semrush_keywords!$A:$D, semrush_keywords!$D:$D=$C5), 2, 1), 3, 3), """") "),110.0) -> 110
A6: 5 | B6: Child Support Hub | C6: https://sbrownlawyer.com/child-support/ | D6: =IFERROR(__xludf.DUMMYFUNCTION("IFERROR(INDEX(SORT(FILTER(semrush_keywords!A:D, semrush_keywords!D:D=$C6), 2, 1), 1, 1), """")"),"angleton child support attorney") -> angleton child support attorney | E6: =IFERROR(__xludf.DUMMYFUNCTION("IFERROR(INDEX(SORT(FILTER(semrush_keywords!A:D, semrush_keywords!D:D=$C6), 2, 1), 1, 2), """")"),29.0) -> 29 | F6: =IFERROR(__xludf.DUMMYFUNCTION("IFERROR(INDEX(SORT(FILTER(semrush_keywords!A:D, semrush_keywords!D:D=$C6), 2, 1), 1, 3), """")"),50.0) -> 50 | G6: =IFERROR(__xludf.DUMMYFUNCTION("IFERROR(INDEX(SORT(FILTER(semrush_keywords!A:D, semrush_keywords!D:D=$C6), 2, 1), 2, 1), """")"),"texas child support attorney") -> texas child support attorney | H6: =IFERROR(__xludf.DUMMYFUNCTION("IFERROR(INDEX(SORT(FILTER(semrush_keywords!A:D, semrush_keywords!D:D=$C6), 2, 1), 2, 2), """")"),49.0) -> 49 | I6: =IFERROR(__xludf.DUMMYFUNCTION("IFERROR(INDEX(SORT(FILTER(semrush_keywords!A:D, semrush_keywords!D:D=$C6), 2, 1), 2, 3), """")"),70.0) -> 70 | J6: =IFERROR(__xludf.DUMMYFUNCTION("IFERROR(INDEX(SORT(FILTER(semrush_keywords!$A:$D, semrush_keywords!$D:$D=$C6), 2, 1), 3, 1), """")"),"houston child support attorneys") -> houston child support attorneys | K6: =IFERROR(__xludf.DUMMYFUNCTION("IFERROR(INDEX(SORT(FILTER(semrush_keywords!$A:$D, semrush_keywords!$D:$D=$C6), 2, 1), 3, 2), """")"),68.0) -> 68 | L6: =IFERROR(__xludf.DUMMYFUNCTION("IFERROR(INDEX(SORT(FILTER(semrush_keywords!$A:$D, semrush_keywords!$D:$D=$C6), 2, 1), 3, 3), """") "),70.0) -> 70
A7: 6 | B7: Spousal Support / Alimony Hub | C7: https://sbrownlawyer.com/attorneys-working-to-achieve-your-alimony-goals/ | D7: =IFERROR(__xludf.DUMMYFUNCTION("IFERROR(INDEX(SORT(FILTER(semrush_keywords!A:D, semrush_keywords!D:D=$C7), 2, 1), 1, 1), """")"),"") | E7: =IFERROR(__xludf.DUMMYFUNCTION("IFERROR(INDEX(SORT(FILTER(semrush_keywords!A:D, semrush_keywords!D:D=$C7), 2, 1), 1, 2), """")"),"") | F7: =IFERROR(__xludf.DUMMYFUNCTION("IFERROR(INDEX(SORT(FILTER(semrush_keywords!A:D, semrush_keywords!D:D=$C7), 2, 1), 1, 3), """")"),"") | G7: =IFERROR(__xludf.DUMMYFUNCTION("IFERROR(INDEX(SORT(FILTER(semrush_keywords!A:D, semrush_keywords!D:D=$C7), 2, 1), 2, 1), """")"),"") | H7: =IFERROR(__xludf.DUMMYFUNCTION("IFERROR(INDEX(SORT(FILTER(semrush_keywords!A:D, semrush_keywords!D:D=$C7), 2, 1), 2, 2), """")"),"") | I7: =IFERROR(__xludf.DUMMYFUNCTION("IFERROR(INDEX(SORT(FILTER(semrush_keywords!A:D, semrush_keywords!D:D=$C7), 2, 1), 2, 3), """")"),"") | J7: =IFERROR(__xludf.DUMMYFUNCTION("IFERROR(INDEX(SORT(FILTER(semrush_keywords!$A:$D, semrush_keywords!$D:$D=$C7), 2, 1), 3, 1), """")"),"") | K7: =IFERROR(__xludf.DUMMYFUNCTION("IFERROR(INDEX(SORT(FILTER(semrush_keywords!$A:$D, semrush_keywords!$D:$D=$C7), 2, 1), 3, 2), """")"),"") | L7: =IFERROR(__xludf.DUMMYFUNCTION("IFERROR(INDEX(SORT(FILTER(semrush_keywords!$A:$D, semrush_keywords!$D:$D=$C7), 2, 1), 3, 3), """") "),"")
A8: 7 | B8: Property Division Hub | C8: https://sbrownlawyer.com/division-of-property/ | D8: =IFERROR(__xludf.DUMMYFUNCTION("IFERROR(INDEX(SORT(FILTER(semrush_keywords!A:D, semrush_keywords!D:D=$C8), 2, 1), 1, 1), """")"),"foreclosures in brazoria county texas") -> foreclosures in brazoria county texas | E8: =IFERROR(__xludf.DUMMYFUNCTION("IFERROR(INDEX(SORT(FILTER(semrush_keywords!A:D, semrush_keywords!D:D=$C8), 2, 1), 1, 2), """")"),79.0) -> 79 | F8: =IFERROR(__xludf.DUMMYFUNCTION("IFERROR(INDEX(SORT(FILTER(semrush_keywords!A:D, semrush_keywords!D:D=$C8), 2, 1), 1, 3), """")"),40.0) -> 40 | G8: =IFERROR(__xludf.DUMMYFUNCTION("IFERROR(INDEX(SORT(FILTER(semrush_keywords!A:D, semrush_keywords!D:D=$C8), 2, 1), 2, 1), """")"),"property division attorney the woodlands") -> property division attorney the woodlands | H8: =IFERROR(__xludf.DUMMYFUNCTION("IFERROR(INDEX(SORT(FILTER(semrush_keywords!A:D, semrush_keywords!D:D=$C8), 2, 1), 2, 2), """")"),79.0) -> 79 | I8: =IFERROR(__xludf.DUMMYFUNCTION("IFERROR(INDEX(SORT(FILTER(semrush_keywords!A:D, semrush_keywords!D:D=$C8), 2, 1), 2, 3), """")"),50.0) -> 50 | J8: =IFERROR(__xludf.DUMMYFUNCTION("IFERROR(INDEX(SORT(FILTER(semrush_keywords!$A:$D, semrush_keywords!$D:$D=$C8), 2, 1), 3, 1), """")"),"lawyers in brazoria county") -> lawyers in brazoria county | K8: =IFERROR(__xludf.DUMMYFUNCTION("IFERROR(INDEX(SORT(FILTER(semrush_keywords!$A:$D, semrush_keywords!$D:$D=$C8), 2, 1), 3, 2), """")"),81.0) -> 81 | L8: =IFERROR(__xludf.DUMMYFUNCTION("IFERROR(INDEX(SORT(FILTER(semrush_keywords!$A:$D, semrush_keywords!$D:$D=$C8), 2, 1), 3, 3), """") "),50.0) -> 50
A9: 8 | B9: Paternity Hub | C9: https://sbrownlawyer.com/paternity/ | D9: =IFERROR(__xludf.DUMMYFUNCTION("IFERROR(INDEX(SORT(FILTER(semrush_keywords!A:D, semrush_keywords!D:D=$C9), 2, 1), 1, 1), """")"),"") | E9: =IFERROR(__xludf.DUMMYFUNCTION("IFERROR(INDEX(SORT(FILTER(semrush_keywords!A:D, semrush_keywords!D:D=$C9), 2, 1), 1, 2), """")"),"") | F9: =IFERROR(__xludf.DUMMYFUNCTION("IFERROR(INDEX(SORT(FILTER(semrush_keywords!A:D, semrush_keywords!D:D=$C9), 2, 1), 1, 3), """")"),"") | G9: =IFERROR(__xludf.DUMMYFUNCTION("IFERROR(INDEX(SORT(FILTER(semrush_keywords!A:D, semrush_keywords!D:D=$C9), 2, 1), 2, 1), """")"),"") | H9: =IFERROR(__xludf.DUMMYFUNCTION("IFERROR(INDEX(SORT(FILTER(semrush_keywords!A:D, semrush_keywords!D:D=$C9), 2, 1), 2, 2), """")"),"") | I9: =IFERROR(__xludf.DUMMYFUNCTION("IFERROR(INDEX(SORT(FILTER(semrush_keywords!A:D, semrush_keywords!D:D=$C9), 2, 1), 2, 3), """")"),"") | J9: =IFERROR(__xludf.DUMMYFUNCTION("IFERROR(INDEX(SORT(FILTER(semrush_keywords!$A:$D, semrush_keywords!$D:$D=$C9), 2, 1), 3, 1), """")"),"") | K9: =IFERROR(__xludf.DUMMYFUNCTION("IFERROR(INDEX(SORT(FILTER(semrush_keywords!$A:$D, semrush_keywords!$D:$D=$C9), 2, 1), 3, 2), """")"),"") | L9: =IFERROR(__xludf.DUMMYFUNCTION("IFERROR(INDEX(SORT(FILTER(semrush_keywords!$A:$D, semrush_keywords!$D:$D=$C9), 2, 1), 3, 3), """") "),"")
A10: 10 | B10: Contested Divorce | C10: https://sbrownlawyer.com/complex-and-contested-divorce-attorneys/ | D10: =IFERROR(__xludf.DUMMYFUNCTION("IFERROR(INDEX(SORT(FILTER(semrush_keywords!A:D, semrush_keywords!D:D=$C10), 2, 1), 1, 1), """")"),"contested divorce attorneys in houston tx") -> contested divorce attorneys in houston tx | E10: =IFERROR(__xludf.DUMMYFUNCTION("IFERROR(INDEX(SORT(FILTER(semrush_keywords!A:D, semrush_keywords!D:D=$C10), 2, 1), 1, 2), """")"),40.0) -> 40 | F10: =IFERROR(__xludf.DUMMYFUNCTION("IFERROR(INDEX(SORT(FILTER(semrush_keywords!A:D, semrush_keywords!D:D=$C10), 2, 1), 1, 3), """")"),70.0) -> 70 | G10: =IFERROR(__xludf.DUMMYFUNCTION("IFERROR(INDEX(SORT(FILTER(semrush_keywords!A:D, semrush_keywords!D:D=$C10), 2, 1), 2, 1), """")"),"contested divorce lawyers in houston tx") -> contested divorce lawyers in houston tx | H10: =IFERROR(__xludf.DUMMYFUNCTION("IFERROR(INDEX(SORT(FILTER(semrush_keywords!A:D, semrush_keywords!D:D=$C10), 2, 1), 2, 2), """")"),42.0) -> 42 | I10: =IFERROR(__xludf.DUMMYFUNCTION("IFERROR(INDEX(SORT(FILTER(semrush_keywords!A:D, semrush_keywords!D:D=$C10), 2, 1), 2, 3), """")"),50.0) -> 50 | J10: =IFERROR(__xludf.DUMMYFUNCTION("IFERROR(INDEX(SORT(FILTER(semrush_keywords!$A:$D, semrush_keywords!$D:$D=$C10), 2, 1), 3, 1), """")"),"") | K10: =IFERROR(__xludf.DUMMYFUNCTION("IFERROR(INDEX(SORT(FILTER(semrush_keywords!$A:$D, semrush_keywords!$D:$D=$C10), 2, 1), 3, 2), """")"),"") | L10: =IFERROR(__xludf.DUMMYFUNCTION("IFERROR(INDEX(SORT(FILTER(semrush_keywords!$A:$D, semrush_keywords!$D:$D=$C10), 2, 1), 3, 3), """") "),"")
A11: 11 | B11: Uncontested Divorce | C11: https://sbrownlawyer.com/uncontested-divorce-lawyer-in-pearland/ | D11: =IFERROR(__xludf.DUMMYFUNCTION("IFERROR(INDEX(SORT(FILTER(semrush_keywords!A:D, semrush_keywords!D:D=$C11), 2, 1), 1, 1), """")"),"divorce lawyers in pearland tx") -> divorce lawyers in pearland tx | E11: =IFERROR(__xludf.DUMMYFUNCTION("IFERROR(INDEX(SORT(FILTER(semrush_keywords!A:D, semrush_keywords!D:D=$C11), 2, 1), 1, 2), """")"),37.0) -> 37 | F11: =IFERROR(__xludf.DUMMYFUNCTION("IFERROR(INDEX(SORT(FILTER(semrush_keywords!A:D, semrush_keywords!D:D=$C11), 2, 1), 1, 3), """")"),50.0) -> 50 | G11: =IFERROR(__xludf.DUMMYFUNCTION("IFERROR(INDEX(SORT(FILTER(semrush_keywords!A:D, semrush_keywords!D:D=$C11), 2, 1), 2, 1), """")"),"divorce lawyers pearland") -> divorce lawyers pearland | H11: =IFERROR(__xludf.DUMMYFUNCTION("IFERROR(INDEX(SORT(FILTER(semrush_keywords!A:D, semrush_keywords!D:D=$C11), 2, 1), 2, 2), """")"),40.0) -> 40 | I11: =IFERROR(__xludf.DUMMYFUNCTION("IFERROR(INDEX(SORT(FILTER(semrush_keywords!A:D, semrush_keywords!D:D=$C11), 2, 1), 2, 3), """")"),170.0) -> 170 | J11: =IFERROR(__xludf.DUMMYFUNCTION("IFERROR(INDEX(SORT(FILTER(semrush_keywords!$A:$D, semrush_keywords!$D:$D=$C11), 2, 1), 3, 1), """")"),"divorce law firm pearland") -> divorce law firm pearland | K11: =IFERROR(__xludf.DUMMYFUNCTION("IFERROR(INDEX(SORT(FILTER(semrush_keywords!$A:$D, semrush_keywords!$D:$D=$C11), 2, 1), 3, 2), """")"),47.0) -> 47 | L11: =IFERROR(__xludf.DUMMYFUNCTION("IFERROR(INDEX(SORT(FILTER(semrush_keywords!$A:$D, semrush_keywords!$D:$D=$C11), 2, 1), 3, 3), """") "),40.0) -> 40
A12: 12 | B12: Child Custody Modification | C12: https://sbrownlawyer.com/modification-of-custody/ | D12: =IFERROR(__xludf.DUMMYFUNCTION("IFERROR(INDEX(SORT(FILTER(semrush_keywords!A:D, semrush_keywords!D:D=$C12), 2, 1), 1, 1), """")"),"angleton child custody lawyer") -> angleton child custody lawyer | E12: =IFERROR(__xludf.DUMMYFUNCTION("IFERROR(INDEX(SORT(FILTER(semrush_keywords!A:D, semrush_keywords!D:D=$C12), 2, 1), 1, 2), """")"),27.0) -> 27 | F12: =IFERROR(__xludf.DUMMYFUNCTION("IFERROR(INDEX(SORT(FILTER(semrush_keywords!A:D, semrush_keywords!D:D=$C12), 2, 1), 1, 3), """")"),70.0) -> 70 | G12: =IFERROR(__xludf.DUMMYFUNCTION("IFERROR(INDEX(SORT(FILTER(semrush_keywords!A:D, semrush_keywords!D:D=$C12), 2, 1), 2, 1), """")"),"child custody attorney angleton") -> child custody attorney angleton | H12: =IFERROR(__xludf.DUMMYFUNCTION("IFERROR(INDEX(SORT(FILTER(semrush_keywords!A:D, semrush_keywords!D:D=$C12), 2, 1), 2, 2), """")"),48.0) -> 48 | I12: =IFERROR(__xludf.DUMMYFUNCTION("IFERROR(INDEX(SORT(FILTER(semrush_keywords!A:D, semrush_keywords!D:D=$C12), 2, 1), 2, 3), """")"),50.0) -> 50 | J12: =IFERROR(__xludf.DUMMYFUNCTION("IFERROR(INDEX(SORT(FILTER(semrush_keywords!$A:$D, semrush_keywords!$D:$D=$C12), 2, 1), 3, 1), """")"),"angleton child custody attorney") -> angleton child custody attorney | K12: =IFERROR(__xludf.DUMMYFUNCTION("IFERROR(INDEX(SORT(FILTER(semrush_keywords!$A:$D, semrush_keywords!$D:$D=$C12), 2, 1), 3, 2), """")"),53.0) -> 53 | L12: =IFERROR(__xludf.DUMMYFUNCTION("IFERROR(INDEX(SORT(FILTER(semrush_keywords!$A:$D, semrush_keywords!$D:$D=$C12), 2, 1), 3, 3), """") "),50.0) -> 50
A13: 13 | B13: Child Support Modification | C13: https://sbrownlawyer.com/child-support-modifications/ | D13: =IFERROR(__xludf.DUMMYFUNCTION("IFERROR(INDEX(SORT(FILTER(semrush_keywords!A:D, semrush_keywords!D:D=$C13), 2, 1), 1, 1), """")"),"") | E13: =IFERROR(__xludf.DUMMYFUNCTION("IFERROR(INDEX(SORT(FILTER(semrush_keywords!A:D, semrush_keywords!D:D=$C13), 2, 1), 1, 2), """")"),"") | F13: =IFERROR(__xludf.DUMMYFUNCTION("IFERROR(INDEX(SORT(FILTER(semrush_keywords!A:D, semrush_keywords!D:D=$C13), 2, 1), 1, 3), """")"),"") | G13: =IFERROR(__xludf.DUMMYFUNCTION("IFERROR(INDEX(SORT(FILTER(semrush_keywords!A:D, semrush_keywords!D:D=$C13), 2, 1), 2, 1), """")"),"") | H13: =IFERROR(__xludf.DUMMYFUNCTION("IFERROR(INDEX(SORT(FILTER(semrush_keywords!A:D, semrush_keywords!D:D=$C13), 2, 1), 2, 2), """")"),"") | I13: =IFERROR(__xludf.DUMMYFUNCTION("IFERROR(INDEX(SORT(FILTER(semrush_keywords!A:D, semrush_keywords!D:D=$C13), 2, 1), 2, 3), """")"),"") | J13: =IFERROR(__xludf.DUMMYFUNCTION("IFERROR(INDEX(SORT(FILTER(semrush_keywords!$A:$D, semrush_keywords!$D:$D=$C13), 2, 1), 3, 1), """")"),"") | K13: =IFERROR(__xludf.DUMMYFUNCTION("IFERROR(INDEX(SORT(FILTER(semrush_keywords!$A:$D, semrush_keywords!$D:$D=$C13), 2, 1), 3, 2), """")"),"") | L13: =IFERROR(__xludf.DUMMYFUNCTION("IFERROR(INDEX(SORT(FILTER(semrush_keywords!$A:$D, semrush_keywords!$D:$D=$C13), 2, 1), 3, 3), """") "),"")
A14: 14 | B14: Child Support Enforcement | C14: https://sbrownlawyer.com/enforcing-child-support-orders/ | D14: =IFERROR(__xludf.DUMMYFUNCTION("IFERROR(INDEX(SORT(FILTER(semrush_keywords!A:D, semrush_keywords!D:D=$C14), 2, 1), 1, 1), """")"),"") | E14: =IFERROR(__xludf.DUMMYFUNCTION("IFERROR(INDEX(SORT(FILTER(semrush_keywords!A:D, semrush_keywords!D:D=$C14), 2, 1), 1, 2), """")"),"") | F14: =IFERROR(__xludf.DUMMYFUNCTION("IFERROR(INDEX(SORT(FILTER(semrush_keywords!A:D, semrush_keywords!D:D=$C14), 2, 1), 1, 3), """")"),"") | G14: =IFERROR(__xludf.DUMMYFUNCTION("IFERROR(INDEX(SORT(FILTER(semrush_keywords!A:D, semrush_keywords!D:D=$C14), 2, 1), 2, 1), """")"),"") | H14: =IFERROR(__xludf.DUMMYFUNCTION("IFERROR(INDEX(SORT(FILTER(semrush_keywords!A:D, semrush_keywords!D:D=$C14), 2, 1), 2, 2), """")"),"") | I14: =IFERROR(__xludf.DUMMYFUNCTION("IFERROR(INDEX(SORT(FILTER(semrush_keywords!A:D, semrush_keywords!D:D=$C14), 2, 1), 2, 3), """")"),"") | J14: =IFERROR(__xludf.DUMMYFUNCTION("IFERROR(INDEX(SORT(FILTER(semrush_keywords!$A:$D, semrush_keywords!$D:$D=$C14), 2, 1), 3, 1), """")"),"") | K14: =IFERROR(__xludf.DUMMYFUNCTION("IFERROR(INDEX(SORT(FILTER(semrush_keywords!$A:$D, semrush_keywords!$D:$D=$C14), 2, 1), 3, 2), """")"),"") | L14: =IFERROR(__xludf.DUMMYFUNCTION("IFERROR(INDEX(SORT(FILTER(semrush_keywords!$A:$D, semrush_keywords!$D:$D=$C14), 2, 1), 3, 3), """") "),"")
A15: 15 | B15: Parenting Plans | C15: https://sbrownlawyer.com/creative-custody-agreements/ | D15: =IFERROR(__xludf.DUMMYFUNCTION("IFERROR(INDEX(SORT(FILTER(semrush_keywords!A:D, semrush_keywords!D:D=$C15), 2, 1), 1, 1), """")"),"") | E15: =IFERROR(__xludf.DUMMYFUNCTION("IFERROR(INDEX(SORT(FILTER(semrush_keywords!A:D, semrush_keywords!D:D=$C15), 2, 1), 1, 2), """")"),"") | F15: =IFERROR(__xludf.DUMMYFUNCTION("IFERROR(INDEX(SORT(FILTER(semrush_keywords!A:D, semrush_keywords!D:D=$C15), 2, 1), 1, 3), """")"),"") | G15: =IFERROR(__xludf.DUMMYFUNCTION("IFERROR(INDEX(SORT(FILTER(semrush_keywords!A:D, semrush_keywords!D:D=$C15), 2, 1), 2, 1), """")"),"") | H15: =IFERROR(__xludf.DUMMYFUNCTION("IFERROR(INDEX(SORT(FILTER(semrush_keywords!A:D, semrush_keywords!D:D=$C15), 2, 1), 2, 2), """")"),"") | I15: =IFERROR(__xludf.DUMMYFUNCTION("IFERROR(INDEX(SORT(FILTER(semrush_keywords!A:D, semrush_keywords!D:D=$C15), 2, 1), 2, 3), """")"),"") | J15: =IFERROR(__xludf.DUMMYFUNCTION("IFERROR(INDEX(SORT(FILTER(semrush_keywords!$A:$D, semrush_keywords!$D:$D=$C15), 2, 1), 3, 1), """")"),"") | K15: =IFERROR(__xludf.DUMMYFUNCTION("IFERROR(INDEX(SORT(FILTER(semrush_keywords!$A:$D, semrush_keywords!$D:$D=$C15), 2, 1), 3, 2), """")"),"") | L15: =IFERROR(__xludf.DUMMYFUNCTION("IFERROR(INDEX(SORT(FILTER(semrush_keywords!$A:$D, semrush_keywords!$D:$D=$C15), 2, 1), 3, 3), """") "),"")
A16: 17 | B16: Equitable Distribution | C16: https://sbrownlawyer.com/how-is-community-property-divided/ | D16: =IFERROR(__xludf.DUMMYFUNCTION("IFERROR(INDEX(SORT(FILTER(semrush_keywords!A:D, semrush_keywords!D:D=$C16), 2, 1), 1, 1), """")"),"") | E16: =IFERROR(__xludf.DUMMYFUNCTION("IFERROR(INDEX(SORT(FILTER(semrush_keywords!A:D, semrush_keywords!D:D=$C16), 2, 1), 1, 2), """")"),"") | F16: =IFERROR(__xludf.DUMMYFUNCTION("IFERROR(INDEX(SORT(FILTER(semrush_keywords!A:D, semrush_keywords!D:D=$C16), 2, 1), 1, 3), """")"),"") | G16: =IFERROR(__xludf.DUMMYFUNCTION("IFERROR(INDEX(SORT(FILTER(semrush_keywords!A:D, semrush_keywords!D:D=$C16), 2, 1), 2, 1), """")"),"") | H16: =IFERROR(__xludf.DUMMYFUNCTION("IFERROR(INDEX(SORT(FILTER(semrush_keywords!A:D, semrush_keywords!D:D=$C16), 2, 1), 2, 2), """")"),"") | I16: =IFERROR(__xludf.DUMMYFUNCTION("IFERROR(INDEX(SORT(FILTER(semrush_keywords!A:D, semrush_keywords!D:D=$C16), 2, 1), 2, 3), """")"),"") | J16: =IFERROR(__xludf.DUMMYFUNCTION("IFERROR(INDEX(SORT(FILTER(semrush_keywords!$A:$D, semrush_keywords!$D:$D=$C16), 2, 1), 3, 1), """")"),"") | K16: =IFERROR(__xludf.DUMMYFUNCTION("IFERROR(INDEX(SORT(FILTER(semrush_keywords!$A:$D, semrush_keywords!$D:$D=$C16), 2, 1), 3, 2), """")"),"") | L16: =IFERROR(__xludf.DUMMYFUNCTION("IFERROR(INDEX(SORT(FILTER(semrush_keywords!$A:$D, semrush_keywords!$D:$D=$C16), 2, 1), 3, 3), """") "),"")
A17: 18 | B17: Establishing Paternity | C17: https://sbrownlawyer.com/paternity-attorney/ | D17: =IFERROR(__xludf.DUMMYFUNCTION("IFERROR(INDEX(SORT(FILTER(semrush_keywords!A:D, semrush_keywords!D:D=$C17), 2, 1), 1, 1), """")"),"paternity law firm the woodlands") -> paternity law firm the woodlands | E17: =IFERROR(__xludf.DUMMYFUNCTION("IFERROR(INDEX(SORT(FILTER(semrush_keywords!A:D, semrush_keywords!D:D=$C17), 2, 1), 1, 2), """")"),78.0) -> 78 | F17: =IFERROR(__xludf.DUMMYFUNCTION("IFERROR(INDEX(SORT(FILTER(semrush_keywords!A:D, semrush_keywords!D:D=$C17), 2, 1), 1, 3), """")"),50.0) -> 50 | G17: =IFERROR(__xludf.DUMMYFUNCTION("IFERROR(INDEX(SORT(FILTER(semrush_keywords!A:D, semrush_keywords!D:D=$C17), 2, 1), 2, 1), """")"),"paternity issues attorneys the woodlands") -> paternity issues attorneys the woodlands | H17: =IFERROR(__xludf.DUMMYFUNCTION("IFERROR(INDEX(SORT(FILTER(semrush_keywords!A:D, semrush_keywords!D:D=$C17), 2, 1), 2, 2), """")"),80.0) -> 80 | I17: =IFERROR(__xludf.DUMMYFUNCTION("IFERROR(INDEX(SORT(FILTER(semrush_keywords!A:D, semrush_keywords!D:D=$C17), 2, 1), 2, 3), """")"),50.0) -> 50 | J17: =IFERROR(__xludf.DUMMYFUNCTION("IFERROR(INDEX(SORT(FILTER(semrush_keywords!$A:$D, semrush_keywords!$D:$D=$C17), 2, 1), 3, 1), """")"),"pearland family lawyers") -> pearland family lawyers | K17: =IFERROR(__xludf.DUMMYFUNCTION("IFERROR(INDEX(SORT(FILTER(semrush_keywords!$A:$D, semrush_keywords!$D:$D=$C17), 2, 1), 3, 2), """")"),84.0) -> 84 | L17: =IFERROR(__xludf.DUMMYFUNCTION("IFERROR(INDEX(SORT(FILTER(semrush_keywords!$A:$D, semrush_keywords!$D:$D=$C17), 2, 1), 3, 3), """") "),70.0) -> 70
A18: 19 | B18: Emergency Custody Orders | C18: https://sbrownlawyer.com/child-custody/emergency/ | D18: =IFERROR(__xludf.DUMMYFUNCTION("IFERROR(INDEX(SORT(FILTER(semrush_keywords!A:D, semrush_keywords!D:D=$C18), 2, 1), 1, 1), """")"),"emergency custody attorney") -> emergency custody attorney | E18: =IFERROR(__xludf.DUMMYFUNCTION("IFERROR(INDEX(SORT(FILTER(semrush_keywords!A:D, semrush_keywords!D:D=$C18), 2, 1), 1, 2), """")"),33.0) -> 33 | F18: =IFERROR(__xludf.DUMMYFUNCTION("IFERROR(INDEX(SORT(FILTER(semrush_keywords!A:D, semrush_keywords!D:D=$C18), 2, 1), 1, 3), """")"),70.0) -> 70 | G18: =IFERROR(__xludf.DUMMYFUNCTION("IFERROR(INDEX(SORT(FILTER(semrush_keywords!A:D, semrush_keywords!D:D=$C18), 2, 1), 2, 1), """")"),"emergency custody lawyer") -> emergency custody lawyer | H18: =IFERROR(__xludf.DUMMYFUNCTION("IFERROR(INDEX(SORT(FILTER(semrush_keywords!A:D, semrush_keywords!D:D=$C18), 2, 1), 2, 2), """")"),43.0) -> 43 | I18: =IFERROR(__xludf.DUMMYFUNCTION("IFERROR(INDEX(SORT(FILTER(semrush_keywords!A:D, semrush_keywords!D:D=$C18), 2, 1), 2, 3), """")"),210.0) -> 210 | J18: =IFERROR(__xludf.DUMMYFUNCTION("IFERROR(INDEX(SORT(FILTER(semrush_keywords!$A:$D, semrush_keywords!$D:$D=$C18), 2, 1), 3, 1), """")"),"") | K18: =IFERROR(__xludf.DUMMYFUNCTION("IFERROR(INDEX(SORT(FILTER(semrush_keywords!$A:$D, semrush_keywords!$D:$D=$C18), 2, 1), 3, 2), """")"),"") | L18: =IFERROR(__xludf.DUMMYFUNCTION("IFERROR(INDEX(SORT(FILTER(semrush_keywords!$A:$D, semrush_keywords!$D:$D=$C18), 2, 1), 3, 3), """") "),"")
A19: 20 | B19: Marital vs Separate Property | C19: https://sbrownlawyer.com/assets-and-liability/ | D19: =IFERROR(__xludf.DUMMYFUNCTION("IFERROR(INDEX(SORT(FILTER(semrush_keywords!A:D, semrush_keywords!D:D=$C19), 2, 1), 1, 1), """")"),"") | E19: =IFERROR(__xludf.DUMMYFUNCTION("IFERROR(INDEX(SORT(FILTER(semrush_keywords!A:D, semrush_keywords!D:D=$C19), 2, 1), 1, 2), """")"),"") | F19: =IFERROR(__xludf.DUMMYFUNCTION("IFERROR(INDEX(SORT(FILTER(semrush_keywords!A:D, semrush_keywords!D:D=$C19), 2, 1), 1, 3), """")"),"") | G19: =IFERROR(__xludf.DUMMYFUNCTION("IFERROR(INDEX(SORT(FILTER(semrush_keywords!A:D, semrush_keywords!D:D=$C19), 2, 1), 2, 1), """")"),"") | H19: =IFERROR(__xludf.DUMMYFUNCTION("IFERROR(INDEX(SORT(FILTER(semrush_keywords!A:D, semrush_keywords!D:D=$C19), 2, 1), 2, 2), """")"),"") | I19: =IFERROR(__xludf.DUMMYFUNCTION("IFERROR(INDEX(SORT(FILTER(semrush_keywords!A:D, semrush_keywords!D:D=$C19), 2, 1), 2, 3), """")"),"") | J19: =IFERROR(__xludf.DUMMYFUNCTION("IFERROR(INDEX(SORT(FILTER(semrush_keywords!$A:$D, semrush_keywords!$D:$D=$C19), 2, 1), 3, 1), """")"),"") | K19: =IFERROR(__xludf.DUMMYFUNCTION("IFERROR(INDEX(SORT(FILTER(semrush_keywords!$A:$D, semrush_keywords!$D:$D=$C19), 2, 1), 3, 2), """")"),"") | L19: =IFERROR(__xludf.DUMMYFUNCTION("IFERROR(INDEX(SORT(FILTER(semrush_keywords!$A:$D, semrush_keywords!$D:$D=$C19), 2, 1), 3, 3), """") "),"")
A20: 21 | B20: Long-Term Spousal Support | C20: https://sbrownlawyer.com/the-unique-aspects-of-alimony-spousal-maintenance-in-texas/ | D20: =IFERROR(__xludf.DUMMYFUNCTION("IFERROR(INDEX(SORT(FILTER(semrush_keywords!A:D, semrush_keywords!D:D=$C20), 2, 1), 1, 1), """")"),"") | E20: =IFERROR(__xludf.DUMMYFUNCTION("IFERROR(INDEX(SORT(FILTER(semrush_keywords!A:D, semrush_keywords!D:D=$C20), 2, 1), 1, 2), """")"),"") | F20: =IFERROR(__xludf.DUMMYFUNCTION("IFERROR(INDEX(SORT(FILTER(semrush_keywords!A:D, semrush_keywords!D:D=$C20), 2, 1), 1, 3), """")"),"") | G20: =IFERROR(__xludf.DUMMYFUNCTION("IFERROR(INDEX(SORT(FILTER(semrush_keywords!A:D, semrush_keywords!D:D=$C20), 2, 1), 2, 1), """")"),"") | H20: =IFERROR(__xludf.DUMMYFUNCTION("IFERROR(INDEX(SORT(FILTER(semrush_keywords!A:D, semrush_keywords!D:D=$C20), 2, 1), 2, 2), """")"),"") | I20: =IFERROR(__xludf.DUMMYFUNCTION("IFERROR(INDEX(SORT(FILTER(semrush_keywords!A:D, semrush_keywords!D:D=$C20), 2, 1), 2, 3), """")"),"") | J20: =IFERROR(__xludf.DUMMYFUNCTION("IFERROR(INDEX(SORT(FILTER(semrush_keywords!$A:$D, semrush_keywords!$D:$D=$C20), 2, 1), 3, 1), """")"),"") | K20: =IFERROR(__xludf.DUMMYFUNCTION("IFERROR(INDEX(SORT(FILTER(semrush_keywords!$A:$D, semrush_keywords!$D:$D=$C20), 2, 1), 3, 2), """")"),"") | L20: =IFERROR(__xludf.DUMMYFUNCTION("IFERROR(INDEX(SORT(FILTER(semrush_keywords!$A:$D, semrush_keywords!$D:$D=$C20), 2, 1), 3, 3), """") "),"")
A21: 30 | B21: Relocation / Move-Away Custody Disputes | C21: https://sbrownlawyer.com/parental-relocation/ | D21: =IFERROR(__xludf.DUMMYFUNCTION("IFERROR(INDEX(SORT(FILTER(semrush_keywords!A:D, semrush_keywords!D:D=$C21), 2, 1), 1, 1), """")"),"texas child relocation attorney") -> texas child relocation attorney | E21: =IFERROR(__xludf.DUMMYFUNCTION("IFERROR(INDEX(SORT(FILTER(semrush_keywords!A:D, semrush_keywords!D:D=$C21), 2, 1), 1, 2), """")"),35.0) -> 35 | F21: =IFERROR(__xludf.DUMMYFUNCTION("IFERROR(INDEX(SORT(FILTER(semrush_keywords!A:D, semrush_keywords!D:D=$C21), 2, 1), 1, 3), """")"),50.0) -> 50 | G21: =IFERROR(__xludf.DUMMYFUNCTION("IFERROR(INDEX(SORT(FILTER(semrush_keywords!A:D, semrush_keywords!D:D=$C21), 2, 1), 2, 1), """")"),"texas child relocation attorneys") -> texas child relocation attorneys | H21: =IFERROR(__xludf.DUMMYFUNCTION("IFERROR(INDEX(SORT(FILTER(semrush_keywords!A:D, semrush_keywords!D:D=$C21), 2, 1), 2, 2), """")"),39.0) -> 39 | I21: =IFERROR(__xludf.DUMMYFUNCTION("IFERROR(INDEX(SORT(FILTER(semrush_keywords!A:D, semrush_keywords!D:D=$C21), 2, 1), 2, 3), """")"),50.0) -> 50 | J21: =IFERROR(__xludf.DUMMYFUNCTION("IFERROR(INDEX(SORT(FILTER(semrush_keywords!$A:$D, semrush_keywords!$D:$D=$C21), 2, 1), 3, 1), """")"),"texas child relocation lawyers") -> texas child relocation lawyers | K21: =IFERROR(__xludf.DUMMYFUNCTION("IFERROR(INDEX(SORT(FILTER(semrush_keywords!$A:$D, semrush_keywords!$D:$D=$C21), 2, 1), 3, 2), """")"),49.0) -> 49 | L21: =IFERROR(__xludf.DUMMYFUNCTION("IFERROR(INDEX(SORT(FILTER(semrush_keywords!$A:$D, semrush_keywords!$D:$D=$C21), 2, 1), 3, 3), """") "),50.0) -> 50
A22: 31 | B22: Divorce Involving Business Ownership | C22: https://sbrownlawyer.com/business-owner-divorce/ | D22: =IFERROR(__xludf.DUMMYFUNCTION("IFERROR(INDEX(SORT(FILTER(semrush_keywords!A:D, semrush_keywords!D:D=$C22), 2, 1), 1, 1), """")"),"business owner divorce lawyer") -> business owner divorce lawyer | E22: =IFERROR(__xludf.DUMMYFUNCTION("IFERROR(INDEX(SORT(FILTER(semrush_keywords!A:D, semrush_keywords!D:D=$C22), 2, 1), 1, 2), """")"),78.0) -> 78 | F22: =IFERROR(__xludf.DUMMYFUNCTION("IFERROR(INDEX(SORT(FILTER(semrush_keywords!A:D, semrush_keywords!D:D=$C22), 2, 1), 1, 3), """")"),50.0) -> 50 | G22: =IFERROR(__xludf.DUMMYFUNCTION("IFERROR(INDEX(SORT(FILTER(semrush_keywords!A:D, semrush_keywords!D:D=$C22), 2, 1), 2, 1), """")"),"texas business valuation lawyers") -> texas business valuation lawyers | H22: =IFERROR(__xludf.DUMMYFUNCTION("IFERROR(INDEX(SORT(FILTER(semrush_keywords!A:D, semrush_keywords!D:D=$C22), 2, 1), 2, 2), """")"),79.0) -> 79 | I22: =IFERROR(__xludf.DUMMYFUNCTION("IFERROR(INDEX(SORT(FILTER(semrush_keywords!A:D, semrush_keywords!D:D=$C22), 2, 1), 2, 3), """")"),50.0) -> 50 | J22: =IFERROR(__xludf.DUMMYFUNCTION("IFERROR(INDEX(SORT(FILTER(semrush_keywords!$A:$D, semrush_keywords!$D:$D=$C22), 2, 1), 3, 1), """")"),"") | K22: =IFERROR(__xludf.DUMMYFUNCTION("IFERROR(INDEX(SORT(FILTER(semrush_keywords!$A:$D, semrush_keywords!$D:$D=$C22), 2, 1), 3, 2), """")"),"") | L22: =IFERROR(__xludf.DUMMYFUNCTION("IFERROR(INDEX(SORT(FILTER(semrush_keywords!$A:$D, semrush_keywords!$D:$D=$C22), 2, 1), 3, 3), """") "),"")
A23: 32 | B23: High-Conflict Custody | C23: https://sbrownlawyer.com/contested-custody/ | D23: =IFERROR(__xludf.DUMMYFUNCTION("IFERROR(INDEX(SORT(FILTER(semrush_keywords!A:D, semrush_keywords!D:D=$C23), 2, 1), 1, 1), """")"),"") | E23: =IFERROR(__xludf.DUMMYFUNCTION("IFERROR(INDEX(SORT(FILTER(semrush_keywords!A:D, semrush_keywords!D:D=$C23), 2, 1), 1, 2), """")"),"") | F23: =IFERROR(__xludf.DUMMYFUNCTION("IFERROR(INDEX(SORT(FILTER(semrush_keywords!A:D, semrush_keywords!D:D=$C23), 2, 1), 1, 3), """")"),"") | G23: =IFERROR(__xludf.DUMMYFUNCTION("IFERROR(INDEX(SORT(FILTER(semrush_keywords!A:D, semrush_keywords!D:D=$C23), 2, 1), 2, 1), """")"),"") | H23: =IFERROR(__xludf.DUMMYFUNCTION("IFERROR(INDEX(SORT(FILTER(semrush_keywords!A:D, semrush_keywords!D:D=$C23), 2, 1), 2, 2), """")"),"") | I23: =IFERROR(__xludf.DUMMYFUNCTION("IFERROR(INDEX(SORT(FILTER(semrush_keywords!A:D, semrush_keywords!D:D=$C23), 2, 1), 2, 3), """")"),"") | J23: =IFERROR(__xludf.DUMMYFUNCTION("IFERROR(INDEX(SORT(FILTER(semrush_keywords!$A:$D, semrush_keywords!$D:$D=$C23), 2, 1), 3, 1), """")"),"") | K23: =IFERROR(__xludf.DUMMYFUNCTION("IFERROR(INDEX(SORT(FILTER(semrush_keywords!$A:$D, semrush_keywords!$D:$D=$C23), 2, 1), 3, 2), """")"),"") | L23: =IFERROR(__xludf.DUMMYFUNCTION("IFERROR(INDEX(SORT(FILTER(semrush_keywords!$A:$D, semrush_keywords!$D:$D=$C23), 2, 1), 3, 3), """") "),"")
A24: 35 | B24: Long-Term Marriage Divorce | C24: https://sbrownlawyer.com/gray-divorce/ | D24: =IFERROR(__xludf.DUMMYFUNCTION("IFERROR(INDEX(SORT(FILTER(semrush_keywords!A:D, semrush_keywords!D:D=$C24), 2, 1), 1, 1), """")"),"gray divorce lawyer") -> gray divorce lawyer | E24: =IFERROR(__xludf.DUMMYFUNCTION("IFERROR(INDEX(SORT(FILTER(semrush_keywords!A:D, semrush_keywords!D:D=$C24), 2, 1), 1, 2), """")"),68.0) -> 68 | F24: =IFERROR(__xludf.DUMMYFUNCTION("IFERROR(INDEX(SORT(FILTER(semrush_keywords!A:D, semrush_keywords!D:D=$C24), 2, 1), 1, 3), """")"),110.0) -> 110 | G24: =IFERROR(__xludf.DUMMYFUNCTION("IFERROR(INDEX(SORT(FILTER(semrush_keywords!A:D, semrush_keywords!D:D=$C24), 2, 1), 2, 1), """")"),"") | H24: =IFERROR(__xludf.DUMMYFUNCTION("IFERROR(INDEX(SORT(FILTER(semrush_keywords!A:D, semrush_keywords!D:D=$C24), 2, 1), 2, 2), """")"),"") | I24: =IFERROR(__xludf.DUMMYFUNCTION("IFERROR(INDEX(SORT(FILTER(semrush_keywords!A:D, semrush_keywords!D:D=$C24), 2, 1), 2, 3), """")"),"") | J24: =IFERROR(__xludf.DUMMYFUNCTION("IFERROR(INDEX(SORT(FILTER(semrush_keywords!$A:$D, semrush_keywords!$D:$D=$C24), 2, 1), 3, 1), """")"),"") | K24: =IFERROR(__xludf.DUMMYFUNCTION("IFERROR(INDEX(SORT(FILTER(semrush_keywords!$A:$D, semrush_keywords!$D:$D=$C24), 2, 1), 3, 2), """")"),"") | L24: =IFERROR(__xludf.DUMMYFUNCTION("IFERROR(INDEX(SORT(FILTER(semrush_keywords!$A:$D, semrush_keywords!$D:$D=$C24), 2, 1), 3, 3), """") "),"")
A25: 36 | B25: Business Valuation and Division | C25: https://sbrownlawyer.com/business-and-professional-practices-in-divorce/ | D25: =IFERROR(__xludf.DUMMYFUNCTION("IFERROR(INDEX(SORT(FILTER(semrush_keywords!A:D, semrush_keywords!D:D=$C25), 2, 1), 1, 1), """")"),"") | E25: =IFERROR(__xludf.DUMMYFUNCTION("IFERROR(INDEX(SORT(FILTER(semrush_keywords!A:D, semrush_keywords!D:D=$C25), 2, 1), 1, 2), """")"),"") | F25: =IFERROR(__xludf.DUMMYFUNCTION("IFERROR(INDEX(SORT(FILTER(semrush_keywords!A:D, semrush_keywords!D:D=$C25), 2, 1), 1, 3), """")"),"") | G25: =IFERROR(__xludf.DUMMYFUNCTION("IFERROR(INDEX(SORT(FILTER(semrush_keywords!A:D, semrush_keywords!D:D=$C25), 2, 1), 2, 1), """")"),"") | H25: =IFERROR(__xludf.DUMMYFUNCTION("IFERROR(INDEX(SORT(FILTER(semrush_keywords!A:D, semrush_keywords!D:D=$C25), 2, 1), 2, 2), """")"),"") | I25: =IFERROR(__xludf.DUMMYFUNCTION("IFERROR(INDEX(SORT(FILTER(semrush_keywords!A:D, semrush_keywords!D:D=$C25), 2, 1), 2, 3), """")"),"") | J25: =IFERROR(__xludf.DUMMYFUNCTION("IFERROR(INDEX(SORT(FILTER(semrush_keywords!$A:$D, semrush_keywords!$D:$D=$C25), 2, 1), 3, 1), """")"),"") | K25: =IFERROR(__xludf.DUMMYFUNCTION("IFERROR(INDEX(SORT(FILTER(semrush_keywords!$A:$D, semrush_keywords!$D:$D=$C25), 2, 1), 3, 2), """")"),"") | L25: =IFERROR(__xludf.DUMMYFUNCTION("IFERROR(INDEX(SORT(FILTER(semrush_keywords!$A:$D, semrush_keywords!$D:$D=$C25), 2, 1), 3, 3), """") "),"")
A26: 38 | B26: Parenting Time Disputes | C26: https://sbrownlawyer.com/family-law/visitation/ | D26: =IFERROR(__xludf.DUMMYFUNCTION("IFERROR(INDEX(SORT(FILTER(semrush_keywords!A:D, semrush_keywords!D:D=$C26), 2, 1), 1, 1), """")"),"angleton grandparents rights attorney") -> angleton grandparents rights attorney | E26: =IFERROR(__xludf.DUMMYFUNCTION("IFERROR(INDEX(SORT(FILTER(semrush_keywords!A:D, semrush_keywords!D:D=$C26), 2, 1), 1, 2), """")"),24.0) -> 24 | F26: =IFERROR(__xludf.DUMMYFUNCTION("IFERROR(INDEX(SORT(FILTER(semrush_keywords!A:D, semrush_keywords!D:D=$C26), 2, 1), 1, 3), """")"),50.0) -> 50 | G26: =IFERROR(__xludf.DUMMYFUNCTION("IFERROR(INDEX(SORT(FILTER(semrush_keywords!A:D, semrush_keywords!D:D=$C26), 2, 1), 2, 1), """")"),"angleton grandparents rights lawyer") -> angleton grandparents rights lawyer | H26: =IFERROR(__xludf.DUMMYFUNCTION("IFERROR(INDEX(SORT(FILTER(semrush_keywords!A:D, semrush_keywords!D:D=$C26), 2, 1), 2, 2), """")"),24.0) -> 24 | I26: =IFERROR(__xludf.DUMMYFUNCTION("IFERROR(INDEX(SORT(FILTER(semrush_keywords!A:D, semrush_keywords!D:D=$C26), 2, 1), 2, 3), """")"),50.0) -> 50 | J26: =IFERROR(__xludf.DUMMYFUNCTION("IFERROR(INDEX(SORT(FILTER(semrush_keywords!$A:$D, semrush_keywords!$D:$D=$C26), 2, 1), 3, 1), """")"),"child custody attorney angleton") -> child custody attorney angleton | K26: =IFERROR(__xludf.DUMMYFUNCTION("IFERROR(INDEX(SORT(FILTER(semrush_keywords!$A:$D, semrush_keywords!$D:$D=$C26), 2, 1), 3, 2), """")"),29.0) -> 29 | L26: =IFERROR(__xludf.DUMMYFUNCTION("IFERROR(INDEX(SORT(FILTER(semrush_keywords!$A:$D, semrush_keywords!$D:$D=$C26), 2, 1), 3, 3), """") "),50.0) -> 50
A27: 39 | B27: High-Income Spousal Support Disputes | C27: https://sbrownlawyer.com/high-net-worth-divorce/ | D27: =IFERROR(__xludf.DUMMYFUNCTION("IFERROR(INDEX(SORT(FILTER(semrush_keywords!A:D, semrush_keywords!D:D=$C27), 2, 1), 1, 1), """")"),"") | E27: =IFERROR(__xludf.DUMMYFUNCTION("IFERROR(INDEX(SORT(FILTER(semrush_keywords!A:D, semrush_keywords!D:D=$C27), 2, 1), 1, 2), """")"),"") | F27: =IFERROR(__xludf.DUMMYFUNCTION("IFERROR(INDEX(SORT(FILTER(semrush_keywords!A:D, semrush_keywords!D:D=$C27), 2, 1), 1, 3), """")"),"") | G27: =IFERROR(__xludf.DUMMYFUNCTION("IFERROR(INDEX(SORT(FILTER(semrush_keywords!A:D, semrush_keywords!D:D=$C27), 2, 1), 2, 1), """")"),"") | H27: =IFERROR(__xludf.DUMMYFUNCTION("IFERROR(INDEX(SORT(FILTER(semrush_keywords!A:D, semrush_keywords!D:D=$C27), 2, 1), 2, 2), """")"),"") | I27: =IFERROR(__xludf.DUMMYFUNCTION("IFERROR(INDEX(SORT(FILTER(semrush_keywords!A:D, semrush_keywords!D:D=$C27), 2, 1), 2, 3), """")"),"") | J27: =IFERROR(__xludf.DUMMYFUNCTION("IFERROR(INDEX(SORT(FILTER(semrush_keywords!$A:$D, semrush_keywords!$D:$D=$C27), 2, 1), 3, 1), """")"),"") | K27: =IFERROR(__xludf.DUMMYFUNCTION("IFERROR(INDEX(SORT(FILTER(semrush_keywords!$A:$D, semrush_keywords!$D:$D=$C27), 2, 1), 3, 2), """")"),"") | L27: =IFERROR(__xludf.DUMMYFUNCTION("IFERROR(INDEX(SORT(FILTER(semrush_keywords!$A:$D, semrush_keywords!$D:$D=$C27), 2, 1), 3, 3), """") "),"")
A28: 42 | B28: Hidden Assets and Financial Misconduct | C28: https://sbrownlawyer.com/hidden-assets/ | D28: =IFERROR(__xludf.DUMMYFUNCTION("IFERROR(INDEX(SORT(FILTER(semrush_keywords!A:D, semrush_keywords!D:D=$C28), 2, 1), 1, 1), """")"),"") | E28: =IFERROR(__xludf.DUMMYFUNCTION("IFERROR(INDEX(SORT(FILTER(semrush_keywords!A:D, semrush_keywords!D:D=$C28), 2, 1), 1, 2), """")"),"") | F28: =IFERROR(__xludf.DUMMYFUNCTION("IFERROR(INDEX(SORT(FILTER(semrush_keywords!A:D, semrush_keywords!D:D=$C28), 2, 1), 1, 3), """")"),"") | G28: =IFERROR(__xludf.DUMMYFUNCTION("IFERROR(INDEX(SORT(FILTER(semrush_keywords!A:D, semrush_keywords!D:D=$C28), 2, 1), 2, 1), """")"),"") | H28: =IFERROR(__xludf.DUMMYFUNCTION("IFERROR(INDEX(SORT(FILTER(semrush_keywords!A:D, semrush_keywords!D:D=$C28), 2, 1), 2, 2), """")"),"") | I28: =IFERROR(__xludf.DUMMYFUNCTION("IFERROR(INDEX(SORT(FILTER(semrush_keywords!A:D, semrush_keywords!D:D=$C28), 2, 1), 2, 3), """")"),"") | J28: =IFERROR(__xludf.DUMMYFUNCTION("IFERROR(INDEX(SORT(FILTER(semrush_keywords!$A:$D, semrush_keywords!$D:$D=$C28), 2, 1), 3, 1), """")"),"") | K28: =IFERROR(__xludf.DUMMYFUNCTION("IFERROR(INDEX(SORT(FILTER(semrush_keywords!$A:$D, semrush_keywords!$D:$D=$C28), 2, 1), 3, 2), """")"),"") | L28: =IFERROR(__xludf.DUMMYFUNCTION("IFERROR(INDEX(SORT(FILTER(semrush_keywords!$A:$D, semrush_keywords!$D:$D=$C28), 2, 1), 3, 3), """") "),"")

Sheet Date Ranges
A1: Period | B1: Start Date | C1: End Date | D1: Description
A2: L3M (Current) | B2: Oct 22, 2025 | C2: Jan 21, 2026 | D2: Last 3 Months
A3: Prev 3M | B3: Jul 22, 2025 | C3: Oct 21, 2025 | D3: Previous 3 Months
A4: L3M LY (YoY) | B4: Oct 22, 2024 | C4: Jan 21, 2025 | D4: Same period last year

Sheet L3m_search_console_all
A1: Address | B1: Status Code | C1: Title 1 | D1: Indexability | E1: Indexability Status | F1: Clicks | G1: Impressions | H1: CTR | I1: Position
A2: https://sbrownlawyer.com/ | B2: 200 | C2: Scott M. Brown & Associates | Family, Criminal & Injury Law Firm in Texas | D2: Indexable | F2: 406 | G2: 41890 | H2: 0.01 | I2: 28.1
A3: https://sbrownlawyer.com/texas/locations/pearland/ | B3: 200 | C3: Pearland Divorce & Family Lawyers | Scott M. Brown & Associates | D3: Indexable | F3: 48 | G3: 29652 | H3: 0.002 | I3: 13.19
A4: https://sbrownlawyer.com/modifications/ | B4: 200 | C4: Child Custody Modification in Texas | Scott M. Brown & Associates | D4: Indexable | F4: 0 | G4: 307 | H4: 0 | I4: 59.23
A5: https://sbrownlawyer.com/areas-we-serve/brazoria-county/ | B5: 200 | C5: Brazoria County Divorce & Family Lawyers | Scott M. Brown & Associates | D5: Indexable | F5: 3 | G5: 628 | H5: 0.005 | I5: 32.86
A6: https://sbrownlawyer.com/debt-division/ | B6: 200 | C6: Debt Division Attorney | Angleton, Texas | D6: Indexable | F6: 0 | G6: 175 | H6: 0 | I6: 26.38
A7: https://sbrownlawyer.com/protective-services/ | B7: 200 | C7: Child Protective Services Lawyers Pearland | CPS Attorneys | D7: Indexable | F7: 2 | G7: 880 | H7: 0.002 | I7: 56.02
A8: https://sbrownlawyer.com/texas/locations/angleton/ | B8: 200 | C8: Angleton Divorce & Family Lawyers | Scott M. Brown & Associates | D8: Indexable | F8: 21 | G8: 11988 | H8: 0.002 | I8: 9.77
A9: https://sbrownlawyer.com/careers/ | B9: 200 | C9: Careers | Scott M. Brown & Associates | D9: Indexable | F9: 10 | G9: 339 | H9: 0.029 | I9: 10.78
A10: https://sbrownlawyer.com/areas-we-serve/galveston-county/ | B10: 200 | C10: Galveston County Divorce & Family Lawyers | Scott M. Brown & Associates | D10: Indexable | F10: 3 | G10: 1592 | H10: 0.002 | I10: 17.56
A11: https://sbrownlawyer.com/adoption/ | B11: 200 | C11: Adoption in Texas | Scott M. Brown & Associates | D11: Indexable | F11: 1 | G11: 3048 | H11: 0 | I11: 45.72
A12: https://sbrownlawyer.com/prenuptial-agreements/ | B12: 200 | C12: Prenuptial & Postnuptial Agreements in Texas | Scott M. Brown & Associates | D12: Indexable | F12: 0 | G12: 604 | H12: 0 | I12: 39.33
A13: https://sbrownlawyer.com/blog/ | B13: 200 | C13: Family Law Blog | Scott M. Brown & Associates | D13: Indexable | F13: 0 | G13: 124 | H13: 0 | I13: 9.25
A14: https://sbrownlawyer.com/2024/07/08/open-vs-closed-aoption-angleton-texas/ | B14: 200 | C14: Understanding Open vs. Closed Adoption | Angleton, TX | D14: Indexable | F14: 1 | G14: 1894 | H14: 0 | I14: 24.82
A15: https://sbrownlawyer.com/immigration/ | B15: 301 | D15: Non-Indexable | E15: Redirected | F15: 8 | G15: 1190 | H15: 0.007 | I15: 28.5
A16: https://sbrownlawyer.com/privacy-policy | B16: 301 | D16: Non-Indexable | E16: Redirected | F16: 0 | G16: 66 | H16: 0 | I16: 37.73
A17: https://sbrownlawyer.com/divorce/ | B17: 200 | C17: Divorce in Texas | Scott M. Brown & Associates | D17: Indexable | F17: 7 | G17: 12101 | H17: 0.001 | I17: 19.25
A18: https://sbrownlawyer.com/gray-divorce/ | B18: 200 | C18: Texas Gray Divorce Attorney | Angleton, TX | D18: Indexable | F18: 1 | G18: 760 | H18: 0.001 | I18: 10.43
A19: https://sbrownlawyer.com/lgbtq-divorce/ | B19: 200 | C19: LGBTQ Divorce Lawyer | Pearland, Texas | D19: Indexable | F19: 1 | G19: 1590 | H19: 0.001 | I19: 27.72
A20: https://sbrownlawyer.com/attorneys-working-to-achieve-your-alimony-goals/ | B20: 200 | C20: Alimony in Texas | Scott M. Brown & Associates | D20: Indexable | F20: 0 | G20: 535 | H20: 0 | I20: 21.07
A21: https://sbrownlawyer.com/texas/locations/league-city/ | B21: 200 | C21: League City Divorce & Family Lawyers | Scott M. Brown & Associates | D21: Indexable | F21: 10 | G21: 6889 | H21: 0.002 | I21: 15.5
A22: https://sbrownlawyer.com/criminal-defense-videos/ | B22: 200 | C22: Criminal Defense Videos | Scott M. Brown & Associates | D22: Indexable | F22: 0 | G22: 175 | H22: 0 | I22: 12.67
A23: https://sbrownlawyer.com/news/ | B23: 200 | C23: In the News | Scott M. Brown & Associates | D23: Indexable | F23: 1 | G23: 224 | H23: 0.004 | I23: 9.12
A24: https://sbrownlawyer.com/disclaimer/ | B24: 200 | C24: Disclaimer | Scott M. Brown & Associates | D24: Indexable | F24: 0 | G24: 44 | H24: 0 | I24: 6.91
A25: https://sbrownlawyer.com/business-owner-divorce/ | B25: 200 | C25: Business Owner Property Division in Texas | Scott M. Brown & Associates | D25: Indexable | F25: 1 | G25: 1534 | H25: 0.001 | I25: 28.52
A26: https://sbrownlawyer.com/areas-we-serve/matagorda-county/ | B26: 200 | C26: Matagorda County Family Law & Divorce Lawyers | Scott M. Brown & Associates | D26: Indexable | F26: 3 | G26: 505 | H26: 0.006 | I26: 10.44
A27: https://sbrownlawyer.com/child-custody/ | B27: 200 | C27: Child Custody in Texas | Scott M. Brown & Associates | D27: Indexable | F27: 2 | G27: 3310 | H27: 0.001 | I27: 35.73
A28: https://sbrownlawyer.com/Scott-M-Brown/ | B28: 200 | C28: Divorce & Family Law Attorney Scott M. Brown | Scott M. Brown & Associates | D28: Non-Indexable | E28: Canonicalised
A29: https://sbrownlawyer.com/child-support/child-support-modifications/ | B29: 200 | C29: Child Support Modifications | Angleton Modification Attorney | D29: Indexable | F29: 0 | G29: 80 | H29: 0 | I29: 32.66
A30: https://sbrownlawyer.com/case-results/ | B30: 200 | C30: Successful Case Results from Houston, Texas | D30: Indexable | F30: 1 | G30: 88 | H30: 0.011 | I30: 11.06
A31: https://sbrownlawyer.com/contact/ | B31: 200 | C31: Contact Scott M. Brown | Angleton, Pearland and League City | D31: Indexable | F31: 15 | G31: 12711 | H31: 0.001 | I31: 7.96
A32: https://sbrownlawyer.com/cohabitation/ | B32: 200 | C32: Cohabitation Agreement Texas | Pearland, TX | D32: Indexable | F32: 4 | G32: 5811 | H32: 0.001 | I32: 14.73
A33: https://sbrownlawyer.com/areas-we-serve/ | B33: 200 | C33: Texas Family Law Service Areas | Scott M. Brown & Associates | D33: Indexable | F33: 1 | G33: 145 | H33: 0.007 | I33: 10.12
A34: https://sbrownlawyer.com/personal-injury/ | B34: 200 | C34: Personal Injury Lawyers Protecting Texans | Scott M. Brown & Associates | D34: Indexable | F34: 3 | G34: 3446 | H34: 0.001 | I34: 33.72
A35: https://sbrownlawyer.com/paternity-attorney/ | B35: 200 | C35: Pearland Paternity Lawyers | Scott M. Brown & Associates | D35: Indexable | F35: 1 | G35: 954 | H35: 0.001 | I35: 12.54
A36: https://sbrownlawyer.com/testimonials/ | B36: 200 | C36: Client Reviews | Scott M. Brown & Associates | D36: Indexable | F36: 14 | G36: 613 | H36: 0.023 | I36: 5.73
A37: https://sbrownlawyer.com/criminal-defense-book/ | B37: 200 | C37: Criminal Defense Book | Scott M. Brown & Associates | D37: Indexable | F37: 3 | G37: 1183 | H37: 0.003 | I37: 28
A38: https://sbrownlawyer.com/personal-injury-videos/ | B38: 200 | C38: Personal Injury videos | Scott M. Brown & Associates | D38: Indexable | F38: 0 | G38: 23 | H38: 0 | I38: 29.17
A39: https://sbrownlawyer.com/enforcement/ | B39: 200 | C39: Child Support Enforcement in Texas | Scott M. Brown & Associates | D39: Indexable | F39: 1 | G39: 136 | H39: 0.007 | I39: 27.64
A40: https://sbrownlawyer.com/attorneys/ | B40: 200 | C40: Texas Family Law & Divorce Lawyers | Scott M. Brown & Associates | D40: Indexable | F40: 57 | G40: 19373 | H40: 0.003 | I40: 19.07
... A44: https://sbrownlawyer.com/criminal-defense/ | B44: 200 | C44: Criminal Defense Lawyers | Angleton, Pearland, League City, Houston | Scott M. Brown & Associates | D44: Indexable | F44: 0 | G44: 2155 | H44: 0 | I44: 20.67
A45: https://sbrownlawyer.com/terms-of-service | B45: 301 | D45: Non-Indexable | E45: Redirected | F45: 0 | G45: 20 | H45: 0 | I45: 32.1
A46: https://sbrownlawyer.com/criminal-law/ | B46: 200 | C46: Criminal Defense | Criminal Defense Lawyer | Pearland, Texas | D46: Non-Indexable | E46: Canonicalised,noindex
A47: https://sbrownlawyer.com/areas-we-serve/fort-bend-county/ | B47: 200 | C47: Fort Bend County Family Law & Divorce Lawyers | Scott M. Brown & Associates | D47: Indexable | F47: 2 | G47: 1381 | H47: 0.001 | I47: 32.5
A48: https://sbrownlawyer.com/estate-planning-probate/ | B48: 200 | C48: Texas Estate Planning Lawyers | Scott M. Brown & Associates | D48: Indexable | F48: 1 | G48: 504 | H48: 0.002 | I48: 36.99
A49: https://sbrownlawyer.com/videos-5/ | B49: 200 | C49: Videos | Scott M. Brown & Associates | | D49: Indexable | F49: 0 | G49: 118 | H49: 0 | I49: 16.08
A50: https://sbrownlawyer.com/asset-division/ | B50: 200 | C50: Texas Property and Asset Division | Texas | D50: Indexable | F50: 0 | G50: 974 | H50: 0 | I50: 31.46
A51: https://sbrownlawyer.com/divorce-modification/ | B51: 200 | C51: Modifying a Divorce Decree in Texas | Scott M. Brown & Associates | D51: Indexable | F51: 0 | G51: 490 | H51: 0 | I51: 25.37
A52: https://sbrownlawyer.com/immigration-videos/ | B52: 301 | D52: Non-Indexable | E52: Redirected | F52: 4 | G52: 342 | H52: 0.012 | I52: 36.28
A53: https://sbrownlawyer.com/texas/locations/sugar-land/ | B53: 200 | C53: Sugar Land Divorce & Family Lawyers | Scott M. Brown & Associates | D53: Indexable | F53: 2 | G53: 3095 | H53: 0.001 | I53: 42.01
A54: https://sbrownlawyer.com/privacy-policy/ | B54: 200 | C54: Privacy Policy | Scott M. Brown, P.C. | Pearland, Texas | D54: Indexable | F54: 0 | G54: 66 | H54: 0 | I54: 37.73
A55: https://sbrownlawyer.com/division-of-property/ | B55: 200 | C55: Property Division in Texas | Scott M. Brown & Associates | D55: Indexable | F55: 2 | G55: 499 | H55: 0.004 | I55: 18.25
A56: https://sbrownlawyer.com/2024/03/26/grandparent-custody-rights/ | B56: 200 | C56: Grandparents’ Custody Rights in Texas | Houston, TX | D56: Indexable | F56: 4 | G56: 2422 | H56: 0.002 | I56: 25.5
A57: https://sbrownlawyer.com/client-video-testimonials/ | B57: 200 | C57: Client Video Testimonials | Scott M. Brown & Associates | D57: Indexable | F57: 1 | G57: 368 | H57: 0.003 | I57: 23.52
A58: https://sbrownlawyer.com/texas/locations/ | B58: 200 | C58: Texas Family Law Office Locations | Scott M. Brown & Associates | D58: Indexable | F58: 2 | G58: 1703 | H58: 0.001 | I58: 17.18
A59: https://sbrownlawyer.com/high-net-worth-divorce/ | B59: 200 | C59: High-Net-Worth Divorces in Texas | Scott M. Brown & Associates | D59: Indexable | F59: 0 | G59: 176 | H59: 0 | I59: 57.66
A60: https://sbrownlawyer.com/firm-overview/ | B60: 200 | C60: Our Story | Scott M. Brown & Associates | D60: Indexable | F60: 10 | G60: 3611 | H60: 0.003 | I60: 9.16
A61: https://sbrownlawyer.com/family-law/visitation/ | B61: 200 | C61: Child Visitation Attorneys | Pearland & Angleton, TX | D61: Indexable | F61: 0 | G61: 253 | H61: 0 | I61: 30.57
A62: https://sbrownlawyer.com/texas-family-law-attorney/ | B62: 200 | C62: Texas Family Law | Scott M. Brown & Associates | D62: Indexable | F62: 0 | G62: 1530 | H62: 0 | I62: 11.84
A63: https://sbrownlawyer.com/doctor-divorce-videos/ | B63: 200 | C63: Doctor Divorce Videos | Scott M. Brown & Associates | D63: Indexable | F63: 11 | G63: 1407 | H63: 0.008 | I63: 9.6
A64: https://sbrownlawyer.com/2024/04/24/texas-alimony-am-i-entitled/ | B64: 200 | C64: Am I Entitled to Spousal Support? | Pearland, TX | D64: Indexable | F64: 69 | G64: 26560 | H64: 0.003 | I64: 8.03
... A117: https://sbrownlawyer.com/sexual-abuse/ | B117: 200 | C117: Sexual Abuse | Sexual Abuse Defense Lawyer | Pearland, Texas | D117: Indexable | F117: 2 | G117: 1074 | H117: 0.002 | I117: 32.27
A118: https://sbrownlawyer.com/Contact/ | B118: 200 | C118: Contact Scott M. Brown | Angleton, Pearland and League City | D118: Non-Indexable | E118: Canonicalised
A119: https://sbrownlawyer.com/Attorneys | B119: 301 | D119: Non-Indexable | E119: Redirected
A120: https://sbrownlawyer.com/pearland-probation-violations-lawyer/ | B120: 200 | C120: Probation Violation Defense | Angleton, TX | D120: Indexable | F120: 0 | G120: 406 | H120: 0 | I120: 42.26
A121: https://sbrownlawyer.com/areas-we-serve/brazoria-county/clute/ | B121: 200 | C121: Family Lawyer in Clute | Scott M. Brown & Associates | D121: Indexable | F121: 0 | G121: 21 | H121: 0 | I121: 14.14
A122: https://sbrownlawyer.com/t-bone-accident/ | B122: 200 | C122: Pearland, TX T-Bone Accident Attorney | Pearland, TX | D122: Indexable | F122: 0 | G122: 2235 | H122: 0 | I122: 60.71
A123: https://sbrownlawyer.com/areas-we-serve/brazoria-county/lake-jackson/ | B123: 200 | C123: Family Lawyer in Lake Jackson | Scott M. Brown & Associates | D123: Indexable | F123: 3 | G123: 755 | H123: 0.004 | I123: 14.45
A124: https://sbrownlawyer.com/family-law | B124: 301 | D124: Non-Indexable | E124: Redirected
A125: https://sbrownlawyer.com/Firm-Overview | B125: 301 | D125: Non-Indexable | E125: Redirected
A126: https://sbrownlawyer.com/areas-we-serve/brazoria-county/freeport/ | B126: 200 | C126: Family Lawyer in Freeport | Scott M. Brown & Associates | D126: Indexable | F126: 0 | G126: 226 | H126: 0 | I126: 36.41
A127: https://sbrownlawyer.com/areas-we-serve/brazoria-county/alvin/ | B127: 200 | C127: Family Lawyer in Alvin | Scott M. Brown & Associates | D127: Indexable | F127: 0 | G127: 120 | H127: 0 | I127: 15.98
A128: https://sbrownlawyer.com/2022/08/12/job-opportunity-were-looking-for-an-associate-attorney/ | B128: 200 | C128: JOB OPPORTUNITY: We're Looking for an Associate Attorney! | Scott M. Brown & Associates | D128: Indexable | F128: 0 | G128: 11 | H128: 0 | I128: 11.73
A129: https://sbrownlawyer.com/areas-we-serve/galveston-county/galveston/ | B129: 200 | C129: Family Lawyer in Galveston | Scott M. Brown & Associates | D129: Indexable | F129: 1 | G129: 119 | H129: 0.008 | I129: 37.83
A130: https://sbrownlawyer.com/areas-we-serve/galveston-county/texas-city/ | B130: 200 | C130: Family Lawyer in Texas City | Scott M. Brown & Associates | D130: Indexable | F130: 0 | G130: 284 | H130: 0 | I130: 13.82
A131: https://sbrownlawyer.com/stepparent-rights/ | B131: 200 | C131: Step Parents Lawyer | For Divorce & Adoption - Angleton, Pearland & League City, TX | Scott M. Brown & Associates | D131: Indexable | F131: 0 | G131: 73 | H131: 0 | I131: 55.19
A132: https://sbrownlawyer.com/2023/01/06/job-opportunity-senior-attorney/ | B132: 200 | C132: JOB OPPORTUNITY: We're Looking for a Senior Family Law Attorney! | Brazoria County, TX | D132: Indexable | F132: 0 | G132: 1 | H132: 0 | I132: 11
A133: https://sbrownlawyer.com/areas-we-serve/galveston-county/friendswood/ | B133: 200 | C133: Family Lawyer in Friendswood | Scott M. Brown & Associates | D133: Indexable | F133: 0 | G133: 203 | H133: 0 | I133: 28.52
A134: https://sbrownlawyer.com/Contact | B134: 301 | D134: Non-Indexable | E134: Redirected
A135: https://sbrownlawyer.com/areas-we-serve/galveston-county/dickinson/ | B135: 200 | C135: Family Lawyer in Dickinson | Scott M. Brown & Associates | D135: Indexable | F135: 0 | G135: 146 | H135: 0 | I135: 10.14
A136: https://sbrownlawyer.com/2024/09/23/is-leaving-the-scene-of-an-accident-a-felony-in-angleton/ | B136: 200 | C136: Hit-and-Run Accidents | Truck Accident Attorney Angleton | D136: Indexable | F136: 1 | G136: 975 | H136: 0.001 | I136: 7.01
A137: https://sbrownlawyer.com/2024/08/01/felony-misdemeanor-difference-league-city/ | B137: 200 | C137: Felony vs Misdemeanor League City | Scott M. Brown | D137: Indexable | F137: 2 | G137: 4008 | H137: 0 | I137: 6.18
A138: https://sbrownlawyer.com/2024/08/30/car-accidents/ | B138: 200 | C138: Car Accident Injury Attorneys | Pearland, TX | D138: Indexable | F138: 0 | G138: 406 | H138: 0 | I138: 53.4
A139: https://sbrownlawyer.com/2024/07/04/expungement-vs-sealing-what-is-the-best-option/ | B139: 200 | C139: Expungement vs. Sealing: What is the Best? | Angleton, TX | D139: Indexable | F139: 2 | G139: 1242 | H139: 0.002 | I139: 34.57
A140: https://sbrownlawyer.com/2024/08/20/no-fault-divorce-vs-fault-divorce-angleton-texas/ | B140: 200 | C140: No-Fault Divorce vs Fault Divorce | Divorce Lawyer Angleton | D140: Indexable | F140: 0 | G140: 177 | H140: 0 | I140: 10.36
A141: https://sbrownlawyer.com/2024/12/23/compensation-for-paralysis-injuries-your-guide-to-texas-law/ | B141: 200 | C141: Compensation for Paralysis Injuries | Angleton, TX | D141: Indexable | F141: 0 | G141: 238 | H141: 0 | I141: 23.87
A142: https://sbrownlawyer.com/blog/page/2/?et_blog | B142: 200 | C142: Scott M. Brown & Associates | Angleton, League City, Pearland | D142: Non-Indexable | E142: Canonicalised | F142: 0 | G142: 6 | H142: 0 | I142: 48.17
A143: https://sbrownlawyer.com/How-is-property-divided-in-a-Texas-divorce | B143: 301 | D143: Non-Indexable | E143: Redirected
A144: https://sbrownlawyer.com/2024/10/09/legal-rights-for-pedestrian-injury-victims-in-texas/ | B144: 200 | C144: Legal Rights for Pedestrian Injury Victims in Texas: What You Need to Know | Texas | D144: Indexable | F144: 13 | G144: 3566 | H144: 0.004 | I144: 12.66
A145: https://sbrownlawyer.com/2024/10/08/car-accident-in-houston-understanding-your-rights-and-responsibilities/ | B145: 200 | C145: Car Accident in Houston: Know Your Rights & Responsibilities | D145: Indexable | F145: 1 | G145: 201 | H145: 0.005 | I145: 10.33
A146: https://sbrownlawyer.com/protecting-your-assets/ | B146: 200 | C146: Protecting Your Assets in Divorce | Brazoria County Law Firm - Scott M. Brown & Associates | D146: Indexable | F146: 0 | G146: 19 | H146: 0 | I146: 43.79
A147: https://sbrownlawyer.com/pearland-family-law-office/ | B147: 200 | C147: Pearland Family Law Office | Scott M. Brown & Associates | Pearland, Texas | D147: Non-Indexable | E147: Canonicalised,noindex | F147: 0 | G147: 1 | H147: 0 | I147: 1
A148: https://sbrownlawyer.com/2024/10/18/over-55-divorce/ | B148: 200 | C148: Over 55 Divorce in Texas | Pearland, Texas | D148: Indexable | F148: 28 | G148: 1205 | H148: 0.023 | I148: 4.67
A149: https://sbrownlawyer.com/league-city-divorce-lawyer/ | B149: 301 | D149: Non-Indexable | E149: Redirected
A150: https://sbrownlawyer.com/articles/What-happens-to-pets-in-a-Texas-divorce | B150: 301 | D150: Non-Indexable | E150: Redirected
A151: https://sbrownlawyer.com/Don-t-let-family-violence-allegations-affect-your-open-carry-rights | B151: 301 | D151: Non-Indexable | E151: Redirected
A152: https://sbrownlawyer.com/rule-1-file-first/ | B152: 200 | C152: Rule 1: File for Divorce First | Attorney Scott M. Brown | D152: Indexable | F152: 0 | G152: 12 | H152: 0 | I152: 31.33
A153: https://sbrownlawyer.com/Financial-Steps-To-Take-Before-Filing-For-Divorce | B153: 301 | D153: Non-Indexable | E153: Redirected
A154: https://sbrownlawyer.com/uncontested-divorce-lawyer-in-pearland/ | B154: 200 | C154: Pearland Uncontested Divorce Lawyers | Scott M. Brown & Associates | D154: Indexable | F154: 4 | G154: 1454 | H154: 0.003 | I154: 51.36
A155: https://sbrownlawyer.com/When-alcohol-becomes-a-factor-in-divorce-proceedings | B155: 301 | D155: Non-Indexable | E155: Redirected
...

Sheet L3m_analytics_all
A1: Address | B1: Status Code | C1: Title 1 | D1: Indexability | E1: Indexability Status | F1: GA4 Sessions | G1: GA4 Views | H1: GA4 Engaged sessions | I1: GA4 Engagement rate | J1: GA4 Key events | K1: GA4 Event count | L1: GA4 Total revenue | M1: GA4 New users
A2: https://sbrownlawyer.com/ | B2: 200 | C2: Scott M. Brown & Associates | Family, Criminal & Injury Law Firm in Texas | D2: Indexable | F2: 1077 | G2: 3155 | H2: 731 | I2: 0.68 | J2: 123 | K2: 10767 | L2: 0 | M2: 803
A3: https://sbrownlawyer.com/texas/locations/pearland/ | B3: 200 | C3: Pearland Divorce & Family Lawyers | Scott M. Brown & Associates | D3: Indexable | F3: 157 | G3: 355 | H3: 121 | I3: 0.77 | J3: 7 | K3: 1203 | L3: 0 | M3: 121
A4: https://sbrownlawyer.com/modifications/ | B4: 200 | C4: Child Custody Modification in Texas | Scott M. Brown & Associates | D4: Indexable | F4: 3 | G4: 3 | H4: 0 | I4: 0 | J4: 0 | K4: 25 | L4: 0 | M4: 3
A5: https://sbrownlawyer.com/areas-we-serve/brazoria-county/ | B5: 200 | C5: Brazoria County Divorce & Family Lawyers | Scott M. Brown & Associates | D5: Indexable | F5: 6 | G5: 15 | H5: 6 | I5: 1 | J5: 0 | K5: 37 | L5: 0 | M5: 2
A6: https://sbrownlawyer.com/debt-division/ | B6: 200 | C6: Debt Division Attorney | Angleton, Texas | D6: Indexable | F6: 1 | G6: 1 | H6: 0 | I6: 0 | J6: 0 | K6: 3 | L6: 0 | M6: 1
A7: https://sbrownlawyer.com/protective-services/ | B7: 200 | C7: Child Protective Services Lawyers Pearland | CPS Attorneys | D7: Indexable | F7: 7 | G7: 8 | H7: 2 | I7: 0.29 | J7: 0 | K7: 30 | L7: 0 | M7: 5
A8: https://sbrownlawyer.com/texas/locations/angleton/ | B8: 200 | C8: Angleton Divorce & Family Lawyers | Scott M. Brown & Associates | D8: Indexable | F8: 146 | G8: 306 | H8: 119 | I8: 0.82 | J8: 5 | K8: 1026 | L8: 0 | M8: 121
A9: https://sbrownlawyer.com/careers/ | B9: 200 | C9: Careers | Scott M. Brown & Associates | D9: Indexable | F9: 10 | G9: 13 | H9: 9 | I9: 0.9 | J9: 0 | K9: 48 | L9: 0 | M9: 8
A10: https://sbrownlawyer.com/areas-we-serve/galveston-county/ | B10: 200 | C10: Galveston County Divorce & Family Lawyers | Scott M. Brown & Associates | D10: Indexable | F10: 2 | G10: 3 | H10: 1 | I10: 0.5 | J10: 0 | K10: 9 | L10: 0 | M10: 2
A11: https://sbrownlawyer.com/adoption/ | B11: 200 | C11: Adoption in Texas | Scott M. Brown & Associates | D11: Indexable | F11: 2 | G11: 2 | H11: 1 | I11: 0.5 | J11: 0 | K11: 7 | L11: 0 | M11: 1
A12: https://sbrownlawyer.com/prenuptial-agreements/ | B12: 200 | C12: Prenuptial & Postnuptial Agreements in Texas | Scott M. Brown & Associates | D12: Indexable | F12: 1 | G12: 1 | H12: 0 | I12: 0 | J12: 0 | K12: 3 | L12: 0 | M12: 1
A13: https://sbrownlawyer.com/blog/ | B13: 200 | C13: Family Law Blog | Scott M. Brown & Associates | D13: Indexable | F13: 1 | G13: 1 | H13: 0 | I13: 0 | J13: 0 | K13: 3 | L13: 0 | M13: 1
A14: https://sbrownlawyer.com/2024/07/08/open-vs-closed-aoption-angleton-texas/ | B14: 200 | C14: Understanding Open vs. Closed Adoption | Angleton, TX | D14: Indexable | F14: 3 | G14: 3 | H14: 0 | I14: 0 | J14: 0 | K14: 8 | L14: 0 | M14: 2
A15: https://sbrownlawyer.com/immigration/ | B15: 301 | D15: Non-Indexable | E15: Redirected | F15: 7 | G15: 8 | H15: 3 | I15: 0.43 | J15: 0 | K15: 24 | L15: 0 | M15: 5
A16: https://sbrownlawyer.com/privacy-policy | B16: 301 | D16: Non-Indexable | E16: Redirected | F16: 3 | G16: 3 | H16: 2 | I16: 0.67 | J16: 0 | K16: 27 | L16: 0 | M16: 3
A17: https://sbrownlawyer.com/divorce/ | B17: 200 | C17: Divorce in Texas | Scott M. Brown & Associates | D17: Indexable | F17: 23 | G17: 120 | H17: 18 | I17: 0.78 | J17: 0 | K17: 439 | L17: 0 | M17: 13
A18: https://sbrownlawyer.com/gray-divorce/ | B18: 200 | C18: Texas Gray Divorce Attorney | Angleton, TX | D18: Indexable | F18: 4 | G18: 4 | H18: 0 | I18: 0 | J18: 0 | K18: 14 | L18: 0 | M18: 3
A19: https://sbrownlawyer.com/lgbtq-divorce/ | B19: 200 | C19: LGBTQ Divorce Lawyer | Pearland, Texas | D19: Indexable | F19: 1 | G19: 1 | H19: 0 | I19: 0 | J19: 0 | K19: 3 | L19: 0 | M19: 1
A20: https://sbrownlawyer.com/attorneys-working-to-achieve-your-alimony-goals/ | B20: 200 | C20: Alimony in Texas | Scott M. Brown & Associates | D20: Indexable | F20: 1 | G20: 1 | H20: 0 | I20: 0 | J20: 0 | K20: 3 | L20: 0 | M20: 1
A21: https://sbrownlawyer.com/texas/locations/league-city/ | B21: 200 | C21: League City Divorce & Family Lawyers | Scott M. Brown & Associates | D21: Indexable | F21: 97 | G21: 238 | H21: 76 | I21: 0.78 | J21: 6 | K21: 731 | L21: 0 | M21: 84
A22: https://sbrownlawyer.com/criminal-defense-videos/ | B22: 200 | C22: Criminal Defense Videos | Scott M. Brown & Associates | D22: Indexable | F22: 1 | G22: 1 | H22: 0 | I22: 0 | J22: 0 | K22: 3 | L22: 0 | M22: 1
A23: https://sbrownlawyer.com/news/ | B23: 200 | C23: In the News | Scott M. Brown & Associates | D23: Indexable | F23: 2 | G23: 3 | H23: 1 | I23: 0.5 | J23: 0 | K23: 8 | L23: 0 | M23: 1
A24: https://sbrownlawyer.com/disclaimer/ | B24: 200 | C24: Disclaimer | Scott M. Brown & Associates | D24: Indexable | F24: 1 | G24: 1 | H24: 0 | I24: 0 | J24: 0 | K24: 3 | L24: 0 | M24: 1
A25: https://sbrownlawyer.com/business-owner-divorce/ | B25: 200 | C25: Business Owner Property Division in Texas | Scott M. Brown & Associates | D25: Indexable | F25: 2 | G25: 3 | H25: 1 | I25: 0.5 | J25: 0 | K25: 9 | L25: 0 | M25: 2
A26: https://sbrownlawyer.com/areas-we-serve/matagorda-county/ | B26: 200 | C26: Matagorda County Family Law & Divorce Lawyers | Scott M. Brown & Associates | D26: Indexable | F26: 2 | G26: 4 | H26: 2 | I26: 1 | J26: 0 | K26: 13 | L26: 0 | M26: 2
A27: https://sbrownlawyer.com/child-custody/ | B27: 200 | C27: Child Custody in Texas | Scott M. Brown & Associates | D27: Indexable | F27: 6 | G27: 8 | H27: 2 | I27: 0.33 | J27: 1 | K27: 30 | L27: 0 | M27: 5
A28: https://sbrownlawyer.com/Scott-M-Brown/ | B28: 200 | C28: Divorce & Family Law Attorney Scott M. Brown | Scott M. Brown & Associates | D28: Non-Indexable | E28: Canonicalised | F28: 21 | G28: 51 | H28: 18 | I28: 0.86 | J28: 1 | K28: 193 | L28: 0 | M28: 17
A29: https://sbrownlawyer.com/child-support/child-support-modifications/ | B29: 200 | C29: Child Support Modifications | Angleton Modification Attorney | D29: Indexable | F29: 2 | G29: 3 | H29: 1 | I29: 0.5 | J29: 0 | K29: 10 | L29: 0 | M29: 2
A30: https://sbrownlawyer.com/case-results/ | B30: 200 | C30: Successful Case Results from Houston, Texas | D30: Indexable | F30: 4 | G30: 5 | H30: 3 | I30: 0.75 | J30: 0 | K30: 17 | L30: 0 | M30: 2
A31: https://sbrownlawyer.com/contact/ | B31: 200 | C31: Contact Scott M. Brown | Angleton, Pearland and League City | D31: Indexable | F31: 39 | G31: 64 | H31: 23 | I31: 0.59 | J31: 4 | K31: 294 | L31: 0 | M31: 32
A32: https://sbrownlawyer.com/cohabitation/ | B32: 200 | C32: Cohabitation Agreement Texas | Pearland, TX | D32: Indexable | F32: 8 | G32: 8 | H32: 4 | I32: 0.5 | J32: 0 | K32: 42 | L32: 0 | M32: 8
A33: https://sbrownlawyer.com/areas-we-serve/ | B33: 200 | C33: Texas Family Law Service Areas | Scott M. Brown & Associates | D33: Indexable | F33: 7 | G33: 39 | H33: 3 | I33: 0.43 | J33: 0 | K33: 230 | L33: 0 | M33: 3
A34: https://sbrownlawyer.com/personal-injury/ | B34: 200 | C34: Personal Injury Lawyers Protecting Texans | Scott M. Brown & Associates | D34: Indexable | F34: 5 | G34: 11 | H34: 3 | I34: 0.6 | J34: 0 | K34: 47 | L34: 0 | M34: 4
A35: https://sbrownlawyer.com/paternity-attorney/ | B35: 200 | C35: Pearland Paternity Lawyers | Scott M. Brown & Associates | D35: Indexable | F35: 3 | G35: 3 | H35: 0 | I35: 0 | J35: 0 | K35: 10 | L35: 0 | M35: 3
A36: https://sbrownlawyer.com/testimonials/ | B36: 200 | C36: Client Reviews | Scott M. Brown & Associates | D36: Indexable | F36: 13 | G36: 21 | H36: 10 | I36: 0.77 | J36: 1 | K36: 71 | L36: 0 | M36: 7
A37: https://sbrownlawyer.com/criminal-defense-book/ | B37: 200 | C37: Criminal Defense Book | Scott M. Brown & Associates | D37: Indexable | F37: 4 | G37: 9 | H37: 3 | I37: 0.75 | J37: 0 | K37: 25 | L37: 0 | M37: 4
A38: https://sbrownlawyer.com/personal-injury-videos/ | B38: 200 | C38: Personal Injury videos | Scott M. Brown & Associates | D38: Indexable | F38: 2 | G38: 3 | H38: 1 | I38: 0.5 | J38: 0 | K38: 21 | L38: 0 | M38: 2
A39: https://sbrownlawyer.com/enforcement/ | B39: 200 | C39: Child Support Enforcement in Texas | Scott M. Brown & Associates | D39: Indexable | F39: 3 | G39: 4 | H39: 1 | I39: 0.33 | J39: 0 | K39: 16 | L39: 0 | M39: 3
A40: https://sbrownlawyer.com/attorneys/ | B40: 200 | C40: Texas Family Law & Divorce Lawyers | Scott M. Brown & Associates | D40: Indexable | F40: 107 | G40: 272 | H40: 78 | I40: 0.73 | J40: 0 | K40: 809 | L40: 0 | M40: 71
... A44: https://sbrownlawyer.com/criminal-defense/ | B44: 200 | C44: Criminal Defense Lawyers | Angleton, Pearland, League City, Houston | Scott M. Brown & Associates | D44: Indexable | F44: 7 | G44: 26 | H44: 5 | I44: 0.71 | J44: 0 | K44: 66 | L44: 0 | M44: 6
A45: https://sbrownlawyer.com/terms-of-service | B45: 301 | D45: Non-Indexable | E45: Redirected | F45: 5 | G45: 5 | H45: 1 | I45: 0.2 | J45: 0 | K45: 49 | L45: 0 | M45: 4
A46: https://sbrownlawyer.com/criminal-law/ | B46: 200 | C46: Criminal Defense | Criminal Defense Lawyer | Pearland, Texas | D46: Non-Indexable | E46: Canonicalised,noindex | F46: 2 | G46: 5 | H46: 1 | I46: 0.5 | J46: 0 | K46: 12 | L46: 0 | M46: 1
A47: https://sbrownlawyer.com/areas-we-serve/fort-bend-county/ | B47: 200 | C47: Fort Bend County Family Law & Divorce Lawyers | Scott M. Brown & Associates | D47: Indexable | F47: 1 | G47: 10 | H47: 1 | I47: 1 | J47: 0 | K47: 20 | L47: 0 | M47: 1
A48: https://sbrownlawyer.com/estate-planning-probate/ | B48: 200 | C48: Texas Estate Planning Lawyers | Scott M. Brown & Associates | D48: Indexable | F48: 1 | G48: 1 | H48: 1 | I48: 1 | J48: 0 | K48: 4 | L48: 0 | M48: 1
A49: https://sbrownlawyer.com/videos-5/ | B49: 200 | C49: Videos | Scott M. Brown & Associates | | D49: Indexable | F49: 3 | G49: 3 | H49: 0 | I49: 0 | J49: 0 | K49: 10 | L49: 0 | M49: 3
A50: https://sbrownlawyer.com/asset-division/ | B50: 200 | C50: Texas Property and Asset Division | Texas | D50: Indexable | F50: 2 | G50: 2 | H50: 0 | I50: 0 | J50: 0 | K50: 6 | L50: 0 | M50: 2
A51: https://sbrownlawyer.com/divorce-modification/ | B51: 200 | C51: Modifying a Divorce Decree in Texas | Scott M. Brown & Associates | D51: Indexable | F51: 2 | G51: 6 | H51: 1 | I51: 0.5 | J51: 0 | K51: 14 | L51: 0 | M51: 1
A52: https://sbrownlawyer.com/immigration-videos/ | B52: 301 | D52: Non-Indexable | E52: Redirected | F52: 5 | G52: 5 | H52: 0 | I52: 0 | J52: 0 | K52: 17 | L52: 0 | M52: 5
A53: https://sbrownlawyer.com/texas/locations/sugar-land/ | B53: 200 | C53: Sugar Land Divorce & Family Lawyers | Scott M. Brown & Associates | D53: Indexable | F53: 3 | G53: 6 | H53: 3 | I53: 1 | J53: 0 | K53: 18 | L53: 0 | M53: 2
A54: https://sbrownlawyer.com/privacy-policy/ | B54: 200 | C54: Privacy Policy | Scott M. Brown, P.C. | Pearland, Texas | D54: Indexable | F54: 3 | G54: 3 | H54: 2 | I54: 0.67 | J54: 0 | K54: 27 | L54: 0 | M54: 3
A55: https://sbrownlawyer.com/division-of-property/ | B55: 200 | C55: Property Division in Texas | Scott M. Brown & Associates | D55: Indexable | F55: 5 | G55: 9 | H55: 1 | I55: 0.2 | J55: 0 | K55: 25 | L55: 0 | M55: 4
A56: https://sbrownlawyer.com/2024/03/26/grandparent-custody-rights/ | B56: 200 | C56: Grandparents’ Custody Rights in Texas | Houston, TX | D56: Indexable | F56: 8 | G56: 8 | H56: 3 | I56: 0.38 | J56: 0 | K56: 27 | L56: 0 | M56: 7
A57: https://sbrownlawyer.com/client-video-testimonials/ | B57: 200 | C57: Client Video Testimonials | Scott M. Brown & Associates | D57: Indexable | F57: 13 | G57: 25 | H57: 7 | I57: 0.54 | J57: 0 | K57: 88 | L57: 0 | M57: 4
A58: https://sbrownlawyer.com/texas/locations/ | B58: 200 | C58: Texas Family Law Office Locations | Scott M. Brown & Associates | D58: Indexable | F58: 24 | G58: 175 | H58: 18 | I58: 0.75 | J58: 1 | K58: 391 | L58: 0 | M58: 8
A59: https://sbrownlawyer.com/high-net-worth-divorce/ | B59: 200 | C59: High-Net-Worth Divorces in Texas | Scott M. Brown & Associates | D59: Indexable | F59: 2 | G59: 2 | H59: 0 | I59: 0 | J59: 0 | K59: 6 | L59: 0 | M59: 2
A60: https://sbrownlawyer.com/firm-overview/ | B60: 200 | C60: Our Story | Scott M. Brown & Associates | D60: Indexable | F60: 15 | G60: 36 | H60: 11 | I60: 0.73 | J60: 2 | K60: 93 | L60: 0 | M60: 11
A61: https://sbrownlawyer.com/family-law/visitation/ | B61: 200 | C61: Child Visitation Attorneys | Pearland & Angleton, TX | D61: Indexable | F61: 1 | G61: 1 | H61: 0 | I61: 0 | J61: 0 | K61: 5 | L61: 0 | M61: 1
A62: https://sbrownlawyer.com/texas-family-law-attorney/ | B62: 200 | C62: Texas Family Law | Scott M. Brown & Associates | D62: Indexable | F62: 6 | G62: 7 | H62: 3 | I62: 0.5 | J62: 0 | K62: 18 | L62: 0 | M62: 2
A63: https://sbrownlawyer.com/doctor-divorce-videos/ | B63: 200 | C63: Doctor Divorce Videos | Scott M. Brown & Associates | D63: Indexable | F63: 4 | G63: 4 | H63: 0 | I63: 0 | J63: 0 | K63: 13 | L63: 0 | M63: 4
A64: https://sbrownlawyer.com/2024/04/24/texas-alimony-am-i-entitled/ | B64: 200 | C64: Am I Entitled to Spousal Support? | Pearland, TX | D64: Indexable | F64: 88 | G64: 107 | H64: 45 | I64: 0.51 | J64: 3 | K64: 408 | L64: 0 | M64: 77
... A69: https://sbrownlawyer.com/personal-injury-in-texas/boat-accidents/ | B69: 200 | C69: Boat Accidents Attorney | Angleton, TX | D69: Indexable | F69: 2 | G69: 2 | H69: 0 | I69: 0 | J69: 0 | K69: 7 | L69: 0 | M69: 2
A70: https://sbrownlawyer.com/personal-injury-2/nonvehicle-liability-insurance/ | B70: 200 | C70: Non-Vehicle Liability Insurance Attorneys | Pearland, TX | D70: Indexable
A71: https://sbrownlawyer.com/truck-accident/ | B71: 200 | C71: Truck Accidents | Truck Accident Attorneys | Pearland, Texas | D71: Indexable | F71: 1 | G71: 1 | H71: 0 | I71: 0 | J71: 0 | K71: 3 | L71: 0 | M71: 1
A72: https://sbrownlawyer.com/rape-sexual-assault/ | B72: 200 | C72: Sexual Assault Lawyers Pearland Tx | Rape & Sexual Assault | D72: Indexable | F72: 2 | G72: 2 | H72: 1 | I72: 0.5 | J72: 0 | K72: 7 | L72: 0 | M72: 2
A73: https://sbrownlawyer.com/uber-lyft-accidents/ | B73: 200 | C73: Angleton Uber Accident Lawyer | Angleton, TX | D73: Indexable | F73: 3 | G73: 3 | H73: 1 | I73: 0.33 | J73: 0 | K73: 12 | L73: 0 | M73: 3
A74: https://sbrownlawyer.com/criminal-law/indecent-exposure/ | B74: 200 | C74: Indecent Exposure | Indecent Exposure Attorney | Houston, TX | D74: Indexable | F74: 4 | G74: 5 | H74: 2 | I74: 0.5 | J74: 0 | K74: 20 | L74: 0 | M74: 4
A75: https://sbrownlawyer.com/premises-liability/ | B75: 200 | C75: Houston Premises Liability Attorney | Premises Liability | D75: Indexable | F75: 1 | G75: 1 | H75: 0 | I75: 0 | J75: 0 | K75: 3 | L75: 0 | M75: 1
A76: https://sbrownlawyer.com/aggravated-sexual-assault/ | B76: 200 | C76: Houston Aggravated Sexual Assault Attorney | Houston, Texas | D76: Indexable | F76: 2 | G76: 2 | H76: 1 | I76: 0.5 | J76: 0 | K76: 9 | L76: 0 | M76: 2
A77: https://sbrownlawyer.com/assault/ | B77: 200 | C77: Assault | Assault Attorney | Houston, Texas | D77: Indexable | F77: 2 | G77: 2 | H77: 1 | I77: 0.5 | J77: 0 | K77: 9 | L77: 0 | M77: 2
A78: https://sbrownlawyer.com/motorcycle-accident/ | B78: 200 | C78: Motorcycle Accidents | Texas Motorcycle Accident Lawyer | D78: Indexable | F78: 1 | G78: 1 | H78: 0 | I78: 0 | J78: 0 | K78: 3 | L78: 0 | M78: 1
A79: https://sbrownlawyer.com/grand-theft/ | B79: 200 | C79: Grand Theft | Grand Theft Attorney | Houston, TX | D79: Indexable | F79: 3 | G79: 3 | H79: 0 | I79: 0 | J79: 0 | K79: 9 | L79: 0 | M79: 3
A80: https://sbrownlawyer.com/drug-crimes/ | B80: 200 | C80: Drug Crimes | Drug Crimes Attorney | Houston, Texas | D80: Indexable | F80: 2 | G80: 2 | H80: 1 | I80: 0.5 | J80: 0 | K80: 8 | L80: 0 | M80: 2
A81: https://sbrownlawyer.com/product-liability/ | B81: 200 | C81: Product Liability Attorneys | Pearland, Texas | D81: Indexable | F81: 2 | G81: 2 | H81: 1 | I81: 0.5 | J81: 0 | K81: 7 | L81: 0 | M81: 2
A82: https://sbrownlawyer.com/face-injury/ | B82: 200 | C82: Face Injury | Face Injury Attorney | Pearland, TX | D82: Indexable | F82: 4 | G82: 5 | H82: 1 | I82: 0.25 | J82: 0 | K82: 14 | L82: 0 | M82: 4
... A102: https://sbrownlawyer.com/obscenity/ | B102: 200 | C102: Obscenity in Criminal Defense | Houston, TX | D102: Indexable | F102: 10 | G102: 10 | H102: 8 | I102: 0.8 | J102: 2 | K102: 56 | L102: 0 | M102: 10
A103: https://sbrownlawyer.com/personal-injury-2/burn-injury/ | B103: 200 | C103: Burn Injury | Burn Injury Attorneys | Pearland, TX | D103: Indexable
A104: https://sbrownlawyer.com/misdemeanor/ | B104: 200 | C104: Misdemeanor Attorney in Pearland, TX | Pearland, TX | D104: Indexable | F104: 5 | G104: 6 | H104: 2 | I104: 0.4 | J104: 0 | K104: 19 | L104: 0 | M104: 4
A105: https://sbrownlawyer.com/sex-crimes/ | B105: 200 | C105: Sex Crimes | sex crimes attorney | Houston, Texas | D105: Indexable | F105: 2 | G105: 2 | H105: 1 | I105: 0.5 | J105: 0 | K105: 7 | L105: 0 | M105: 2
A106: https://sbrownlawyer.com/brain-injury/ | B106: 200 | C106: Brain Injury Attorney in Texas | Houston, Texas | D106: Indexable | F106: 2 | G106: 2 | H106: 0 | I106: 0 | J106: 0 | K106: 6 | L106: 0 | M106: 2
A107: https://sbrownlawyer.com/expungement/ | B107: 200 | C107: Expungement Lawyer | Pearland, TX | D107: Indexable | F107: 3 | G107: 4 | H107: 2 | I107: 0.67 | J107: 2 | K107: 21 | L107: 0 | M107: 3
A108: https://sbrownlawyer.com/hit-and-run/ | B108: 200 | C108: League City Hit and Run Defense Lawyer | League City, TX | D108: Indexable | F108: 1 | G108: 1 | H108: 0 | I108: 0 | J108: 0 | K108: 3 | L108: 0 | M108: 1
A109: https://sbrownlawyer.com/sex-crimes/overview-of-sex-crime-defense/ | B109: 200 | C109: Defenses to Sex Crime Charges in Texas | Pearland, TX | D109: Indexable | F109: 1 | G109: 1 | H109: 0 | I109: 0 | J109: 0 | K109: 4 | L109: 0 | M109: 1
A110: https://sbrownlawyer.com/pedestrian-accidents/ | B110: 200 | C110: Pedestrian Accidents in Texas | Houston, Texas | D110: Indexable | F110: 1 | G110: 1 | H110: 0 | I110: 0 | J110: 0 | K110: 3 | L110: 0 | M110: 1
A111: https://sbrownlawyer.com/road-hazard/ | B111: 200 | C111: Road Hazard Attorney Pearland TX | Scott M. Brown & Associates | D111: Indexable | F111: 1 | G111: 1 | H111: 0 | I111: 0 | J111: 0 | K111: 3 | L111: 0 | M111: 1
A112: https://sbrownlawyer.com/neck-injury/ | B112: 200 | C112: Texas Neck Injury Lawyer | Scott M. Brown & Associates | D112: Indexable | F112: 1 | G112: 1 | H112: 0 | I112: 0 | J112: 0 | K112: 3 | L112: 0 | M112: 1
A113: https://sbrownlawyer.com/spinal-cord-injury/ | B113: 200 | C113: Spinal Cord Injury in Texas | Houston, Texas | D113: Indexable | F113: 4 | G113: 4 | H113: 1 | I113: 0.25 | J113: 0 | K113: 31 | L113: 0 | M113: 3
A114: https://sbrownlawyer.com/team-member-testimonials/ | B114: 200 | C114: Team Member Testimonials | Scott M. Brown & Associates | D114: Indexable | F114: 4 | G114: 4 | H114: 1 | I114: 0.25 | J114: 0 | K114: 29 | L114: 0 | M114: 4
A115: https://sbrownlawyer.com/rape/ | B115: 200 | C115: Pearland TX Rape Defense Attorney | Pearland, TX | D115: Indexable | F115: 1 | G115: 1 | H115: 0 | I115: 0 | J115: 0 | K115: 3 | L115: 0 | M115: 1
... A117: https://sbrownlawyer.com/sexual-abuse/ | B117: 200 | C117: Sexual Abuse | Sexual Abuse Defense Lawyer | Pearland, Texas | D117: Indexable | F117: 4 | G117: 5 | H117: 2 | I117: 0.5 | J117: 1 | K117: 20 | L117: 0 | M117: 4
A118: https://sbrownlawyer.com/Contact/ | B118: 200 | C118: Contact Scott M. Brown | Angleton, Pearland and League City | D118: Non-Indexable | E118: Canonicalised | F118: 1 | G118: 1 | H118: 0 | I118: 0 | J118: 0 | K118: 17 | L118: 0 | M118: 1
A119: https://sbrownlawyer.com/Attorneys | B119: 301 | D119: Non-Indexable | E119: Redirected | F119: 4 | G119: 11 | H119: 3 | I119: 0.75 | J119: 0 | K119: 29 | L119: 0 | M119: 2
A120: https://sbrownlawyer.com/pearland-probation-violations-lawyer/ | B120: 200 | C120: Probation Violation Defense | Angleton, TX | D120: Indexable | F120: 1 | G120: 1 | H120: 0 | I120: 0 | J120: 0 | K120: 3 | L120: 0 | M120: 1
A121: https://sbrownlawyer.com/areas-we-serve/brazoria-county/clute/ | B121: 200 | C121: Family Lawyer in Clute | Scott M. Brown & Associates | D121: Indexable | F121: 1 | G121: 2 | H121: 1 | I121: 1 | J121: 0 | K121: 6 | L121: 0 | M121: 1
A122: https://sbrownlawyer.com/t-bone-accident/ | B122: 200 | C122: Pearland, TX T-Bone Accident Attorney | Pearland, TX | D122: Indexable | F122: 1 | G122: 1 | H122: 0 | I122: 0 | J122: 0 | K122: 3 | L122: 0 | M122: 1
A123: https://sbrownlawyer.com/areas-we-serve/brazoria-county/lake-jackson/ | B123: 200 | C123: Family Lawyer in Lake Jackson | Scott M. Brown & Associates | D123: Indexable | F123: 3 | G123: 7 | H123: 3 | I123: 1 | J123: 1 | K123: 25 | L123: 0 | M123: 3
A124: https://sbrownlawyer.com/family-law | B124: 301 | D124: Non-Indexable | E124: Redirected
A125: https://sbrownlawyer.com/Firm-Overview | B125: 301 | D125: Non-Indexable | E125: Redirected
A126: https://sbrownlawyer.com/areas-we-serve/brazoria-county/freeport/ | B126: 200 | C126: Family Lawyer in Freeport | Scott M. Brown & Associates | D126: Indexable
A127: https://sbrownlawyer.com/areas-we-serve/brazoria-county/alvin/ | B127: 200 | C127: Family Lawyer in Alvin | Scott M. Brown & Associates | D127: Indexable
...

Sheet P3M_analytics
A1: # ----------------------------------------
A2: # Landing page: Landing page
A3: # Account: Scott M Brown and Associates
A4: # Property: sbrownlawyer.com
A5: # ----------------------------------------
A6: #
A7: # All Users
A8: # Start date: 20250722
A9: # End date: 20251021
A10: Landing page | B10: Sessions | C10: Active users | D10: New users | E10: Average engagement time per session | F10: Key events | G10: Total revenue | H10: Session key event rate
A11: / | B11: 2081 | C11: 1689 | D11: 1615 | E11: 48.645843 | F11: 243 | G11: 0 | H11: 0.052859202
A12: /general-family-law-lp | B12: 695 | C12: 639 | D12: 621 | E12: 38.014388 | F12: 26 | G12: 0 | H12: 0.024460432
A13: /2024/04/24/texas-alimony-am-i-entitled | B13: 223 | C13: 201 | D13: 201 | E13: 81.901345 | F13: 2 | G13: 0 | H13: 0.0089686099
A14: /contact | B14: 211 | C14: 196 | D14: 170 | E14: 39.64455 | F14: 11 | G14: 0 | H14: 0.023696682
A15: /attorneys | B15: 205 | C15: 166 | D15: 125 | E15: 31.297561 | F15: 11 | G15: 0 | H15: 0.019512195
A16: /2024/12/27/understanding-the-naturalization-timeline-for-texas-residents | B16: 178 | C16: 154 | D16: 153 | E16: 68.977528 | F16: 3 | G16: 0 | H16: 0.016853933
A17: /2024/05/28/impact-of-a-criminal-record-on-child-custody-cases | B17: 169 | C17: 158 | D17: 157 | E17: 90.230769 | F17: 0 | G17: 0 | H17: 0
A18: /texas/locations/angleton | B18: 166 | C18: 153 | D18: 139 | E18: 79.433735 | F18: 10 | G18: 0 | H18: 0.048192771
A19: /criminal-defense-attorney-in-texas | B19: 137 | C19: 115 | D19: 105 | E19: 60.335766 | F19: 72 | G19: 0 | H19: 0.10218978
A20: /texas/locations/pearland | B20: 121 | C20: 106 | D20: 94 | E20: 55.801653 | F20: 9 | G20: 0 | H20: 0.049586777
A21: /peggy-bittick | B21: 111 | C21: 99 | D21: 93 | E21: 46.81982 | F21: 9 | G21: 0 | H21: 0.054054054
A22: /2020/10/29/how-to-tell-if-youre-too-drunk-to-drive-and-how-to-prevent-yourself-from-becoming-a-drunk-driver | B22: 108 | C22: 97 | D22: 97 | E22: 32.361111 | F22: 3 | G22: 0 | H22: 0.027777778
... A416: /why-do-you-need-a-divorce-lawyer | B416: 1 | C416: 1 | D416: 1 | E416: 1 | F416: 0 | G416: 0 | H416: 0

Sheet P3m_search_console
A1: Address | B1: Status Code | C1: Title 1 | D1: Indexability | E1: Indexability Status | F1: Clicks | G1: Impressions | H1: CTR | I1: Position
A2: https://sbrownlawyer.com/ | B2: 200 | C2: Scott M. Brown & Associates | Family, Criminal & Injury Law Firm in Texas | D2: Indexable | F2: 524 | G2: 80635 | H2: 0.006 | I2: 37.31
A3: https://sbrownlawyer.com/areas-we-serve/brazoria-county/ | B3: 200 | C3: Brazoria County Divorce & Family Lawyers | Scott M. Brown & Associates | D3: Indexable
A4: https://sbrownlawyer.com/careers/ | B4: 200 | C4: Careers | Scott M. Brown & Associates | D4: Indexable | F4: 12 | G4: 513 | H4: 0.023 | I4: 28.85
A5: https://sbrownlawyer.com/debt-division/ | B5: 200 | C5: Debt Division Attorney | Angleton, Texas | D5: Indexable | F5: 3 | G5: 369 | H5: 0.008 | I5: 40.8
A6: https://sbrownlawyer.com/texas/locations/pearland/ | B6: 200 | C6: Pearland Divorce & Family Lawyers | Scott M. Brown & Associates | D6: Indexable | F6: 32 | G6: 18552 | H6: 0.002 | I6: 15.75
A7: https://sbrownlawyer.com/texas/locations/angleton/ | B7: 200 | C7: Angleton Divorce & Family Lawyers | Scott M. Brown & Associates | D7: Indexable | F7: 12 | G7: 8520 | H7: 0.001 | I7: 8.14
A8: https://sbrownlawyer.com/areas-we-serve/galveston-county/ | B8: 200 | C8: Galveston County Divorce & Family Lawyers | Scott M. Brown & Associates | D8: Indexable
A9: https://sbrownlawyer.com/gray-divorce/ | B9: 200 | C9: Texas Gray Divorce Attorney | Angleton, TX | D9: Indexable | F9: 0 | G9: 2258 | H9: 0 | I9: 20.52
A10: https://sbrownlawyer.com/modifications/ | B10: 200 | C10: Child Custody Modification in Texas | Scott M. Brown & Associates | D10: Indexable | F10: 0 | G10: 1909 | H10: 0 | I10: 55.09
A11: https://sbrownlawyer.com/prenuptial-agreements/ | B11: 200 | C11: Prenuptial & Postnuptial Agreements in Texas | Scott M. Brown & Associates | D11: Indexable | F11: 2 | G11: 4557 | H11: 0 | I11: 56.25
A12: https://sbrownlawyer.com/blog/ | B12: 200 | C12: Family Law Blog | Scott M. Brown & Associates | D12: Indexable | F12: 1 | G12: 198 | H12: 0.005 | I12: 7.8
A13: https://sbrownlawyer.com/protective-services/ | B13: 200 | C13: Child Protective Services Lawyers Pearland | CPS Attorneys | D13: Indexable | F13: 5 | G13: 4247 | H13: 0.001 | I13: 46.16
A14: https://sbrownlawyer.com/2024/07/08/open-vs-closed-aoption-angleton-texas/ | B14: 200 | C14: Understanding Open vs. Closed Adoption | Angleton, TX | D14: Indexable | F14: 1 | G14: 4029 | H14: 0 | I14: 39.37
A15: https://sbrownlawyer.com/immigration/ | B15: 301 | D15: Non-Indexable | E15: Redirected
A16: https://sbrownlawyer.com/divorce/ | B16: 200 | C16: Divorce in Texas | Scott M. Brown & Associates | D16: Indexable | F16: 24 | G16: 18218 | H16: 0.001 | I16: 23.86
A17: https://sbrownlawyer.com/lgbtq-divorce/ | B17: 200 | C17: LGBTQ Divorce Lawyer | Pearland, Texas | D17: Indexable | F17: 0 | G17: 2119 | H17: 0 | I17: 49.74
A18: https://sbrownlawyer.com/privacy-policy | B18: 301 | D18: Non-Indexable | E18: Redirected | F18: 0 | G18: 36 | H18: 0 | I18: 14
A19: https://sbrownlawyer.com/adoption/ | B19: 200 | C19: Adoption in Texas | Scott M. Brown & Associates | D19: Indexable | F19: 3 | G19: 20165 | H19: 0 | I19: 54.19
A20: https://sbrownlawyer.com/disclaimer/ | B20: 200 | C20: Disclaimer | Scott M. Brown & Associates | D20: Indexable | F20: 0 | G20: 175 | H20: 0 | I20: 5.09
A21: https://sbrownlawyer.com/texas/locations/league-city/ | B21: 200 | C21: League City Divorce & Family Lawyers | Scott M. Brown & Associates | D21: Indexable | F21: 8 | G21: 7349 | H21: 0.001 | I21: 19.04
A22: https://sbrownlawyer.com/areas-we-serve/matagorda-county/ | B22: 200 | C22: Matagorda County Family Law & Divorce Lawyers | Scott M. Brown & Associates | D22: Indexable
A23: https://sbrownlawyer.com/case-results/ | B23: 200 | C23: Successful Case Results from Houston, Texas | D23: Indexable | F23: 1 | G23: 110 | H23: 0.009 | I23: 20.55
A24: https://sbrownlawyer.com/news/ | B24: 200 | C24: In the News | Scott M. Brown & Associates | D24: Indexable | F24: 10 | G24: 206 | H24: 0.049 | I24: 8.12
A25: https://sbrownlawyer.com/attorneys-working-to-achieve-your-alimony-goals/ | B25: 200 | C25: Alimony in Texas | Scott M. Brown & Associates | D25: Indexable | F25: 3 | G25: 1731 | H25: 0.002 | I25: 16.36
A26: https://sbrownlawyer.com/business-owner-divorce/ | B26: 200 | C26: Business Owner Property Division in Texas | Scott M. Brown & Associates | D26: Indexable | F26: 0 | G26: 3324 | H26: 0 | I26: 46.5
A27: https://sbrownlawyer.com/Scott-M-Brown/ | B27: 200 | C27: Divorce & Family Law Attorney Scott M. Brown | Scott M. Brown & Associates | D27: Non-Indexable | E27: Canonicalised
A28: https://sbrownlawyer.com/child-support/child-support-modifications/ | B28: 200 | C28: Child Support Modifications | Angleton Modification Attorney | D28: Indexable | F28: 2 | G28: 508 | H28: 0.004 | I28: 40.58
A29: https://sbrownlawyer.com/criminal-defense-videos/ | B29: 200 | C29: Criminal Defense Videos | Scott M. Brown & Associates | D29: Indexable | F29: 1 | G29: 821 | H29: 0.001 | I29: 14.37
A30: https://sbrownlawyer.com/personal-injury-videos/ | B30: 200 | C30: Personal Injury videos | Scott M. Brown & Associates | D30: Indexable | F30: 0 | G30: 263 | H30: 0 | I30: 37.61
A31: https://sbrownlawyer.com/criminal-defense-book/ | B31: 200 | C31: Criminal Defense Book | Scott M. Brown & Associates | D31: Indexable | F31: 6 | G31: 1642 | H31: 0.004 | I31: 32.98
A32: https://sbrownlawyer.com/child-custody/ | B32: 200 | C32: Child Custody in Texas | Scott M. Brown & Associates | D32: Indexable | F32: 9 | G32: 28578 | H32: 0 | I32: 55.46
A33: https://sbrownlawyer.com/enforcement/ | B33: 200 | C33: Child Support Enforcement in Texas | Scott M. Brown & Associates | D33: Indexable | F33: 1 | G33: 823 | H33: 0.001 | I33: 45.06
A34: https://sbrownlawyer.com/contact/ | B34: 200 | C34: Contact Scott M. Brown | Angleton, Pearland and League City | D34: Indexable | F34: 32 | G34: 26598 | H34: 0.001 | I34: 9.37
A35: https://sbrownlawyer.com/personal-injury/ | B35: 200 | C35: Personal Injury Lawyers Protecting Texans | Scott M. Brown & Associates | D35: Indexable | F35: 1 | G35: 22128 | H35: 0 | I35: 48.57
A36: https://sbrownlawyer.com/cohabitation/ | B36: 200 | C36: Cohabitation Agreement Texas | Pearland, TX | D36: Indexable | F36: 10 | G36: 6114 | H36: 0.002 | I36: 31.48
A37: https://sbrownlawyer.com/paternity-attorney/ | B37: 200 | C37: Pearland Paternity Lawyers | Scott M. Brown & Associates | D37: Indexable | F37: 0 | G37: 4461 | H37: 0 | I37: 14.78
A38: https://sbrownlawyer.com/testimonials/ | B38: 200 | C38: Client Reviews | Scott M. Brown & Associates | D38: Indexable | F38: 19 | G38: 580 | H38: 0.033 | I38: 11.27
A39: https://sbrownlawyer.com/areas-we-serve/ | B39: 200 | C39: Texas Family Law Service Areas | Scott M. Brown & Associates | D39: Indexable | F39: 6 | G39: 979 | H39: 0.006 | I39: 38.32
... A41: https://sbrownlawyer.com/videos-5/ | B41: 200 | C41: Videos | Scott M. Brown & Associates | | D41: Indexable | F41: 0 | G41: 153 | H41: 0 | I41: 19.27
A42: https://sbrownlawyer.com/areas-we-serve/harris-county/ | B42: 200 | C42: Harris County Divorce & Family Lawyers | Scott M. Brown & Associates | D42: Indexable
A43: https://sbrownlawyer.com/areas-we-serve/fort-bend-county/ | B43: 200 | C43: Fort Bend County Family Law & Divorce Lawyers | Scott M. Brown & Associates | D43: Indexable
A44: https://sbrownlawyer.com/criminal-defense/ | B44: 200 | C44: Criminal Defense Lawyers | Angleton, Pearland, League City, Houston | Scott M. Brown & Associates | D44: Indexable
A45: https://sbrownlawyer.com/attorneys/ | B45: 200 | C45: Texas Family Law & Divorce Lawyers | Scott M. Brown & Associates | D45: Indexable | F45: 101 | G45: 34633 | H45: 0.003 | I45: 19.69
A46: https://sbrownlawyer.com/terms-of-service | B46: 301 | D46: Non-Indexable | E46: Redirected | F46: 0 | G46: 8 | H46: 0 | I46: 75.13
A47: https://sbrownlawyer.com/criminal-law/ | B47: 200 | C47: Criminal Defense | Criminal Defense Lawyer | Pearland, Texas | D47: Non-Indexable | E47: Canonicalised,noindex
A48: https://sbrownlawyer.com/estate-planning-probate/ | B48: 200 | C48: Texas Estate Planning Lawyers | Scott M. Brown & Associates | D48: Indexable
A49: https://sbrownlawyer.com/grandparents-rights/ | B49: 200 | C49: Grandparents' Visitation Rights in Texas | Scott M. Brown & Associates | D49: Indexable | F49: 0 | G49: 1651 | H49: 0 | I49: 27.63
A50: https://sbrownlawyer.com/division-of-property/ | B50: 200 | C50: Property Division in Texas | Scott M. Brown & Associates | D50: Indexable | F50: 5 | G50: 577 | H50: 0.009 | I50: 29.67
A51: https://sbrownlawyer.com/divorce-modification/ | B51: 200 | C51: Modifying a Divorce Decree in Texas | Scott M. Brown & Associates | D51: Indexable | F51: 0 | G51: 4220 | H51: 0 | I51: 19.41
A52: https://sbrownlawyer.com/privacy-policy/ | B52: 200 | C52: Privacy Policy | Scott M. Brown, P.C. | Pearland, Texas | D52: Indexable | F52: 0 | G52: 36 | H52: 0 | I52: 14
A53: https://sbrownlawyer.com/asset-division/ | B53: 200 | C53: Texas Property and Asset Division | Texas | D53: Indexable | F53: 1 | G53: 10688 | H53: 0 | I53: 51.62
A54: https://sbrownlawyer.com/immigration-videos/ | B54: 301 | D54: Non-Indexable | E54: Redirected | F54: 4 | G54: 7757 | H54: 0 | I54: 54.99
A55: https://sbrownlawyer.com/client-video-testimonials/ | B55: 200 | C55: Client Video Testimonials | Scott M. Brown & Associates | D55: Indexable | F55: 0 | G55: 185 | H55: 0 | I55: 60.18
A56: https://sbrownlawyer.com/high-net-worth-divorce/ | B56: 200 | C56: High-Net-Worth Divorces in Texas | Scott M. Brown & Associates | D56: Indexable | F56: 0 | G56: 411 | H56: 0 | I56: 72.81
A57: https://sbrownlawyer.com/texas/locations/sugar-land/ | B57: 200 | C57: Sugar Land Divorce & Family Lawyers | Scott M. Brown & Associates | D57: Indexable
A58: https://sbrownlawyer.com/family-law/visitation/ | B58: 200 | C58: Child Visitation Attorneys | Pearland & Angleton, TX | D58: Indexable | F58: 0 | G58: 695 | H58: 0 | I58: 19.4
A59: https://sbrownlawyer.com/texas-family-law-attorney/ | B59: 200 | C59: Texas Family Law | Scott M. Brown & Associates | D59: Indexable | F59: 1 | G59: 2402 | H59: 0 | I59: 9.44
A60: https://sbrownlawyer.com/2024/03/26/grandparent-custody-rights/ | B60: 200 | C60: Grandparents’ Custody Rights in Texas | Houston, TX | D60: Indexable | F60: 6 | G60: 6072 | H60: 0.001 | I60: 40.82
A61: https://sbrownlawyer.com/texas/locations/ | B61: 200 | C61: Texas Family Law Office Locations | Scott M. Brown & Associates | D61: Indexable | F61: 0 | G61: 300 | H61: 0 | I61: 11.19
A62: https://sbrownlawyer.com/2024/04/24/texas-alimony-am-i-entitled/ | B62: 200 | C62: Am I Entitled to Spousal Support? | Pearland, TX | D62: Indexable | F62: 201 | G62: 50323 | H62: 0.004 | I62: 12.56
A63: https://sbrownlawyer.com/doctor-divorce-videos/ | B63: 200 | C63: Doctor Divorce Videos | Scott M. Brown & Associates | D63: Indexable | F63: 1 | G63: 680 | H63: 0.002 | I63: 12.57
A64: https://sbrownlawyer.com/divorce-book/ | B64: 200 | C64: The Divorce Book in Angleton, TX | Step By Step Guide | D64: Indexable | F64: 0 | G64: 118 | H64: 0 | I64: 36.74
A65: https://sbrownlawyer.com/firm-overview/ | B65: 200 | C65: Our Story | Scott M. Brown & Associates | D65: Indexable | F65: 11 | G65: 9362 | H65: 0.001 | I65: 20.33
A66: https://sbrownlawyer.com/postnuptial-agreements/ | B66: 200 | C66: Postnuptial Agreement Attorney | Pearland, TX | D66: Indexable | F66: 2 | G66: 3986 | H66: 0 | I66: 49.6
A67: https://sbrownlawyer.com/personal-injury-in-texas/boat-accidents/ | B67: 200 | C67: Boat Accidents Attorney | Angleton, TX | D67: Indexable | F67: 1 | G67: 3147 | H67: 0 | I67: 75.74
A68: https://sbrownlawyer.com/areas-we-serve/brazoria-county/freeport/ | B68: 200 | C68: Family Lawyer in Freeport | Scott M. Brown & Associates | D68: Indexable
A69: https://sbrownlawyer.com/areas-we-serve/brazoria-county/clute/ | B69: 200 | C69: Family Lawyer in Clute | Scott M. Brown & Associates | D69: Indexable
A70: https://sbrownlawyer.com/areas-we-serve/brazoria-county/lake-jackson/ | B70: 200 | C70: Family Lawyer in Lake Jackson | Scott M. Brown & Associates | D70: Indexable
A71: https://sbrownlawyer.com/traumatic-brain-injury/ | B71: 200 | C71: Traumatic Brain Injury Lawyer in Pearland | TBI Attorney | D71: Indexable | F71: 0 | G71: 6658 | H71: 0 | I71: 38.93
A72: https://sbrownlawyer.com/personal-injury-2/nonvehicle-liability-insurance/ | B72: 200 | C72: Non-Vehicle Liability Insurance Attorneys | Pearland, TX | D72: Indexable
A73: https://sbrownlawyer.com/head-injury/ | B73: 200 | C73: Head Injury in Texas | Head Injury Attorney | Houston, Texas | D73: Indexable | F73: 1 | G73: 4060 | H73: 0 | I73: 62.19
A74: https://sbrownlawyer.com/criminal-law/indecent-exposure/ | B74: 200 | C74: Indecent Exposure | Indecent Exposure Attorney | Houston, TX | D74: Indexable | F74: 2 | G74: 6529 | H74: 0 | I74: 42.52
A75: https://sbrownlawyer.com/truck-accident/ | B75: 200 | C75: Truck Accidents | Truck Accident Attorneys | Pearland, Texas | D75: Indexable | F75: 0 | G75: 3120 | H75: 0 | I75: 51.64
A76: https://sbrownlawyer.com/uber-lyft-accidents/ | B76: 200 | C76: Angleton Uber Accident Lawyer | Angleton, TX | D76: Indexable | F76: 0 | G76: 8130 | H76: 0 | I76: 69.95
A77: https://sbrownlawyer.com/rape-sexual-assault/ | B77: 200 | C77: Sexual Assault Lawyers Pearland Tx | Rape & Sexual Assault | D77: Indexable | F77: 2 | G77: 5405 | H77: 0 | I77: 44.35
A78: https://sbrownlawyer.com/premises-liability/ | B78: 200 | C78: Houston Premises Liability Attorney | Premises Liability | D78: Indexable | F78: 1 | G78: 7853 | H78: 0 | I78: 47.7
A79: https://sbrownlawyer.com/motorcycle-accident/ | B79: 200 | C79: Motorcycle Accidents | Texas Motorcycle Accident Lawyer | D79: Indexable | F79: 0 | G79: 3989 | H79: 0 | I79: 48.27
A80: https://sbrownlawyer.com/drug-crimes/ | B80: 200 | C80: Drug Crimes | Drug Crimes Attorney | Houston, Texas | D80: Indexable | F80: 0 | G80: 10380 | H80: 0 | I80: 60.68
A81: https://sbrownlawyer.com/aggravated-sexual-assault/ | B81: 200 | C81: Houston Aggravated Sexual Assault Attorney | Houston, Texas | D81: Indexable | F81: 1 | G81: 4046 | H81: 0 | I81: 67.2
A82: https://sbrownlawyer.com/product-liability/ | B82: 200 | C82: Product Liability Attorneys | Pearland, Texas | D82: Indexable | F82: 1 | G82: 2304 | H82: 0 | I82: 62.27
A83: https://sbrownlawyer.com/assault/ | B83: 200 | C83: Assault | Assault Attorney | Houston, Texas | D83: Indexable | F83: 0 | G83: 4287 | H83: 0 | I83: 65.68
A84: https://sbrownlawyer.com/vehicular-accidents/ | B84: 200 | C84: Houston TX Vehicular Accidents Attorney |Houston, TX | D84: Indexable | F84: 1 | G84: 4001 | H84: 0 | I84: 71.26
... A89: https://sbrownlawyer.com/title-ix-defense-campus-sexual-assault/ | B89: 200 | C89: Houston Campus Sexual Assault Attorney | Sexual Assault Lawyer | D89: Indexable | F89: 1 | G89: 15445 | H89: 0 | I89: 49.94
A90: https://sbrownlawyer.com/areas-we-serve/brazoria-county/alvin/ | B90: 200 | C90: Family Lawyer in Alvin | Scott M. Brown & Associates | D90: Indexable
A91: https://sbrownlawyer.com/health-coverage-accident-claims/ | B91: 200 | C91: Health Coverage and Accident Claims | Scott M. Brown & Associates | D91: Indexable | F91: 5 | G91: 508 | H91: 0.01 | I91: 46.84
A92: https://sbrownlawyer.com/hiring-sexual-assault-defense-lawyer/ | B92: 200 | C92: Hiring A Sexual Assault Defense Lawyer | Pearland, TX | D92: Indexable | F92: 2 | G92: 12093 | H92: 0 | I92: 41.65
A93: https://sbrownlawyer.com/steps-in-settling-your-claim-in-texas/ | B93: 200 | C93: Steps in Settling Your Claim in Texas | Houston, Texas | D93: Indexable | F93: 10 | G93: 7126 | H93: 0.001 | I93: 63.27
A94: https://sbrownlawyer.com/date-rape/ | B94: 200 | C94: Webster Date Rape Lawyer | Date Rape Attorney | Webster, TX | D94: Indexable | F94: 1 | G94: 1845 | H94: 0 | I94: 47.06
A95: https://sbrownlawyer.com/what-is-dwi/ | B95: 200 | C95: DWI | dwi attorney | Houston, Texas | D95: Indexable | F95: 1 | G95: 2849 | H95: 0 | I95: 49.13
A96: https://sbrownlawyer.com/child-pornography/ | B96: 200 | C96: Child Pornography | Child Pornography Attorney | Houston, TX | D96: Indexable | F96: 12 | G96: 9472 | H96: 0.001 | I96: 36.06
A97: https://sbrownlawyer.com/sex-crimes/sex-offender-registration/ | B97: 200 | C97: Sex Offender Registration Lawyer | Pearland, Texas | D97: Indexable | F97: 12 | G97: 955 | H97: 0.013 | I97: 33.55
A98: https://sbrownlawyer.com/back-injury/ | B98: 200 | C98: Back Injury in Texas | Back Injury Attorneys | Houston,TX | D98: Indexable | F98: 0 | G98: 5433 | H98: 0 | I98: 50.12
A99: https://sbrownlawyer.com/slip-and-fall-accidents/ | B99: 200 | C99: Slip and Fall Accidents in Texas | Houston, Texas | D99: Indexable | F99: 10 | G99: 51944 | H99: 0 | I99: 55.54
A100: https://sbrownlawyer.com/domestic-violence-attorney/ | B100: 200 | C100: Domestic Violence & Protection Orders in Texas | Scott M. Brown & Associates | D100: Indexable | F100: 0 | G100: 12315 | H100: 0 | I100: 44.78
A101: https://sbrownlawyer.com/consular-processing-pearland-lawyer/ | B101: 200 | C101: Trusted Visa Approval Help | Pearland Consular Processing | D101: Indexable | F101: 0 | G101: 739 | H101: 0 | I101: 38.65
A102: https://sbrownlawyer.com/paralysis/ | B102: 200 | C102: Texas Paralysis Attorney | Scott M. Brown & Associates | D102: Indexable | F102: 2 | G102: 4415 | H102: 0 | I102: 29.69
A103: https://sbrownlawyer.com/internet-sex-crimes/ | B103: 200 | C103: What To Know About Internet Sex Crimes in Texas | Angleton | D103: Indexable | F103: 5 | G103: 2128 | H103: 0.002 | I103: 43.49
A104: https://sbrownlawyer.com/personal-injury-2/burn-injury/ | B104: 200 | C104: Burn Injury | Burn Injury Attorneys | Pearland, TX | D104: Indexable
A105: https://sbrownlawyer.com/misdemeanor/ | B105: 200 | C105: Misdemeanor Attorney in Pearland, TX | Pearland, TX | D105: Indexable | F105: 1 | G105: 2453 | H105: 0 | I105: 28.97
...

Sheet L3M_LY_search_console
A1: Top pages | B1: Clicks | C1: Impressions | D1: CTR | E1: Position
A2: https://sbrownlawyer.com/2024/03/20/texas-child-support-2024/ | B2: 884 | C2: 35502 | D2: 0.0249 | E2: 17.34
A3: https://sbrownlawyer.com/2024/04/24/texas-alimony-am-i-entitled/ | B3: 703 | C3: 60150 | D3: 0.0117 | E3: 16.34
A4: https://sbrownlawyer.com/ | B4: 240 | C4: 34304 | D4: 0.007 | E4: 33.63
A5: https://sbrownlawyer.com/2020/10/29/how-to-tell-if-youre-too-drunk-to-drive-and-how-to-prevent-yourself-from-becoming-a-drunk-driver/ | B5: 240 | C5: 19912 | D5: 0.0121 | E5: 14.7
A6: https://sbrownlawyer.com/2024/05/28/impact-of-a-criminal-record-on-child-custody-cases/ | B6: 208 | C6: 11613 | D6: 0.0179 | E6: 9.85
A7: https://sbrownlawyer.com/2020/01/05/texas-passes-new-law-for-assault-on-a-pregnant-woman/ | B7: 200 | C7: 6224 | D7: 0.0321 | E7: 10.28
A8: https://sbrownlawyer.com/criminal-law/first-offenders/ | B8: 149 | C8: 6710 | D8: 0.0222 | E8: 24.02
A9: http://www.sbrownlawyer.com/?utm_campaign=gmbangleton | B9: 137 | C9: 12645 | D9: 0.0108 | E9: 6.6
A10: https://sbrownlawyer.com/2021/04/07/reasons-grandparents-can-file-for-custody-of-grandchild-in-texas/ | B10: 130 | C10: 9497 | D10: 0.0137 | E10: 31.23
A11: https://sbrownlawyer.com/scott-m-brown/ | B11: 114 | C11: 5771 | D11: 0.0198 | E11: 17.88
A12: https://sbrownlawyer.com/2018/04/06/can-you-adopt-a-child-in-texas-without-the-biological-fathers-consent/ | B12: 112 | C12: 4007 | D12: 0.028 | E12: 33.38
A13: http://www.sbrownlawyer.com/?utm_campaign=gmbpearland | B13: 89 | C13: 4336 | D13: 0.0205 | E13: 7.29
... A834: https://sbrownlawyer.com/2019/08/01/7-common-texas-dwi-myths-busted/ | B834: 0 | C834: 1 | D834: 0 | E834: 155

Sheet L3M_LY_analytics
A1: # ----------------------------------------
A2: # Landing page: Landing page
A3: # Account: Scott M Brown and Associates
A4: # Property: sbrownlawyer.com
A5: # ----------------------------------------
A6: #
A7: # All Users
A8: # Start date: 20241022
A9: # End date: 20250121
A10: Landing page | B10: Sessions | C10: Active users | D10: New users | E10: Average engagement time per session | F10: Key events | G10: Total revenue | H10: Session key event rate
A11: /f1p6mlb1g | B11: 17758 | C11: 16494 | D11: 16452 | E11: 1.6744003 | F11: 75 | G11: 0 | H11: 0.0038855727
A12: / | B12: 15089 | C12: 9799 | D12: 9702 | E12: 9.6199881 | F12: 882 | G12: 0 | H12: 0.018158924
A13: /careers | B13: 2323 | C13: 1964 | D13: 1955 | E13: 2.795523 | F13: 6 | G13: 0 | H13: 0.0012914335
A14: /divorce | B14: 2218 | C14: 2210 | D14: 2202 | E14: 32.194319 | F14: 66 | G14: 0 | H14: 0.013525699
A15: /spanish-lp | B15: 1655 | C15: 1543 | D15: 1529 | E15: 18.338369 | F15: 318 | G15: 0 | H15: 0.038670695
A16: /2024/03/20/texas-child-support-2024 | B16: 1347 | C16: 1238 | D16: 1234 | E16: 64.042316 | F16: 126 | G16: 0 | H16: 0.037119525
A17: (not set) | B17: 907 | C17: 2531 | D17: 1 | E17: 430.2613 | F17: 1275 | G17: 0 | H17: 0.022050717
A18: /2024/04/24/texas-alimony-am-i-entitled | B18: 828 | C18: 740 | D18: 738 | E18: 86.422705 | F18: 68 | G18: 0 | H18: 0.032608696
A19: /criminal-defense-attorney-in-texas | B19: 578 | C19: 498 | D19: 483 | E19: 8.4532872 | F19: 75 | G19: 0 | H19: 0.039792388
A20: /contact | B20: 505 | C20: 477 | D20: 455 | E20: 13.419802 | F20: 76 | G20: 0 | H20: 0.067326733
A21: /personal-injury-in-texas | B21: 482 | C21: 430 | D21: 418 | E21: 4.5352697 | F21: 27 | G21: 0 | H21: 0.024896266
A22: /general-family-law-lp | B22: 449 | C22: 395 | D22: 386 | E22: 21.396437 | F22: 148 | G22: 0 | H22: 0.048997773
... A449: /why-do-you-need-a-divorce-lawyer | B449: 1 | C449: 1 | D449: 0 | E449: 40 | F449: 0 | G449: 0 | H449: 0

Sheet semrush_keywords
A1: Keyword | B1: Position | C1: Search Volume | D1: URL | E1: Previous position | F1: Keyword Difficulty | G1: CPC | H1: Traffic | I1: Traffic (%) | J1: Traffic Cost | K1: Competition | L1: Number of Results | M1: Trends | N1: Timestamp | O1: SERP Features by Keyword | P1: Keyword Intents | Q1: Position Type
A2: marc anthony daughter arianna | B2: 1 | C2: 110 | D2: https://sbrownlawyer.com/2014/06/20/lopez-anthony-divorce-has-interesting-child-custody-agreement/ | E2: 0 | F2: 23 | G2: 0 | H2: 0 | I2: 0 | J2: 0 | K2: 0 | L2: 78800 | M2: [54,29,35,18,14,18,18,14,14,18,18,29] | N2: 46043 | O2: Image pack, Video, Image, People also ask, Related searches, AI overview | P2: informational | Q2: People also ask
A3: texas divorce law spousal support | B3: 1 | C3: 40 | D3: https://sbrownlawyer.com/2024/04/24/texas-alimony-am-i-entitled/ | E3: 0 | F3: 20 | G3: 0.64 | H3: 1 | I3: 0.06 | J3: 0 | K3: 0.28 | L3: 549000 | M3: [15,19,19,34,26,15,11,15,11,11,15,11] | N3: 46042 | O3: Sitelinks, Video Carousel, People also ask, Related searches, Short videos, Things to know, Discussions and forums, AI overview | P3: informational | Q3: People also ask
A4: can prenup protect future earnings | B4: 1 | C4: 110 | D4: https://sbrownlawyer.com/2018/05/15/prenuptial-agreements-in-texas-what-they-do-do-not-protect/ | E4: 0 | F4: 5 | G4: 5.15 | H4: 0 | I4: 0 | J4: 0 | K4: 0.05 | L4: 34600 | M4: [52,66,42,66,42,52,33,42,52,42,33,42] | N4: 46042 | O4: Sitelinks, Video, People also ask, Related searches, Discussions and forums, AI overview | P4: informational | Q4: People also ask
A5: can i get spousal support in texas | B5: 1 | C5: 30 | D5: https://sbrownlawyer.com/2024/04/24/texas-alimony-am-i-entitled/ | E5: 0 | F5: 20 | G5: 2.01 | H5: 0 | I5: 0 | J5: 0 | K5: 0.44 | L5: 7500000 | M5: [7,15,7,15,11,15,19,7,15,15,11,7] | N5: 46042 | O5: Sitelinks, Video, People also ask, Related searches, Discussions and forums, AI overview | P5: informational | Q5: People also ask
A6: ariana marc anthony daughter | B6: 1 | C6: 70 | D6: https://sbrownlawyer.com/2014/06/20/lopez-anthony-divorce-has-interesting-child-custody-agreement/ | E6: 0 | F6: 23 | G6: 0 | H6: 0 | I6: 0 | J6: 0 | K6: 0 | L6: 859000 | M6: [42,34,42,26,19,19,19,26,26,42,26,42] | N6: 46042 | O6: Video, Image, People also ask, Related searches, AI overview | P6: informational | Q6: People also ask
A7: nadia ferreira and marc anthony | B7: 1 | C7: 90 | D7: https://sbrownlawyer.com/2014/06/20/lopez-anthony-divorce-has-interesting-child-custody-agreement/ | E7: 0 | F7: 24 | G7: 0 | H7: 0 | I7: 0 | J7: 0 | K7: 0 | L7: 1550000 | M7: [52,41,100,100,64,41,41,23,41,64,29,52] | N7: 46042 | O7: Image pack, Sitelinks, Video, Image, Video Carousel, People also ask, Related searches, Things to know | P7: informational | Q7: People also ask
A8: possession of firearm by felon texas | B8: 1 | C8: 50 | D8: https://sbrownlawyer.com/criminal-law/first-offenders/ | E8: 0 | F8: 16 | G8: 3.52 | H8: 0 | I8: 0 | J8: 0 | K8: 0.03 | L8: 1350000 | M8: [0,23,23,29,29,23,52,52,52,29,17,17] | N8: 46042 | O8: Sitelinks, Video, People also ask, Related searches, Short videos, AI overview | P8: informational | Q8: People also ask
A9: motion for bond reduction texas form | B9: 1 | C9: 30 | D9: https://sbrownlawyer.com/2018/04/23/how-do-bond-reductions-work/ | E9: 0 | F9: 7 | G9: 2.74 | H9: 0 | I9: 0 | J9: 0 | K9: 0.19 | L9: 4030000 | M9: [18,18,18,9,63,63,45,18,18,18,18,36] | N9: 46042 | O9: Image pack, People also ask, Related searches, AI overview | P9: informational | Q9: AI overview
A10: motion for bond reduction texas form | B10: 1 | C10: 30 | D10: https://sbrownlawyer.com/2018/04/23/how-do-bond-reductions-work/ | E10: 0 | F10: 7 | G10: 2.74 | H10: 1 | I10: 0.06 | J10: 2 | K10: 0.19 | L10: 4030000 | M10: [18,18,18,9,63,63,45,18,18,18,18,36] | N10: 46042 | O10: Image pack, People also ask, Related searches, AI overview | P10: informational | Q10: AI overview
A11: attorney angleton tx | B11: 1 | C11: 40 | D11: https://sbrownlawyer.com/texas/locations/angleton/?utm_campaign=gmbangleton | E11: 1 | F11: 36 | G11: 12.07 | H11: 9 | I11: 0.59 | J11: 108 | K11: 0.52 | L11: 63600 | M11: [36,18,45,18,18,9,18,36,81,9,100,100] | N11: 46041 | O11: Local pack, Image, Related searches | P11: commercial | Q11: Local pack
A12: alimony in texas divorce | B12: 1 | C12: 110 | D12: https://sbrownlawyer.com/2024/04/24/texas-alimony-am-i-entitled/ | E12: 1 | F12: 11 | G12: 0.92 | H12: 0 | I12: 0 | J12: 0 | K12: 0.37 | L12: 2370000 | M12: [42,42,80,80,52,42,42,52,33,33,66,42] | N12: 46041 | O12: Video, People also ask, Related searches, Things to know, AI overview | P12: informational | Q12: People also ask
A13: how many hours can you drive after drinking | B13: 1 | C13: 40 | D13: https://sbrownlawyer.com/2020/10/29/how-to-tell-if-youre-too-drunk-to-drive-and-how-to-prevent-yourself-from-becoming-a-drunk-driver/ | E13: 1 | F13: 18 | G13: 0 | H13: 0 | I13: 0 | J13: 0 | K13: 0.33 | L13: 848000000 | M13: [50,35,35,21,50,100,14,14,14,14,14,14] | N13: 46040 | O13: Sitelinks, Video, People also ask, Related searches, AI overview | P13: informational | Q13: People also ask
... A21: assault fv texas | B21: 1 | C21: 30 | D21: https://sbrownlawyer.com/criminal-law/first-offenders/ | E21: 1 | F21: 27 | G21: 5.58 | H21: 0 | I21: 0 | J21: 0 | K21: 0.08 | L21: 1700000 | M21: [9,19,9,14,19,9,9,9,14,14,23,42] | N21: 46038 | O21: Video, People also ask, Related searches, AI overview | P21: informational | Q21: People also ask
A22: family law pearland texas | B22: 1 | C22: 50 | D22: https://sbrownlawyer.com/texas/locations/pearland/?utm_campaign=gmbpearland | E22: 1 | G22: 16.24 | H22: 4 | I22: 0.26 | J22: 64 | K22: 0.67 | L22: 997000 | M22: [6,6,4,14,10,10,14,4,4,6,14,43] | N22: 46038 | O22: Local pack, Sitelinks, Video, Image, People also ask, Related searches | P22: commercial | Q22: Local pack
A23: does a prenup prevent alimony | B23: 1 | C23: 110 | D23: https://sbrownlawyer.com/2018/05/15/prenuptial-agreements-in-texas-what-they-do-do-not-protect/ | E23: 1 | F23: 8 | G23: 4.74 | H23: 0 | I23: 0 | J23: 0 | K23: 0.03 | L23: 509000 | M23: [26,34,34,42,65,34,53,53,100,53,42,19] | N23: 46038 | O23: Sitelinks, Video, People also ask, Related searches, AI overview | P23: informational | Q23: People also ask
A24: us citizenship and immigration services irving texas | B24: 1 | C24: 40 | D24: https://sbrownlawyer.com/2024/12/27/understanding-the-naturalization-timeline-for-texas-residents/ | E24: 1 | F24: 42 | G24: 3.36 | H24: 0 | I24: 0 | J24: 0 | K24: 0.05 | L24: 358000 | M24: [0,0,0,0,0,0,100,0,0,0,0,0] | N24: 46037 | O24: Knowledge panel, Sitelinks, Video, People also ask, Related searches | P24: navigational | Q24: People also ask
A25: marc anthony and dayanara torres | B25: 1 | C25: 50 | D25: https://sbrownlawyer.com/2014/06/20/lopez-anthony-divorce-has-interesting-child-custody-agreement/ | E25: 1 | F25: 18 | G25: 0 | H25: 0 | I25: 0 | J25: 0 | K25: 0 | L25: 183000 | M25: [19,14,23,0,19,4,19,23,23,19,42,52] | N25: 46036 | O25: Image pack, Video, Image, People also ask, Related searches | P25: informational | Q25: People also ask
A26: marc anthony joven | B26: 1 | C26: 260 | D26: https://sbrownlawyer.com/2014/06/20/lopez-anthony-divorce-has-interesting-child-custody-agreement/ | E26: 1 | G26: 0 | H26: 5 | I26: 0.33 | J26: 0 | K26: 0 | L26: 7650000 | M26: [20,16,13,24,13,10,10,10,10,10,30,24] | N26: 46036 | O26: Image pack, Video, Image, Video Carousel, People also ask, Related searches | P26: informational, transactional | Q26: People also ask
A27: recent pictures of jennifer lopez twins | B27: 1 | C27: 40 | D27: https://sbrownlawyer.com/2014/06/20/lopez-anthony-divorce-has-interesting-child-custody-agreement/ | E27: 1 | F27: 32 | G27: 0 | H27: 0 | I27: 0 | J27: 0 | K27: 0.33 | L27: 12000000 | M27: [15,26,19,26,26,15,7,7,7,7,7,42] | N27: 46036 | O27: Image pack, Video, Image, Video Carousel, People also ask, Related searches | P27: informational, transactional | Q27: People also ask
A28: how long after drinking can drive | B28: 1 | C28: 390 | D28: https://sbrownlawyer.com/2020/10/29/how-to-tell-if-youre-too-drunk-to-drive-and-how-to-prevent-yourself-from-becoming-a-drunk-driver/ | E28: 1 | F28: 30 | G28: 0 | H28: 15 | I28: 0.99 | J28: 0 | K28: 0 | L28: 609000000 | M28: [7,23,12,15,23,54,100,67,19,19,67,67] | N28: 46036 | O28: Sitelinks, Video, People also ask, Related searches, Discussions and forums, AI overview | P28: informational | Q28: People also ask
A29: marc anthony age | B29: 1 | C29: 2400 | D29: https://sbrownlawyer.com/2014/06/20/lopez-anthony-divorce-has-interesting-child-custody-agreement/ | E29: 1 | F29: 42 | G29: 0 | H29: 0 | I29: 0 | J29: 0 | K29: 0 | L29: 137000000 | M29: [16,7,7,19,7,7,8,5,5,5,24,7] | N29: 46036 | O29: Instant answer, Knowledge panel, Image pack, Sitelinks, Video, Image, People also ask, Related searches | P29: informational | Q29: People also ask
A30: can my husband adopt my child | B30: 1 | C30: 260 | D30: https://sbrownlawyer.com/2018/04/06/can-you-adopt-a-child-in-texas-without-the-biological-fathers-consent/ | E30: 1 | F30: 13 | G30: 0 | H30: 8 | I30: 0.52 | J30: 0 | K30: 0 | L30: 83200000 | M30: [53,53,82,100,100,66,53,43,66,82,66,66] | N30: 46036 | O30: Sitelinks, Video, Video Carousel, People also ask, Related searches, Short videos, AI overview | P30: informational | Q30: People also ask
A31: felony theft in texas | B31: 1 | C31: 50 | D31: https://sbrownlawyer.com/criminal-law/first-offenders/ | E31: 1 | G31: 7.09 | H31: 0 | I31: 0 | J31: 0 | K31: 0.04 | L31: 7710000 | M31: [29,29,41,41,41,64,41,11,41,17,41,29] | N31: 46036 | O31: Sitelinks, Video, Video Carousel, People also ask, Related searches, AI overview | P31: informational | Q31: People also ask
A32: felony possession of a firearm texas | B32: 1 | C32: 110 | D32: https://sbrownlawyer.com/criminal-law/first-offenders/ | E32: 1 | F32: 19 | G32: 10.4 | H32: 0 | I32: 0 | J32: 0 | K32: 0.02 | L32: 2220000 | M32: [28,34,28,21,28,15,81,43,43,65,34,34] | N32: 46036 | O32: Video, Video Carousel, People also ask, Related searches, AI overview | P32: informational | Q32: People also ask
A33: assault with deadly weapon texas | B33: 1 | C33: 170 | D33: https://sbrownlawyer.com/criminal-law/first-offenders/ | E33: 1 | F33: 1 | G33: 4.5 | H33: 0 | I33: 0 | J33: 0 | K33: 0.12 | L33: 5050000 | M33: [22,29,35,54,22,29,22,35,66,29,29,35] | N33: 46036 | O33: Video, Video Carousel, People also ask, Related searches, AI overview | P33: informational | Q33: People also ask
A34: do prenups protect future assets | B34: 1 | C34: 50 | D34: https://sbrownlawyer.com/2018/05/15/prenuptial-agreements-in-texas-what-they-do-do-not-protect/ | E34: 1 | F34: 11 | G34: 0 | H34: 0 | I34: 0 | J34: 0 | K34: 0.05 | L34: 257000 | M34: [18,18,27,18,100,18,100,18,100,63,36,27] | N34: 46035 | O34: Sitelinks, Video, People also ask, Related searches, Discussions and forums, AI overview | P34: informational | Q34: People also ask
A35: does texas do alimony | B35: 1 | C35: 90 | D35: https://sbrownlawyer.com/2024/04/24/texas-alimony-am-i-entitled/ | E35: 1 | F35: 7 | G35: 0 | H35: 0 | I35: 0 | J35: 0 | K35: 0.03 | L35: 3200000 | M35: [41,41,41,41,100,64,64,52,64,64,52,41] | N35: 46035 | O35: Sitelinks, Video, Video Carousel, People also ask, Related searches, AI overview | P35: informational | Q35: People also ask
A36: jennifer lopez twins images | B36: 1 | C36: 50 | D36: https://sbrownlawyer.com/2014/06/20/lopez-anthony-divorce-has-interesting-child-custody-agreement/ | E36: 1 | F36: 31 | G36: 0 | H36: 1 | I36: 0.06 | J36: 0 | K36: 0.33 | L36: 7540000 | M36: [29,23,17,41,29,52,29,11,64,11,11,64] | N36: 46034 | O36: Image pack, Video, Image, Video Carousel, People also ask, Related searches | P36: informational, transactional | Q36: People also ask
A37: what did oliver anthony's wife get in the divorce | B37: 1 | C37: 50 | D37: https://sbrownlawyer.com/2014/06/20/lopez-anthony-divorce-has-interesting-child-custody-agreement/ | E37: 1 | F37: 23 | G37: 0 | H37: 0 | I37: 0 | J37: 0 | K37: 0.33 | L37: 6010000 | M37: [0,0,0,0,0,0,0,100,80,52,9,9] | N37: 46034 | O37: Image pack, Video, Image, Video Carousel, People also ask, Related searches, AI overview | P37: informational | Q37: People also ask
A38: marck an | B38: 1 | C38: 320 | D38: https://sbrownlawyer.com/2014/06/20/lopez-anthony-divorce-has-interesting-child-custody-agreement/ | E38: 1 | F38: 79 | G38: 0 | H38: 0 | I38: 0 | J38: 0 | K38: 0 | L38: 646000000 | M38: [54,0,0,100,0,0,0,0,0,0,0,0] | N38: 46033 | O38: Knowledge panel, Video, Image, Video Carousel, People also ask, Related searches | P38: informational, transactional | Q38: People also ask
A39: mike's hard lemonade margarita lime hard lemonade | B39: 1 | C39: 390 | D39: https://sbrownlawyer.com/2020/10/29/how-to-tell-if-youre-too-drunk-to-drive-and-how-to-prevent-yourself-from-becoming-a-drunk-driver/ | E39: 1 | F39: 17 | G39: 0 | H39: 0 | I39: 0 | J39: 0 | K39: 0 | L39: 366000 | M39: [100,0,0,0,0] | N39: 46033 | O39: Image pack, Sitelinks, Video, People also ask, Related searches, Short videos, AI overview | P39: commercial, informational | Q39: People also ask
A40: marc anthony film | B40: 1 | C40: 3600 | D40: https://sbrownlawyer.com/2014/06/20/lopez-anthony-divorce-has-interesting-child-custody-agreement/ | E40: 1 | F40: 61 | G40: 0 | H40: 0 | I40: 0 | J40: 0 | K40: 0 | L40: 116000000 | M40: [0,24,3,81,100,100,43,54,0,4,100,81] | N40: 46033 | O40: Knowledge panel, Video, Image, People also ask, Related searches | P40: informational | Q40: People also ask
A41: marc anthony tracks | B41: 1 | C41: 8100 | D41: https://sbrownlawyer.com/2014/06/20/lopez-anthony-divorce-has-interesting-child-custody-agreement/ | E41: 1 | F41: 55 | G41: 0 | H41: 0 | I41: 0 | J41: 0 | K41: 0 | L41: 24500000 | M41: [1,4,0,100,44,54,44,36,0,1,36,44] | N41: 46033 | O41: Knowledge panel, Video, Image, Video Carousel, People also ask, Related searches | P41: informational | Q41: People also ask
A42: jlo and marc anthony | B42: 1 | C42: 590 | D42: https://sbrownlawyer.com/2014/06/20/lopez-anthony-divorce-has-interesting-child-custody-agreement/ | E42: 1 | F42: 41 | G42: 0 | H42: 0 | I42: 0 | J42: 0 | K42: 0 | L42: 5050000 | M42: [8,7,7,7,5,4,5,4,4,7,19,19] | N42: 46033 | O42: Image pack, Video, Image, Video Carousel, People also ask, Related searches, Things to know, Discussions and forums, AI overview | P42: informational | Q42: People also ask
A43: marc anthony marc | B43: 1 | C43: 33100 | D43: https://sbrownlawyer.com/2014/06/20/lopez-anthony-divorce-has-interesting-child-custody-agreement/ | E43: 1 | F43: 82 | G43: 0.43 | H43: 0 | I43: 0 | J43: 0 | K43: 0 | L43: 112000000 | M43: [0,0,0,13,100,55,55,67,0,1,30,16] | N43: 46032 | O43: Knowledge panel, Video, Image, Video Carousel, People also ask, Related searches | P43: informational, transactional | Q43: People also ask
... A54: is there a cap on child support in texas | B54: 1 | C54: 90 | D54: https://sbrownlawyer.com/2024/03/20/texas-child-support-2024/ | E54: 1 | F54: 9 | G54: 0 | H54: 0 | I54: 0 | J54: 0 | K54: 0 | L54: 301000000 | M54: [34,34,42,53,53,42,34,26,26,26,53,34] | N54: 46028 | O54: Video, People also ask, Related searches, Short videos, AI overview | P54: informational | Q54: People also ask
A55: reckless driving charges | B55: 1 | C55: 170 | D55: https://sbrownlawyer.com/reckless-driving/ | E55: 1 | G55: 5.26 | H55: 0 | I55: 0 | J55: 0 | K55: 0.04 | L55: 13400000 | M55: [100,3,1,1,1,0,5,5,7,2,26,39] | N55: 46028 | O55: People also ask, Related searches, AI overview | P55: informational | Q55: People also ask
A56: examples of reckless driving | B56: 1 | C56: 110 | D56: https://sbrownlawyer.com/reckless-driving/ | E56: 1 | G56: 0 | H56: 0 | I56: 0 | J56: 0 | K56: 0 | L56: 8600000 | M56: [64,52,52,82,82,82,64,52,41,52,100,64] | N56: 46028 | O56: Sitelinks, Video, Video Carousel, People also ask, Related searches, AI overview | P56: informational | Q56: People also ask
A57: marc anthony and jennifer lopez wedding | B57: 1 | C57: 90 | D57: https://sbrownlawyer.com/2014/06/20/lopez-anthony-divorce-has-interesting-child-custody-agreement/ | E57: 1 | F57: 28 | G57: 0 | H57: 0 | I57: 0 | J57: 0 | K57: 0 | L57: 488000 | M57: [17,23,28,17,28,17,23,23,17,17,28,35] | N57: 46028 | O57: Image pack, Video, Image, People also ask, Discussions and forums, AI overview | P57: informational | Q57: People also ask
A58: child support process in texas | B58: 1 | C58: 110 | D58: https://sbrownlawyer.com/2024/03/20/texas-child-support-2024/ | E58: 1 | F58: 40 | G58: 0 | H58: 0 | I58: 0 | J58: 0 | K58: 0 | L58: 236000000 | M58: [15,23,5,15,18,23,18,18,23,23,18,11] | N58: 46028 | O58: Sitelinks, Video, People also ask, Related searches, AI overview | P58: informational | Q58: People also ask
A59: carmelo and lala divorce | B59: 1 | C59: 90 | D59: https://sbrownlawyer.com/2014/06/20/lopez-anthony-divorce-has-interesting-child-custody-agreement/ | E59: 1 | F59: 39 | G59: 0 | H59: 1 | I59: 0.06 | J59: 0 | K59: 0 | L59: 15200 | M59: [34,15,15,15,21,21,28,28,28,28,81,28] | N59: 46028 | O59: Sitelinks, Video, Image, Video Carousel, People also ask, Related searches, Short videos, AI overview | P59: informational | Q59: People also ask
A60: what's indecent exposure | B60: 1 | C60: 90 | D60: https://sbrownlawyer.com/criminal-law/indecent-exposure/ | E60: 1 | F60: 39 | G60: 0 | H60: 0 | I60: 0 | J60: 0 | K60: 0 | L60: 8350000 | M60: [14,14,14,78,0,78,78,78,64,100,78,100] | N60: 46028 | O60: Video, Video Carousel, People also ask, Related searches, AI overview | P60: informational | Q60: People also ask
A61: child support laws texas | B61: 1 | C61: 70 | D61: https://sbrownlawyer.com/2024/03/20/texas-child-support-2024/ | E61: 1 | F61: 39 | G61: 0 | H61: 1 | I61: 0.06 | J61: 0 | K61: 0 | L61: 137000000 | M61: [35,28,50,50,50,50,50,35,50,64,64,50] | N61: 46028 | O61: Sitelinks, Video, People also ask, Related searches, AI overview | P61: informational | Q61: People also ask
A62: grand theft in texas | B62: 1 | C62: 70 | D62: https://sbrownlawyer.com/grand-theft/ | E62: 1 | F62: 0 | G62: 0 | H62: 0 | I62: 0 | J62: 0 | K62: 0 | L62: 22100000 | M62: [29,29,41,41,41,41,41,41,41,52,29,41] | N62: 46028 | O62: Video, Video Carousel, People also ask, Related searches, AI overview | P62: informational | Q62: AI overview
A63: i love my husband but want a divorce | B63: 1 | C63: 30 | D63: https://sbrownlawyer.com/2020/06/16/accepting-divorce-our-advice-for-overcoming-grief-and-frustration/ | E63: 1 | G63: 1.14 | H63: 0 | I63: 0 | J63: 0 | K63: 0.27 | L63: 193000000 | M63: [17,23,17,17,17,17,17,5,29,17,23,29] | N63: 46028 | O63: Sitelinks, Video, Image, Ads bottom, Video Carousel, People also ask, Related searches, AI overview | P63: informational | Q63: People also ask
A64: end of marriage | B64: 1 | C64: 70 | D64: https://sbrownlawyer.com/2020/06/16/accepting-divorce-our-advice-for-overcoming-grief-and-frustration/ | E64: 1 | F64: 38 | G64: 1 | H64: 0 | I64: 0 | J64: 0 | K64: 0.14 | L64: 723000000 | M64: [17,41,41,41,82,52,11,17,41,52,23,29] | N64: 46027 | O64: Sitelinks, Video, Image, Video Carousel, People also ask, Related searches, Things to know, Discussions and forums, AI overview | P64: commercial, informational | Q64: People also ask
A65: grand larceny texas | B65: 1 | C65: 140 | D65: https://sbrownlawyer.com/grand-theft/ | E65: 1 | F65: 1 | G65: 5.43 | H65: 0 | I65: 0 | J65: 0 | K65: 0.03 | L65: 924000 | M65: [8,8,6,5,6,8,5,6,6,8,8,8] | N65: 46027 | O65: Video, People also ask, Related searches, AI overview | P65: informational | Q65: AI overview
A66: unlawful exposure | B66: 1 | C66: 70 | D66: https://sbrownlawyer.com/criminal-law/indecent-exposure/ | E66: 1 | F66: 37 | G66: 0 | H66: 0 | I66: 0 | J66: 0 | K66: 0 | L66: 15200000 | M66: [11,100,11,11,11,64,64,52,64,52,23,64] | N66: 46027 | O66: Video, Video Carousel, People also ask, Related searches, AI overview | P66: informational, transactional | Q66: People also ask
A67: angleton divorce attorney | B67: 1 | C67: 50 | D67: https://sbrownlawyer.com/texas/locations/angleton/?utm_campaign=gmbangleton | E67: 1 | F67: 9 | G67: 13.98 | H67: 4 | I67: 0.26 | J67: 55 | K67: 0.45 | L67: 24000 | M67: [9,27,27,27,27,27,27,45,81,100,45,63] | N67: 46026 | O67: Local pack, Sitelinks, Video, Related searches | P67: commercial | Q67: Local pack
A68: new child support laws 2024 texas | B68: 1 | C68: 40 | D68: https://sbrownlawyer.com/2024/03/20/texas-child-support-2024/ | E68: 1 | F68: 3 | G68: 0 | H68: 5 | I68: 0.33 | J68: 0 | K68: 0 | L68: 104000000 | M68: [9,28,100,0,0,0,0,0,0,0,0,0] | N68: 46026 | O68: Video, Related searches, AI overview | P68: informational | Q68: Organic
A69: ryan putz | B69: 1 | C69: 40 | D69: https://sbrownlawyer.com/ryan-r-putz/ | E69: 1 | F69: 15 | G69: 0 | H69: 10 | I69: 0.66 | J69: 0 | K69: 0.33 | L69: 631000 | M69: [2,2,2,11,17,2,3,2,2,2,2,2] | N69: 46024 | O69: Knowledge panel, Image pack, Video, Image, Video Carousel | P69: informational | Q69: Image pack
A70: brazoria county attorneys | B70: 1 | C70: 90 | D70: https://sbrownlawyer.com/texas/locations/angleton/?utm_campaign=gmbangleton | E70: 1 | F70: 39 | G70: 14.43 | H70: 11 | I70: 0.72 | J70: 158 | K70: 0.61 | L70: 457000 | M70: [41,82,64,100,17,52,41,23,52,11,52,41] | N70: 46023 | O70: Local pack, Sitelinks, Image, Related searches | P70: commercial | Q70: Local pack
A71: pearland attorneys | B71: 1 | C71: 70 | D71: https://sbrownlawyer.com/texas/locations/pearland/?utm_campaign=gmbpearland | E71: 1 | F71: 22 | G71: 12.96 | H71: 5 | I71: 0.33 | J71: 64 | K71: 0.63 | L71: 234000 | M71: [3,2,7,4,3,2,3,2,4,2,5,3] | N71: 46022 | O71: Local pack, Image | P71: commercial | Q71: Local pack
A72: brazoria county divorce lawyers | B72: 1 | C72: 30 | D72: https://sbrownlawyer.com/texas/locations/angleton/?utm_campaign=gmbangleton | E72: 1 | F72: 44 | G72: 22.36 | H72: 2 | I72: 0.13 | J72: 44 | K72: 0.99 | L72: 18700 | M72: [80,40,40,80,40,40,60,100,60,60,40,40] | N72: 46022 | O72: Local pack, Sitelinks, Ads bottom, Related searches | P72: commercial | Q72: Local pack
A73: scott brown lawyer | B73: 1 | C73: 70 | D73: https://sbrownlawyer.com/ | E73: 1 | F73: 3 | G73: 0 | H73: 17 | I73: 1.12 | J73: 0 | K73: 0 | L73: 476000000 | M73: [15,12,15,9,9,15,19,19,4,2,0,0] | N73: 46022 | O73: Local pack, Sitelinks, Video Carousel, See results about | P73: commercial | Q73: Organic
A74: angleton child custody lawyer | B74: 1 | C74: 70 | D74: https://sbrownlawyer.com/texas/locations/angleton/?utm_campaign=gmbangleton | E74: 1 | F74: 14 | G74: 0 | H74: 5 | I74: 0.33 | J74: 0 | K74: 0 | L74: 37900 | M74: [0,5,5,11,11,11,23,82,100,100,41,29] | N74: 46020 | O74: Local pack, Sitelinks, Image, Ads bottom, Related searches | P74: commercial | Q74: Local pack
A75: texas reckless driving charge | B75: 1 | C75: 40 | D75: https://sbrownlawyer.com/reckless-driving/ | E75: 1 | F75: 3 | G75: 7.85 | H75: 2 | I75: 0.13 | J75: 15 | K75: 0.05 | L75: 3170000 | M75: [5,17,11,17,41,23,11,52,41,11,23,11] | N75: 46018 | O75: Video, Related searches, AI overview | P75: informational | Q75: AI overview
... A165: unlawful carry weapon texas | B165: 2 | C165: 320 | D165: https://sbrownlawyer.com/criminal-law/first-offenders/ | E165: 2 | F165: 10 | G165: 9.14 | H165: 0 | I165: 0 | J165: 0 | K165: 0.05 | L165: 1660000 | M165: [15,23,36,67,7,2,15,23,67,100,81,29] | N165: 46032 | O165: Video, Image, Video Carousel, People also ask, Related searches, Things to know, AI overview | P165: informational | Q165: People also ask
A166: child custody attorney angleton | B166: 2 | C166: 50 | D166: https://sbrownlawyer.com/ | E166: 2 | G166: 0 | H166: 2 | I166: 0.13 | J166: 0 | K166: 0 | L166: 39600 | M166: [5,5,5,5,5,0,23,82,100,82,41,41] | N166: 46030 | O166: Local pack, Video, Image, People also ask, Related searches | P166: commercial | Q166: Organic
A167: child support san antonio | B167: 2 | C167: 40 | D167: https://sbrownlawyer.com/2024/03/20/texas-child-support-2024/ | E167: 2 | F167: 56 | G167: 0 | H167: 0 | I167: 0 | J167: 0 | K167: 0 | L167: 142000000 | M167: [0,2,2,7,2,5,5,7,53,17,2,0] | N167: 46027 | O167: Local pack, Sitelinks, Video, People also ask, Related searches | P167: navigational | Q167: People also ask
A168: ryan putz | B168: 2 | C168: 40 | D168: https://sbrownlawyer.com/ryan-r-putz/ | E168: 2 | F168: 15 | G168: 0 | H168: 0 | I168: 0 | J168: 0 | K168: 0.33 | L168: 631000 | M168: [2,2,2,11,17,2,3,2,2,2,2,2] | N168: 46024 | O168: Knowledge panel, Image pack, Video, Image, Video Carousel | P168: informational | Q168: Organic
A169: family lawyer angleton | B169: 2 | C169: 170 | D169: https://sbrownlawyer.com/ | E169: 2 | F169: 19 | G169: 13.28 | H169: 7 | I169: 0.46 | J169: 92 | K169: 0.21 | L169: 60800 | M169: [0,43,35,53,17,17,35,100,66,53,53,28] | N169: 46017 | O169: Local pack, Sitelinks, Video, Image, Related searches | P169: commercial | Q169: Organic
A170: angleton divorce lawyer | B170: 2 | C170: 90 | D170: https://sbrownlawyer.com/ | E170: 2 | F170: 14 | G170: 13.98 | H170: 3 | I170: 0.19 | J170: 41 | K170: 0.45 | L170: 19100 | M170: [0,19,19,9,9,14,23,66,100,100,52,52] | N170: 46015 | O170: Local pack, Sitelinks, Video, Image, People also ask, Related searches | P170: commercial | Q170: Organic
A171: angleton family lawyer | B171: 2 | C171: 70 | D171: https://sbrownlawyer.com/ | E171: 2 | F171: 33 | G171: 0 | H171: 3 | I171: 0.19 | J171: 0 | K171: 0.16 | L171: 302000 | M171: [5,11,17,29,29,11,64,52,100,64,52,52] | N171: 46015 | O171: Local pack, Sitelinks, Video, Image, Ads bottom, Related searches | P171: commercial | Q171: Organic
A172: n400 processing time in dallas | B172: 2 | C172: 70 | D172: https://sbrownlawyer.com/2024/12/27/understanding-the-naturalization-timeline-for-texas-residents/ | E172: 2 | F172: 25 | G172: 0 | H172: 0 | I172: 0 | J172: 0 | K172: 0 | L172: 27000 | M172: [45,63,45,45,45,27,63,63,100,63,63,63] | N172: 46008 | O172: Sitelinks, Video, People also ask, Related searches, AI overview | P172: informational | Q172: People also ask
A173: scott brown attorney | B173: 2 | C173: 140 | D173: https://sbrownlawyer.com/scott-m-brown/ | E173: 2 | F173: 4 | G173: 3.93 | H173: 6 | I173: 0.39 | J173: 23 | K173: 0.13 | L173: 77100000 | M173: [15,19,15,15,19,15,15,10,19,15,12,12] | N173: 46004 | O173: Local pack, Sitelinks, Video, See results about | P173: commercial | Q173: Organic
A174: indecent exposure texas penal code | B174: 2 | C174: 590 | D174: https://sbrownlawyer.com/criminal-law/indecent-exposure/ | E174: 2 | F174: 4 | G174: 5.11 | H174: 10 | I174: 0.66 | J174: 51 | K174: 0.02 | L174: 167000 | M174: [81,81,54,23,100,81,81,54,81,100,100,100] | N174: 45988 | O174: Video, Video Carousel, People also ask, Related searches, AI overview | P174: informational | Q174: People also ask
A175: angleton family attorney | B175: 2 | C175: 50 | D175: https://sbrownlawyer.com/ | E175: 2 | F175: 9 | G175: 0 | H175: 2 | I175: 0.13 | J175: 0 | K175: 0.02 | L175: 9 | M175: [0,0,0,28,21,50,78,14,28,78,100,78] | N175: 45978 | O175: Local pack, Sitelinks, Video, Image, Related searches | P175: commercial | Q175: Organic
A176: s brown & associates | B176: 3 | C176: 70 | D176: https://sbrownlawyer.com/ | E176: 2 | F176: 29 | G176: 0 | H176: 1 | I176: 0.06 | J176: 0 | K176: 0.03 | L176: 233000000 | M176: [45,45,45,27,45,63,63,63,63,63,63,81] | N176: 46042 | O176: Sitelinks, Image, People also ask, Related searches, See results about | P176: navigational | Q176: Organic
A177: texas alimony guidelines | B177: 3 | C177: 170 | D177: https://sbrownlawyer.com/2024/04/24/texas-alimony-am-i-entitled/ | E177: 3 | F177: 7 | G177: 0.47 | H177: 2 | I177: 0.13 | J177: 0 | K177: 0.05 | L177: 160000 | M177: [43,29,29,22,43,54,54,18,22,54,14,10] | N177: 46039 | O177: Video, Video Carousel, People also ask, Related searches, AI overview | P177: informational | Q177: People also ask
A178: jennifer lopez marc anthony song | B178: 3 | C178: 70 | D178: https://sbrownlawyer.com/2014/06/20/lopez-anthony-divorce-has-interesting-child-custody-agreement/ | E178: 3 | F178: 46 | G178: 0 | H178: 0 | I178: 0 | J178: 0 | K178: 0 | L178: 6490000 | M178: [33,52,42,42,23,19,52,33,14,23,33,33] | N178: 46036 | O178: Knowledge panel, Video, Featured video, Image, People also ask, Related searches, Short videos | P178: informational, transactional | Q178: People also ask
... A194: angleton grandparents rights lawyer | B194: 4 | C194: 50 | D194: https://sbrownlawyer.com/ | E194: 4 | F194: 3 | G194: 5.11 | H194: 2 | I194: 0.13 | J194: 10 | K194: 0.12 | L194: 34000 | M194: [0,0,0,0,5,5,17,82,100,82,41,52] | N194: 46027 | O194: Local pack, Video, People also ask, Related searches, AI overview | P194: commercial, informational | Q194: Organic
A195: divorce lawyers in league city texas | B195: 4 | C195: 30 | D195: https://sbrownlawyer.com/texas/locations/league-city/ | E195: 4 | G195: 17.48 | H195: 0 | I195: 0 | J195: 0 | K195: 0.53 | L195: 6790000 | M195: [27,18,18,27,45,9,9,100,27,9,45,36] | N195: 46026 | O195: Local pack, Sitelinks, Video, Related searches | P195: commercial | Q195: Organic
A196: family law attorney angleton tx | B196: 4 | C196: 140 | D196: https://sbrownlawyer.com/ | E196: 4 | F196: 25 | G196: 13.98 | H196: 4 | I196: 0.26 | J196: 55 | K196: 0.45 | L196: 33000 | M196: [15,53,43,34,15,15,43,100,43,34,43,43] | N196: 46024 | O196: Local pack, Sitelinks, Video, Image, Related searches | P196: commercial | Q196: Organic
A197: scott brown lawyer | B197: 4 | C197: 70 | D197: https://sbrownlawyer.com/texas/locations/league-city/?utm_campaign=gmbleaguecity | E197: 4 | F197: 3 | G197: 0 | H197: 2 | I197: 0.13 | J197: 0 | K197: 0 | L197: 476000000 | M197: [15,12,15,9,9,15,19,19,4,2,0,0] | N197: 46022 | O197: Local pack, Sitelinks, Video Carousel, See results about | P197: commercial | Q197: Local pack
A198: scott brown lawyer | B198: 4 | C198: 70 | D198: https://sbrownlawyer.com/texas/locations/pearland/?utm_campaign=gmbpearland | E198: 4 | F198: 3 | G198: 0 | H198: 2 | I198: 0.13 | J198: 0 | K198: 0 | L198: 476000000 | M198: [15,12,15,9,9,15,19,19,4,2,0,0] | N198: 46022 | O198: Local pack, Sitelinks, Video Carousel, See results about | P198: commercial | Q198: Local pack
A199: scott brown lawyer | B199: 4 | C199: 70 | D199: https://sbrownlawyer.com/texas/locations/angleton/?utm_campaign=gmbangleton | E199: 4 | F199: 3 | G199: 0 | H199: 3 | I199: 0.19 | J199: 0 | K199: 0 | L199: 476000000 | M199: [15,12,15,9,9,15,19,19,4,2,0,0] | N199: 46022 | O199: Local pack, Sitelinks, Video Carousel, See results about | P199: commercial | Q199: Local pack
A200: angleton family law attorney | B200: 4 | C200: 70 | D200: https://sbrownlawyer.com/ | E200: 4 | F200: 25 | G200: 13.28 | H200: 2 | I200: 0.13 | J200: 26 | K200: 0.21 | L200: 69700 | M200: [7,28,28,50,35,21,28,50,100,78,64,35] | N200: 46017 | O200: Local pack, Sitelinks, Video, Image, Related searches | P200: commercial | Q200: Organic
A201: katie stahl | B201: 4 | C201: 90 | D201: https://sbrownlawyer.com/katie-stahl/ | E201: 4 | F201: 12 | G201: 0 | H201: 3 | I201: 0.19 | J201: 0 | K201: 0 | L201: 1950000 | M201: [23,23,23,33,66,42,52,33,33,33,42,52] | N201: 46015 | O201: Image pack, Video, Image, People also ask, See results about | P201: informational | Q201: Organic
A202: n400 processing time houston | B202: 4 | C202: 90 | D202: https://sbrownlawyer.com/2024/12/27/understanding-the-naturalization-timeline-for-texas-residents/ | E202: 4 | F202: 26 | G202: 0 | H202: 0 | I202: 0 | J202: 0 | K202: 0 | L202: 45900 | M202: [23,23,42,33,42,42,42,52,42,42,42,33] | N202: 46014 | O202: Sitelinks, Video, Related searches, AI overview | P202: informational | Q202: Organic
A203: n400 dallas processing time | B203: 4 | C203: 70 | D203: https://sbrownlawyer.com/2024/12/27/understanding-the-naturalization-timeline-for-texas-residents/ | E203: 4 | F203: 18 | G203: 0 | H203: 0 | I203: 0 | J203: 0 | K203: 0 | L203: 31800 | M203: [45,81,45,45,63,81,45,63,100,63,81,63] | N203: 46008 | O203: Sitelinks, Video, People also ask, Related searches, AI overview | P203: informational | Q203: People also ask
A204: alimony in texas 2024 | B204: 4 | C204: 50 | D204: https://sbrownlawyer.com/2024/04/24/texas-alimony-am-i-entitled/ | E204: 4 | F204: 2 | G204: 0 | H204: 1 | I204: 0.06 | J204: 0 | K204: 0 | L204: 1350000 | M204: [64,100,78,14,78,14,14,14,14,14,14,14] | N204: 45993 | O204: Video, People also ask, Related searches, AI overview | P204: informational | Q204: Organic
A205: how to tell if you're sober enough to drive | B205: 4 | C205: 90 | D205: https://sbrownlawyer.com/2020/10/29/how-to-tell-if-youre-too-drunk-to-drive-and-how-to-prevent-yourself-from-becoming-a-drunk-driver/ | E205: 4 | F205: 3 | G205: 0 | H205: 1 | I205: 0.06 | J205: 0 | K205: 0.01 | L205: 9 | M205: [34,15,21,21,21,34,28,28,28,43,43,28] | N205: 45986 | O205: Sitelinks, Video, People also ask, Related searches, Discussions and forums, AI overview | P205: informational | Q205: Organic
A206: divorce attorney angleton | B206: 4 | C206: 170 | D206: https://sbrownlawyer.com/ | E206: 4 | F206: 10 | G206: 10.08 | H206: 5 | I206: 0.33 | J206: 50 | K206: 0.13 | L206: 8 | M206: [15,15,53,43,65,34,43,34,100,43,34,100] | N206: 45984 | O206: Local pack, Sitelinks, Image, Related searches | P206: commercial | Q206: Organic
A207: angleton grandparents rights attorney | B207: 5 | C207: 50 | D207: https://sbrownlawyer.com/grandparents-rights/ | E207: 5 | F207: 0 | G207: 0 | H207: 1 | I207: 0.06 | J207: 0 | K207: 0.33 | L207: 12900 | M207: [0,0,0,0,5,5,11,64,100,100,41,52] | N207: 46033 | O207: Local pack, Video, People also ask, AI overview | P207: commercial, informational | Q207: Organic
... A214: family law attorney angleton | B214: 5 | C214: 110 | D214: https://sbrownlawyer.com/ | E214: 5 | F214: 12 | G214: 13.92 | H214: 2 | I214: 0.13 | J214: 27 | K214: 0.06 | L214: 10 | M214: [6,15,43,34,21,28,28,43,43,65,53,34] | N214: 45984 | O214: Local pack, Sitelinks, Image, Related searches | P214: commercial | Q214: Organic
A215: family law pearland texas | B215: 6 | C215: 50 | D215: https://sbrownlawyer.com/texas/locations/pearland/ | E215: 6 | G215: 16.24 | H215: 0 | I215: 0 | J215: 0 | K215: 0.67 | L215: 997000 | M215: [6,6,4,14,10,10,14,4,4,6,14,43] | N215: 46038 | O215: Local pack, Sitelinks, Video, Image, People also ask, Related searches | P215: commercial | Q215: Organic
A216: pearland family lawyer | B216: 6 | C216: 50 | D216: https://sbrownlawyer.com/texas/locations/pearland/ | E216: 6 | F216: 12 | G216: 11.04 | H216: 0 | I216: 0 | J216: 0 | K216: 0.47 | L216: 143000 | M216: [0,14,21,21,21,21,21,14,64,100,100,100] | N216: 46034 | O216: Local pack, Sitelinks, Image, People also ask, Related searches | P216: commercial | Q216: Organic
A217: family law lawyer pearland | B217: 6 | C217: 50 | D217: https://sbrownlawyer.com/texas/locations/pearland/ | E217: 6 | F217: 31 | G217: 16.24 | H217: 1 | I217: 0.06 | J217: 16 | K217: 0.67 | L217: 214000 | M217: [0,18,18,0,18,9,45,63,100,100,81,81] | N217: 46032 | O217: Local pack, Video, Image, Related searches | P217: commercial | Q217: Organic
A218: family law attorneys pearland | B218: 6 | C218: 40 | D218: https://sbrownlawyer.com/texas/locations/pearland/ | E218: 6 | F218: 14 | G218: 16.24 | H218: 0 | I218: 0 | J218: 0 | K218: 0.67 | L218: 121000 | M218: [11,11,22,22,22,11,11,77,100,100,100,100] | N218: 46032 | O218: Local pack, Sitelinks, Video, People also ask, Related searches | P218: commercial | Q218: Organic
A219: angleton child support attorney | B219: 6 | C219: 50 | D219: https://sbrownlawyer.com/ | E219: 6 | F219: 15 | G219: 0 | H219: 1 | I219: 0.06 | J219: 0 | K219: 0 | L219: 97600 | M219: [0,5,5,0,5,0,17,64,100,82,41,23] | N219: 46031 | O219: Local pack, Sitelinks, Video, Featured snippet, Related searches | P219: commercial | Q219: Organic
A220: family attorney pearland | B220: 6 | C220: 50 | D220: https://sbrownlawyer.com/texas/locations/pearland/ | E220: 6 | F220: 12 | G220: 0 | H220: 1 | I220: 0.06 | J220: 0 | K220: 0.24 | L220: 293000 | M220: [0,0,14,14,14,14,35,50,78,78,100,64] | N220: 46030 | O220: Local pack, Sitelinks, Image, People also ask, Related searches | P220: commercial | Q220: Organic
A221: divorce attorneys pearland | B221: 6 | C221: 50 | D221: https://sbrownlawyer.com/texas/locations/pearland/ | E221: 6 | F221: 14 | G221: 0 | H221: 0 | I221: 0 | J221: 0 | K221: 0 | L221: 34200 | M221: [0,0,0,0,0,0,28,78,100,100,78,78] | N221: 46030 | O221: Local pack, Sitelinks, Video, People also ask, Related searches | P221: commercial | Q221: Organic
A222: pearland family attorney | B222: 6 | C222: 70 | D222: https://sbrownlawyer.com/texas/locations/pearland/ | E222: 6 | F222: 12 | G222: 11.04 | H222: 1 | I222: 0.06 | J222: 11 | K222: 0.47 | L222: 245000 | M222: [23,23,9,52,52,52,52,9,9,9,52,23] | N222: 46028 | O222: Local pack, Video, Image, Related searches | P222: commercial | Q222: Organic
A223: is iggy azalea married | B223: 6 | C223: 170 | D223: https://sbrownlawyer.com/2014/10/17/iggy-azalea-isnt-married-but-she-was-sued-for-divorce-in-texas/ | E223: 6 | F223: 21 | G223: 0 | H223: 4 | I223: 0.26 | J223: 0 | K223: 0 | L223: 2170000 | M223: [22,18,35,18,22,14,18,18,18,66,100,66] | N223: 46024 | O223: Image pack, Video, Image, Related searches, AI overview | P223: informational | Q223: Organic
A224: iggy azalea married | B224: 6 | C224: 110 | D224: https://sbrownlawyer.com/2014/10/17/iggy-azalea-isnt-married-but-she-was-sued-for-divorce-in-texas/ | E224: 6 | F224: 12 | G224: 0 | H224: 2 | I224: 0.13 | J224: 0 | K224: 0 | L224: 2170000 | M224: [4,8,22,14,35,22,35,22,18,29,66,22] | N224: 46024 | O224: Image pack, Sitelinks, Video, Image, Related searches, AI overview | P224: informational | Q224: Organic
A225: pearland divorce attorney | B225: 6 | C225: 140 | D225: https://sbrownlawyer.com/ | E225: 6 | F225: 20 | G225: 16.24 | H225: 3 | I225: 0.19 | J225: 48 | K225: 0.67 | L225: 47200 | M225: [4,7,12,10,7,7,12,19,19,29,23,29] | N225: 46023 | O225: Local pack, Sitelinks, Video, Image, Ads bottom, Related searches, Discussions and forums | P225: commercial | Q225: Organic
A226: brazoria county divorce lawyers | B226: 6 | C226: 30 | D226: https://sbrownlawyer.com/ | E226: 6 | F226: 44 | G226: 22.36 | H226: 0 | I226: 0 | J226: 0 | K226: 0.99 | L226: 18700 | M226: [80,40,40,80,40,40,60,100,60,60,40,40] | N226: 46022 | O226: Local pack, Sitelinks, Ads bottom, Related searches | P226: commercial | Q226: Organic
A227: pearland family law attorney | B227: 6 | C227: 210 | D227: https://sbrownlawyer.com/texas/locations/pearland/ | E227: 6 | F227: 31 | G227: 16.24 | H227: 1 | I227: 0.06 | J227: 16 | K227: 0.67 | L227: 141000 | M227: [22,43,35,81,81,43,43,66,43,18,54,35] | N227: 46022 | O227: Local pack, Sitelinks, Image, People also ask, Related searches | P227: commercial | Q227: Organic
...

Sheet L3M_search_console
A1: Address | B1: Status Code | C1: Title 1 | D1: Indexability | E1: Indexability Status | F1: Clicks | G1: Impressions | H1: CTR | I1: Position
A2: https://www.sterlinglawyers.com/illinois/ | B2: 200 | C2: Sterling Lawyers, LLC | Illinois Divorce & Family Law Firm | D2: Indexable | F2: 132 | G2: 16963 | H2: 0.008 | I2: 35.14
A3: https://www.sterlinglawyers.com/illinois/attorneys/reyna-herrera/reviews/ | B3: 200 | C3: Reviews: Attorney Reyna Herrera | Sterling Lawyers, LLC | D3: Indexable | F3: 9 | G3: 225 | H3: 0.04 | I3: 7.82
A4: https://www.sterlinglawyers.com/illinois/attorneys/alexandra-isroff/reviews/ | B4: 200 | C4: Reviews: Attorney Alexandra Isroff | Sterling Lawyers, LLC | D4: Indexable | F4: 11 | G4: 437 | H4: 0.025 | I4: 15.07
A5: https://www.sterlinglawyers.com/illinois/attorneys/cynthia-toscano/reviews/ | B5: 200 | C5: Reviews: Attorney Cynthia Toscano | Sterling Lawyers, LLC | D5: Indexable | F5: 7 | G5: 320 | H5: 0.022 | I5: 14.24
A6: https://www.sterlinglawyers.com/illinois/locations/st-charles/ | B6: 200 | C6: St. Charles Family Law & Divorce Lawyers | Sterling Lawyers, LLC | D6: Indexable | F6: 19 | G6: 11438 | H6: 0.002 | I6: 24.04
A7: https://www.sterlinglawyers.com/illinois/attorneys/ryan-shope/reviews/ | B7: 200 | C7: Reviews: Attorney Ryan Shope | Sterling Lawyers, LLC | D7: Indexable | F7: 4 | G7: 138 | H7: 0.029 | I7: 17.27
A8: https://www.sterlinglawyers.com/illinois/attorneys/jacqueline-mcclellan/reviews/ | B8: 200 | C8: Reviews: Attorney Jacqueline N. McClellan | Sterling Lawyers, LLC | D8: Indexable | F8: 8 | G8: 486 | H8: 0.017 | I8: 7.27
A9: https://www.sterlinglawyers.com/illinois/attorneys/jeff-hughes/reviews/ | B9: 200 | C9: Divorce & Family Law Attorney Reviews - Attorney Jeff Hughes | Sterling Lawyers, LLC | D9: Non-Indexable | E9: noindex
A10: https://www.sterlinglawyers.com/about-us/ | B10: 200 | C10: About Us | Sterling Lawyers, LLC | D10: Indexable | F10: 11 | G10: 3431 | H10: 0.003 | I10: 11.8
A11: https://www.sterlinglawyers.com/illinois/attorneys/reyna-herrera/ | B11: 200 | C11: Divorce & Family Law Attorney Reyna Herrera | Sterling Lawyers, LLC | D11: Indexable | F11: 42 | G11: 1457 | H11: 0.029 | I11: 6.7
A12: https://www.sterlinglawyers.com/illinois/divorce/uncontested-divorce/ | B12: 200 | C12: Uncontested Divorce in Illinois | Sterling Lawyers, LLC | D12: Indexable | F12: 223 | G12: 45381 | H12: 0.005 | I12: 15.26
A13: https://www.sterlinglawyers.com/illinois/attorneys/ryan-shope/ | B13: 200 | C13: Divorce & Family Law Attorney Ryan Shope | Sterling Lawyers, LLC | D13: Indexable | F13: 25 | G13: 2113 | H13: 0.012 | I13: 35.8
A14: https://www.sterlinglawyers.com/illinois/locations/naperville/ | B14: 200 | C14: Naperville Family Law & Divorce Lawyers | Sterling Lawyers, LLC | D14: Indexable | F14: 35 | G14: 26256 | H14: 0.001 | I14: 26.18
A15: https://www.sterlinglawyers.com/illinois/attorneys/katie-vandeusen/reviews/ | B15: 200 | C15: Reviews: Attorney Katie VanDeusen | Sterling Lawyers, LLC | D15: Indexable | F15: 3 | G15: 275 | H15: 0.011 | I15: 6.31
A16: https://www.sterlinglawyers.com/illinois/child-custody/ | B16: 200 | C16: Illinois Child Custody Laws | Sterling Lawyers, LLC | D16: Indexable | F16: 418 | G16: 55237 | H16: 0.008 | I16: 11.22
A17: https://www.sterlinglawyers.com/illinois/guardianship/ | B17: 200 | C17: Illinois Guardianship Laws | Sterling Lawyers, LLC | D17: Indexable | F17: 121 | G17: 16050 | H17: 0.007 | I17: 9.42
A18: https://www.sterlinglawyers.com/reviews/ | B18: 200 | C18: Reviews & Testimonials | Sterling Lawyers, LLC | D18: Indexable | F18: 43 | G18: 3299 | H18: 0.013 | I18: 13.48
A19: https://www.sterlinglawyers.com/illinois/locations/evanston/ | B19: 200 | C19: Evanston Family Law & Divorce Lawyers | Sterling Lawyers, LLC | D19: Indexable | F19: 37 | G19: 31289 | H19: 0.001 | I19: 44.02
A20: https://www.sterlinglawyers.com/illinois/attorneys/jacqueline-mcclellan/ | B20: 200 | C20: Divorce & Family Law Attorney Jacqueline N. McClellan | Sterling Lawyers, LLC | D20: Indexable | F20: 33 | G20: 875 | H20: 0.038 | I20: 9.91
A21: https://www.sterlinglawyers.com/illinois/blog/protecting-interests-navigating-uncontested-divorce-evanston/ | B21: 200 | C21: Protecting Your Interests Navigating Uncontested Divorce in Evanston | Sterling Lawyers, LLC | D21: Indexable | F21: 0 | G21: 16 | H21: 0 | I21: 15.94
A22: https://www.sterlinglawyers.com/illinois/attorneys/jeff-hughes/ | B22: 200 | C22: Divorce & Family Law Attorney Jeff Hughes | Sterling Lawyers, LLC | D22: Non-Indexable | E22: noindex
A23: https://www.sterlinglawyers.com/illinois/property-division/worksheet/ | B23: 200 | C23: Illinois Property Division Worksheet | Sterling Lawyers, LLC | D23: Indexable | F23: 67 | G23: 2534 | H23: 0.026 | I23: 13.33
A24: https://www.sterlinglawyers.com/illinois/child-custody/fathers-rights/ | B24: 200 | C24: Father’s Rights in Illinois | Sterling Lawyers, LLC | D24: Indexable | F24: 535 | G24: 58042 | H24: 0.009 | I24: 10.2
A25: https://www.sterlinglawyers.com/illinois/locations/ | B25: 200 | C25: Illinois Locations & Hours | Sterling Lawyers, LLC | D25: Indexable | F25: 24 | G25: 4259 | H25: 0.006 | I25: 15.24
A26: https://www.sterlinglawyers.com/illinois/attorneys/alexandra-isroff/ | B26: 200 | C26: Divorce & Family Law Attorney Alexandra Isroff | Sterling Lawyers, LLC | D26: Indexable | F26: 43 | G26: 1508 | H26: 0.029 | I26: 21.91
A27: https://www.sterlinglawyers.com/illinois/locations/plainfield/ | B27: 200 | C27: Plainfield Family Law & Divorce Lawyers | Sterling Lawyers, LLC | D27: Indexable | F27: 33 | G27: 7707 | H27: 0.004 | I27: 22.59
A28: https://www.sterlinglawyers.com/illinois/attorneys/cynthia-toscano/ | B28: 200 | C28: Cynthia Toscano | Sterling Lawyers, LLC | D28: Indexable | F28: 69 | G28: 521 | H28: 0.132 | I28: 7.74
A29: https://www.sterlinglawyers.com/privacy-policy/ | B29: 200 | C29: Privacy Policy | Wisconsin | Sterling Lawyers, LLC | D29: Indexable | F29: 1 | G29: 96 | H29: 0.01 | I29: 25.88
A30: https://www.sterlinglawyers.com/illinois/attorneys/lea-diaz/ | B30: 200 | C30: Divorce & Family Law Attorney Lea C. Diaz | Sterling Lawyers, LLC | D30: Indexable | F30: 32 | G30: 1394 | H30: 0.023 | I30: 14.14
A31: https://www.sterlinglawyers.com/illinois/divorce/contested/ | B31: 200 | C31: Contested Divorce in Illinois | Sterling Lawyers, LLC | D31: Indexable | F31: 83 | G31: 8895 | H31: 0.009 | I31: 18.19
A32: https://www.sterlinglawyers.com/illinois/family-law-case-types-cost/ | B32: 200 | C32: Understand Case Types and Cost in Illinois | Sterling Lawyers, LLC | D32: Indexable | F32: 23 | G32: 4406 | H32: 0.005 | I32: 9.91
A33: https://www.sterlinglawyers.com/illinois/locations/schaumburg/ | B33: 200 | C33: Schaumburg Family Law & Divorce Lawyers | Sterling Lawyers, LLC | D33: Indexable | F33: 57 | G33: 54396 | H33: 0.001 | I33: 30.34
A34: https://www.sterlinglawyers.com/lp-untying-knots/ | B34: 200 | C34: Before You Untie the Knot - Untying Knots | D34: Indexable | F34: 2 | G34: 775 | H34: 0.003 | I34: 10.92
... A44: https://www.sterlinglawyers.com/illinois/spousal-support/ | B44: 200 | C44: Illinois Alimony Laws | Sterling Lawyers, LLC | D44: Indexable | F44: 239 | G44: 31202 | H44: 0.008 | I44: 12.39
A45: https://www.sterlinglawyers.com/illinois/reviews/ | B45: 200 | C45: Reviews | Sterling Lawyers, LLC | D45: Non-Indexable | E45: Canonicalised
A46: https://www.sterlinglawyers.com/illinois/family-law-process/ | B46: 200 | C46: Illinois Family Law Process Start to Finish | Sterling Lawyers, LLC | D46: Indexable | F46: 2 | G46: 85 | H46: 0.024 | I46: 14.45
A47: https://www.sterlinglawyers.com/careers/ | B47: 200 | C47: Careers | Sterling Lawyers, LLC | D47: Indexable | F47: 78 | G47: 1922 | H47: 0.041 | I47: 6.81
A48: https://www.sterlinglawyers.com/illinois/attorneys/natalie-mccray/ | B48: 301 | D48: Non-Indexable | E48: Redirected
A49: https://www.sterlinglawyers.com/illinois/pricing/ | B49: 200 | C49: Family Law Pricing | Sterling Lawyers, LLC | D49: Indexable | F49: 29 | G49: 6657 | H49: 0.004 | I49: 27.08
A50: https://www.sterlinglawyers.com/illinois/divorce/forms/ | B50: 200 | C50: (Free) Illinois Divorce Forms | Sterling Lawyers, LLC | D50: Indexable | F50: 69 | G50: 18384 | H50: 0.004 | I50: 11.39
A51: https://www.sterlinglawyers.com/illinois/child-support/ | B51: 200 | C51: Illinois Child Support Laws | Sterling Lawyers, LLC | D51: Indexable | F51: 61 | G51: 16176 | H51: 0.004 | I51: 6.26
A52: https://www.sterlinglawyers.com/illinois/attorneys/nina-kelly/reviews/ | B52: 200 | C52: Reviews: Attorney Nina Kelly | Sterling Lawyers, LLC | D52: Indexable | F52: 8 | G52: 430 | H52: 0.019 | I52: 14.43
A53: https://www.sterlinglawyers.com/illinois/child-custody/parental-alienation/ | B53: 200 | C53: Parental Alienation in Illinois | Sterling Lawyers, LLC | D53: Indexable | F53: 234 | G53: 20817 | H53: 0.011 | I53: 9.26
A54: https://www.sterlinglawyers.com/illinois/seminar/ | B54: 200 | C54: Divorce Workshops in Illinois | Sterling Lawyers, LLC | D54: Indexable | F54: 3 | G54: 164 | H54: 0.018 | I54: 25.98
A55: https://www.sterlinglawyers.com/illinois/locations/arlington-heights/ | B55: 200 | C55: Arlington Heights Family Law & Divorce Lawyers | Sterling Lawyers, LLC | D55: Indexable | F55: 30 | G55: 23359 | H55: 0.001 | I55: 29.94
A56: https://www.sterlinglawyers.com/illinois/locations/hoffman-estates/ | B56: 200 | C56: Hoffman Estates Family Law & Divorce Lawyers | Sterling Lawyers, LLC | D56: Indexable | F56: 9 | G56: 14608 | H56: 0.001 | I56: 26.1
A57: https://www.sterlinglawyers.com/illinois/attorneys/katie-vandeusen/ | B57: 200 | C57: Divorce & Family Law Attorney Katie VanDeusen | Sterling Lawyers, LLC | D57: Indexable | F57: 35 | G57: 1567 | H57: 0.022 | I57: 20.61
A58: https://www.sterlinglawyers.com/scholarship/ | B58: 200 | C58: Student Scholarship | Sterling Lawyers, LLC | D58: Indexable | F58: 17 | G58: 475 | H58: 0.036 | I58: 7.72
A59: https://www.sterlinglawyers.com/illinois/divorce/diy/ | B59: 200 | C59: How to Get a Divorce Without a Lawyer in Illinois | Sterling Lawyers, LLC | D59: Indexable | F59: 229 | G59: 32004 | H59: 0.007 | I59: 14.38
A60: https://www.sterlinglawyers.com/illinois/spousal-support/calculator/ | B60: 200 | C60: 2026 Illinois (Maintenance) Alimony Calculator | Sterling Lawyers, LLC | D60: Indexable | F60: 5145 | G60: 80510 | H60: 0.064 | I60: 11.81
... A67: https://www.sterlinglawyers.com/illinois/child-custody/co-parenting/ | B67: 200 | C67: Co-Parenting in Illinois | Sterling Lawyers, LLC | D67: Indexable | F67: 16 | G67: 3425 | H67: 0.005 | I67: 12.28
A68: https://www.sterlinglawyers.com/illinois/divorce/how-long-divorce-Illinois/ | B68: 200 | C68: How Long Does a Divorce Take in Illinois? | Sterling Lawyers, LLC | D68: Non-Indexable | E68: Canonicalised
A69: https://www.sterlinglawyers.com/illinois/divorce/marriage-license/ | B69: 200 | C69: How Long Does It Take To Get a Marriage License in Illinois? | Sterling Lawyers, LLC | D69: Indexable | F69: 300 | G69: 47619 | H69: 0.006 | I69: 6.33
A70: https://www.sterlinglawyers.com/illinois/locations/chicago/child-support-lawyers/ | B70: 200 | C70: Chicago Child Support Lawyers | Sterling Lawyers, LLC | D70: Indexable | F70: 2 | G70: 834 | H70: 0.002 | I70: 70.79
A71: https://www.sterlinglawyers.com/illinois/locations/chicago/collaborative-divorce-lawyers/ | B71: 200 | C71: Chicago Collaborative Divorce Lawyers | Sterling Lawyers, LLC | D71: Indexable | F71: 2 | G71: 1094 | H71: 0.002 | I71: 45.54
A72: https://www.sterlinglawyers.com/illinois/locations/chicago/contested-divorce-lawyers/ | B72: 200 | C72: Chicago Contested Divorce Lawyers | Sterling Lawyers, LLC | D72: Indexable | F72: 1 | G72: 653 | H72: 0.002 | I72: 67.99
A73: https://www.sterlinglawyers.com/illinois/locations/chicago/uncontested-divorce-lawyers/ | B73: 200 | C73: Chicago Uncontested Divorce Lawyers | Sterling Lawyers, LLC | D73: Indexable | F73: 1 | G73: 391 | H73: 0.003 | I73: 39.28
A74: https://www.sterlinglawyers.com/illinois/locations/chicago/property-division-lawyers/ | B74: 200 | C74: Chicago Property Division Lawyers | Sterling Lawyers, LLC | D74: Indexable | F74: 0 | G74: 1532 | H74: 0 | I74: 23.69
A75: https://www.sterlinglawyers.com/illinois/locations/chicago/child-custody-lawyers/ | B75: 200 | C75: Chicago Child Custody Lawyers | Sterling Lawyers, LLC | D75: Indexable | F75: 3 | G75: 10053 | H75: 0 | I75: 54.88
A76: https://www.sterlinglawyers.com/illinois/locations/chicago/paternity-lawyers/ | B76: 200 | C76: Chicago Paternity Lawyers | Sterling Lawyers, LLC | D76: Indexable | F76: 0 | G76: 1676 | H76: 0 | I76: 32.24
A77: https://www.sterlinglawyers.com/illinois/locations/chicago/military-divorce-lawyers/ | B77: 200 | C77: Chicago Military Divorce Lawyers | Sterling Lawyers, LLC | D77: Indexable | F77: 6 | G77: 6611 | H77: 0.001 | I77: 57.34
A78: https://www.sterlinglawyers.com/illinois/locations/chicago/divorce-mediation-lawyers/ | B78: 200 | C78: Chicago Divorce Mediation Lawyers | Sterling Lawyers, LLC | D78: Indexable | F78: 1 | G78: 429 | H78: 0.002 | I78: 58.69
A79: https://www.sterlinglawyers.com/illinois/attorneys/reyna-herrera/reviews/page/4/ | B79: 200 | C79: Reviews: Attorney Reyna Herrera | Sterling Lawyers, LLC | D79: Non-Indexable | E79: Canonicalised
A80: https://www.sterlinglawyers.com/illinois/attorneys/reyna-herrera/reviews/page/2/ | B80: 200 | C80: Reviews: Attorney Reyna Herrera | Sterling Lawyers, LLC | D80: Non-Indexable | E80: Canonicalised | F80: 0 | G80: 6 | H80: 0 | I80: 5.5
A81: https://www.sterlinglawyers.com/illinois/attorneys/reyna-herrera/reviews/page/3/ | B81: 200 | C81: Reviews: Attorney Reyna Herrera | Sterling Lawyers, LLC | D81: Non-Indexable | E81: Canonicalised | F81: 0 | G81: 4 | H81: 0 | I81: 5.5
A82: https://www.sterlinglawyers.com/illinois/attorneys/alexandra-isroff/reviews/page/2/ | B82: 200 | C82: Reviews: Attorney Alexandra Isroff | Sterling Lawyers, LLC | D82: Non-Indexable | E82: Canonicalised | F82: 0 | G82: 30 | H82: 0 | I82: 10.4
A83: https://www.sterlinglawyers.com/illinois/attorneys/alexandra-isroff/reviews/page/43/ | B83: 200 | C83: Reviews: Attorney Alexandra Isroff | Sterling Lawyers, LLC | D83: Non-Indexable | E83: Canonicalised
A84: https://www.sterlinglawyers.com/illinois/attorneys/cynthia-toscano/reviews/page/8/ | B84: 200 | C84: Reviews: Attorney Cynthia Toscano | Sterling Lawyers, LLC | D84: Non-Indexable | E84: Canonicalised | F84: 0 | G84: 7 | H84: 0 | I84: 6.86
A85: https://www.sterlinglawyers.com/illinois/attorneys/cynthia-toscano/reviews/page/3/ | B85: 200 | C85: Reviews: Attorney Cynthia Toscano | Sterling Lawyers, LLC | D85: Non-Indexable | E85: Canonicalised | F85: 0 | G85: 25 | H85: 0 | I85: 15.48
A86: https://www.sterlinglawyers.com/illinois/attorneys/cynthia-toscano/reviews/page/2/ | B86: 200 | C86: Reviews: Attorney Cynthia Toscano | Sterling Lawyers, LLC | D86: Non-Indexable | E86: Canonicalised | F86: 0 | G86: 12 | H86: 0 | I86: 10.67
A87: https://www.sterlinglawyers.com/illinois/locations/aurora/ | B87: 200 | C87: Aurora Family Law & Divorce Lawyers | Sterling Lawyers, LLC | D87: Indexable | F87: 0 | G87: 493 | H87: 0 | I87: 29.51
A88: https://www.sterlinglawyers.com/illinois/divorce/annulment/ | B88: 200 | C88: How to Get an Annulment in Illinois | Sterling Lawyers, LLC | D88: Indexable | F88: 396 | G88: 36816 | H88: 0.011 | I88: 14.52
A89: https://www.sterlinglawyers.com/illinois /reviews/ | B89: 301 | D89: Non-Indexable | E89: Redirected
A90: https://www.sterlinglawyers.com/illinois/blog/supporting-fathers-evanston-child-custody-disputes/ | B90: 200 | C90: Supporting Fathers in Evanston Child Custody Disputes | Sterling Lawyers, LLC | D90: Indexable | F90: 0 | G90: 71 | H90: 0 | I90: 14.42
A91: https://www.sterlinglawyers.com/illinois/divorce/temporary-order/ | B91: 200 | C91: Getting a Temporary Order during an Illinois Divorce | Sterling Lawyers, LLC | D91: Indexable | F91: 24 | G91: 1963 | H91: 0.012 | I91: 15.65
A92: https://www.sterlinglawyers.com/illinois/divorce/how/ | B92: 200 | C92: Common Law Marriage in Illinois | Sterling Lawyers, LLC | D92: Indexable | F92: 11 | G92: 1769 | H92: 0.006 | I92: 5.67
A93: https://www.sterlinglawyers.com/illinois/divorce/grounds-for-divorce/ | B93: 200 | C93: Legal Grounds to File for Divorce in Illinois | Sterling Lawyers, LLC | D93: Indexable | F93: 56 | G93: 15735 | H93: 0.004 | I93: 11.56
A94: https://www.sterlinglawyers.com/illinois/events/ | B94: 200 | C94: Divorce Webinars & Educational Events in Illinois | Sterling Lawyers, LLC | D94: Indexable | F94: 2 | G94: 146 | H94: 0.014 | I94: 25.81
A95: https://www.sterlinglawyers.com/illinois/divorce/file-for-divorce/file-cook-county/ | B95: 200 | C95: How to File for Divorce in Illinois | Sterling Lawyers, LLC | D95: Indexable | F95: 193 | G95: 31245 | H95: 0.006 | I95: 9.88
A96: https://www.sterlinglawyers.com/illinois/divorce/waiting-period/ | B96: 200 | C96: Waiting Period to File for Divorce in Illinois | Sterling Lawyers, LLC | D96: Indexable | F96: 117 | G96: 15678 | H96: 0.007 | I96: 5.73
A97: https://www.sterlinglawyers.com/illinois/locations/st-charles/divorce-mediation-lawyers/ | B97: 200 | C97: St. Charles Divorce Mediation Lawyers | Sterling Lawyers, LLC | D97: Indexable
A98: https://www.sterlinglawyers.com/illinois/divorce/litigation/ | B98: 200 | C98: Divorce Litigation in Illinois | Sterling Lawyers, LLC | D98: Indexable | F98: 2 | G98: 1471 | H98: 0.001 | I98: 23
A99: https://www.sterlinglawyers.com/illinois/divorce/selecting-attorney/ | B99: 200 | C99: What to Look for When Selecting an Attorney | Sterling Lawyers, LLC | D99: Non-Indexable | E99: Canonicalised | F99: 0 | G99: 168 | H99: 0 | I99: 6.52
A100: https://www.sterlinglawyers.com/illinois/attorneys/ryan-shope/reviews/page/16/ | B100: 200 | C100: Reviews: Attorney Ryan Shope | Sterling Lawyers, LLC | D100: Non-Indexable | E100: Canonicalised | F100: 0 | G100: 2 | H100: 0 | I100: 10
A101: https://www.sterlinglawyers.com/illinois/attorneys/ryan-shope/reviews/page/2/ | B101: 200 | C101: Reviews: Attorney Ryan Shope | Sterling Lawyers, LLC | D101: Non-Indexable | E101: Canonicalised | F101: 0 | G101: 1 | H101: 0 | I101: 6
A102: https://www.sterlinglawyers.com/illinois/attorneys/ryan-shope/reviews/page/3/ | B102: 200 | C102: Reviews: Attorney Ryan Shope | Sterling Lawyers, LLC | D102: Non-Indexable | E102: Canonicalised | F102: 0 | G102: 10 | H102: 0 | I102: 6.7
A103: https://www.sterlinglawyers.com/illinois/blog/surviving-property-division-storm-evanston-lawyers/ | B103: 200 | C103: Surviving the Property Division Storm with Evanston Lawyers | Sterling Lawyers, LLC | D103: Indexable | F103: 0 | G103: 94 | H103: 0 | I103: 29.76
A104: https://www.sterlinglawyers.com/illinois/child-custody/50-50-schedules/ | B104: 200 | C104: 50/50 Joint Custody in Illinois | Sterling Lawyers, LLC | D104: Indexable | F104: 304 | G104: 35680 | H104: 0.009 | I104: 10.62
A105: https://www.sterlinglawyers.com/illinois/attorneys/jacqueline-mcclellan/reviews/page/2/ | B105: 200 | C105: Reviews: Attorney Jacqueline N. McClellan | Sterling Lawyers, LLC | D105: Non-Indexable | E105: Canonicalised | F105: 0 | G105: 25 | H105: 0 | I105: 29.28
A106: https://www.sterlinglawyers.com/illinois/attorneys/jacqueline-mcclellan/reviews/page/3/ | B106: 200 | C106: Reviews: Attorney Jacqueline N. McClellan | Sterling Lawyers, LLC | D106: Non-Indexable | E106: Canonicalised | F106: 0 | G106: 46 | H106: 0 | I106: 13.85
A107: https://www.sterlinglawyers.com/illinois/child-custody/third-party-visitation/ | B107: 200 | C107: Grandparents Rights in Illinois Explained | Sterling Lawyers, LLC | D107: Indexable | F107: 414 | G107: 27710 | H107: 0.015 | I107: 7.24
A108: https://www.sterlinglawyers.com/illinois/attorneys/jacqueline-mcclellan/reviews/page/14/ | B108: 200 | C108: Reviews: Attorney Jacqueline N. McClellan | Sterling Lawyers, LLC | D108: Non-Indexable | E108: Canonicalised
A109: https://www.sterlinglawyers.com/illinois/blog/developing-plan-schaumburg-military-divorce/ | B109: 200 | C109: Developing a Plan for a Schaumburg Military Divorce | Sterling Lawyers, LLC | D109: Indexable
A110: https://www.sterlinglawyers.com/illinois/attorneys/jeff-hughes/reviews/page/2/ | B110: 200 | C110: Divorce & Family Law Attorney Reviews - Attorney Jeff Hughes | Sterling Lawyers, LLC | D110: Non-Indexable | E110: noindex
A111: https://www.sterlinglawyers.com/illinois/attorneys/jeff-hughes/reviews/page/3/ | B111: 200 | C111: Divorce & Family Law Attorney Reviews - Attorney Jeff Hughes | Sterling Lawyers, LLC | D111: Non-Indexable | E111: noindex
A112: https://www.sterlinglawyers.com/illinois/attorneys/jeff-hughes/reviews/page/13/ | B112: 200 | C112: Divorce & Family Law Attorney Reviews - Attorney Jeff Hughes | Sterling Lawyers, LLC | D112: Non-Indexable | E112: noindex
A113: https://www.sterlinglawyers.com/child-custody/parenting-plan/ | B113: 200 | C113: Parenting Plan | Sterling Lawyers, LLC | D113: Indexable | F113: 7 | G113: 954 | H113: 0.007 | I113: 26.62
A114: https://www.sterlinglawyers.com/attorneys/ | B114: 200 | C114: Attorneys in Illinois & Wisconsin | Sterling Lawyers, LLC | D114: Indexable | F114: 16 | G114: 2664 | H114: 0.006 | I114: 58.59
A115: https://www.sterlinglawyers.com/wisconsin/attorneys/ | B115: 200 | C115: Wisconsin Family Law & Divorce Lawyers | Sterling Lawyers, LLC | D115: Indexable | F115: 33 | G115: 40774 | H115: 0.001 | I115: 31.41
...

Sheet Sterling Lawyers Illinois _ Con
A1: CURRENT IL PAGES (NO BLOGS)
A2: https://www.sterlinglawyers.com/illinois/
A3: https://www.sterlinglawyers.com/illinois/divorce/
A4: https://www.sterlinglawyers.com/illinois/paternity/
A5: https://www.sterlinglawyers.com/illinois/child-custody/
A6: https://www.sterlinglawyers.com/illinois/attorneys/
A7: https://www.sterlinglawyers.com/illinois/locations/
A8: https://www.sterlinglawyers.com/illinois/pricing/
A9: https://www.sterlinglawyers.com/illinois/guardianship/
A10: https://www.sterlinglawyers.com/illinois/child-support/
A11: https://www.sterlinglawyers.com/illinois/property-division/
A12: https://www.sterlinglawyers.com/illinois/spousal-support/
... A229: https://www.sterlinglawyers.com/illinois/property-division/survivorship-marital-property/

Sheet Family Law Content Mapping - Co
A1: Project Name | B1: Tier | C1: Description | D1: Impact
A2: Attorney Hub (Pages) - Identify if they are using the About page as the Attorney Hub (very common)
A3: Location Hub (Pages if not multi or Hub not present)
